Workbook
Name CANYON: #REF!
Name TP_LINK: #REF!
Name DELL: #REF!
Name GENERIC: #REF!
Name SEAGATE: #REF!
Name DELL_EMC: #REF!
Name MANTA_MULTIMEDIA: #REF!
Name PRESTIGIO: #REF!
Name PERENIO: #REF!
Name LOGITECH: #REF!
Name APPLE: #REF!

Sheet Inverter price analysis BayWa
A1: BEU: | C1: Partner: | G1: Location: | P1: COMPETITION PRICES
G2: *distr.price+freight | J2: *devide (LCP CY)/(1-GM)
B3: Brand | C3: Description | D3: Type | E3: QTY | F3: Distributor BayWa r.e. Price | G3: LCP CY (€) | H3: Final LCP CY | I3: ASKY GM % | J3: Final Price to Customer | K3: Revenue | L3: LCP CY Revenue | M3: Desired GM | N3: LANITIS ENERGY | O3: BIG SOLAR | P3: DR. ENERGY | Q3: TRIKKIS ENERGY | R3: KAFKAS | S3: MERXU
B4: ='ALL DATA & IT4PROFIT'!A6 -> HUAWEI | C4: ='ALL DATA & IT4PROFIT'!B6 -> SUN2000-2KTL-L1 | D4: ='ALL DATA & IT4PROFIT'!C6 -> 1PH HYBRID | E4: 1 | F4: ='ALL DATA & IT4PROFIT'!J6 -> *se container | G4: =F4+$G$193 -> #VALUE! | H4: =(G4*$E$193)+G4 -> #VALUE! | I4: =(J4-H4)/J4 -> #VALUE! | J4: =H4/(1-M4) -> #VALUE! | K4: =SUM(E4*J4) -> #VALUE! | L4: =SUM(E4*H4) -> #VALUE! | M4: 0.07 | N4: 420 | P4: ='ALL DATA & IT4PROFIT'!H6 -> 557 | Q4: ='ALL DATA & IT4PROFIT'!K6 -> 344 | R4: ='ALL DATA & IT4PROFIT'!D6 -> 489
B5: ='ALL DATA & IT4PROFIT'!A7 -> HUAWEI | C5: ='ALL DATA & IT4PROFIT'!B7 -> SUN2000-3KTL-L1 | D5: ='ALL DATA & IT4PROFIT'!C7 -> 1PH HYBRID | E5: 1 | F5: ='ALL DATA & IT4PROFIT'!J7 -> 550 | G5: =F5+$G$193 -> 575 | H5: =(G5*$E$193)+G5 -> 589.375 | I5: =(J5-H5)/J5 -> 0 | J5: =H5/(1-M5) -> 589.375 | K5: =SUM(E5*J5) -> 589.375 | L5: =SUM(E5*H5) -> 589.375 | M5: 0 | N5: 510 | P5: ='ALL DATA & IT4PROFIT'!H7 -> 545 | Q5: ='ALL DATA & IT4PROFIT'!K7 -> 432 | R5: ='ALL DATA & IT4PROFIT'!D7 -> 575
B6: ='ALL DATA & IT4PROFIT'!A8 -> HUAWEI | C6: ='ALL DATA & IT4PROFIT'!B8 -> SUN2000-3.68KTL-L1 | D6: ='ALL DATA & IT4PROFIT'!C8 -> 1PH HYBRID | E6: 1 | F6: ='ALL DATA & IT4PROFIT'!J8 | G6: =F6+$G$193 -> 25 | H6: =(G6*$E$193)+G6 -> 25.625 | I6: =(J6-H6)/J6 -> 0.05 | J6: =H6/(1-M6) -> 26.973684 | K6: =SUM(E6*J6) -> 26.973684 | L6: =SUM(E6*H6) -> 25.625 | M6: 0.05 | N6: 580 | P6: ='ALL DATA & IT4PROFIT'!H8 | Q6: ='ALL DATA & IT4PROFIT'!K8 | R6: ='ALL DATA & IT4PROFIT'!D8 -> 677
B7: ='ALL DATA & IT4PROFIT'!A9 -> HUAWEI | C7: ='ALL DATA & IT4PROFIT'!B9 -> SUN2000-4KTL-L1 | D7: ='ALL DATA & IT4PROFIT'!C9 -> 1PH HYBRID | E7: 1 | F7: ='ALL DATA & IT4PROFIT'!J9 -> 674 | G7: =F7+$G$193 -> 699 | H7: =(G7*$E$193)+G7 -> 716.475 | I7: =(J7-H7)/J7 -> 0 | J7: =H7/(1-M7) -> 716.475 | K7: =SUM(E7*J7) -> 716.475 | L7: =SUM(E7*H7) -> 716.475 | M7: 0 | N7: 620 | P7: ='ALL DATA & IT4PROFIT'!H9 -> 580 | Q7: ='ALL DATA & IT4PROFIT'!K9 -> 563 | R7: ='ALL DATA & IT4PROFIT'!D9 -> 705
B8: ='ALL DATA & IT4PROFIT'!A10 -> HUAWEI | C8: ='ALL DATA & IT4PROFIT'!B10 -> SUN2000-4.6KTL-L1 | D8: ='ALL DATA & IT4PROFIT'!C10 -> 1PH HYBRID | E8: 1 | F8: ='ALL DATA & IT4PROFIT'!J10 | G8: =F8+$G$193 -> 25 | H8: =(G8*$E$193)+G8 -> 25.625 | I8: =(J8-H8)/J8 -> 0.05 | J8: =H8/(1-M8) -> 26.973684 | K8: =SUM(E8*J8) -> 26.973684 | L8: =SUM(E8*H8) -> 25.625 | M8: 0.05 | N8: 645 | P8: ='ALL DATA & IT4PROFIT'!H10 -> 595 | Q8: ='ALL DATA & IT4PROFIT'!K10 -> 616 | R8: ='ALL DATA & IT4PROFIT'!D10 -> 756
B9: ='ALL DATA & IT4PROFIT'!A11 -> HUAWEI | C9: ='ALL DATA & IT4PROFIT'!B11 -> SUN2000-5KTL-L1 | D9: ='ALL DATA & IT4PROFIT'!C11 -> 1PH HYBRID | E9: 1 | F9: ='ALL DATA & IT4PROFIT'!J11 -> 731 | G9: =F9+$G$193 -> 756 | H9: =(G9*$E$193)+G9 -> 774.9 | I9: =(J9-H9)/J9 -> 0 | J9: =H9/(1-M9) -> 774.9 | K9: =SUM(E9*J9) -> 774.9 | L9: =SUM(E9*H9) -> 774.9 | M9: 0 | N9: 660 | P9: ='ALL DATA & IT4PROFIT'!H11 -> 620 | Q9: ='ALL DATA & IT4PROFIT'!K11 -> 624 | R9: ='ALL DATA & IT4PROFIT'!D11 -> 764
B10: ='ALL DATA & IT4PROFIT'!A12 -> HUAWEI | C10: ='ALL DATA & IT4PROFIT'!B12 -> SUN2000-6KTL-L1 | D10: ='ALL DATA & IT4PROFIT'!C12 -> 1PH HYBRID | E10: 1 | F10: ='ALL DATA & IT4PROFIT'!J12 | G10: =F10+$G$193 -> 25 | H10: =(G10*$E$193)+G10 -> 25.625 | I10: =(J10-H10)/J10 -> 0.05 | J10: =H10/(1-M10) -> 26.973684 | K10: =SUM(E10*J10) -> 26.973684 | L10: =SUM(E10*H10) -> 25.625 | M10: 0.05 | P10: ='ALL DATA & IT4PROFIT'!H12 | Q10: ='ALL DATA & IT4PROFIT'!K12 | R10: ='ALL DATA & IT4PROFIT'!D12 -> 868
B11: ='ALL DATA & IT4PROFIT'!A13 -> HUAWEI | C11: ='ALL DATA & IT4PROFIT'!B13 -> SUN2000-3KTL-M1 | D11: ='ALL DATA & IT4PROFIT'!C13 -> 3PH HYBRID | E11: 1 | F11: ='ALL DATA & IT4PROFIT'!J13 -> 794 | G11: =F11+$G$193 -> 819 | H11: =(G11*$E$193)+G11 -> 839.475 | I11: =(J11-H11)/J11 -> 0.01 | J11: =H11/(1-M11) -> 847.95455 | K11: =SUM(E11*J11) -> 847.95455 | L11: =SUM(E11*H11) -> 839.475 | M11: 0.01 | N11: 845 | P11: ='ALL DATA & IT4PROFIT'!H13 -> 907 | Q11: ='ALL DATA & IT4PROFIT'!K13 -> 832 | R11: ='ALL DATA & IT4PROFIT'!D13 -> 880
B12: ='ALL DATA & IT4PROFIT'!A14 -> HUAWEI | C12: ='ALL DATA & IT4PROFIT'!B14 -> SUN2000-4KTL-M1 | D12: ='ALL DATA & IT4PROFIT'!C14 -> 3PH HYBRID | E12: 1 | F12: ='ALL DATA & IT4PROFIT'!J14 -> 830 | G12: =F12+$G$193 -> 855 | H12: =(G12*$E$193)+G12 -> 876.375 | I12: =(J12-H12)/J12 -> 0.01 | J12: =H12/(1-M12) -> 885.22727 | K12: =SUM(E12*J12) -> 885.22727 | L12: =SUM(E12*H12) -> 876.375 | M12: 0.01 | N12: 880 | P12: ='ALL DATA & IT4PROFIT'!H14 -> 906 | Q12: ='ALL DATA & IT4PROFIT'!K14 -> 871 | R12: ='ALL DATA & IT4PROFIT'!D14 -> 920
B13: ='ALL DATA & IT4PROFIT'!A15 -> HUAWEI | C13: ='ALL DATA & IT4PROFIT'!B15 -> SUN2000-5KTL-M1 | D13: ='ALL DATA & IT4PROFIT'!C15 -> 3PH HYBRID | E13: 1 | F13: ='ALL DATA & IT4PROFIT'!J15 -> 876 | G13: =F13+$G$193 -> 901 | H13: =(G13*$E$193)+G13 -> 923.525 | I13: =(J13-H13)/J13 -> 0.01 | J13: =H13/(1-M13) -> 932.85354 | K13: =SUM(E13*J13) -> 932.85354 | L13: =SUM(E13*H13) -> 923.525 | M13: 0.01 | N13: 930 | P13: ='ALL DATA & IT4PROFIT'!H15 -> 930 | Q13: ='ALL DATA & IT4PROFIT'!K15 -> 919 | R13: ='ALL DATA & IT4PROFIT'!D15 -> 971
B14: ='ALL DATA & IT4PROFIT'!A16 -> HUAWEI | C14: ='ALL DATA & IT4PROFIT'!B16 -> SUN2000-6KTL-M1 | D14: ='ALL DATA & IT4PROFIT'!C16 -> 3PH HYBRID | E14: 1 | F14: ='ALL DATA & IT4PROFIT'!J16 -> 980 | G14: =F14+$G$193 -> 1005 | H14: =(G14*$E$193)+G14 -> 1030.125 | I14: =(J14-H14)/J14 -> 0.01 | J14: =H14/(1-M14) -> 1040.5303 | K14: =SUM(E14*J14) -> 1040.5303 | L14: =SUM(E14*H14) -> 1030.125 | M14: 0.01 | N14: 1040 | P14: ='ALL DATA & IT4PROFIT'!H16 -> 1090 | Q14: ='ALL DATA & IT4PROFIT'!K16 -> 1028 | R14: ='ALL DATA & IT4PROFIT'!D16 -> 1086
B15: ='ALL DATA & IT4PROFIT'!A17 -> HUAWEI | C15: ='ALL DATA & IT4PROFIT'!B17 -> SUN2000-8KTL-M1 | D15: ='ALL DATA & IT4PROFIT'!C17 -> 3PH HYBRID | E15: 1 | F15: ='ALL DATA & IT4PROFIT'!J17 -> 1162 | G15: =F15+$G$193 -> 1187 | H15: =(G15*$E$193)+G15 -> 1216.675 | I15: =(J15-H15)/J15 -> 0.015 | J15: =H15/(1-M15) -> 1235.203 | K15: =SUM(E15*J15) -> 1235.203 | L15: =SUM(E15*H15) -> 1216.675 | M15: 0.015 | N15: 1235 | P15: ='ALL DATA & IT4PROFIT'!H17 -> 1260 | Q15: ='ALL DATA & IT4PROFIT'!K17 -> 1219 | R15: ='ALL DATA & IT4PROFIT'!D17 -> 1289
B16: ='ALL DATA & IT4PROFIT'!A18 -> HUAWEI | C16: ='ALL DATA & IT4PROFIT'!B18 -> SUN2000-10KTL-M1 | D16: ='ALL DATA & IT4PROFIT'!C18 -> 3PH HYBRID | E16: 1 | F16: ='ALL DATA & IT4PROFIT'!J18 -> 1306 | G16: =F16+$G$193 -> 1331 | H16: =(G16*$E$193)+G16 -> 1364.275 | I16: =(J16-H16)/J16 -> 0.015 | J16: =H16/(1-M16) -> 1385.0508 | K16: =SUM(E16*J16) -> 1385.0508 | L16: =SUM(E16*H16) -> 1364.275 | M16: 0.015 | N16: 1385 | P16: ='ALL DATA & IT4PROFIT'!H18 -> 1385 | Q16: ='ALL DATA & IT4PROFIT'!K18 -> 1369 | R16: ='ALL DATA & IT4PROFIT'!D18 -> 1448
B17: ='ALL DATA & IT4PROFIT'!A19 -> HUAWEI | C17: ='ALL DATA & IT4PROFIT'!B19 -> SUN2000-12KTL-M5 | D17: ='ALL DATA & IT4PROFIT'!C19 -> 3PH HYBRID | E17: 1 | F17: ='ALL DATA & IT4PROFIT'!J19 -> 1420 | G17: =F17+$G$193 -> 1445 | H17: =(G17*$E$193)+G17 -> 1481.125 | I17: =(J17-H17)/J17 -> 0 | J17: =H17/(1-M17) -> 1481.125 | K17: =SUM(E17*J17) -> 1481.125 | L17: =SUM(E17*H17) -> 1481.125 | M17: 0 | N17: 1450 | P17: ='ALL DATA & IT4PROFIT'!H19 | Q17: ='ALL DATA & IT4PROFIT'!K19 -> 947.6 | R17: ='ALL DATA & IT4PROFIT'!D19 -> 1515
B18: ='ALL DATA & IT4PROFIT'!A20 -> HUAWEI | C18: ='ALL DATA & IT4PROFIT'!B20 -> SUN2000-15KTL-M5 | D18: ='ALL DATA & IT4PROFIT'!C20 -> 3PH HYBRID | E18: 1 | F18: ='ALL DATA & IT4PROFIT'!J20 -> 1580 | G18: =F18+$G$193 -> 1605 | H18: =(G18*$E$193)+G18 -> 1645.125 | I18: =(J18-H18)/J18 -> 0 | J18: =H18/(1-M18) -> 1645.125 | K18: =SUM(E18*J18) -> 1645.125 | L18: =SUM(E18*H18) -> 1645.125 | M18: 0 | N18: 1640 | P18: ='ALL DATA & IT4PROFIT'!H20 | Q18: ='ALL DATA & IT4PROFIT'!K20 -> 1133.5 | R18: ='ALL DATA & IT4PROFIT'!D20 -> 1710
B19: ='ALL DATA & IT4PROFIT'!A21 -> HUAWEI | C19: ='ALL DATA & IT4PROFIT'!B21 -> SUN2000-17KTL-M5 | D19: ='ALL DATA & IT4PROFIT'!C21 -> 3PH HYBRID | E19: 1 | F19: ='ALL DATA & IT4PROFIT'!J21 -> 1615 | G19: =F19+$G$193 -> 1640 | H19: =(G19*$E$193)+G19 -> 1681 | I19: =(J19-H19)/J19 -> 0 | J19: =H19/(1-M19) -> 1681 | K19: =SUM(E19*J19) -> 1681 | L19: =SUM(E19*H19) -> 1681 | M19: 0 | N19: 1675 | P19: ='ALL DATA & IT4PROFIT'!H21 | Q19: ='ALL DATA & IT4PROFIT'!K21 -> 1167.6 | R19: ='ALL DATA & IT4PROFIT'!D21 -> 1447
B20: ='ALL DATA & IT4PROFIT'!A22 -> HUAWEI | C20: ='ALL DATA & IT4PROFIT'!B22 -> SUN2000-20KTL-M5 | D20: ='ALL DATA & IT4PROFIT'!C22 -> 3PH HYBRID | E20: 1 | F20: ='ALL DATA & IT4PROFIT'!J22 -> 1704 | G20: =F20+$G$193 -> 1729 | H20: =(G20*$E$193)+G20 -> 1772.225 | I20: =(J20-H20)/J20 -> 0.01 | J20: =H20/(1-M20) -> 1790.1263 | K20: =SUM(E20*J20) -> 1790.1263 | L20: =SUM(E20*H20) -> 1772.225 | M20: 0.01 | N20: 1790 | P20: ='ALL DATA & IT4PROFIT'!H22 | Q20: ='ALL DATA & IT4PROFIT'!K22 -> 1262.2 | R20: ='ALL DATA & IT4PROFIT'!D22 -> 1844
B21: ='ALL DATA & IT4PROFIT'!A23 -> HUAWEI | C21: ='ALL DATA & IT4PROFIT'!B23 -> SUN2000-25KTL-M5 | D21: ='ALL DATA & IT4PROFIT'!C23 -> 3PH HYBRID | E21: 1 | F21: ='ALL DATA & IT4PROFIT'!J23 | G21: =F21+$G$193 -> 25 | H21: =(G21*$E$193)+G21 -> 25.625 | I21: =(J21-H21)/J21 -> 0.05 | J21: =H21/(1-M21) -> 26.973684 | K21: =SUM(E21*J21) -> 26.973684 | L21: =SUM(E21*H21) -> 25.625 | M21: 0.05 | N21: 1825 | P21: ='ALL DATA & IT4PROFIT'!H23 | Q21: ='ALL DATA & IT4PROFIT'!K23 -> 1320.5 | R21: ='ALL DATA & IT4PROFIT'!D23 -> 1906
B22: ='ALL DATA & IT4PROFIT'!A24 -> HUAWEI | C22: ='ALL DATA & IT4PROFIT'!B24 -> SUN2000-30KTL-M3 | D22: ='ALL DATA & IT4PROFIT'!C24 -> 3PH HYBRID | E22: 1 | F22: ='ALL DATA & IT4PROFIT'!J24 -> 1945 | G22: =F22+$G$193 -> 1970 | H22: =(G22*$E$193)+G22 -> 2019.25 | I22: =(J22-H22)/J22 -> 0.03 | J22: =H22/(1-M22) -> 2081.701 | K22: =SUM(E22*J22) -> 2081.701 | L22: =SUM(E22*H22) -> 2019.25 | M22: 0.03 | N22: 2080 | P22: ='ALL DATA & IT4PROFIT'!H24 | Q22: ='ALL DATA & IT4PROFIT'!K24 -> 1993 | R22: ='ALL DATA & IT4PROFIT'!D24 -> 2106
... B25: ='ALL DATA & IT4PROFIT'!A27 -> HUAWEI | C25: ='ALL DATA & IT4PROFIT'!B27 -> SUN2000-50KTL-M3 | D25: ='ALL DATA & IT4PROFIT'!C27 -> 3PH HYBRID | E25: 1 | F25: ='ALL DATA & IT4PROFIT'!J27 -> 2350 | G25: =F25+$G$193 -> 2375 | H25: =(G25*$E$193)+G25 -> 2434.375 | I25: =(J25-H25)/J25 -> 0 | J25: =H25/(1-M25) -> 2434.375 | K25: =SUM(E25*J25) -> 2434.375 | L25: =SUM(E25*H25) -> 2434.375 | M25: 0 | N25: 2400 | P25: ='ALL DATA & IT4PROFIT'!H27 | Q25: ='ALL DATA & IT4PROFIT'!K27 -> 2405 | R25: ='ALL DATA & IT4PROFIT'!D27 -> 2543
B26: ='ALL DATA & IT4PROFIT'!A28 -> HUAWEI | C26: ='ALL DATA & IT4PROFIT'!B28 -> SUN2000-100KTL-M2-AFCI | D26: ='ALL DATA & IT4PROFIT'!C28 -> 3PH HYBRID | E26: 1 | F26: ='ALL DATA & IT4PROFIT'!J28 | G26: =F26+$G$193 -> 25 | H26: =(G26*$E$193)+G26 -> 25.625 | I26: =(J26-H26)/J26 -> 0.07 | J26: =H26/(1-M26) -> 27.553763 | K26: =SUM(E26*J26) -> 27.553763 | L26: =SUM(E26*H26) -> 25.625 | M26: 0.07 | P26: ='ALL DATA & IT4PROFIT'!H28 | Q26: ='ALL DATA & IT4PROFIT'!K28 -> 3800 | R26: ='ALL DATA & IT4PROFIT'!D28 -> 4020
B27: ='ALL DATA & IT4PROFIT'!A29 -> HUAWEI | C27: ='ALL DATA & IT4PROFIT'!B29 -> IV HU SUN2000 115 KTL M2 | D27: ='ALL DATA & IT4PROFIT'!C29 | E27: 1 | F27: ='ALL DATA & IT4PROFIT'!J29 | G27: =F27+$G$193 -> 25 | H27: =(G27*$E$193)+G27 -> 25.625 | I27: =(J27-H27)/J27 -> 0.07 | J27: =H27/(1-M27) -> 27.553763 | K27: =SUM(E27*J27) -> 27.553763 | L27: =SUM(E27*H27) -> 25.625 | M27: 0.07 | P27: ='ALL DATA & IT4PROFIT'!H29 | Q27: ='ALL DATA & IT4PROFIT'!K29 -> 3842.6 | R27: ='ALL DATA & IT4PROFIT'!D29
B28: ='ALL DATA & IT4PROFIT'!A30 -> HUAWEI | C28: ='ALL DATA & IT4PROFIT'!B30 -> IV HU SUN2000 105 KTL H1 (1500V) | D28: ='ALL DATA & IT4PROFIT'!C30 | E28: 1 | F28: ='ALL DATA & IT4PROFIT'!J30 | G28: =F28+$G$193 -> 25 | H28: =(G28*$E$193)+G28 -> 25.625 | I28: =(J28-H28)/J28 -> 0.07 | J28: =H28/(1-M28) -> 27.553763 | K28: =SUM(E28*J28) -> 27.553763 | L28: =SUM(E28*H28) -> 25.625 | M28: 0.07 | P28: ='ALL DATA & IT4PROFIT'!H30 | Q28: ='ALL DATA & IT4PROFIT'!K30 | R28: ='ALL DATA & IT4PROFIT'!D30
B29: ='ALL DATA & IT4PROFIT'!A31 -> HUAWEI | C29: ='ALL DATA & IT4PROFIT'!B31 -> IV HU SUN2000 215 KTL-H3 (1500V) | D29: ='ALL DATA & IT4PROFIT'!C31 | E29: 1 | F29: ='ALL DATA & IT4PROFIT'!J31 | G29: =F29+$G$193 -> 25 | H29: =(G29*$E$193)+G29 -> 25.625 | I29: =(J29-H29)/J29 -> 0.07 | J29: =H29/(1-M29) -> 27.553763 | K29: =SUM(E29*J29) -> 27.553763 | L29: =SUM(E29*H29) -> 25.625 | M29: 0.07 | P29: ='ALL DATA & IT4PROFIT'!H31 | Q29: ='ALL DATA & IT4PROFIT'!K31 | R29: ='ALL DATA & IT4PROFIT'!D31
B30: ='ALL DATA & IT4PROFIT'!A32 -> HUAWEI | C30: ='ALL DATA & IT4PROFIT'!B32 -> IV HU SUN2000-330KTL-H1 (1500V) | D30: ='ALL DATA & IT4PROFIT'!C32 | E30: 1 | F30: ='ALL DATA & IT4PROFIT'!J32 | G30: =F30+$G$193 -> 25 | H30: =(G30*$E$193)+G30 -> 25.625 | I30: =(J30-H30)/J30 -> 0.07 | J30: =H30/(1-M30) -> 27.553763 | K30: =SUM(E30*J30) -> 27.553763 | L30: =SUM(E30*H30) -> 25.625 | M30: 0.07 | P30: ='ALL DATA & IT4PROFIT'!H32 | Q30: ='ALL DATA & IT4PROFIT'!K32 | R30: ='ALL DATA & IT4PROFIT'!D32
B31: ='ALL DATA & IT4PROFIT'!A34 | C31: ='ALL DATA & IT4PROFIT'!B34 | D31: ='ALL DATA & IT4PROFIT'!C34 | E31: 1 | F31: ='ALL DATA & IT4PROFIT'!J34 | G31: =F31+$G$193 -> 25 | H31: =(G31*$E$193)+G31 -> 25.625 | I31: =(J31-H31)/J31 -> 0.07 | J31: =H31/(1-M31) -> 27.553763 | K31: =SUM(E31*J31) -> 27.553763 | L31: =SUM(E31*H31) -> 25.625 | M31: 0.07 | P31: ='ALL DATA & IT4PROFIT'!H34 | Q31: ='ALL DATA & IT4PROFIT'!K34 | R31: ='ALL DATA & IT4PROFIT'!D34
B32: ='ALL DATA & IT4PROFIT'!A35 -> HUAWEI | C32: ='ALL DATA & IT4PROFIT'!B35 -> SUN2000-450W-P2 | D32: ='ALL DATA & IT4PROFIT'!C35 -> OPTIMIZER | E32: 1 | F32: ='ALL DATA & IT4PROFIT'!J35 -> 45 | G32: =F32+$G$194 -> 48 | H32: =(G32*$E$193)+G32 -> 49.2 | I32: =(J32-H32)/J32 -> 0 | J32: =H32/(1-M32) -> 49.2 | K32: =SUM(E32*J32) -> 49.2 | L32: =SUM(E32*H32) -> 49.2 | M32: 0 | N32: 40 | P32: ='ALL DATA & IT4PROFIT'!H35 | Q32: ='ALL DATA & IT4PROFIT'!K35 -> 38.5 | R32: ='ALL DATA & IT4PROFIT'!D35 -> 41
B33: ='ALL DATA & IT4PROFIT'!A36 -> HUAWEI | C33: ='ALL DATA & IT4PROFIT'!B36 -> SUN2000-600W-P | D33: ='ALL DATA & IT4PROFIT'!C36 -> OPTIMIZER | E33: 1 | F33: ='ALL DATA & IT4PROFIT'!J36 -> 45 | G33: =F33+$G$194 -> 48 | H33: =(G33*$E$193)+G33 -> 49.2 | I33: =(J33-H33)/J33 -> 0 | J33: =H33/(1-M33) -> 49.2 | K33: =SUM(E33*J33) -> 49.2 | L33: =SUM(E33*H33) -> 49.2 | M33: 0 | N33: 40 | P33: ='ALL DATA & IT4PROFIT'!H36 | Q33: ='ALL DATA & IT4PROFIT'!K36 -> 39 | R33: ='ALL DATA & IT4PROFIT'!D36 -> 41
B34: ='ALL DATA & IT4PROFIT'!A37 | C34: ='ALL DATA & IT4PROFIT'!B37 | D34: ='ALL DATA & IT4PROFIT'!C37 | E34: 1 | F34: ='ALL DATA & IT4PROFIT'!J37 | G34: =F34+$G$193 -> 25 | H34: =(G34*$E$193)+G34 -> 25.625 | I34: =(J34-H34)/J34 -> 0.07 | J34: =H34/(1-M34) -> 27.553763 | K34: =SUM(E34*J34) -> 27.553763 | L34: =SUM(E34*H34) -> 25.625 | M34: 0.07 | P34: ='ALL DATA & IT4PROFIT'!H37 | Q34: ='ALL DATA & IT4PROFIT'!K37 | R34: ='ALL DATA & IT4PROFIT'!D37
B35: ='ALL DATA & IT4PROFIT'!A38 | C35: ='ALL DATA & IT4PROFIT'!B38 | D35: ='ALL DATA & IT4PROFIT'!C38 | E35: 1 | F35: ='ALL DATA & IT4PROFIT'!J38 | G35: =F35+$G$193 -> 25 | H35: =(G35*$E$193)+G35 -> 25.625 | I35: =(J35-H35)/J35 -> 0.07 | J35: =H35/(1-M35) -> 27.553763 | K35: =SUM(E35*J35) -> 27.553763 | L35: =SUM(E35*H35) -> 25.625 | M35: 0.07 | P35: ='ALL DATA & IT4PROFIT'!H38 | Q35: ='ALL DATA & IT4PROFIT'!K38 | R35: ='ALL DATA & IT4PROFIT'!D38
B36: ='ALL DATA & IT4PROFIT'!A39 -> SUNGROW | C36: ='ALL DATA & IT4PROFIT'!B39 -> IV SUNG SG2.0RS | D36: ='ALL DATA & IT4PROFIT'!C39 -> 1PH | E36: 1 | F36: ='ALL DATA & IT4PROFIT'!J39 | G36: =F36+$G$193 -> 25 | H36: =(G36*$E$193)+G36 -> 25.625 | I36: =(J36-H36)/J36 -> 0.07 | J36: =H36/(1-M36) -> 27.553763 | K36: =SUM(E36*J36) -> 27.553763 | L36: =SUM(E36*H36) -> 25.625 | M36: 0.07 | P36: ='ALL DATA & IT4PROFIT'!H39 | Q36: ='ALL DATA & IT4PROFIT'!K39 | R36: ='ALL DATA & IT4PROFIT'!D39
B37: ='ALL DATA & IT4PROFIT'!A40 -> SUNGROW | C37: ='ALL DATA & IT4PROFIT'!B40 -> IV SUNG SG3.0RS | D37: ='ALL DATA & IT4PROFIT'!C40 -> 1PH | E37: 1 | F37: ='ALL DATA & IT4PROFIT'!J40 | G37: =F37+$G$193 -> 25 | H37: =(G37*$E$193)+G37 -> 25.625 | I37: =(J37-H37)/J37 -> 0.07 | J37: =H37/(1-M37) -> 27.553763 | K37: =SUM(E37*J37) -> 27.553763 | L37: =SUM(E37*H37) -> 25.625 | M37: 0.07 | P37: ='ALL DATA & IT4PROFIT'!H40 | Q37: ='ALL DATA & IT4PROFIT'!K40 | R37: ='ALL DATA & IT4PROFIT'!D40
B38: ='ALL DATA & IT4PROFIT'!A41 -> SUNGROW | C38: ='ALL DATA & IT4PROFIT'!B41 -> IV SUNG SG4.0RS | D38: ='ALL DATA & IT4PROFIT'!C41 -> 1PH | E38: 1 | F38: ='ALL DATA & IT4PROFIT'!J41 | G38: =F38+$G$193 -> 25 | H38: =(G38*$E$193)+G38 -> 25.625 | I38: =(J38-H38)/J38 -> 0.07 | J38: =H38/(1-M38) -> 27.553763 | K38: =SUM(E38*J38) -> 27.553763 | L38: =SUM(E38*H38) -> 25.625 | M38: 0.07 | P38: ='ALL DATA & IT4PROFIT'!H41 | Q38: ='ALL DATA & IT4PROFIT'!K41 | R38: ='ALL DATA & IT4PROFIT'!D41
B39: ='ALL DATA & IT4PROFIT'!A42 -> SUNGROW | C39: ='ALL DATA & IT4PROFIT'!B42 -> IV SUNG SG5.0RS | D39: ='ALL DATA & IT4PROFIT'!C42 -> 1PH | E39: 1 | F39: ='ALL DATA & IT4PROFIT'!J42 | G39: =F39+$G$193 -> 25 | H39: =(G39*$E$193)+G39 -> 25.625 | I39: =(J39-H39)/J39 -> 0.07 | J39: =H39/(1-M39) -> 27.553763 | K39: =SUM(E39*J39) -> 27.553763 | L39: =SUM(E39*H39) -> 25.625 | M39: 0.07 | P39: ='ALL DATA & IT4PROFIT'!H42 | Q39: ='ALL DATA & IT4PROFIT'!K42 | R39: ='ALL DATA & IT4PROFIT'!D42
B40: ='ALL DATA & IT4PROFIT'!A43 -> SUNGROW | C40: ='ALL DATA & IT4PROFIT'!B43 -> IV SUNG SG3.0RT | D40: ='ALL DATA & IT4PROFIT'!C43 -> 3PH | E40: 1 | F40: ='ALL DATA & IT4PROFIT'!J43 | G40: =F40+$G$193 -> 25 | H40: =(G40*$E$193)+G40 -> 25.625 | I40: =(J40-H40)/J40 -> 0.07 | J40: =H40/(1-M40) -> 27.553763 | K40: =SUM(E40*J40) -> 27.553763 | L40: =SUM(E40*H40) -> 25.625 | M40: 0.07 | P40: ='ALL DATA & IT4PROFIT'!H43 | Q40: ='ALL DATA & IT4PROFIT'!K43 | R40: ='ALL DATA & IT4PROFIT'!D43
B41: ='ALL DATA & IT4PROFIT'!A44 -> SUNGROW | C41: ='ALL DATA & IT4PROFIT'!B44 -> IV SUNG SG4.0RT | D41: ='ALL DATA & IT4PROFIT'!C44 -> 3PH | E41: 1 | F41: ='ALL DATA & IT4PROFIT'!J44 | G41: =F41+$G$193 -> 25 | H41: =(G41*$E$193)+G41 -> 25.625 | I41: =(J41-H41)/J41 -> 0.07 | J41: =H41/(1-M41) -> 27.553763 | K41: =SUM(E41*J41) -> 27.553763 | L41: =SUM(E41*H41) -> 25.625 | M41: 0.07 | P41: ='ALL DATA & IT4PROFIT'!H44 | Q41: ='ALL DATA & IT4PROFIT'!K44 | R41: ='ALL DATA & IT4PROFIT'!D44
B42: ='ALL DATA & IT4PROFIT'!A45 -> SUNGROW | C42: ='ALL DATA & IT4PROFIT'!B45 -> IV SUNG SG5.0RT | D42: ='ALL DATA & IT4PROFIT'!C45 -> 3PH | E42: 1 | F42: ='ALL DATA & IT4PROFIT'!J45 | G42: =F42+$G$193 -> 25 | H42: =(G42*$E$193)+G42 -> 25.625 | I42: =(J42-H42)/J42 -> 0.07 | J42: =H42/(1-M42) -> 27.553763 | K42: =SUM(E42*J42) -> 27.553763 | L42: =SUM(E42*H42) -> 25.625 | M42: 0.07 | P42: ='ALL DATA & IT4PROFIT'!H45 | Q42: ='ALL DATA & IT4PROFIT'!K45 | R42: ='ALL DATA & IT4PROFIT'!D45
B43: ='ALL DATA & IT4PROFIT'!A46 -> SUNGROW | C43: ='ALL DATA & IT4PROFIT'!B46 -> IV SUNG SG6.0RT | D43: ='ALL DATA & IT4PROFIT'!C46 -> 3PH | E43: 1 | F43: ='ALL DATA & IT4PROFIT'!J46 | G43: =F43+$G$193 -> 25 | H43: =(G43*$E$193)+G43 -> 25.625 | I43: =(J43-H43)/J43 -> 0.07 | J43: =H43/(1-M43) -> 27.553763 | K43: =SUM(E43*J43) -> 27.553763 | L43: =SUM(E43*H43) -> 25.625 | M43: 0.07 | P43: ='ALL DATA & IT4PROFIT'!H46 | Q43: ='ALL DATA & IT4PROFIT'!K46 | R43: ='ALL DATA & IT4PROFIT'!D46
B44: ='ALL DATA & IT4PROFIT'!A47 -> SUNGROW | C44: ='ALL DATA & IT4PROFIT'!B47 -> IV SUNG SG8.0RT | D44: ='ALL DATA & IT4PROFIT'!C47 -> 3PH | E44: 1 | F44: ='ALL DATA & IT4PROFIT'!J47 | G44: =F44+$G$193 -> 25 | H44: =(G44*$E$193)+G44 -> 25.625 | I44: =(J44-H44)/J44 -> 0.07 | J44: =H44/(1-M44) -> 27.553763 | K44: =SUM(E44*J44) -> 27.553763 | L44: =SUM(E44*H44) -> 25.625 | M44: 0.07 | P44: ='ALL DATA & IT4PROFIT'!H47 | Q44: ='ALL DATA & IT4PROFIT'!K47 | R44: ='ALL DATA & IT4PROFIT'!D47
B45: ='ALL DATA & IT4PROFIT'!A48 -> SUNGROW | C45: ='ALL DATA & IT4PROFIT'!B48 -> IV SUNG SG10.0RT | D45: ='ALL DATA & IT4PROFIT'!C48 -> 3PH | E45: 1 | F45: ='ALL DATA & IT4PROFIT'!J48 | G45: =F45+$G$193 -> 25 | H45: =(G45*$E$193)+G45 -> 25.625 | I45: =(J45-H45)/J45 -> 0.07 | J45: =H45/(1-M45) -> 27.553763 | K45: =SUM(E45*J45) -> 27.553763 | L45: =SUM(E45*H45) -> 25.625 | M45: 0.07 | P45: ='ALL DATA & IT4PROFIT'!H48 | Q45: ='ALL DATA & IT4PROFIT'!K48 | R45: ='ALL DATA & IT4PROFIT'!D48
... B59: ='ALL DATA & IT4PROFIT'!A62 | C59: ='ALL DATA & IT4PROFIT'!B62 | D59: ='ALL DATA & IT4PROFIT'!C62 | E59: 1 | F59: ='ALL DATA & IT4PROFIT'!J62 | G59: =F59+$G$193 -> 25 | H59: =(G59*$E$193)+G59 -> 25.625 | I59: =(J59-H59)/J59 -> 0.07 | J59: =H59/(1-M59) -> 27.553763 | K59: =SUM(E59*J59) -> 27.553763 | L59: =SUM(E59*H59) -> 25.625 | M59: 0.07 | P59: ='ALL DATA & IT4PROFIT'!H62 | Q59: ='ALL DATA & IT4PROFIT'!K62 | R59: ='ALL DATA & IT4PROFIT'!D62
B60: ='ALL DATA & IT4PROFIT'!A63 -> FRONIUS | C60: ='ALL DATA & IT4PROFIT'!B63 -> PRIMO 3.0 | D60: ='ALL DATA & IT4PROFIT'!C63 -> 1PH | E60: 1 | F60: ='ALL DATA & IT4PROFIT'!J63 -> 844 | G60: =F60+$G$193 -> 869 | H60: =(G60*$E$193)+G60 -> 890.725 | I60: =(J60-H60)/J60 -> 0.05242 | J60: =H60/(1-M60) -> 939.99979 | K60: =SUM(E60*J60) -> 939.99979 | L60: =SUM(E60*H60) -> 890.725 | M60: 0.05242 | O60: =1570-1570*0.42 -> 910.6 | P60: ='ALL DATA & IT4PROFIT'!H63 -> 950 | Q60: ='ALL DATA & IT4PROFIT'!K63 | R60: ='ALL DATA & IT4PROFIT'!D63
B61: ='ALL DATA & IT4PROFIT'!A64 -> FRONIUS | C61: ='ALL DATA & IT4PROFIT'!B64 -> Fronius Primo 3.6-1 | D61: ='ALL DATA & IT4PROFIT'!C64 | E61: 1 | F61: ='ALL DATA & IT4PROFIT'!J64 | G61: =F61+$G$193 -> 25 | H61: =(G61*$E$193)+G61 -> 25.625 | I61: =(J61-H61)/J61 -> 0.05 | J61: =H61/(1-M61) -> 26.973684 | K61: =SUM(E61*J61) -> 26.973684 | L61: =SUM(E61*H61) -> 25.625 | M61: 0.05 | P61: ='ALL DATA & IT4PROFIT'!H64 | Q61: ='ALL DATA & IT4PROFIT'!K64 | R61: ='ALL DATA & IT4PROFIT'!D64
B62: ='ALL DATA & IT4PROFIT'!A65 -> FRONIUS | C62: ='ALL DATA & IT4PROFIT'!B65 -> PRIMO 4.0 | D62: ='ALL DATA & IT4PROFIT'!C65 -> 1PH | E62: 1 | F62: ='ALL DATA & IT4PROFIT'!J65 -> 934 | G62: =F62+$G$193 -> 959 | H62: =(G62*$E$193)+G62 -> 982.975 | I62: =(J62-H62)/J62 -> 0.04 | J62: =H62/(1-M62) -> 1023.9323 | K62: =SUM(E62*J62) -> 1023.9323 | L62: =SUM(E62*H62) -> 982.975 | M62: 0.04 | O62: =1740-1740*0.42 -> 1009.2 | P62: ='ALL DATA & IT4PROFIT'!H65 -> 1026 | Q62: ='ALL DATA & IT4PROFIT'!K65 | R62: ='ALL DATA & IT4PROFIT'!D65
B63: ='ALL DATA & IT4PROFIT'!A66 -> FRONIUS | C63: ='ALL DATA & IT4PROFIT'!B66 -> Fronius Primo 4.6-1 | D63: ='ALL DATA & IT4PROFIT'!C66 | E63: 1 | F63: ='ALL DATA & IT4PROFIT'!J66 | G63: =F63+$G$193 -> 25 | H63: =(G63*$E$193)+G63 -> 25.625 | I63: =(J63-H63)/J63 -> 0.05 | J63: =H63/(1-M63) -> 26.973684 | K63: =SUM(E63*J63) -> 26.973684 | L63: =SUM(E63*H63) -> 25.625 | M63: 0.05 | P63: ='ALL DATA & IT4PROFIT'!H66 | Q63: ='ALL DATA & IT4PROFIT'!K66 | R63: ='ALL DATA & IT4PROFIT'!D66
B64: ='ALL DATA & IT4PROFIT'!A67 -> FRONIUS | C64: ='ALL DATA & IT4PROFIT'!B67 -> PRIMO 5.0 | D64: ='ALL DATA & IT4PROFIT'!C67 -> 1PH | E64: 1 | F64: ='ALL DATA & IT4PROFIT'!J67 -> 1027 | G64: =F64+$G$193 -> 1052 | H64: =(G64*$E$193)+G64 -> 1078.3 | I64: =(J64-H64)/J64 -> 0.025 | J64: =H64/(1-M64) -> 1105.9487 | K64: =SUM(E64*J64) -> 1105.9487 | L64: =SUM(E64*H64) -> 1078.3 | M64: 0.025 | O64: =1905-1905*0.42 -> 1104.9 | P64: ='ALL DATA & IT4PROFIT'!H67 -> 1124 | Q64: ='ALL DATA & IT4PROFIT'!K67 | R64: ='ALL DATA & IT4PROFIT'!D67
B65: ='ALL DATA & IT4PROFIT'!A68 | C65: ='ALL DATA & IT4PROFIT'!B68 | D65: ='ALL DATA & IT4PROFIT'!C68 | E65: 1 | F65: ='ALL DATA & IT4PROFIT'!J68 | G65: =F65+$G$193 -> 25 | H65: =(G65*$E$193)+G65 -> 25.625 | I65: =(J65-H65)/J65 -> 0.05 | J65: =H65/(1-M65) -> 26.973684 | K65: =SUM(E65*J65) -> 26.973684 | L65: =SUM(E65*H65) -> 25.625 | M65: 0.05 | P65: ='ALL DATA & IT4PROFIT'!H68 | Q65: ='ALL DATA & IT4PROFIT'!K68 | R65: ='ALL DATA & IT4PROFIT'!D68
B66: ='ALL DATA & IT4PROFIT'!A69 -> FRONIUS | C66: ='ALL DATA & IT4PROFIT'!B69 -> SYMO 3.0-S | D66: ='ALL DATA & IT4PROFIT'!C69 -> 3PH | E66: 1 | F66: ='ALL DATA & IT4PROFIT'!J69 -> 835 | G66: =F66+$G$193 -> 860 | H66: =(G66*$E$193)+G66 -> 881.5 | I66: =(J66-H66)/J66 -> 0.07 | J66: =H66/(1-M66) -> 947.84946 | K66: =SUM(E66*J66) -> 947.84946 | L66: =SUM(E66*H66) -> 881.5 | M66: 0.07 | O66: =1630-1630*0.42 -> 945.4 | P66: ='ALL DATA & IT4PROFIT'!H69 -> 955 | Q66: ='ALL DATA & IT4PROFIT'!K69 | R66: ='ALL DATA & IT4PROFIT'!D69
B67: ='ALL DATA & IT4PROFIT'!A70 -> FRONIUS | C67: ='ALL DATA & IT4PROFIT'!B70 -> SYMO 3.7-S | D67: ='ALL DATA & IT4PROFIT'!C70 -> 3PH | E67: 1 | F67: ='ALL DATA & IT4PROFIT'!J70 | G67: =F67+$G$193 -> 25 | H67: =(G67*$E$193)+G67 -> 25.625 | I67: =(J67-H67)/J67 -> 0.07 | J67: =H67/(1-M67) -> 27.553763 | K67: =SUM(E67*J67) -> 27.553763 | L67: =SUM(E67*H67) -> 25.625 | M67: 0.07 | O67: =1790-1790*0.42 -> 1038.2 | P67: ='ALL DATA & IT4PROFIT'!H70 -> 960 | Q67: ='ALL DATA & IT4PROFIT'!K70 | R67: ='ALL DATA & IT4PROFIT'!D70
B68: ='ALL DATA & IT4PROFIT'!A71 -> FRONIUS | C68: ='ALL DATA & IT4PROFIT'!B71 -> SYMO 4.5-S | D68: ='ALL DATA & IT4PROFIT'!C71 -> 3PH | E68: 1 | F68: ='ALL DATA & IT4PROFIT'!J71 -> 912 | G68: =F68+$G$193 -> 937 | H68: =(G68*$E$193)+G68 -> 960.425 | I68: =(J68-H68)/J68 -> 0.12 | J68: =H68/(1-M68) -> 1091.392 | K68: =SUM(E68*J68) -> 1091.392 | L68: =SUM(E68*H68) -> 960.425 | M68: 0.12 | O68: =1980-1980*0.42 -> 1148.4 | P68: ='ALL DATA & IT4PROFIT'!H71 | Q68: ='ALL DATA & IT4PROFIT'!K71 | R68: ='ALL DATA & IT4PROFIT'!D71
B69: ='ALL DATA & IT4PROFIT'!A72 -> FRONIUS | C69: ='ALL DATA & IT4PROFIT'!B72 -> SYMO 3.0-M | D69: ='ALL DATA & IT4PROFIT'!C72 -> 3PH | E69: 1 | F69: ='ALL DATA & IT4PROFIT'!J72 -> 925 | G69: =F69+$G$193 -> 950 | H69: =(G69*$E$193)+G69 -> 973.75 | I69: =(J69-H69)/J69 -> 0.06 | J69: =H69/(1-M69) -> 1035.9043 | K69: =SUM(E69*J69) -> 1035.9043 | L69: =SUM(E69*H69) -> 973.75 | M69: 0.06 | O69: =1800-1800*0.42 -> 1044 | P69: ='ALL DATA & IT4PROFIT'!H72 -> 1040 | Q69: ='ALL DATA & IT4PROFIT'!K72 | R69: ='ALL DATA & IT4PROFIT'!D72
B70: ='ALL DATA & IT4PROFIT'!A73 -> FRONIUS | C70: ='ALL DATA & IT4PROFIT'!B73 -> SYMO 3.7-M | D70: ='ALL DATA & IT4PROFIT'!C73 -> 3PH | E70: 1 | F70: ='ALL DATA & IT4PROFIT'!J73 -> 1015 | G70: =F70+$G$193 -> 1040 | H70: =(G70*$E$193)+G70 -> 1066 | I70: =(J70-H70)/J70 -> 0.07 | J70: =H70/(1-M70) -> 1146.2366 | K70: =SUM(E70*J70) -> 1146.2366 | L70: =SUM(E70*H70) -> 1066 | M70: 0.07 | O70: =1980-1980*0.42 -> 1148.4 | P70: ='ALL DATA & IT4PROFIT'!H73 -> 1168 | Q70: ='ALL DATA & IT4PROFIT'!K73 | R70: ='ALL DATA & IT4PROFIT'!D73
B71: ='ALL DATA & IT4PROFIT'!A74 -> FRONIUS | C71: ='ALL DATA & IT4PROFIT'!B74 -> SYMO 4.5-M | D71: ='ALL DATA & IT4PROFIT'!C74 -> 3PH | E71: 1 | F71: ='ALL DATA & IT4PROFIT'!J74 -> 1070 | G71: =F71+$G$193 -> 1095 | H71: =(G71*$E$193)+G71 -> 1122.375 | I71: =(J71-H71)/J71 -> 0.08 | J71: =H71/(1-M71) -> 1219.9728 | K71: =SUM(E71*J71) -> 1219.9728 | L71: =SUM(E71*H71) -> 1122.375 | M71: 0.08 | O71: =2090-2090*0.42 -> 1212.2 | P71: ='ALL DATA & IT4PROFIT'!H74 -> 1240 | Q71: ='ALL DATA & IT4PROFIT'!K74 | R71: ='ALL DATA & IT4PROFIT'!D74
B72: ='ALL DATA & IT4PROFIT'!A75 -> FRONIUS | C72: ='ALL DATA & IT4PROFIT'!B75 -> SYMO 5.0-M | D72: ='ALL DATA & IT4PROFIT'!C75 -> 3PH | E72: 1 | F72: ='ALL DATA & IT4PROFIT'!J75 -> 1090 | G72: =F72+$G$193 -> 1115 | H72: =(G72*$E$193)+G72 -> 1142.875 | I72: =(J72-H72)/J72 -> 0.07 | J72: =H72/(1-M72) -> 1228.8978 | K72: =SUM(E72*J72) -> 1228.8978 | L72: =SUM(E72*H72) -> 1142.875 | M72: 0.07 | O72: =2120-2120*0.42 -> 1229.6 | P72: ='ALL DATA & IT4PROFIT'!H75 -> 1250 | Q72: ='ALL DATA & IT4PROFIT'!K75 | R72: ='ALL DATA & IT4PROFIT'!D75
B73: ='ALL DATA & IT4PROFIT'!A76 -> FRONIUS | C73: ='ALL DATA & IT4PROFIT'!B76 -> SYMO 6.0-M | D73: ='ALL DATA & IT4PROFIT'!C76 -> 3PH | E73: 1 | F73: ='ALL DATA & IT4PROFIT'!J76 -> 1110 | G73: =F73+$G$193 -> 1135 | H73: =(G73*$E$193)+G73 -> 1163.375 | I73: =(J73-H73)/J73 -> 0.07 | J73: =H73/(1-M73) -> 1250.9409 | K73: =SUM(E73*J73) -> 1250.9409 | L73: =SUM(E73*H73) -> 1163.375 | M73: 0.07 | O73: =2160-2160*0.42 -> 1252.8 | P73: ='ALL DATA & IT4PROFIT'!H76 -> 1274 | Q73: ='ALL DATA & IT4PROFIT'!K76 | R73: ='ALL DATA & IT4PROFIT'!D76
B74: ='ALL DATA & IT4PROFIT'!A77 -> FRONIUS | C74: ='ALL DATA & IT4PROFIT'!B77 -> SYMO 7.0-M | D74: ='ALL DATA & IT4PROFIT'!C77 -> 3PH | E74: 1 | F74: ='ALL DATA & IT4PROFIT'!J77 -> 1375 | G74: =F74+$G$193 -> 1400 | H74: =(G74*$E$193)+G74 -> 1435 | I74: =(J74-H74)/J74 -> 0.07 | J74: =H74/(1-M74) -> 1543.0108 | K74: =SUM(E74*J74) -> 1543.0108 | L74: =SUM(E74*H74) -> 1435 | M74: 0.07 | O74: =2670-2670*0.42 -> 1548.6 | P74: ='ALL DATA & IT4PROFIT'!H77 -> 1580 | Q74: ='ALL DATA & IT4PROFIT'!K77 | R74: ='ALL DATA & IT4PROFIT'!D77
B75: ='ALL DATA & IT4PROFIT'!A78 -> FRONIUS | C75: ='ALL DATA & IT4PROFIT'!B78 -> SYMO 8.2-M | D75: ='ALL DATA & IT4PROFIT'!C78 -> 3PH | E75: 1 | F75: ='ALL DATA & IT4PROFIT'!J78 -> 1520 | G75: =F75+$G$193 -> 1545 | H75: =(G75*$E$193)+G75 -> 1583.625 | I75: =(J75-H75)/J75 -> 0.07 | J75: =H75/(1-M75) -> 1702.8226 | K75: =SUM(E75*J75) -> 1702.8226 | L75: =SUM(E75*H75) -> 1583.625 | M75: 0.07 | O75: =2950-2950*0.42 -> 1711 | P75: ='ALL DATA & IT4PROFIT'!H78 -> 1740 | Q75: ='ALL DATA & IT4PROFIT'!K78 | R75: ='ALL DATA & IT4PROFIT'!D78
B76: ='ALL DATA & IT4PROFIT'!A79 -> FRONIUS | C76: ='ALL DATA & IT4PROFIT'!B79 -> SYMO 10.0-M | D76: ='ALL DATA & IT4PROFIT'!C79 -> 3PH | E76: 1 | F76: ='ALL DATA & IT4PROFIT'!J79 -> 1600 | G76: =F76+$G$193 -> 1625 | H76: =(G76*$E$193)+G76 -> 1665.625 | I76: =(J76-H76)/J76 -> 0.07 | J76: =H76/(1-M76) -> 1790.9946 | K76: =SUM(E76*J76) -> 1790.9946 | L76: =SUM(E76*H76) -> 1665.625 | M76: 0.07 | O76: =3100-3100*0.42 -> 1798 | P76: ='ALL DATA & IT4PROFIT'!H79 -> 1895 | Q76: ='ALL DATA & IT4PROFIT'!K79 | R76: ='ALL DATA & IT4PROFIT'!D79
B77: ='ALL DATA & IT4PROFIT'!A80 -> FRONIUS | C77: ='ALL DATA & IT4PROFIT'!B80 -> SYMO 12.5-3-M | D77: ='ALL DATA & IT4PROFIT'!C80 -> 3PH | E77: 1 | F77: ='ALL DATA & IT4PROFIT'!J80 -> 1810 | G77: =F77+$G$193 -> 1835 | H77: =(G77*$E$193)+G77 -> 1880.875 | I77: =(J77-H77)/J77 -> 0.07 | J77: =H77/(1-M77) -> 2022.4462 | K77: =SUM(E77*J77) -> 2022.4462 | L77: =SUM(E77*H77) -> 1880.875 | M77: 0.07 | P77: ='ALL DATA & IT4PROFIT'!H80 | Q77: ='ALL DATA & IT4PROFIT'!K80 | R77: ='ALL DATA & IT4PROFIT'!D80
B78: ='ALL DATA & IT4PROFIT'!A81 -> FRONIUS | C78: ='ALL DATA & IT4PROFIT'!B81 -> SYMO 15.0-3-M | D78: ='ALL DATA & IT4PROFIT'!C81 -> 3PH | E78: 1 | F78: ='ALL DATA & IT4PROFIT'!J81 -> 1825 | G78: =F78+$G$193 -> 1850 | H78: =(G78*$E$193)+G78 -> 1896.25 | I78: =(J78-H78)/J78 -> 0.07 | J78: =H78/(1-M78) -> 2038.9785 | K78: =SUM(E78*J78) -> 2038.9785 | L78: =SUM(E78*H78) -> 1896.25 | M78: 0.07 | P78: ='ALL DATA & IT4PROFIT'!H81 | Q78: ='ALL DATA & IT4PROFIT'!K81 | R78: ='ALL DATA & IT4PROFIT'!D81
B79: ='ALL DATA & IT4PROFIT'!A82 -> FRONIUS | C79: ='ALL DATA & IT4PROFIT'!B82 -> SYMO 17.5-3-M | D79: ='ALL DATA & IT4PROFIT'!C82 -> 3PH | E79: 1 | F79: ='ALL DATA & IT4PROFIT'!J82 -> 1945 | G79: =F79+$G$193 -> 1970 | H79: =(G79*$E$193)+G79 -> 2019.25 | I79: =(J79-H79)/J79 -> 0.07 | J79: =H79/(1-M79) -> 2171.2366 | K79: =SUM(E79*J79) -> 2171.2366 | L79: =SUM(E79*H79) -> 2019.25 | M79: 0.07 | P79: ='ALL DATA & IT4PROFIT'!H82 | Q79: ='ALL DATA & IT4PROFIT'!K82 | R79: ='ALL DATA & IT4PROFIT'!D82
B80: ='ALL DATA & IT4PROFIT'!A83 -> FRONIUS | C80: ='ALL DATA & IT4PROFIT'!B83 -> SYMO 20.0-3-M | D80: ='ALL DATA & IT4PROFIT'!C83 -> 3PH | E80: 1 | F80: ='ALL DATA & IT4PROFIT'!J83 -> 2035 | G80: =F80+$G$193 -> 2060 | H80: =(G80*$E$193)+G80 -> 2111.5 | I80: =(J80-H80)/J80 -> 0.07 | J80: =H80/(1-M80) -> 2270.4301 | K80: =SUM(E80*J80) -> 2270.4301 | L80: =SUM(E80*H80) -> 2111.5 | M80: 0.07 | P80: ='ALL DATA & IT4PROFIT'!H83 | Q80: ='ALL DATA & IT4PROFIT'!K83 | R80: ='ALL DATA & IT4PROFIT'!D83
B81: ='ALL DATA & IT4PROFIT'!A84 | C81: ='ALL DATA & IT4PROFIT'!B84 | D81: ='ALL DATA & IT4PROFIT'!C84 | E81: 1 | F81: ='ALL DATA & IT4PROFIT'!J84 | G81: =F81+$G$193 -> 25 | H81: =(G81*$E$193)+G81 -> 25.625 | I81: =(J81-H81)/J81 -> 0.07 | J81: =H81/(1-M81) -> 27.553763 | K81: =SUM(E81*J81) -> 27.553763 | L81: =SUM(E81*H81) -> 25.625 | M81: 0.07 | P81: ='ALL DATA & IT4PROFIT'!H84 | Q81: ='ALL DATA & IT4PROFIT'!K84 | R81: ='ALL DATA & IT4PROFIT'!D84
B82: ='ALL DATA & IT4PROFIT'!A85 -> FRONIUS | C82: ='ALL DATA & IT4PROFIT'!B85 -> Fronius Symo GEN24 3.0 | D82: ='ALL DATA & IT4PROFIT'!C85 -> 3PH H lock | E82: 1 | F82: ='ALL DATA & IT4PROFIT'!J85 | G82: =F82+$G$193 -> 25 | H82: =(G82*$E$193)+G82 -> 25.625 | I82: =(J82-H82)/J82 -> 0.07 | J82: =H82/(1-M82) -> 27.553763 | K82: =SUM(E82*J82) -> 27.553763 | L82: =SUM(E82*H82) -> 25.625 | M82: 0.07 | P82: ='ALL DATA & IT4PROFIT'!H85 | Q82: ='ALL DATA & IT4PROFIT'!K85 | R82: ='ALL DATA & IT4PROFIT'!D85
B83: ='ALL DATA & IT4PROFIT'!A86 -> FRONIUS | C83: ='ALL DATA & IT4PROFIT'!B86 -> Fronius Symo GEN24 4.0 | D83: ='ALL DATA & IT4PROFIT'!C86 -> 3PH H lock | E83: 1 | F83: ='ALL DATA & IT4PROFIT'!J86 | G83: =F83+$G$193 -> 25 | H83: =(G83*$E$193)+G83 -> 25.625 | I83: =(J83-H83)/J83 -> 0.07 | J83: =H83/(1-M83) -> 27.553763 | K83: =SUM(E83*J83) -> 27.553763 | L83: =SUM(E83*H83) -> 25.625 | M83: 0.07 | P83: ='ALL DATA & IT4PROFIT'!H86 | Q83: ='ALL DATA & IT4PROFIT'!K86 | R83: ='ALL DATA & IT4PROFIT'!D86
B84: ='ALL DATA & IT4PROFIT'!A87 -> FRONIUS | C84: ='ALL DATA & IT4PROFIT'!B87 -> Fronius Symo GEN24 5.0 | D84: ='ALL DATA & IT4PROFIT'!C87 -> 3PH H lock | E84: 1 | F84: ='ALL DATA & IT4PROFIT'!J87 | G84: =F84+$G$193 -> 25 | H84: =(G84*$E$193)+G84 -> 25.625 | I84: =(J84-H84)/J84 -> 0.07 | J84: =H84/(1-M84) -> 27.553763 | K84: =SUM(E84*J84) -> 27.553763 | L84: =SUM(E84*H84) -> 25.625 | M84: 0.07 | P84: ='ALL DATA & IT4PROFIT'!H87 | Q84: ='ALL DATA & IT4PROFIT'!K87 | R84: ='ALL DATA & IT4PROFIT'!D87
B85: ='ALL DATA & IT4PROFIT'!A88 -> FRONIUS | C85: ='ALL DATA & IT4PROFIT'!B88 -> Fronius Symo GEN24 6.0 | D85: ='ALL DATA & IT4PROFIT'!C88 -> 3PH H lock | E85: 1 | F85: ='ALL DATA & IT4PROFIT'!J88 | G85: =F85+$G$193 -> 25 | H85: =(G85*$E$193)+G85 -> 25.625 | I85: =(J85-H85)/J85 -> 0.07 | J85: =H85/(1-M85) -> 27.553763 | K85: =SUM(E85*J85) -> 27.553763 | L85: =SUM(E85*H85) -> 25.625 | M85: 0.07 | P85: ='ALL DATA & IT4PROFIT'!H88 | Q85: ='ALL DATA & IT4PROFIT'!K88 | R85: ='ALL DATA & IT4PROFIT'!D88
B86: ='ALL DATA & IT4PROFIT'!A89 -> FRONIUS | C86: ='ALL DATA & IT4PROFIT'!B89 -> Fronius Symo GEN24 8.0 | D86: ='ALL DATA & IT4PROFIT'!C89 -> 3PH H lock | E86: 1 | F86: ='ALL DATA & IT4PROFIT'!J89 | G86: =F86+$G$193 -> 25 | H86: =(G86*$E$193)+G86 -> 25.625 | I86: =(J86-H86)/J86 -> 0.07 | J86: =H86/(1-M86) -> 27.553763 | K86: =SUM(E86*J86) -> 27.553763 | L86: =SUM(E86*H86) -> 25.625 | M86: 0.07 | P86: ='ALL DATA & IT4PROFIT'!H89 | Q86: ='ALL DATA & IT4PROFIT'!K89 | R86: ='ALL DATA & IT4PROFIT'!D89
B87: ='ALL DATA & IT4PROFIT'!A90 -> FRONIUS | C87: ='ALL DATA & IT4PROFIT'!B90 -> Fronius Symo GEN24 10.0 | D87: ='ALL DATA & IT4PROFIT'!C90 -> 3PH H lock | E87: 1 | F87: ='ALL DATA & IT4PROFIT'!J90 | G87: =F87+$G$193 -> 25 | H87: =(G87*$E$193)+G87 -> 25.625 | I87: =(J87-H87)/J87 -> 0.07 | J87: =H87/(1-M87) -> 27.553763 | K87: =SUM(E87*J87) -> 27.553763 | L87: =SUM(E87*H87) -> 25.625 | M87: 0.07 | P87: ='ALL DATA & IT4PROFIT'!H90 | Q87: ='ALL DATA & IT4PROFIT'!K90 | R87: ='ALL DATA & IT4PROFIT'!D90
B88: ='ALL DATA & IT4PROFIT'!A91 | C88: ='ALL DATA & IT4PROFIT'!B91 | D88: ='ALL DATA & IT4PROFIT'!C91 | E88: 1 | F88: ='ALL DATA & IT4PROFIT'!J91 | G88: =F88+$G$193 -> 25 | H88: =(G88*$E$193)+G88 -> 25.625 | I88: =(J88-H88)/J88 -> 0.07 | J88: =H88/(1-M88) -> 27.553763 | K88: =SUM(E88*J88) -> 27.553763 | L88: =SUM(E88*H88) -> 25.625 | M88: 0.07 | P88: ='ALL DATA & IT4PROFIT'!H91 | Q88: ='ALL DATA & IT4PROFIT'!K91 | R88: ='ALL DATA & IT4PROFIT'!D91
... B102: ='ALL DATA & IT4PROFIT'!A105 | C102: ='ALL DATA & IT4PROFIT'!B105 | D102: ='ALL DATA & IT4PROFIT'!C105 | E102: 1 | F102: ='ALL DATA & IT4PROFIT'!J105 | G102: =F102+$G$193 -> 25 | H102: =(G102*$E$193)+G102 -> 25.625 | I102: =(J102-H102)/J102 -> 0.07 | J102: =H102/(1-M102) -> 27.553763 | K102: =SUM(E102*J102) -> 27.553763 | L102: =SUM(E102*H102) -> 25.625 | M102: 0.07 | P102: ='ALL DATA & IT4PROFIT'!H105 | Q102: ='ALL DATA & IT4PROFIT'!K105 | R102: ='ALL DATA & IT4PROFIT'!D105
B103: ='ALL DATA & IT4PROFIT'!A125 -> SOLAREDGE | C103: ='ALL DATA & IT4PROFIT'!B125 -> SE 17 k SETAPP WITH PLASTIC COVER | D103: ='ALL DATA & IT4PROFIT'!C125 -> 3PH | E103: 1 | F103: ='ALL DATA & IT4PROFIT'!J125 | G103: =F103+$G$193 -> 25 | H103: =(G103*$E$193)+G103 -> 25.625 | I103: =(J103-H103)/J103 -> 0.07 | J103: =H103/(1-M103) -> 27.553763 | K103: =SUM(E103*J103) -> 27.553763 | L103: =SUM(E103*H103) -> 25.625 | M103: 0.07 | P103: ='ALL DATA & IT4PROFIT'!H125 | Q103: ='ALL DATA & IT4PROFIT'!K125 | R103: ='ALL DATA & IT4PROFIT'!D125
B104: ='ALL DATA & IT4PROFIT'!A126 -> SOLAREDGE | C104: ='ALL DATA & IT4PROFIT'!B126 -> SE20 k SETAPP | D104: ='ALL DATA & IT4PROFIT'!C126 -> 3PH | E104: 1 | F104: ='ALL DATA & IT4PROFIT'!J126 | G104: =F104+$G$193 -> 25 | H104: =(G104*$E$193)+G104 -> 25.625 | I104: =(J104-H104)/J104 -> 0.07 | J104: =H104/(1-M104) -> 27.553763 | K104: =SUM(E104*J104) -> 27.553763 | L104: =SUM(E104*H104) -> 25.625 | M104: 0.07 | P104: ='ALL DATA & IT4PROFIT'!H126 | Q104: ='ALL DATA & IT4PROFIT'!K126 | R104: ='ALL DATA & IT4PROFIT'!D126
B105: ='ALL DATA & IT4PROFIT'!$A$287 -> JINKO | C105: ='ALL DATA & IT4PROFIT'!$B$343 -> JinkoSolar JKM435N-54HL4R-V | D105: PV PANEL | E105: 36 | F105: ='ALL DATA & IT4PROFIT'!$J$343 -> 62.64 | G105: =F105+2 -> 64.64 | H105: =(G105*$E$193)+G105 -> 66.256 | I105: =(J105-H105)/J105 -> 0.1282 | J105: =H105/(1-M105) -> 75.999082 | K105: =SUM(E105*J105) -> 2735.967 | L105: =SUM(E105*H105) -> 2385.216 | M105: 0.1282 | P105: ='ALL DATA & IT4PROFIT'!H143 | Q105: ='ALL DATA & IT4PROFIT'!K143 | R105: ='ALL DATA & IT4PROFIT'!D143
B106: ='ALL DATA & IT4PROFIT'!$A$287 -> JINKO | C106: ='ALL DATA & IT4PROFIT'!B287 -> JKM440N-54HL4R | D106: PV PANEL | E106: 36 | F106: ='ALL DATA & IT4PROFIT'!S287 -> 63.8 | G106: =F106+$G$195 -> 71.8 | H106: =(G106*$E$193)+G106 -> 73.595 | I106: =(J106-H106)/J106 -> 0.07 | J106: =H106/(1-M106) -> 79.134409 | K106: =SUM(E106*J106) -> 2848.8387 | L106: =SUM(E106*H106) -> 2649.42 | M106: 0.07 | P106: ='ALL DATA & IT4PROFIT'!H144 | Q106: ='ALL DATA & IT4PROFIT'!K144 | R106: ='ALL DATA & IT4PROFIT'!D144
B107: ='ALL DATA & IT4PROFIT'!A288 -> LONGI | C107: ='ALL DATA & IT4PROFIT'!B288 -> LR5-72HTH 585 | D107: PV PANEL | E107: 31 | F107: ='ALL DATA & IT4PROFIT'!S288 -> 87.75 | G107: =F107+$G$195 -> 95.75 | H107: =(G107*$E$193)+G107 -> 98.14375 | I107: =(J107-H107)/J107 -> 0.07 | J107: =H107/(1-M107) -> 105.53091 | K107: =SUM(E107*J107) -> 3271.4583 | L107: =SUM(E107*H107) -> 3042.4563 | M107: 0.07 | P107: ='ALL DATA & IT4PROFIT'!H159 | Q107: ='ALL DATA & IT4PROFIT'!K159 | R107: ='ALL DATA & IT4PROFIT'!D159
B108: ='ALL DATA & IT4PROFIT'!A160 | C108: ='ALL DATA & IT4PROFIT'!B160 | D108: ='ALL DATA & IT4PROFIT'!C160 | E108: 1 | F108: ='ALL DATA & IT4PROFIT'!J160 | G108: =F108+$G$193 -> 25 | H108: =(G108*$E$193)+G108 -> 25.625 | I108: =(J108-H108)/J108 -> 0.07 | J108: =H108/(1-M108) -> 27.553763 | K108: =SUM(E108*J108) -> 27.553763 | L108: =SUM(E108*H108) -> 25.625 | M108: 0.07 | P108: ='ALL DATA & IT4PROFIT'!H160 | Q108: ='ALL DATA & IT4PROFIT'!K160 | R108: ='ALL DATA & IT4PROFIT'!D160
B109: ='ALL DATA & IT4PROFIT'!A161 | C109: ='ALL DATA & IT4PROFIT'!B161 | D109: ='ALL DATA & IT4PROFIT'!C161 | E109: 1 | F109: ='ALL DATA & IT4PROFIT'!J161 | G109: =F109+$G$193 -> 25 | H109: =(G109*$E$193)+G109 -> 25.625 | I109: =(J109-H109)/J109 -> 0.07 | J109: =H109/(1-M109) -> 27.553763 | K109: =SUM(E109*J109) -> 27.553763 | L109: =SUM(E109*H109) -> 25.625 | M109: 0.07 | P109: ='ALL DATA & IT4PROFIT'!H161 | Q109: ='ALL DATA & IT4PROFIT'!K161 | R109: ='ALL DATA & IT4PROFIT'!D161
B110: ='ALL DATA & IT4PROFIT'!A162 -> SOLAX | C110: ='ALL DATA & IT4PROFIT'!B162 -> X1 2.0-S-D(L) Mini G3 | D110: ='ALL DATA & IT4PROFIT'!C162 -> 1PH | E110: 1 | F110: ='ALL DATA & IT4PROFIT'!J162 | G110: =F110+$G$193 -> 25 | H110: =(G110*$E$193)+G110 -> 25.625 | I110: =(J110-H110)/J110 -> 0.07 | J110: =H110/(1-M110) -> 27.553763 | K110: =SUM(E110*J110) -> 27.553763 | L110: =SUM(E110*H110) -> 25.625 | M110: 0.07 | O110: =615-615*0.4 -> 369 | P110: ='ALL DATA & IT4PROFIT'!H162 | Q110: ='ALL DATA & IT4PROFIT'!K162 | R110: ='ALL DATA & IT4PROFIT'!D162
B111: ='ALL DATA & IT4PROFIT'!A163 -> SOLAX | C111: ='ALL DATA & IT4PROFIT'!B163 -> X1 3.3-T-D(L) BOOST | D111: ='ALL DATA & IT4PROFIT'!C163 -> 1PH | E111: 1 | F111: ='ALL DATA & IT4PROFIT'!J163 | G111: =F111+$G$193 -> 25 | H111: =(G111*$E$193)+G111 -> 25.625 | I111: =(J111-H111)/J111 -> 0.07 | J111: =H111/(1-M111) -> 27.553763 | K111: =SUM(E111*J111) -> 27.553763 | L111: =SUM(E111*H111) -> 25.625 | M111: 0.07 | O111: =920-920*0.4 -> 552 | P111: ='ALL DATA & IT4PROFIT'!H163 | Q111: ='ALL DATA & IT4PROFIT'!K163 | R111: ='ALL DATA & IT4PROFIT'!D163
B112: ='ALL DATA & IT4PROFIT'!A164 -> SOLAX | C112: ='ALL DATA & IT4PROFIT'!B164 -> X1 4.2-T-D(L) BOOST | D112: ='ALL DATA & IT4PROFIT'!C164 -> 1PH | E112: 1 | F112: ='ALL DATA & IT4PROFIT'!J164 | G112: =F112+$G$193 -> 25 | H112: =(G112*$E$193)+G112 -> 25.625 | I112: =(J112-H112)/J112 -> 0.07 | J112: =H112/(1-M112) -> 27.553763 | K112: =SUM(E112*J112) -> 27.553763 | L112: =SUM(E112*H112) -> 25.625 | M112: 0.07 | O112: =985-985*0.4 -> 591 | P112: ='ALL DATA & IT4PROFIT'!H164 | Q112: ='ALL DATA & IT4PROFIT'!K164 | R112: ='ALL DATA & IT4PROFIT'!D164
B113: ='ALL DATA & IT4PROFIT'!A165 -> SOLAX | C113: ='ALL DATA & IT4PROFIT'!B165 -> X1 5.0-T-D(L) BOOST | D113: ='ALL DATA & IT4PROFIT'!C165 -> 1PH | E113: 1 | F113: ='ALL DATA & IT4PROFIT'!J165 | G113: =F113+$G$193 -> 25 | H113: =(G113*$E$193)+G113 -> 25.625 | I113: =(J113-H113)/J113 -> 0.07 | J113: =H113/(1-M113) -> 27.553763 | K113: =SUM(E113*J113) -> 27.553763 | L113: =SUM(E113*H113) -> 25.625 | M113: 0.07 | O113: =1055-1055*0.4 -> 633 | P113: ='ALL DATA & IT4PROFIT'!H165 | Q113: ='ALL DATA & IT4PROFIT'!K165 | R113: ='ALL DATA & IT4PROFIT'!D165
B114: ='ALL DATA & IT4PROFIT'!A166 -> SOLAX | C114: ='ALL DATA & IT4PROFIT'!B166 -> X3-MIC-4.0K-G2 | D114: ='ALL DATA & IT4PROFIT'!C166 -> 3PH | E114: 1 | F114: ='ALL DATA & IT4PROFIT'!J166 | G114: =F114+$G$193 -> 25 | H114: =(G114*$E$193)+G114 -> 25.625 | I114: =(J114-H114)/J114 -> 0.07 | J114: =H114/(1-M114) -> 27.553763 | K114: =SUM(E114*J114) -> 27.553763 | L114: =SUM(E114*H114) -> 25.625 | M114: 0.07 | O114: =1465-1465*0.4 -> 879 | P114: ='ALL DATA & IT4PROFIT'!H166 | Q114: ='ALL DATA & IT4PROFIT'!K166 | R114: ='ALL DATA & IT4PROFIT'!D166
B115: ='ALL DATA & IT4PROFIT'!A167 -> SOLAX | C115: ='ALL DATA & IT4PROFIT'!B167 -> X3-MIC-5.0K-G2 | D115: ='ALL DATA & IT4PROFIT'!C167 -> 3PH | E115: 1 | F115: ='ALL DATA & IT4PROFIT'!J167 | G115: =F115+$G$193 -> 25 | H115: =(G115*$E$193)+G115 -> 25.625 | I115: =(J115-H115)/J115 -> 0.07 | J115: =H115/(1-M115) -> 27.553763 | K115: =SUM(E115*J115) -> 27.553763 | L115: =SUM(E115*H115) -> 25.625 | M115: 0.07 | O115: =1530-1530*0.4 -> 918 | P115: ='ALL DATA & IT4PROFIT'!H167 | Q115: ='ALL DATA & IT4PROFIT'!K167 | R115: ='ALL DATA & IT4PROFIT'!D167
B116: ='ALL DATA & IT4PROFIT'!A168 -> SOLAX | C116: ='ALL DATA & IT4PROFIT'!B168 -> X3-MIC-6.0K-G2 | D116: ='ALL DATA & IT4PROFIT'!C168 -> 3PH | E116: 1 | F116: ='ALL DATA & IT4PROFIT'!J168 | G116: =F116+$G$193 -> 25 | H116: =(G116*$E$193)+G116 -> 25.625 | I116: =(J116-H116)/J116 -> 0.07 | J116: =H116/(1-M116) -> 27.553763 | K116: =SUM(E116*J116) -> 27.553763 | L116: =SUM(E116*H116) -> 25.625 | M116: 0.07 | O116: =1625-1625*0.4 -> 975 | P116: ='ALL DATA & IT4PROFIT'!H168 | Q116: ='ALL DATA & IT4PROFIT'!K168 | R116: ='ALL DATA & IT4PROFIT'!D168
B117: ='ALL DATA & IT4PROFIT'!A169 -> SOLAX | C117: ='ALL DATA & IT4PROFIT'!B169 -> X3-MIC-8.0K-G2 | D117: ='ALL DATA & IT4PROFIT'!C169 -> 3PH | E117: 1 | F117: ='ALL DATA & IT4PROFIT'!J169 | G117: =F117+$G$193 -> 25 | H117: =(G117*$E$193)+G117 -> 25.625 | I117: =(J117-H117)/J117 -> 0.07 | J117: =H117/(1-M117) -> 27.553763 | K117: =SUM(E117*J117) -> 27.553763 | L117: =SUM(E117*H117) -> 25.625 | M117: 0.07 | O117: =1680-1680*0.4 -> 1008 | P117: ='ALL DATA & IT4PROFIT'!H169 | Q117: ='ALL DATA & IT4PROFIT'!K169 | R117: ='ALL DATA & IT4PROFIT'!D169
B118: ='ALL DATA & IT4PROFIT'!A170 -> SOLAX | C118: ='ALL DATA & IT4PROFIT'!B170 -> X3-MIC-10.0K-G2 | D118: ='ALL DATA & IT4PROFIT'!C170 -> 3PH | E118: 1 | F118: ='ALL DATA & IT4PROFIT'!J170 | G118: =F118+$G$193 -> 25 | H118: =(G118*$E$193)+G118 -> 25.625 | I118: =(J118-H118)/J118 -> 0.07 | J118: =H118/(1-M118) -> 27.553763 | K118: =SUM(E118*J118) -> 27.553763 | L118: =SUM(E118*H118) -> 25.625 | M118: 0.07 | O118: =1840-1840*0.4 -> 1104 | P118: ='ALL DATA & IT4PROFIT'!H170 | Q118: ='ALL DATA & IT4PROFIT'!K170 | R118: ='ALL DATA & IT4PROFIT'!D170
B119: ='ALL DATA & IT4PROFIT'!A171 -> SOLAX | C119: ='ALL DATA & IT4PROFIT'!B171 -> Pocket Wifi (2 years warranty) | D119: ='ALL DATA & IT4PROFIT'!C171 | E119: 1 | F119: ='ALL DATA & IT4PROFIT'!J171 | G119: =F119+$G$193 -> 25 | H119: =(G119*$E$193)+G119 -> 25.625 | I119: =(J119-H119)/J119 -> 0.07 | J119: =H119/(1-M119) -> 27.553763 | K119: =SUM(E119*J119) -> 27.553763 | L119: =SUM(E119*H119) -> 25.625 | M119: 0.07 | O119: =50-50*0.4 -> 30 | P119: ='ALL DATA & IT4PROFIT'!H171 | Q119: ='ALL DATA & IT4PROFIT'!K171 | R119: ='ALL DATA & IT4PROFIT'!D171
B120: ='ALL DATA & IT4PROFIT'!A172 -> SOLAX | C120: ='ALL DATA & IT4PROFIT'!B172 -> Pocket Lan 3.0 (2 years warranty) | D120: ='ALL DATA & IT4PROFIT'!C172 | E120: 1 | F120: ='ALL DATA & IT4PROFIT'!J172 | G120: =F120+$G$193 -> 25 | H120: =(G120*$E$193)+G120 -> 25.625 | I120: =(J120-H120)/J120 -> 0.07 | J120: =H120/(1-M120) -> 27.553763 | K120: =SUM(E120*J120) -> 27.553763 | L120: =SUM(E120*H120) -> 25.625 | M120: 0.07 | O120: =50-50*0.4 -> 30 | P120: ='ALL DATA & IT4PROFIT'!H172 | Q120: ='ALL DATA & IT4PROFIT'!K172 | R120: ='ALL DATA & IT4PROFIT'!D172
B121: ='ALL DATA & IT4PROFIT'!A173 | C121: ='ALL DATA & IT4PROFIT'!B173 | D121: ='ALL DATA & IT4PROFIT'!C173 | E121: 1 | F121: ='ALL DATA & IT4PROFIT'!J173 | G121: =F121+$G$193 -> 25 | H121: =(G121*$E$193)+G121 -> 25.625 | I121: =(J121-H121)/J121 -> 0.07 | J121: =H121/(1-M121) -> 27.553763 | K121: =SUM(E121*J121) -> 27.553763 | L121: =SUM(E121*H121) -> 25.625 | M121: 0.07 | P121: ='ALL DATA & IT4PROFIT'!H173 | Q121: ='ALL DATA & IT4PROFIT'!K173 | R121: ='ALL DATA & IT4PROFIT'!D173
B122: ='ALL DATA & IT4PROFIT'!A174 -> SMA | C122: ='ALL DATA & IT4PROFIT'!B174 -> SMA Hybrid Sunny Tripower 5.0 Smart Energy | D122: ='ALL DATA & IT4PROFIT'!C174 -> 3PH HYBRID | E122: 1 | F122: ='ALL DATA & IT4PROFIT'!J174 | G122: =F122+$G$193 -> 25 | H122: =(G122*$E$193)+G122 -> 25.625 | I122: =(J122-H122)/J122 -> 0.07 | J122: =H122/(1-M122) -> 27.553763 | K122: =SUM(E122*J122) -> 27.553763 | L122: =SUM(E122*H122) -> 25.625 | M122: 0.07 | P122: ='ALL DATA & IT4PROFIT'!H174 | Q122: ='ALL DATA & IT4PROFIT'!K174 | R122: ='ALL DATA & IT4PROFIT'!D174
B123: ='ALL DATA & IT4PROFIT'!A175 -> SMA | C123: ='ALL DATA & IT4PROFIT'!B175 -> SMA Hybrid Sunny Tripower 6.0 Smart Energy | D123: ='ALL DATA & IT4PROFIT'!C175 -> 3PH HYBRID | E123: 1 | F123: ='ALL DATA & IT4PROFIT'!J175 | G123: =F123+$G$193 -> 25 | H123: =(G123*$E$193)+G123 -> 25.625 | I123: =(J123-H123)/J123 -> 0.07 | J123: =H123/(1-M123) -> 27.553763 | K123: =SUM(E123*J123) -> 27.553763 | L123: =SUM(E123*H123) -> 25.625 | M123: 0.07 | P123: ='ALL DATA & IT4PROFIT'!H175 | Q123: ='ALL DATA & IT4PROFIT'!K175 | R123: ='ALL DATA & IT4PROFIT'!D175
B124: ='ALL DATA & IT4PROFIT'!A176 -> SMA | C124: ='ALL DATA & IT4PROFIT'!B176 -> SMA Hybrid Sunny Tripower 8.0 Smart Energy | D124: ='ALL DATA & IT4PROFIT'!C176 -> 3PH HYBRID | E124: 1 | F124: ='ALL DATA & IT4PROFIT'!J176 | G124: =F124+$G$193 -> 25 | H124: =(G124*$E$193)+G124 -> 25.625 | I124: =(J124-H124)/J124 -> 0.07 | J124: =H124/(1-M124) -> 27.553763 | K124: =SUM(E124*J124) -> 27.553763 | L124: =SUM(E124*H124) -> 25.625 | M124: 0.07 | P124: ='ALL DATA & IT4PROFIT'!H176 | Q124: ='ALL DATA & IT4PROFIT'!K176 | R124: ='ALL DATA & IT4PROFIT'!D176
B125: ='ALL DATA & IT4PROFIT'!A177 -> SMA | C125: ='ALL DATA & IT4PROFIT'!B177 -> SMA Hybrid Sunny Tripower 10.0 Smart Energy | D125: ='ALL DATA & IT4PROFIT'!C177 -> 3PH HYBRID | E125: 1 | F125: ='ALL DATA & IT4PROFIT'!J177 | G125: =F125+$G$193 -> 25 | H125: =(G125*$E$193)+G125 -> 25.625 | I125: =(J125-H125)/J125 -> 0.07 | J125: =H125/(1-M125) -> 27.553763 | K125: =SUM(E125*J125) -> 27.553763 | L125: =SUM(E125*H125) -> 25.625 | M125: 0.07 | P125: ='ALL DATA & IT4PROFIT'!H177 | Q125: ='ALL DATA & IT4PROFIT'!K177 | R125: ='ALL DATA & IT4PROFIT'!D177
B126: ='ALL DATA & IT4PROFIT'!A178 -> SMA | C126: ='ALL DATA & IT4PROFIT'!B178 -> SMA Sunny Boy 1.5 | D126: ='ALL DATA & IT4PROFIT'!C178 -> 1PH | E126: 1 | F126: ='ALL DATA & IT4PROFIT'!J178 | G126: =F126+$G$193 -> 25 | H126: =(G126*$E$193)+G126 -> 25.625 | I126: =(J126-H126)/J126 -> 0.07 | J126: =H126/(1-M126) -> 27.553763 | K126: =SUM(E126*J126) -> 27.553763 | L126: =SUM(E126*H126) -> 25.625 | M126: 0.07 | P126: ='ALL DATA & IT4PROFIT'!H178 | Q126: ='ALL DATA & IT4PROFIT'!K178 | R126: ='ALL DATA & IT4PROFIT'!D178
B127: ='ALL DATA & IT4PROFIT'!A179 -> SMA | C127: ='ALL DATA & IT4PROFIT'!B179 -> SMA Sunny Boy 2.5 | D127: ='ALL DATA & IT4PROFIT'!C179 -> 1PH | E127: 1 | F127: ='ALL DATA & IT4PROFIT'!J179 | G127: =F127+$G$193 -> 25 | H127: =(G127*$E$193)+G127 -> 25.625 | I127: =(J127-H127)/J127 -> 0.07 | J127: =H127/(1-M127) -> 27.553763 | K127: =SUM(E127*J127) -> 27.553763 | L127: =SUM(E127*H127) -> 25.625 | M127: 0.07 | P127: ='ALL DATA & IT4PROFIT'!H179 | Q127: ='ALL DATA & IT4PROFIT'!K179 | R127: ='ALL DATA & IT4PROFIT'!D179
B128: ='ALL DATA & IT4PROFIT'!A180 -> SMA | C128: ='ALL DATA & IT4PROFIT'!B180 -> SMA Sunny Boy 3.0 | D128: ='ALL DATA & IT4PROFIT'!C180 -> 1PH | E128: 1 | F128: ='ALL DATA & IT4PROFIT'!J180 | G128: =F128+$G$193 -> 25 | H128: =(G128*$E$193)+G128 -> 25.625 | I128: =(J128-H128)/J128 -> 0.07 | J128: =H128/(1-M128) -> 27.553763 | K128: =SUM(E128*J128) -> 27.553763 | L128: =SUM(E128*H128) -> 25.625 | M128: 0.07 | P128: ='ALL DATA & IT4PROFIT'!H180 | Q128: ='ALL DATA & IT4PROFIT'!K180 | R128: ='ALL DATA & IT4PROFIT'!D180
...

Sheet Inverter price analysis Krannic
A1: BEU: | C1: Partner: | G1: Location: | P1: COMPETITION PRICES
G2: *distr.price+freight | J2: *devide (LCP CY)/(1-GM)
B3: Brand | C3: Description | D3: Type | E3: QTY | F3: Distributor Krannich Price | G3: LCP CY (€) | H3: Final LCP CY | I3: ASKY GM % | J3: Final Price to Customer | K3: Revenue | L3: LCP CY Revenue | M3: Desired GM | N3: LANITIS ENERGY | O3: BIG SOLAR | P3: DR. ENERGY | Q3: TRIKKIS ENERGY | R3: KAFKAS
B4: ='ALL DATA & IT4PROFIT'!A6 -> HUAWEI | C4: ='ALL DATA & IT4PROFIT'!B6 -> SUN2000-2KTL-L1 | D4: ='ALL DATA & IT4PROFIT'!C6 -> 1PH HYBRID | E4: 1 | F4: ='ALL DATA & IT4PROFIT'!F6 -> 0 | G4: =F4+$G$204 -> 30 | H4: =(G4*$E$204)+G4 -> 30.75 | I4: =(J4-H4)/J4 -> 0.07 | J4: =H4/(1-M4) -> 33.064516 | K4: =SUM(E4*J4) -> 33.064516 | L4: =SUM(E4*H4) -> 30.75 | M4: 0.07 | N4: ='ALL DATA & IT4PROFIT'!L6 -> 420 | P4: ='ALL DATA & IT4PROFIT'!H6 -> 557 | Q4: ='ALL DATA & IT4PROFIT'!K6 -> 344 | R4: ='ALL DATA & IT4PROFIT'!D6 -> 489
B5: ='ALL DATA & IT4PROFIT'!A7 -> HUAWEI | C5: ='ALL DATA & IT4PROFIT'!B7 -> SUN2000-3KTL-L1 | D5: ='ALL DATA & IT4PROFIT'!C7 -> 1PH HYBRID | E5: 1 | F5: ='ALL DATA & IT4PROFIT'!F7 -> 355.8 | G5: =F5+$G$204 -> 385.8 | H5: =(G5*$E$204)+G5 -> 395.445 | I5: =(J5-H5)/J5 -> 0.20911 | J5: =H5/(1-M5) -> 500 | K5: =SUM(E5*J5) -> 500 | L5: =SUM(E5*H5) -> 395.445 | M5: 0.20911 | N5: ='ALL DATA & IT4PROFIT'!L7 -> 510 | P5: ='ALL DATA & IT4PROFIT'!H7 -> 545 | Q5: ='ALL DATA & IT4PROFIT'!K7 -> 432 | R5: ='ALL DATA & IT4PROFIT'!D7 -> 575
B6: ='ALL DATA & IT4PROFIT'!A8 -> HUAWEI | C6: ='ALL DATA & IT4PROFIT'!B8 -> SUN2000-3.68KTL-L1 | D6: ='ALL DATA & IT4PROFIT'!C8 -> 1PH HYBRID | E6: 1 | F6: ='ALL DATA & IT4PROFIT'!F8 -> 0 | G6: =F6+$G$204 -> 30 | H6: =(G6*$E$204)+G6 -> 30.75 | I6: =(J6-H6)/J6 -> 0.05 | J6: =H6/(1-M6) -> 32.368421 | K6: =SUM(E6*J6) -> 32.368421 | L6: =SUM(E6*H6) -> 30.75 | M6: 0.05 | N6: ='ALL DATA & IT4PROFIT'!L8 -> 580 | P6: ='ALL DATA & IT4PROFIT'!H8 | Q6: ='ALL DATA & IT4PROFIT'!K8 | R6: ='ALL DATA & IT4PROFIT'!D8 -> 677
B7: ='ALL DATA & IT4PROFIT'!A9 -> HUAWEI | C7: ='ALL DATA & IT4PROFIT'!B9 -> SUN2000-4KTL-L1 | D7: ='ALL DATA & IT4PROFIT'!C9 -> 1PH HYBRID | E7: 1 | F7: ='ALL DATA & IT4PROFIT'!F9 -> 417.6 | G7: =F7+$G$204 -> 447.6 | H7: =(G7*$E$204)+G7 -> 458.79 | I7: =(J7-H7)/J7 -> 0.18073 | J7: =H7/(1-M7) -> 559.99854 | K7: =SUM(E7*J7) -> 559.99854 | L7: =SUM(E7*H7) -> 458.79 | M7: 0.18073 | N7: ='ALL DATA & IT4PROFIT'!L9 -> 620 | P7: ='ALL DATA & IT4PROFIT'!H9 -> 580 | Q7: ='ALL DATA & IT4PROFIT'!K9 -> 563 | R7: ='ALL DATA & IT4PROFIT'!D9 -> 705
B8: ='ALL DATA & IT4PROFIT'!A10 -> HUAWEI | C8: ='ALL DATA & IT4PROFIT'!B10 -> SUN2000-4.6KTL-L1 | D8: ='ALL DATA & IT4PROFIT'!C10 -> 1PH HYBRID | E8: 1 | F8: ='ALL DATA & IT4PROFIT'!F10 -> 518.4 | G8: =F8+$G$204 -> 548.4 | H8: =(G8*$E$204)+G8 -> 562.11 | I8: =(J8-H8)/J8 -> 0.10063 | J8: =H8/(1-M8) -> 625.00417 | K8: =SUM(E8*J8) -> 625.00417 | L8: =SUM(E8*H8) -> 562.11 | M8: 0.10063 | N8: ='ALL DATA & IT4PROFIT'!L10 -> 645 | P8: ='ALL DATA & IT4PROFIT'!H10 -> 595 | Q8: ='ALL DATA & IT4PROFIT'!K10 -> 616 | R8: ='ALL DATA & IT4PROFIT'!D10 -> 756
B9: ='ALL DATA & IT4PROFIT'!A11 -> HUAWEI | C9: ='ALL DATA & IT4PROFIT'!B11 -> SUN2000-5KTL-L1 | D9: ='ALL DATA & IT4PROFIT'!C11 -> 1PH HYBRID | E9: 1 | F9: ='ALL DATA & IT4PROFIT'!F11 -> 465.6 | G9: =F9+$G$204 -> 495.6 | H9: =(G9*$E$204)+G9 -> 507.99 | I9: =(J9-H9)/J9 -> 0.20001 | J9: =H9/(1-M9) -> 634.99544 | K9: =SUM(E9*J9) -> 634.99544 | L9: =SUM(E9*H9) -> 507.99 | M9: 0.20001 | N9: ='ALL DATA & IT4PROFIT'!L11 -> 660 | P9: ='ALL DATA & IT4PROFIT'!H11 -> 620 | Q9: ='ALL DATA & IT4PROFIT'!K11 -> 624 | R9: ='ALL DATA & IT4PROFIT'!D11 -> 764
B10: ='ALL DATA & IT4PROFIT'!A12 -> HUAWEI | C10: ='ALL DATA & IT4PROFIT'!B12 -> SUN2000-6KTL-L1 | D10: ='ALL DATA & IT4PROFIT'!C12 -> 1PH HYBRID | E10: 1 | F10: ='ALL DATA & IT4PROFIT'!F12 -> 445.8 | G10: =F10+$G$204 -> 475.8 | H10: =(G10*$E$204)+G10 -> 487.695 | I10: =(J10-H10)/J10 -> 0 | J10: =H10/(1-M10) -> 487.695 | K10: =SUM(E10*J10) -> 487.695 | L10: =SUM(E10*H10) -> 487.695 | N10: ='ALL DATA & IT4PROFIT'!L12 | P10: ='ALL DATA & IT4PROFIT'!H12 | Q10: ='ALL DATA & IT4PROFIT'!K12 | R10: ='ALL DATA & IT4PROFIT'!D12 -> 868
B11: ='ALL DATA & IT4PROFIT'!A13 -> HUAWEI | C11: ='ALL DATA & IT4PROFIT'!B13 -> SUN2000-3KTL-M1 | D11: ='ALL DATA & IT4PROFIT'!C13 -> 3PH HYBRID | E11: 1 | F11: ='ALL DATA & IT4PROFIT'!F13 -> 808.2 | G11: =F11+$G$204 -> 838.2 | H11: =(G11*$E$204)+G11 -> 859.155 | I11: =(J11-H11)/J11 -> 0.05 | J11: =H11/(1-M11) -> 904.37368 | K11: =SUM(E11*J11) -> 904.37368 | L11: =SUM(E11*H11) -> 859.155 | M11: 0.05 | N11: ='ALL DATA & IT4PROFIT'!L13 -> 845 | P11: ='ALL DATA & IT4PROFIT'!H13 -> 907 | Q11: ='ALL DATA & IT4PROFIT'!K13 -> 832 | R11: ='ALL DATA & IT4PROFIT'!D13 -> 880
B12: ='ALL DATA & IT4PROFIT'!A14 -> HUAWEI | C12: ='ALL DATA & IT4PROFIT'!B14 -> SUN2000-4KTL-M1 | D12: ='ALL DATA & IT4PROFIT'!C14 -> 3PH HYBRID | E12: 1 | F12: ='ALL DATA & IT4PROFIT'!F14 -> 844.8 | G12: =F12+$G$204 -> 874.8 | H12: =(G12*$E$204)+G12 -> 896.67 | I12: =(J12-H12)/J12 -> 0.05 | J12: =H12/(1-M12) -> 943.86316 | K12: =SUM(E12*J12) -> 943.86316 | L12: =SUM(E12*H12) -> 896.67 | M12: 0.05 | N12: ='ALL DATA & IT4PROFIT'!L14 -> 880 | P12: ='ALL DATA & IT4PROFIT'!H14 -> 906 | Q12: ='ALL DATA & IT4PROFIT'!K14 -> 871 | R12: ='ALL DATA & IT4PROFIT'!D14 -> 920
B13: ='ALL DATA & IT4PROFIT'!A15 -> HUAWEI | C13: ='ALL DATA & IT4PROFIT'!B15 -> SUN2000-5KTL-M1 | D13: ='ALL DATA & IT4PROFIT'!C15 -> 3PH HYBRID | E13: 1 | F13: ='ALL DATA & IT4PROFIT'!F15 -> 891 | G13: =F13+$G$204 -> 921 | H13: =(G13*$E$204)+G13 -> 944.025 | I13: =(J13-H13)/J13 -> 0.05 | J13: =H13/(1-M13) -> 993.71053 | K13: =SUM(E13*J13) -> 993.71053 | L13: =SUM(E13*H13) -> 944.025 | M13: 0.05 | N13: ='ALL DATA & IT4PROFIT'!L15 -> 930 | P13: ='ALL DATA & IT4PROFIT'!H15 -> 930 | Q13: ='ALL DATA & IT4PROFIT'!K15 -> 919 | R13: ='ALL DATA & IT4PROFIT'!D15 -> 971
B14: ='ALL DATA & IT4PROFIT'!A16 -> HUAWEI | C14: ='ALL DATA & IT4PROFIT'!B16 -> SUN2000-6KTL-M1 | D14: ='ALL DATA & IT4PROFIT'!C16 -> 3PH HYBRID | E14: 1 | F14: ='ALL DATA & IT4PROFIT'!F16 -> 996 | G14: =F14+$G$204 -> 1026 | H14: =(G14*$E$204)+G14 -> 1051.65 | I14: =(J14-H14)/J14 -> 0.05 | J14: =H14/(1-M14) -> 1107 | K14: =SUM(E14*J14) -> 1107 | L14: =SUM(E14*H14) -> 1051.65 | M14: 0.05 | N14: ='ALL DATA & IT4PROFIT'!L16 -> 1040 | P14: ='ALL DATA & IT4PROFIT'!H16 -> 1090 | Q14: ='ALL DATA & IT4PROFIT'!K16 -> 1028 | R14: ='ALL DATA & IT4PROFIT'!D16 -> 1086
B15: ='ALL DATA & IT4PROFIT'!A17 -> HUAWEI | C15: ='ALL DATA & IT4PROFIT'!B17 -> SUN2000-8KTL-M1 | D15: ='ALL DATA & IT4PROFIT'!C17 -> 3PH HYBRID | E15: 1 | F15: ='ALL DATA & IT4PROFIT'!F17 -> 1179.6 | G15: =F15+$G$204 -> 1209.6 | H15: =(G15*$E$204)+G15 -> 1239.84 | I15: =(J15-H15)/J15 -> 0.05 | J15: =H15/(1-M15) -> 1305.0947 | K15: =SUM(E15*J15) -> 1305.0947 | L15: =SUM(E15*H15) -> 1239.84 | M15: 0.05 | N15: ='ALL DATA & IT4PROFIT'!L17 -> 1235 | P15: ='ALL DATA & IT4PROFIT'!H17 -> 1260 | Q15: ='ALL DATA & IT4PROFIT'!K17 -> 1219 | R15: ='ALL DATA & IT4PROFIT'!D17 -> 1289
B16: ='ALL DATA & IT4PROFIT'!A18 -> HUAWEI | C16: ='ALL DATA & IT4PROFIT'!B18 -> SUN2000-10KTL-M1 | D16: ='ALL DATA & IT4PROFIT'!C18 -> 3PH HYBRID | E16: 1 | F16: ='ALL DATA & IT4PROFIT'!F18 -> 1324.2 | G16: =F16+$G$204 -> 1354.2 | H16: =(G16*$E$204)+G16 -> 1388.055 | I16: =(J16-H16)/J16 -> 0.05 | J16: =H16/(1-M16) -> 1461.1105 | K16: =SUM(E16*J16) -> 1461.1105 | L16: =SUM(E16*H16) -> 1388.055 | M16: 0.05 | N16: ='ALL DATA & IT4PROFIT'!L18 -> 1385 | P16: ='ALL DATA & IT4PROFIT'!H18 -> 1385 | Q16: ='ALL DATA & IT4PROFIT'!K18 -> 1369 | R16: ='ALL DATA & IT4PROFIT'!D18 -> 1448
B17: ='ALL DATA & IT4PROFIT'!A19 -> HUAWEI | C17: ='ALL DATA & IT4PROFIT'!B19 -> SUN2000-12KTL-M5 | D17: ='ALL DATA & IT4PROFIT'!C19 -> 3PH HYBRID | E17: 1 | F17: ='ALL DATA & IT4PROFIT'!F19 -> 1387.2 | G17: =F17+$G$204 -> 1417.2 | H17: =(G17*$E$204)+G17 -> 1452.63 | I17: =(J17-H17)/J17 -> 0.05 | J17: =H17/(1-M17) -> 1529.0842 | K17: =SUM(E17*J17) -> 1529.0842 | L17: =SUM(E17*H17) -> 1452.63 | M17: 0.05 | N17: ='ALL DATA & IT4PROFIT'!L19 -> 1450 | P17: ='ALL DATA & IT4PROFIT'!H19 | Q17: ='ALL DATA & IT4PROFIT'!K19 -> 947.6 | R17: ='ALL DATA & IT4PROFIT'!D19 -> 1515
B18: ='ALL DATA & IT4PROFIT'!A20 -> HUAWEI | C18: ='ALL DATA & IT4PROFIT'!B20 -> SUN2000-15KTL-M5 | D18: ='ALL DATA & IT4PROFIT'!C20 -> 3PH HYBRID | E18: 1 | F18: ='ALL DATA & IT4PROFIT'!F20 -> 1564.2 | G18: =F18+$G$204 -> 1594.2 | H18: =(G18*$E$204)+G18 -> 1634.055 | I18: =(J18-H18)/J18 -> 0.05 | J18: =H18/(1-M18) -> 1720.0579 | K18: =SUM(E18*J18) -> 1720.0579 | L18: =SUM(E18*H18) -> 1634.055 | M18: 0.05 | N18: ='ALL DATA & IT4PROFIT'!L20 -> 1640 | P18: ='ALL DATA & IT4PROFIT'!H20 | Q18: ='ALL DATA & IT4PROFIT'!K20 -> 1133.5 | R18: ='ALL DATA & IT4PROFIT'!D20 -> 1710
B19: ='ALL DATA & IT4PROFIT'!A21 -> HUAWEI | C19: ='ALL DATA & IT4PROFIT'!B21 -> SUN2000-17KTL-M5 | D19: ='ALL DATA & IT4PROFIT'!C21 -> 3PH HYBRID | E19: 1 | F19: ='ALL DATA & IT4PROFIT'!F21 -> 1597.2 | G19: =F19+$G$204 -> 1627.2 | H19: =(G19*$E$204)+G19 -> 1667.88 | I19: =(J19-H19)/J19 -> 0.05 | J19: =H19/(1-M19) -> 1755.6632 | K19: =SUM(E19*J19) -> 1755.6632 | L19: =SUM(E19*H19) -> 1667.88 | M19: 0.05 | N19: ='ALL DATA & IT4PROFIT'!L21 -> 1675 | P19: ='ALL DATA & IT4PROFIT'!H21 | Q19: ='ALL DATA & IT4PROFIT'!K21 -> 1167.6 | R19: ='ALL DATA & IT4PROFIT'!D21 -> 1447
B20: ='ALL DATA & IT4PROFIT'!A22 -> HUAWEI | C20: ='ALL DATA & IT4PROFIT'!B22 -> SUN2000-20KTL-M5 | D20: ='ALL DATA & IT4PROFIT'!C22 -> 3PH HYBRID | E20: 1 | F20: ='ALL DATA & IT4PROFIT'!F22 -> 1687.2 | G20: =F20+$G$204 -> 1717.2 | H20: =(G20*$E$204)+G20 -> 1760.13 | I20: =(J20-H20)/J20 -> 0.05 | J20: =H20/(1-M20) -> 1852.7684 | K20: =SUM(E20*J20) -> 1852.7684 | L20: =SUM(E20*H20) -> 1760.13 | M20: 0.05 | N20: ='ALL DATA & IT4PROFIT'!L22 -> 1790 | P20: ='ALL DATA & IT4PROFIT'!H22 | Q20: ='ALL DATA & IT4PROFIT'!K22 -> 1262.2 | R20: ='ALL DATA & IT4PROFIT'!D22 -> 1844
B21: ='ALL DATA & IT4PROFIT'!A23 -> HUAWEI | C21: ='ALL DATA & IT4PROFIT'!B23 -> SUN2000-25KTL-M5 | D21: ='ALL DATA & IT4PROFIT'!C23 -> 3PH HYBRID | E21: 1 | F21: ='ALL DATA & IT4PROFIT'!F23 -> 1742.4 | G21: =F21+$G$204 -> 1772.4 | H21: =(G21*$E$204)+G21 -> 1816.71 | I21: =(J21-H21)/J21 -> 0.05 | J21: =H21/(1-M21) -> 1912.3263 | K21: =SUM(E21*J21) -> 1912.3263 | L21: =SUM(E21*H21) -> 1816.71 | M21: 0.05 | N21: ='ALL DATA & IT4PROFIT'!L23 -> 1825 | P21: ='ALL DATA & IT4PROFIT'!H23 | Q21: ='ALL DATA & IT4PROFIT'!K23 -> 1320.5 | R21: ='ALL DATA & IT4PROFIT'!D23 -> 1906
B22: ='ALL DATA & IT4PROFIT'!A24 -> HUAWEI | C22: ='ALL DATA & IT4PROFIT'!B24 -> SUN2000-30KTL-M3 | D22: ='ALL DATA & IT4PROFIT'!C24 -> 3PH HYBRID | E22: 1 | F22: ='ALL DATA & IT4PROFIT'!F24 -> 1926 | G22: =F22+$G$204 -> 1956 | H22: =(G22*$E$204)+G22 -> 2004.9 | I22: =(J22-H22)/J22 -> 0.05 | J22: =H22/(1-M22) -> 2110.4211 | K22: =SUM(E22*J22) -> 2110.4211 | L22: =SUM(E22*H22) -> 2004.9 | M22: 0.05 | N22: ='ALL DATA & IT4PROFIT'!L24 -> 2080 | P22: ='ALL DATA & IT4PROFIT'!H24 | Q22: ='ALL DATA & IT4PROFIT'!K24 -> 1993 | R22: ='ALL DATA & IT4PROFIT'!D24 -> 2106
... B31: ='ALL DATA & IT4PROFIT'!A33 -> HUAWEI | C31: ='ALL DATA & IT4PROFIT'!B33 -> SUN2000-20KTL-MBO | D31: ='ALL DATA & IT4PROFIT'!C33 -> 3PH HYBRID | E31: 1 | F31: ='ALL DATA & IT4PROFIT'!F33 -> 2034 | G31: =F31+$G$204 -> 2064 | H31: =(G31*$E$204)+G31 -> 2115.6 | I31: =(J31-H31)/J31 -> 0.05 | J31: =H31/(1-M31) -> 2226.9474 | K31: =SUM(E31*J31) -> 2226.9474 | L31: =SUM(E31*H31) -> 2115.6 | M31: 0.05 | N31: ='ALL DATA & IT4PROFIT'!L33 -> 2150 | P31: ='ALL DATA & IT4PROFIT'!H33 | Q31: ='ALL DATA & IT4PROFIT'!K33 | R31: ='ALL DATA & IT4PROFIT'!D33
B32: ='ALL DATA & IT4PROFIT'!A35 -> HUAWEI | C32: ='ALL DATA & IT4PROFIT'!B35 -> SUN2000-450W-P2 | D32: ='ALL DATA & IT4PROFIT'!C35 -> OPTIMIZER | E32: 1 | F32: ='ALL DATA & IT4PROFIT'!F35 -> 36 | G32: =F32+$G$205 -> 39 | H32: =(G32*$E$204)+G32 -> 39.975 | I32: =(J32-H32)/J32 -> 0.1117 | J32: =H32/(1-M32) -> 45.001689 | K32: =SUM(E32*J32) -> 45.001689 | L32: =SUM(E32*H32) -> 39.975 | M32: 0.1117 | N32: ='ALL DATA & IT4PROFIT'!L35 -> 40 | P32: ='ALL DATA & IT4PROFIT'!H35 | Q32: ='ALL DATA & IT4PROFIT'!K35 -> 38.5 | R32: ='ALL DATA & IT4PROFIT'!D35 -> 41
B33: ='ALL DATA & IT4PROFIT'!A36 -> HUAWEI | C33: ='ALL DATA & IT4PROFIT'!B36 -> SUN2000-600W-P | D33: ='ALL DATA & IT4PROFIT'!C36 -> OPTIMIZER | E33: 1 | F33: ='ALL DATA & IT4PROFIT'!F36 -> 39 | G33: =F33+$G$205 -> 42 | H33: =(G33*$E$204)+G33 -> 43.05 | I33: =(J33-H33)/J33 -> 0.103 | J33: =H33/(1-M33) -> 47.993311 | K33: =SUM(E33*J33) -> 47.993311 | L33: =SUM(E33*H33) -> 43.05 | M33: 0.103 | N33: ='ALL DATA & IT4PROFIT'!L36 -> 40 | P33: ='ALL DATA & IT4PROFIT'!H36 | Q33: ='ALL DATA & IT4PROFIT'!K36 -> 39 | R33: ='ALL DATA & IT4PROFIT'!D36 -> 41
B34: ='ALL DATA & IT4PROFIT'!A37 | C34: ='ALL DATA & IT4PROFIT'!B37 | D34: ='ALL DATA & IT4PROFIT'!C37 | E34: 1 | F34: ='ALL DATA & IT4PROFIT'!F37 | G34: =F34+$G$204 -> 30 | H34: =(G34*$E$204)+G34 -> 30.75 | I34: =(J34-H34)/J34 -> 0.1 | J34: =H34/(1-M34) -> 34.166667 | K34: =SUM(E34*J34) -> 34.166667 | L34: =SUM(E34*H34) -> 30.75 | M34: 0.1 | N34: ='ALL DATA & IT4PROFIT'!L37 | P34: ='ALL DATA & IT4PROFIT'!H37 | Q34: ='ALL DATA & IT4PROFIT'!K37 | R34: ='ALL DATA & IT4PROFIT'!D37
B35: ='ALL DATA & IT4PROFIT'!A38 | C35: ='ALL DATA & IT4PROFIT'!B38 | D35: ='ALL DATA & IT4PROFIT'!C38 | E35: 1 | F35: ='ALL DATA & IT4PROFIT'!F38 | G35: =F35+$G$204 -> 30 | H35: =(G35*$E$204)+G35 -> 30.75 | I35: =(J35-H35)/J35 -> 0.1 | J35: =H35/(1-M35) -> 34.166667 | K35: =SUM(E35*J35) -> 34.166667 | L35: =SUM(E35*H35) -> 30.75 | M35: 0.1 | N35: ='ALL DATA & IT4PROFIT'!L38 | P35: ='ALL DATA & IT4PROFIT'!H38 | Q35: ='ALL DATA & IT4PROFIT'!K38 | R35: ='ALL DATA & IT4PROFIT'!D38
B36: ='ALL DATA & IT4PROFIT'!A39 -> SUNGROW | C36: ='ALL DATA & IT4PROFIT'!B39 -> IV SUNG SG2.0RS | D36: ='ALL DATA & IT4PROFIT'!C39 -> 1PH | E36: 1 | F36: ='ALL DATA & IT4PROFIT'!F39 -> 393 | G36: =F36+$G$204 -> 423 | H36: =(G36*$E$204)+G36 -> 433.575 | I36: =(J36-H36)/J36 -> 0.1 | J36: =H36/(1-M36) -> 481.75 | K36: =SUM(E36*J36) -> 481.75 | L36: =SUM(E36*H36) -> 433.575 | M36: 0.1 | N36: ='ALL DATA & IT4PROFIT'!L39 | P36: ='ALL DATA & IT4PROFIT'!H39 | Q36: ='ALL DATA & IT4PROFIT'!K39 | R36: ='ALL DATA & IT4PROFIT'!D39
B37: ='ALL DATA & IT4PROFIT'!A40 -> SUNGROW | C37: ='ALL DATA & IT4PROFIT'!B40 -> IV SUNG SG3.0RS | D37: ='ALL DATA & IT4PROFIT'!C40 -> 1PH | E37: 1 | F37: ='ALL DATA & IT4PROFIT'!F40 -> 462 | G37: =F37+$G$204 -> 492 | H37: =(G37*$E$204)+G37 -> 504.3 | I37: =(J37-H37)/J37 -> 0.1 | J37: =H37/(1-M37) -> 560.33333 | K37: =SUM(E37*J37) -> 560.33333 | L37: =SUM(E37*H37) -> 504.3 | M37: 0.1 | N37: ='ALL DATA & IT4PROFIT'!L40 | P37: ='ALL DATA & IT4PROFIT'!H40 | Q37: ='ALL DATA & IT4PROFIT'!K40 | R37: ='ALL DATA & IT4PROFIT'!D40
B38: ='ALL DATA & IT4PROFIT'!A41 -> SUNGROW | C38: ='ALL DATA & IT4PROFIT'!B41 -> IV SUNG SG4.0RS | D38: ='ALL DATA & IT4PROFIT'!C41 -> 1PH | E38: 1 | F38: ='ALL DATA & IT4PROFIT'!F41 -> 549.6 | G38: =F38+$G$204 -> 579.6 | H38: =(G38*$E$204)+G38 -> 594.09 | I38: =(J38-H38)/J38 -> 0.1 | J38: =H38/(1-M38) -> 660.1 | K38: =SUM(E38*J38) -> 660.1 | L38: =SUM(E38*H38) -> 594.09 | M38: 0.1 | N38: ='ALL DATA & IT4PROFIT'!L41 | P38: ='ALL DATA & IT4PROFIT'!H41 | Q38: ='ALL DATA & IT4PROFIT'!K41 | R38: ='ALL DATA & IT4PROFIT'!D41
B39: ='ALL DATA & IT4PROFIT'!A42 -> SUNGROW | C39: ='ALL DATA & IT4PROFIT'!B42 -> IV SUNG SG5.0RS | D39: ='ALL DATA & IT4PROFIT'!C42 -> 1PH | E39: 1 | F39: ='ALL DATA & IT4PROFIT'!F42 -> 593.4 | G39: =F39+$G$204 -> 623.4 | H39: =(G39*$E$204)+G39 -> 638.985 | I39: =(J39-H39)/J39 -> 0.1 | J39: =H39/(1-M39) -> 709.98333 | K39: =SUM(E39*J39) -> 709.98333 | L39: =SUM(E39*H39) -> 638.985 | M39: 0.1 | N39: ='ALL DATA & IT4PROFIT'!L42 | P39: ='ALL DATA & IT4PROFIT'!H42 | Q39: ='ALL DATA & IT4PROFIT'!K42 | R39: ='ALL DATA & IT4PROFIT'!D42
B40: ='ALL DATA & IT4PROFIT'!A43 -> SUNGROW | C40: ='ALL DATA & IT4PROFIT'!B43 -> IV SUNG SG3.0RT | D40: ='ALL DATA & IT4PROFIT'!C43 -> 3PH | E40: 1 | F40: ='ALL DATA & IT4PROFIT'!F43 -> 648 | G40: =F40+$G$204 -> 678 | H40: =(G40*$E$204)+G40 -> 694.95 | I40: =(J40-H40)/J40 -> 0.1 | J40: =H40/(1-M40) -> 772.16667 | K40: =SUM(E40*J40) -> 772.16667 | L40: =SUM(E40*H40) -> 694.95 | M40: 0.1 | N40: ='ALL DATA & IT4PROFIT'!L43 | P40: ='ALL DATA & IT4PROFIT'!H43 | Q40: ='ALL DATA & IT4PROFIT'!K43 | R40: ='ALL DATA & IT4PROFIT'!D43
B41: ='ALL DATA & IT4PROFIT'!A44 -> SUNGROW | C41: ='ALL DATA & IT4PROFIT'!B44 -> IV SUNG SG4.0RT | D41: ='ALL DATA & IT4PROFIT'!C44 -> 3PH | E41: 1 | F41: ='ALL DATA & IT4PROFIT'!F44 -> 683.4 | G41: =F41+$G$204 -> 713.4 | H41: =(G41*$E$204)+G41 -> 731.235 | I41: =(J41-H41)/J41 -> 0.1 | J41: =H41/(1-M41) -> 812.48333 | K41: =SUM(E41*J41) -> 812.48333 | L41: =SUM(E41*H41) -> 731.235 | M41: 0.1 | N41: ='ALL DATA & IT4PROFIT'!L44 | P41: ='ALL DATA & IT4PROFIT'!H44 | Q41: ='ALL DATA & IT4PROFIT'!K44 | R41: ='ALL DATA & IT4PROFIT'!D44
B42: ='ALL DATA & IT4PROFIT'!A45 -> SUNGROW | C42: ='ALL DATA & IT4PROFIT'!B45 -> IV SUNG SG5.0RT | D42: ='ALL DATA & IT4PROFIT'!C45 -> 3PH | E42: 1 | F42: ='ALL DATA & IT4PROFIT'!F45 -> 729 | G42: =F42+$G$204 -> 759 | H42: =(G42*$E$204)+G42 -> 777.975 | I42: =(J42-H42)/J42 -> 0.1 | J42: =H42/(1-M42) -> 864.41667 | K42: =SUM(E42*J42) -> 864.41667 | L42: =SUM(E42*H42) -> 777.975 | M42: 0.1 | N42: ='ALL DATA & IT4PROFIT'!L45 | P42: ='ALL DATA & IT4PROFIT'!H45 | Q42: ='ALL DATA & IT4PROFIT'!K45 | R42: ='ALL DATA & IT4PROFIT'!D45
B43: ='ALL DATA & IT4PROFIT'!A46 -> SUNGROW | C43: ='ALL DATA & IT4PROFIT'!B46 -> IV SUNG SG6.0RT | D43: ='ALL DATA & IT4PROFIT'!C46 -> 3PH | E43: 1 | F43: ='ALL DATA & IT4PROFIT'!F46 -> 747 | G43: =F43+$G$204 -> 777 | H43: =(G43*$E$204)+G43 -> 796.425 | I43: =(J43-H43)/J43 -> 0.1 | J43: =H43/(1-M43) -> 884.91667 | K43: =SUM(E43*J43) -> 884.91667 | L43: =SUM(E43*H43) -> 796.425 | M43: 0.1 | N43: ='ALL DATA & IT4PROFIT'!L46 | P43: ='ALL DATA & IT4PROFIT'!H46 | Q43: ='ALL DATA & IT4PROFIT'!K46 | R43: ='ALL DATA & IT4PROFIT'!D46
B44: ='ALL DATA & IT4PROFIT'!A47 -> SUNGROW | C44: ='ALL DATA & IT4PROFIT'!B47 -> IV SUNG SG8.0RT | D44: ='ALL DATA & IT4PROFIT'!C47 -> 3PH | E44: 1 | F44: ='ALL DATA & IT4PROFIT'!F47 -> 755.4 | G44: =F44+$G$204 -> 785.4 | H44: =(G44*$E$204)+G44 -> 805.035 | I44: =(J44-H44)/J44 -> 0.1 | J44: =H44/(1-M44) -> 894.48333 | K44: =SUM(E44*J44) -> 894.48333 | L44: =SUM(E44*H44) -> 805.035 | M44: 0.1 | N44: ='ALL DATA & IT4PROFIT'!L47 | P44: ='ALL DATA & IT4PROFIT'!H47 | Q44: ='ALL DATA & IT4PROFIT'!K47 | R44: ='ALL DATA & IT4PROFIT'!D47
B45: ='ALL DATA & IT4PROFIT'!A48 -> SUNGROW | C45: ='ALL DATA & IT4PROFIT'!B48 -> IV SUNG SG10.0RT | D45: ='ALL DATA & IT4PROFIT'!C48 -> 3PH | E45: 1 | F45: ='ALL DATA & IT4PROFIT'!F48 -> 870 | G45: =F45+$G$204 -> 900 | H45: =(G45*$E$204)+G45 -> 922.5 | I45: =(J45-H45)/J45 -> 0.1 | J45: =H45/(1-M45) -> 1025 | K45: =SUM(E45*J45) -> 1025 | L45: =SUM(E45*H45) -> 922.5 | M45: 0.1 | N45: ='ALL DATA & IT4PROFIT'!L48 | P45: ='ALL DATA & IT4PROFIT'!H48 | Q45: ='ALL DATA & IT4PROFIT'!K48 | R45: ='ALL DATA & IT4PROFIT'!D48
... B59: ='ALL DATA & IT4PROFIT'!A62 | C59: ='ALL DATA & IT4PROFIT'!B62 | D59: ='ALL DATA & IT4PROFIT'!C62 | E59: 1 | F59: ='ALL DATA & IT4PROFIT'!F62 | G59: =F59+$G$204 -> 30 | H59: =(G59*$E$204)+G59 -> 30.75 | I59: =(J59-H59)/J59 -> 0.1 | J59: =H59/(1-M59) -> 34.166667 | K59: =SUM(E59*J59) -> 34.166667 | L59: =SUM(E59*H59) -> 30.75 | M59: 0.1 | N59: ='ALL DATA & IT4PROFIT'!L62 | P59: ='ALL DATA & IT4PROFIT'!H62 | Q59: ='ALL DATA & IT4PROFIT'!K62 | R59: ='ALL DATA & IT4PROFIT'!D62
B60: ='ALL DATA & IT4PROFIT'!A63 -> FRONIUS | C60: ='ALL DATA & IT4PROFIT'!B63 -> PRIMO 3.0 | D60: ='ALL DATA & IT4PROFIT'!C63 -> 1PH | E60: 1 | F60: ='ALL DATA & IT4PROFIT'!F63 -> 814.2 | G60: =F60+$G$204 -> 844.2 | H60: =(G60*$E$204)+G60 -> 865.305 | I60: =(J60-H60)/J60 -> 0.1 | J60: =H60/(1-M60) -> 961.45 | K60: =SUM(E60*J60) -> 961.45 | L60: =SUM(E60*H60) -> 865.305 | M60: 0.1 | N60: ='ALL DATA & IT4PROFIT'!L63 | O60: =1570-1570*0.42 -> 910.6 | P60: ='ALL DATA & IT4PROFIT'!H63 -> 950 | Q60: ='ALL DATA & IT4PROFIT'!K63 | R60: ='ALL DATA & IT4PROFIT'!D63
B61: ='ALL DATA & IT4PROFIT'!A64 -> FRONIUS | C61: ='ALL DATA & IT4PROFIT'!B64 -> Fronius Primo 3.6-1 | D61: ='ALL DATA & IT4PROFIT'!C64 | E61: 1 | F61: ='ALL DATA & IT4PROFIT'!F64 -> 0 | G61: =F61+$G$204 -> 30 | H61: =(G61*$E$204)+G61 -> 30.75 | I61: =(J61-H61)/J61 -> 0.1 | J61: =H61/(1-M61) -> 34.166667 | K61: =SUM(E61*J61) -> 34.166667 | L61: =SUM(E61*H61) -> 30.75 | M61: 0.1 | N61: ='ALL DATA & IT4PROFIT'!L64 | P61: ='ALL DATA & IT4PROFIT'!H64 | Q61: ='ALL DATA & IT4PROFIT'!K64 | R61: ='ALL DATA & IT4PROFIT'!D64
B62: ='ALL DATA & IT4PROFIT'!A65 -> FRONIUS | C62: ='ALL DATA & IT4PROFIT'!B65 -> PRIMO 4.0 | D62: ='ALL DATA & IT4PROFIT'!C65 -> 1PH | E62: 1 | F62: ='ALL DATA & IT4PROFIT'!F65 -> 886.2 | G62: =F62+$G$204 -> 916.2 | H62: =(G62*$E$204)+G62 -> 939.105 | I62: =(J62-H62)/J62 -> 0.07 | J62: =H62/(1-M62) -> 1009.7903 | K62: =SUM(E62*J62) -> 1009.7903 | L62: =SUM(E62*H62) -> 939.105 | M62: 0.07 | N62: ='ALL DATA & IT4PROFIT'!L65 | O62: =1740-1740*0.42 -> 1009.2 | P62: ='ALL DATA & IT4PROFIT'!H65 -> 1026 | Q62: ='ALL DATA & IT4PROFIT'!K65 | R62: ='ALL DATA & IT4PROFIT'!D65
B63: ='ALL DATA & IT4PROFIT'!A66 -> FRONIUS | C63: ='ALL DATA & IT4PROFIT'!B66 -> Fronius Primo 4.6-1 | D63: ='ALL DATA & IT4PROFIT'!C66 | E63: 1 | F63: ='ALL DATA & IT4PROFIT'!F66 | G63: =F63+$G$204 -> 30 | H63: =(G63*$E$204)+G63 -> 30.75 | I63: =(J63-H63)/J63 -> 0.1 | J63: =H63/(1-M63) -> 34.166667 | K63: =SUM(E63*J63) -> 34.166667 | L63: =SUM(E63*H63) -> 30.75 | M63: 0.1 | N63: ='ALL DATA & IT4PROFIT'!L66 | P63: ='ALL DATA & IT4PROFIT'!H66 | Q63: ='ALL DATA & IT4PROFIT'!K66 | R63: ='ALL DATA & IT4PROFIT'!D66
B64: ='ALL DATA & IT4PROFIT'!A67 -> FRONIUS | C64: ='ALL DATA & IT4PROFIT'!B67 -> PRIMO 5.0 | D64: ='ALL DATA & IT4PROFIT'!C67 -> 1PH | E64: 1 | F64: ='ALL DATA & IT4PROFIT'!F67 -> 975.6 | G64: =F64+$G$204 -> 1005.6 | H64: =(G64*$E$204)+G64 -> 1030.74 | I64: =(J64-H64)/J64 -> 0.07 | J64: =H64/(1-M64) -> 1108.3226 | K64: =SUM(E64*J64) -> 1108.3226 | L64: =SUM(E64*H64) -> 1030.74 | M64: 0.07 | N64: ='ALL DATA & IT4PROFIT'!L67 | O64: =1905-1905*0.42 -> 1104.9 | P64: ='ALL DATA & IT4PROFIT'!H67 -> 1124 | Q64: ='ALL DATA & IT4PROFIT'!K67 | R64: ='ALL DATA & IT4PROFIT'!D67
B65: ='ALL DATA & IT4PROFIT'!A68 | C65: ='ALL DATA & IT4PROFIT'!B68 | D65: ='ALL DATA & IT4PROFIT'!C68 | E65: 1 | F65: ='ALL DATA & IT4PROFIT'!F68 | G65: =F65+$G$204 -> 30 | H65: =(G65*$E$204)+G65 -> 30.75 | I65: =(J65-H65)/J65 -> 0.1 | J65: =H65/(1-M65) -> 34.166667 | K65: =SUM(E65*J65) -> 34.166667 | L65: =SUM(E65*H65) -> 30.75 | M65: 0.1 | N65: ='ALL DATA & IT4PROFIT'!L68 | P65: ='ALL DATA & IT4PROFIT'!H68 | Q65: ='ALL DATA & IT4PROFIT'!K68 | R65: ='ALL DATA & IT4PROFIT'!D68
B66: ='ALL DATA & IT4PROFIT'!A69 -> FRONIUS | C66: ='ALL DATA & IT4PROFIT'!B69 -> SYMO 3.0-S | D66: ='ALL DATA & IT4PROFIT'!C69 -> 3PH | E66: 1 | F66: ='ALL DATA & IT4PROFIT'!F69 -> 834 | G66: =F66+$G$204 -> 864 | H66: =(G66*$E$204)+G66 -> 885.6 | I66: =(J66-H66)/J66 -> 0.07 | J66: =H66/(1-M66) -> 952.25806 | K66: =SUM(E66*J66) -> 952.25806 | L66: =SUM(E66*H66) -> 885.6 | M66: 0.07 | N66: ='ALL DATA & IT4PROFIT'!L69 | O66: =1630-1630*0.42 -> 945.4 | P66: ='ALL DATA & IT4PROFIT'!H69 -> 955 | Q66: ='ALL DATA & IT4PROFIT'!K69 | R66: ='ALL DATA & IT4PROFIT'!D69
B67: ='ALL DATA & IT4PROFIT'!A70 -> FRONIUS | C67: ='ALL DATA & IT4PROFIT'!B70 -> SYMO 3.7-S | D67: ='ALL DATA & IT4PROFIT'!C70 -> 3PH | E67: 1 | F67: ='ALL DATA & IT4PROFIT'!F70 -> 918 | G67: =F67+$G$204 -> 948 | H67: =(G67*$E$204)+G67 -> 971.7 | I67: =(J67-H67)/J67 -> 0.065 | J67: =H67/(1-M67) -> 1039.2513 | K67: =SUM(E67*J67) -> 1039.2513 | L67: =SUM(E67*H67) -> 971.7 | M67: 0.065 | N67: ='ALL DATA & IT4PROFIT'!L70 | O67: =1790-1790*0.42 -> 1038.2 | P67: ='ALL DATA & IT4PROFIT'!H70 -> 960 | Q67: ='ALL DATA & IT4PROFIT'!K70 | R67: ='ALL DATA & IT4PROFIT'!D70
B68: ='ALL DATA & IT4PROFIT'!A71 -> FRONIUS | C68: ='ALL DATA & IT4PROFIT'!B71 -> SYMO 4.5-S | D68: ='ALL DATA & IT4PROFIT'!C71 -> 3PH | E68: 1 | F68: ='ALL DATA & IT4PROFIT'!F71 -> 1017.6 | G68: =F68+$G$204 -> 1047.6 | H68: =(G68*$E$204)+G68 -> 1073.79 | I68: =(J68-H68)/J68 -> 0.065 | J68: =H68/(1-M68) -> 1148.4385 | K68: =SUM(E68*J68) -> 1148.4385 | L68: =SUM(E68*H68) -> 1073.79 | M68: 0.065 | N68: ='ALL DATA & IT4PROFIT'!L71 | O68: =1980-1980*0.42 -> 1148.4 | P68: ='ALL DATA & IT4PROFIT'!H71 | Q68: ='ALL DATA & IT4PROFIT'!K71 | R68: ='ALL DATA & IT4PROFIT'!D71
B69: ='ALL DATA & IT4PROFIT'!A72 -> FRONIUS | C69: ='ALL DATA & IT4PROFIT'!B72 -> SYMO 3.0-M | D69: ='ALL DATA & IT4PROFIT'!C72 -> 3PH | E69: 1 | F69: ='ALL DATA & IT4PROFIT'!F72 -> 924 | G69: =F69+$G$204 -> 954 | H69: =(G69*$E$204)+G69 -> 977.85 | I69: =(J69-H69)/J69 -> 0.065 | J69: =H69/(1-M69) -> 1045.8289 | K69: =SUM(E69*J69) -> 1045.8289 | L69: =SUM(E69*H69) -> 977.85 | M69: 0.065 | N69: ='ALL DATA & IT4PROFIT'!L72 | O69: =1800-1800*0.42 -> 1044 | P69: ='ALL DATA & IT4PROFIT'!H72 -> 1040 | Q69: ='ALL DATA & IT4PROFIT'!K72 | R69: ='ALL DATA & IT4PROFIT'!D72
B70: ='ALL DATA & IT4PROFIT'!A73 -> FRONIUS | C70: ='ALL DATA & IT4PROFIT'!B73 -> SYMO 3.7-M | D70: ='ALL DATA & IT4PROFIT'!C73 -> 3PH | E70: 1 | F70: ='ALL DATA & IT4PROFIT'!F73 -> 1014 | G70: =F70+$G$204 -> 1044 | H70: =(G70*$E$204)+G70 -> 1070.1 | I70: =(J70-H70)/J70 -> 0.07 | J70: =H70/(1-M70) -> 1150.6452 | K70: =SUM(E70*J70) -> 1150.6452 | L70: =SUM(E70*H70) -> 1070.1 | M70: 0.07 | N70: ='ALL DATA & IT4PROFIT'!L73 | O70: =1980-1980*0.42 -> 1148.4 | P70: ='ALL DATA & IT4PROFIT'!H73 -> 1168 | Q70: ='ALL DATA & IT4PROFIT'!K73 | R70: ='ALL DATA & IT4PROFIT'!D73
B71: ='ALL DATA & IT4PROFIT'!A74 -> FRONIUS | C71: ='ALL DATA & IT4PROFIT'!B74 -> SYMO 4.5-M | D71: ='ALL DATA & IT4PROFIT'!C74 -> 3PH | E71: 1 | F71: ='ALL DATA & IT4PROFIT'!F74 -> 1070.4 | G71: =F71+$G$204 -> 1100.4 | H71: =(G71*$E$204)+G71 -> 1127.91 | I71: =(J71-H71)/J71 -> 0.07 | J71: =H71/(1-M71) -> 1212.8065 | K71: =SUM(E71*J71) -> 1212.8065 | L71: =SUM(E71*H71) -> 1127.91 | M71: 0.07 | N71: ='ALL DATA & IT4PROFIT'!L74 | O71: =2090-2090*0.42 -> 1212.2 | P71: ='ALL DATA & IT4PROFIT'!H74 -> 1240 | Q71: ='ALL DATA & IT4PROFIT'!K74 | R71: ='ALL DATA & IT4PROFIT'!D74
B72: ='ALL DATA & IT4PROFIT'!A75 -> FRONIUS | C72: ='ALL DATA & IT4PROFIT'!B75 -> SYMO 5.0-M | D72: ='ALL DATA & IT4PROFIT'!C75 -> 3PH | E72: 1 | F72: ='ALL DATA & IT4PROFIT'!F75 -> 1087.8 | G72: =F72+$G$204 -> 1117.8 | H72: =(G72*$E$204)+G72 -> 1145.745 | I72: =(J72-H72)/J72 -> 0.07 | J72: =H72/(1-M72) -> 1231.9839 | K72: =SUM(E72*J72) -> 1231.9839 | L72: =SUM(E72*H72) -> 1145.745 | M72: 0.07 | N72: ='ALL DATA & IT4PROFIT'!L75 | O72: =2120-2120*0.42 -> 1229.6 | P72: ='ALL DATA & IT4PROFIT'!H75 -> 1250 | Q72: ='ALL DATA & IT4PROFIT'!K75 | R72: ='ALL DATA & IT4PROFIT'!D75
B73: ='ALL DATA & IT4PROFIT'!A76 -> FRONIUS | C73: ='ALL DATA & IT4PROFIT'!B76 -> SYMO 6.0-M | D73: ='ALL DATA & IT4PROFIT'!C76 -> 3PH | E73: 1 | F73: ='ALL DATA & IT4PROFIT'!F76 -> 1110.6 | G73: =F73+$G$204 -> 1140.6 | H73: =(G73*$E$204)+G73 -> 1169.115 | I73: =(J73-H73)/J73 -> 0.07 | J73: =H73/(1-M73) -> 1257.1129 | K73: =SUM(E73*J73) -> 1257.1129 | L73: =SUM(E73*H73) -> 1169.115 | M73: 0.07 | N73: ='ALL DATA & IT4PROFIT'!L76 | O73: =2160-2160*0.42 -> 1252.8 | P73: ='ALL DATA & IT4PROFIT'!H76 -> 1274 | Q73: ='ALL DATA & IT4PROFIT'!K76 | R73: ='ALL DATA & IT4PROFIT'!D76
B74: ='ALL DATA & IT4PROFIT'!A77 -> FRONIUS | C74: ='ALL DATA & IT4PROFIT'!B77 -> SYMO 7.0-M | D74: ='ALL DATA & IT4PROFIT'!C77 -> 3PH | E74: 1 | F74: ='ALL DATA & IT4PROFIT'!F77 -> 1378.8 | G74: =F74+$G$204 -> 1408.8 | H74: =(G74*$E$204)+G74 -> 1444.02 | I74: =(J74-H74)/J74 -> 0.07 | J74: =H74/(1-M74) -> 1552.7097 | K74: =SUM(E74*J74) -> 1552.7097 | L74: =SUM(E74*H74) -> 1444.02 | M74: 0.07 | N74: ='ALL DATA & IT4PROFIT'!L77 | O74: =2670-2670*0.42 -> 1548.6 | P74: ='ALL DATA & IT4PROFIT'!H77 -> 1580 | Q74: ='ALL DATA & IT4PROFIT'!K77 | R74: ='ALL DATA & IT4PROFIT'!D77
B75: ='ALL DATA & IT4PROFIT'!A78 -> FRONIUS | C75: ='ALL DATA & IT4PROFIT'!B78 -> SYMO 8.2-M | D75: ='ALL DATA & IT4PROFIT'!C78 -> 3PH | E75: 1 | F75: ='ALL DATA & IT4PROFIT'!F78 -> 1524.6 | G75: =F75+$G$204 -> 1554.6 | H75: =(G75*$E$204)+G75 -> 1593.465 | I75: =(J75-H75)/J75 -> 0.07 | J75: =H75/(1-M75) -> 1713.4032 | K75: =SUM(E75*J75) -> 1713.4032 | L75: =SUM(E75*H75) -> 1593.465 | M75: 0.07 | N75: ='ALL DATA & IT4PROFIT'!L78 | O75: =2950-2950*0.42 -> 1711 | P75: ='ALL DATA & IT4PROFIT'!H78 -> 1740 | Q75: ='ALL DATA & IT4PROFIT'!K78 | R75: ='ALL DATA & IT4PROFIT'!D78
B76: ='ALL DATA & IT4PROFIT'!A79 -> FRONIUS | C76: ='ALL DATA & IT4PROFIT'!B79 -> SYMO 10.0-M | D76: ='ALL DATA & IT4PROFIT'!C79 -> 3PH | E76: 1 | F76: ='ALL DATA & IT4PROFIT'!F79 -> 1602.6 | G76: =F76+$G$204 -> 1632.6 | H76: =(G76*$E$204)+G76 -> 1673.415 | I76: =(J76-H76)/J76 -> 0.07 | J76: =H76/(1-M76) -> 1799.371 | K76: =SUM(E76*J76) -> 1799.371 | L76: =SUM(E76*H76) -> 1673.415 | M76: 0.07 | N76: ='ALL DATA & IT4PROFIT'!L79 | O76: =3100-3100*0.42 -> 1798 | P76: ='ALL DATA & IT4PROFIT'!H79 -> 1895 | Q76: ='ALL DATA & IT4PROFIT'!K79 | R76: ='ALL DATA & IT4PROFIT'!D79
B77: ='ALL DATA & IT4PROFIT'!A80 -> FRONIUS | C77: ='ALL DATA & IT4PROFIT'!B80 -> SYMO 12.5-3-M | D77: ='ALL DATA & IT4PROFIT'!C80 -> 3PH | E77: 1 | F77: ='ALL DATA & IT4PROFIT'!F80 -> 1755 | G77: =F77+$G$204 -> 1785 | H77: =(G77*$E$204)+G77 -> 1829.625 | I77: =(J77-H77)/J77 -> 0.1 | J77: =H77/(1-M77) -> 2032.9167 | K77: =SUM(E77*J77) -> 2032.9167 | L77: =SUM(E77*H77) -> 1829.625 | M77: 0.1 | N77: ='ALL DATA & IT4PROFIT'!L80 | P77: ='ALL DATA & IT4PROFIT'!H80 | Q77: ='ALL DATA & IT4PROFIT'!K80 | R77: ='ALL DATA & IT4PROFIT'!D80
B78: ='ALL DATA & IT4PROFIT'!A81 -> FRONIUS | C78: ='ALL DATA & IT4PROFIT'!B81 -> SYMO 15.0-3-M | D78: ='ALL DATA & IT4PROFIT'!C81 -> 3PH | E78: 1 | F78: ='ALL DATA & IT4PROFIT'!F81 -> 1767.6 | G78: =F78+$G$204 -> 1797.6 | H78: =(G78*$E$204)+G78 -> 1842.54 | I78: =(J78-H78)/J78 -> 0.1 | J78: =H78/(1-M78) -> 2047.2667 | K78: =SUM(E78*J78) -> 2047.2667 | L78: =SUM(E78*H78) -> 1842.54 | M78: 0.1 | N78: ='ALL DATA & IT4PROFIT'!L81 | P78: ='ALL DATA & IT4PROFIT'!H81 | Q78: ='ALL DATA & IT4PROFIT'!K81 | R78: ='ALL DATA & IT4PROFIT'!D81
B79: ='ALL DATA & IT4PROFIT'!A82 -> FRONIUS | C79: ='ALL DATA & IT4PROFIT'!B82 -> SYMO 17.5-3-M | D79: ='ALL DATA & IT4PROFIT'!C82 -> 3PH | E79: 1 | F79: ='ALL DATA & IT4PROFIT'!F82 -> 1886.4 | G79: =F79+$G$204 -> 1916.4 | H79: =(G79*$E$204)+G79 -> 1964.31 | I79: =(J79-H79)/J79 -> 0.1 | J79: =H79/(1-M79) -> 2182.5667 | K79: =SUM(E79*J79) -> 2182.5667 | L79: =SUM(E79*H79) -> 1964.31 | M79: 0.1 | N79: ='ALL DATA & IT4PROFIT'!L82 | P79: ='ALL DATA & IT4PROFIT'!H82 | Q79: ='ALL DATA & IT4PROFIT'!K82 | R79: ='ALL DATA & IT4PROFIT'!D82
B80: ='ALL DATA & IT4PROFIT'!A83 -> FRONIUS | C80: ='ALL DATA & IT4PROFIT'!B83 -> SYMO 20.0-3-M | D80: ='ALL DATA & IT4PROFIT'!C83 -> 3PH | E80: 1 | F80: ='ALL DATA & IT4PROFIT'!F83 -> 1970.4 | G80: =F80+$G$204 -> 2000.4 | H80: =(G80*$E$204)+G80 -> 2050.41 | I80: =(J80-H80)/J80 -> 0.1 | J80: =H80/(1-M80) -> 2278.2333 | K80: =SUM(E80*J80) -> 2278.2333 | L80: =SUM(E80*H80) -> 2050.41 | M80: 0.1 | N80: ='ALL DATA & IT4PROFIT'!L83 | P80: ='ALL DATA & IT4PROFIT'!H83 | Q80: ='ALL DATA & IT4PROFIT'!K83 | R80: ='ALL DATA & IT4PROFIT'!D83
B81: ='ALL DATA & IT4PROFIT'!A84 | C81: ='ALL DATA & IT4PROFIT'!B84 | D81: ='ALL DATA & IT4PROFIT'!C84 | E81: 1 | F81: ='ALL DATA & IT4PROFIT'!F84 | G81: =F81+$G$204 -> 30 | H81: =(G81*$E$204)+G81 -> 30.75 | I81: =(J81-H81)/J81 -> 0.1 | J81: =H81/(1-M81) -> 34.166667 | K81: =SUM(E81*J81) -> 34.166667 | L81: =SUM(E81*H81) -> 30.75 | M81: 0.1 | N81: ='ALL DATA & IT4PROFIT'!L84 | P81: ='ALL DATA & IT4PROFIT'!H84 | Q81: ='ALL DATA & IT4PROFIT'!K84 | R81: ='ALL DATA & IT4PROFIT'!D84
B82: ='ALL DATA & IT4PROFIT'!A85 -> FRONIUS | C82: ='ALL DATA & IT4PROFIT'!B85 -> Fronius Symo GEN24 3.0 | D82: ='ALL DATA & IT4PROFIT'!C85 -> 3PH H lock | E82: 1 | F82: ='ALL DATA & IT4PROFIT'!F85 -> 1359.6 | G82: =F82+$G$204 -> 1389.6 | H82: =(G82*$E$204)+G82 -> 1424.34 | I82: =(J82-H82)/J82 -> 0.1 | J82: =H82/(1-M82) -> 1582.6 | K82: =SUM(E82*J82) -> 1582.6 | L82: =SUM(E82*H82) -> 1424.34 | M82: 0.1 | N82: ='ALL DATA & IT4PROFIT'!L85 | P82: ='ALL DATA & IT4PROFIT'!H85 | Q82: ='ALL DATA & IT4PROFIT'!K85 | R82: ='ALL DATA & IT4PROFIT'!D85
B83: ='ALL DATA & IT4PROFIT'!A86 -> FRONIUS | C83: ='ALL DATA & IT4PROFIT'!B86 -> Fronius Symo GEN24 4.0 | D83: ='ALL DATA & IT4PROFIT'!C86 -> 3PH H lock | E83: 1 | F83: ='ALL DATA & IT4PROFIT'!F86 -> 1450.2 | G83: =F83+$G$204 -> 1480.2 | H83: =(G83*$E$204)+G83 -> 1517.205 | I83: =(J83-H83)/J83 -> 0.1 | J83: =H83/(1-M83) -> 1685.7833 | K83: =SUM(E83*J83) -> 1685.7833 | L83: =SUM(E83*H83) -> 1517.205 | M83: 0.1 | N83: ='ALL DATA & IT4PROFIT'!L86 | P83: ='ALL DATA & IT4PROFIT'!H86 | Q83: ='ALL DATA & IT4PROFIT'!K86 | R83: ='ALL DATA & IT4PROFIT'!D86
B84: ='ALL DATA & IT4PROFIT'!A87 -> FRONIUS | C84: ='ALL DATA & IT4PROFIT'!B87 -> Fronius Symo GEN24 5.0 | D84: ='ALL DATA & IT4PROFIT'!C87 -> 3PH H lock | E84: 1 | F84: ='ALL DATA & IT4PROFIT'!F87 -> 1526.4 | G84: =F84+$G$204 -> 1556.4 | H84: =(G84*$E$204)+G84 -> 1595.31 | I84: =(J84-H84)/J84 -> 0.1 | J84: =H84/(1-M84) -> 1772.5667 | K84: =SUM(E84*J84) -> 1772.5667 | L84: =SUM(E84*H84) -> 1595.31 | M84: 0.1 | N84: ='ALL DATA & IT4PROFIT'!L87 | P84: ='ALL DATA & IT4PROFIT'!H87 | Q84: ='ALL DATA & IT4PROFIT'!K87 | R84: ='ALL DATA & IT4PROFIT'!D87
B85: ='ALL DATA & IT4PROFIT'!A88 -> FRONIUS | C85: ='ALL DATA & IT4PROFIT'!B88 -> Fronius Symo GEN24 6.0 | D85: ='ALL DATA & IT4PROFIT'!C88 -> 3PH H lock | E85: 1 | F85: ='ALL DATA & IT4PROFIT'!F88 -> 1816.2 | G85: =F85+$G$204 -> 1846.2 | H85: =(G85*$E$204)+G85 -> 1892.355 | I85: =(J85-H85)/J85 -> 0.1 | J85: =H85/(1-M85) -> 2102.6167 | K85: =SUM(E85*J85) -> 2102.6167 | L85: =SUM(E85*H85) -> 1892.355 | M85: 0.1 | N85: ='ALL DATA & IT4PROFIT'!L88 | P85: ='ALL DATA & IT4PROFIT'!H88 | Q85: ='ALL DATA & IT4PROFIT'!K88 | R85: ='ALL DATA & IT4PROFIT'!D88
B86: ='ALL DATA & IT4PROFIT'!A89 -> FRONIUS | C86: ='ALL DATA & IT4PROFIT'!B89 -> Fronius Symo GEN24 8.0 | D86: ='ALL DATA & IT4PROFIT'!C89 -> 3PH H lock | E86: 1 | F86: ='ALL DATA & IT4PROFIT'!F89 -> 2091 | G86: =F86+$G$204 -> 2121 | H86: =(G86*$E$204)+G86 -> 2174.025 | I86: =(J86-H86)/J86 -> 0.1 | J86: =H86/(1-M86) -> 2415.5833 | K86: =SUM(E86*J86) -> 2415.5833 | L86: =SUM(E86*H86) -> 2174.025 | M86: 0.1 | N86: ='ALL DATA & IT4PROFIT'!L89 | P86: ='ALL DATA & IT4PROFIT'!H89 | Q86: ='ALL DATA & IT4PROFIT'!K89 | R86: ='ALL DATA & IT4PROFIT'!D89
B87: ='ALL DATA & IT4PROFIT'!A90 -> FRONIUS | C87: ='ALL DATA & IT4PROFIT'!B90 -> Fronius Symo GEN24 10.0 | D87: ='ALL DATA & IT4PROFIT'!C90 -> 3PH H lock | E87: 1 | F87: ='ALL DATA & IT4PROFIT'!F90 -> 2184 | G87: =F87+$G$204 -> 2214 | H87: =(G87*$E$204)+G87 -> 2269.35 | I87: =(J87-H87)/J87 -> 0.1 | J87: =H87/(1-M87) -> 2521.5 | K87: =SUM(E87*J87) -> 2521.5 | L87: =SUM(E87*H87) -> 2269.35 | M87: 0.1 | N87: ='ALL DATA & IT4PROFIT'!L90 | P87: ='ALL DATA & IT4PROFIT'!H90 | Q87: ='ALL DATA & IT4PROFIT'!K90 | R87: ='ALL DATA & IT4PROFIT'!D90
B88: ='ALL DATA & IT4PROFIT'!A91 | C88: ='ALL DATA & IT4PROFIT'!B91 | D88: ='ALL DATA & IT4PROFIT'!C91 | E88: 1 | F88: ='ALL DATA & IT4PROFIT'!F91 -> 0 | G88: =F88+$G$204 -> 30 | H88: =(G88*$E$204)+G88 -> 30.75 | I88: =(J88-H88)/J88 -> 0.1 | J88: =H88/(1-M88) -> 34.166667 | K88: =SUM(E88*J88) -> 34.166667 | L88: =SUM(E88*H88) -> 30.75 | M88: 0.1 | N88: ='ALL DATA & IT4PROFIT'!L91 | P88: ='ALL DATA & IT4PROFIT'!H91 | Q88: ='ALL DATA & IT4PROFIT'!K91 | R88: ='ALL DATA & IT4PROFIT'!D91
... B101: ='ALL DATA & IT4PROFIT'!A104 -> FRONIUS | C101: ='ALL DATA & IT4PROFIT'!B104 -> Fronius Symo GEN24 10.0 Plus | D101: ='ALL DATA & IT4PROFIT'!C104 -> 3PH HYBRID | E101: 1 | F101: ='ALL DATA & IT4PROFIT'!F104 -> 2184 | G101: =F101+$G$204 -> 2214 | H101: =(G101*$E$204)+G101 -> 2269.35 | I101: =(J101-H101)/J101 -> 0.1 | J101: =H101/(1-M101) -> 2521.5 | K101: =SUM(E101*J101) -> 2521.5 | L101: =SUM(E101*H101) -> 2269.35 | M101: 0.1 | N101: ='ALL DATA & IT4PROFIT'!L104 | P101: ='ALL DATA & IT4PROFIT'!H104 | Q101: ='ALL DATA & IT4PROFIT'!K104 | R101: ='ALL DATA & IT4PROFIT'!D104
B102: ='ALL DATA & IT4PROFIT'!A105 | C102: ='ALL DATA & IT4PROFIT'!B105 | D102: ='ALL DATA & IT4PROFIT'!C105 | E102: 1
B103: ='ALL DATA & IT4PROFIT'!A125 -> SOLAREDGE | C103: SE 2 200H HD-WAVE SETAPP | E103: 1 | F103: ='ALL DATA & IT4PROFIT'!$F$106 -> 604.2 | G103: =F103+$G$204 -> 634.2 | H103: =(G103*$E$204)+G103 -> 650.055 | I103: =(J103-H103)/J103 -> 0.07 | J103: =H103/(1-M103) -> 698.98387 | K103: =SUM(E103*J103) -> 698.98387 | L103: =SUM(E103*H103) -> 650.055 | M103: 0.07 | N103: ='ALL DATA & IT4PROFIT'!L125 | O103: ='ALL DATA & IT4PROFIT'!$G$106 -> 774 | P103: ='ALL DATA & IT4PROFIT'!H125 | Q103: ='ALL DATA & IT4PROFIT'!K125 | R103: ='ALL DATA & IT4PROFIT'!D125
B104: ='ALL DATA & IT4PROFIT'!A126 -> SOLAREDGE | C104: SE 4 .000 H HD-WAVE SETAPP (WITHOUT DISPLAY) | E104: 1 | F104: ='ALL DATA & IT4PROFIT'!$F$110 -> 849 | G104: =F104+$G$204 -> 879 | H104: =(G104*$E$204)+G104 -> 900.975 | I104: =(J104-H104)/J104 -> 0.05 | J104: =H104/(1-M104) -> 948.39474 | K104: =SUM(E104*J104) -> 948.39474 | L104: =SUM(E104*H104) -> 900.975 | M104: 0.05 | N104: ='ALL DATA & IT4PROFIT'!L126 | O104: ='ALL DATA & IT4PROFIT'!$G$110 -> 906 | P104: ='ALL DATA & IT4PROFIT'!H126 | Q104: ='ALL DATA & IT4PROFIT'!K126 | R104: ='ALL DATA & IT4PROFIT'!D126
B105: ='ALL DATA & IT4PROFIT'!A127 -> SOLAREDGE | C105: SE 5 .000 H HD-WAVE SETAPP (WITHOUT DISPLAY) | E105: 1 | F105: ='ALL DATA & IT4PROFIT'!$F$111 -> 910.8 | G105: =F105+$G$204 -> 940.8 | H105: =(G105*$E$204)+G105 -> 964.32 | I105: =(J105-H105)/J105 -> 0.05 | J105: =H105/(1-M105) -> 1015.0737 | K105: =SUM(E105*J105) -> 1015.0737 | L105: =SUM(E105*H105) -> 964.32 | M105: 0.05 | O105: ='ALL DATA & IT4PROFIT'!$G$111 -> 1014
B106: ='ALL DATA & IT4PROFIT'!A128 -> SOLAREDGE | C106: SE 4 k SETAPP (WITHOUT DISPLAY) | E106: 1 | F106: ='ALL DATA & IT4PROFIT'!$F$114 -> 980.4 | G106: =F106+$G$204 -> 1010.4 | H106: =(G106*$E$204)+G106 -> 1035.66 | I106: =(J106-H106)/J106 -> 0.07 | J106: =H106/(1-M106) -> 1113.6129 | K106: =SUM(E106*J106) -> 1113.6129 | L106: =SUM(E106*H106) -> 1035.66 | M106: 0.07
B107: ='ALL DATA & IT4PROFIT'!A129 -> SOLAREDGE | C107: SE5k SETAPP (WITHOUT DISPLAY) | E107: 1 | F107: ='ALL DATA & IT4PROFIT'!$F$116 -> 1074 | G107: =F107+$G$204 -> 1104 | H107: =(G107*$E$204)+G107 -> 1131.6 | I107: =(J107-H107)/J107 -> 0.07 | J107: =H107/(1-M107) -> 1216.7742 | K107: =SUM(E107*J107) -> 1216.7742 | L107: =SUM(E107*H107) -> 1131.6 | M107: 0.07 | O107: ='ALL DATA & IT4PROFIT'!$G$116 -> 1230
B108: ='ALL DATA & IT4PROFIT'!A130 -> SOLAREDGE | C108: SE6k SETAPP (WITHOUT DISPLAY) | E108: 1 | F108: ='ALL DATA & IT4PROFIT'!$F$118 -> 1163.4 | G108: =F108+$G$204 -> 1193.4 | H108: =(G108*$E$204)+G108 -> 1223.235 | I108: =(J108-H108)/J108 -> 0.07 | J108: =H108/(1-M108) -> 1315.3065 | K108: =SUM(E108*J108) -> 1315.3065 | L108: =SUM(E108*H108) -> 1223.235 | M108: 0.07 | O108: ='ALL DATA & IT4PROFIT'!$G$118 -> 1320
B109: ='ALL DATA & IT4PROFIT'!A131 -> SOLAREDGE | C109: SE7k SETAPP (WITHOUT DISPLAY) | E109: 1 | F109: ='ALL DATA & IT4PROFIT'!$F$119 -> 1212 | G109: =F109+$G$204 -> 1242 | H109: =(G109*$E$204)+G109 -> 1273.05 | I109: =(J109-H109)/J109 -> 0.08 | J109: =H109/(1-M109) -> 1383.75 | K109: =SUM(E109*J109) -> 1383.75 | L109: =SUM(E109*H109) -> 1273.05 | M109: 0.08 | O109: ='ALL DATA & IT4PROFIT'!$G$119 -> 1380
B110: ='ALL DATA & IT4PROFIT'!A129 -> SOLAREDGE | C110: SE8k SETAPP (WITHOUT DISPLAY) | D110: ='ALL DATA & IT4PROFIT'!C144 | E110: 1 | F110: ='ALL DATA & IT4PROFIT'!$F$120 -> 1347 | G110: =F110+$G$204 -> 1377 | H110: =(G110*$E$204)+G110 -> 1411.425 | I110: =(J110-H110)/J110 -> 0.05 | J110: =H110/(1-M110) -> 1485.7105 | K110: =SUM(E110*J110) -> 1485.7105 | L110: =SUM(E110*H110) -> 1411.425 | M110: 0.05 | O110: ='ALL DATA & IT4PROFIT'!$G$120 -> 1476 | P110: ='ALL DATA & IT4PROFIT'!H144 | Q110: ='ALL DATA & IT4PROFIT'!K144 | R110: ='ALL DATA & IT4PROFIT'!D144
B111: ='ALL DATA & IT4PROFIT'!A130 -> SOLAREDGE | C111: SE9k SETAPP (WITHOUT DISPLAY) | D111: ='ALL DATA & IT4PROFIT'!C159 | E111: 1 | F111: ='ALL DATA & IT4PROFIT'!$F$121 -> 1401 | G111: =F111+$G$204 -> 1431 | H111: =(G111*$E$204)+G111 -> 1466.775 | I111: =(J111-H111)/J111 -> 0.05 | J111: =H111/(1-M111) -> 1543.9737 | K111: =SUM(E111*J111) -> 1543.9737 | L111: =SUM(E111*H111) -> 1466.775 | M111: 0.05 | O111: ='ALL DATA & IT4PROFIT'!$G$121 -> 1545 | P111: ='ALL DATA & IT4PROFIT'!H159 | Q111: ='ALL DATA & IT4PROFIT'!K159 | R111: ='ALL DATA & IT4PROFIT'!D159
B112: ='ALL DATA & IT4PROFIT'!A131 -> SOLAREDGE | C112: SE10k SETAPP (WITHOUT DISPLAY) | D112: ='ALL DATA & IT4PROFIT'!C160 | E112: 1 | F112: ='ALL DATA & IT4PROFIT'!$F$122 -> 1455 | G112: =F112+$G$204 -> 1485 | H112: =(G112*$E$204)+G112 -> 1522.125 | I112: =(J112-H112)/J112 -> 0.05 | J112: =H112/(1-M112) -> 1602.2368 | K112: =SUM(E112*J112) -> 1602.2368 | L112: =SUM(E112*H112) -> 1522.125 | M112: 0.05 | O112: ='ALL DATA & IT4PROFIT'!$G$122 -> 1608 | P112: ='ALL DATA & IT4PROFIT'!H160 | Q112: ='ALL DATA & IT4PROFIT'!K160 | R112: ='ALL DATA & IT4PROFIT'!D160
B113: ='ALL DATA & IT4PROFIT'!A161 | C113: ='ALL DATA & IT4PROFIT'!B161 | D113: ='ALL DATA & IT4PROFIT'!C161 | E113: 1 | F113: ='ALL DATA & IT4PROFIT'!F161 | G113: =F113+$G$204 -> 30 | H113: =(G113*$E$204)+G113 -> 30.75 | I113: =(J113-H113)/J113 -> 0.1 | J113: =H113/(1-M113) -> 34.166667 | K113: =SUM(E113*J113) -> 34.166667 | L113: =SUM(E113*H113) -> 30.75 | M113: 0.1 | P113: ='ALL DATA & IT4PROFIT'!H161 | Q113: ='ALL DATA & IT4PROFIT'!K161 | R113: ='ALL DATA & IT4PROFIT'!D161
B114: ='ALL DATA & IT4PROFIT'!A162 -> SOLAX | C114: ='ALL DATA & IT4PROFIT'!B162 -> X1 2.0-S-D(L) Mini G3 | D114: ='ALL DATA & IT4PROFIT'!C162 -> 1PH | E114: 1 | F114: ='ALL DATA & IT4PROFIT'!F162 | G114: =F114+$G$204 -> 30 | H114: =(G114*$E$204)+G114 -> 30.75 | I114: =(J114-H114)/J114 -> 0.1 | J114: =H114/(1-M114) -> 34.166667 | K114: =SUM(E114*J114) -> 34.166667 | L114: =SUM(E114*H114) -> 30.75 | M114: 0.1 | O114: =615-615*0.4 -> 369 | P114: ='ALL DATA & IT4PROFIT'!H162 | Q114: ='ALL DATA & IT4PROFIT'!K162 | R114: ='ALL DATA & IT4PROFIT'!D162
B115: ='ALL DATA & IT4PROFIT'!A163 -> SOLAX | C115: ='ALL DATA & IT4PROFIT'!B163 -> X1 3.3-T-D(L) BOOST | D115: ='ALL DATA & IT4PROFIT'!C163 -> 1PH | E115: 1 | F115: ='ALL DATA & IT4PROFIT'!F163 | G115: =F115+$G$204 -> 30 | H115: =(G115*$E$204)+G115 -> 30.75 | I115: =(J115-H115)/J115 -> 0.1 | J115: =H115/(1-M115) -> 34.166667 | K115: =SUM(E115*J115) -> 34.166667 | L115: =SUM(E115*H115) -> 30.75 | M115: 0.1 | O115: =920-920*0.4 -> 552 | P115: ='ALL DATA & IT4PROFIT'!H163 | Q115: ='ALL DATA & IT4PROFIT'!K163 | R115: ='ALL DATA & IT4PROFIT'!D163
B116: ='ALL DATA & IT4PROFIT'!A164 -> SOLAX | C116: ='ALL DATA & IT4PROFIT'!B164 -> X1 4.2-T-D(L) BOOST | D116: ='ALL DATA & IT4PROFIT'!C164 -> 1PH | E116: 1 | F116: ='ALL DATA & IT4PROFIT'!F164 | G116: =F116+$G$204 -> 30 | H116: =(G116*$E$204)+G116 -> 30.75 | I116: =(J116-H116)/J116 -> 0.1 | J116: =H116/(1-M116) -> 34.166667 | K116: =SUM(E116*J116) -> 34.166667 | L116: =SUM(E116*H116) -> 30.75 | M116: 0.1 | O116: =985-985*0.4 -> 591 | P116: ='ALL DATA & IT4PROFIT'!H164 | Q116: ='ALL DATA & IT4PROFIT'!K164 | R116: ='ALL DATA & IT4PROFIT'!D164
B117: ='ALL DATA & IT4PROFIT'!A165 -> SOLAX | C117: ='ALL DATA & IT4PROFIT'!B165 -> X1 5.0-T-D(L) BOOST | D117: ='ALL DATA & IT4PROFIT'!C165 -> 1PH | E117: 1 | F117: ='ALL DATA & IT4PROFIT'!F165 | G117: =F117+$G$204 -> 30 | H117: =(G117*$E$204)+G117 -> 30.75 | I117: =(J117-H117)/J117 -> 0.1 | J117: =H117/(1-M117) -> 34.166667 | K117: =SUM(E117*J117) -> 34.166667 | L117: =SUM(E117*H117) -> 30.75 | M117: 0.1 | O117: =1055-1055*0.4 -> 633 | P117: ='ALL DATA & IT4PROFIT'!H165 | Q117: ='ALL DATA & IT4PROFIT'!K165 | R117: ='ALL DATA & IT4PROFIT'!D165
B118: ='ALL DATA & IT4PROFIT'!A166 -> SOLAX | C118: ='ALL DATA & IT4PROFIT'!B166 -> X3-MIC-4.0K-G2 | D118: ='ALL DATA & IT4PROFIT'!C166 -> 3PH | E118: 1 | F118: ='ALL DATA & IT4PROFIT'!F166 | G118: =F118+$G$204 -> 30 | H118: =(G118*$E$204)+G118 -> 30.75 | I118: =(J118-H118)/J118 -> 0.1 | J118: =H118/(1-M118) -> 34.166667 | K118: =SUM(E118*J118) -> 34.166667 | L118: =SUM(E118*H118) -> 30.75 | M118: 0.1 | O118: =1465-1465*0.4 -> 879 | P118: ='ALL DATA & IT4PROFIT'!H166 | Q118: ='ALL DATA & IT4PROFIT'!K166 | R118: ='ALL DATA & IT4PROFIT'!D166
B119: ='ALL DATA & IT4PROFIT'!A167 -> SOLAX | C119: ='ALL DATA & IT4PROFIT'!B167 -> X3-MIC-5.0K-G2 | D119: ='ALL DATA & IT4PROFIT'!C167 -> 3PH | E119: 1 | F119: ='ALL DATA & IT4PROFIT'!F167 | G119: =F119+$G$204 -> 30 | H119: =(G119*$E$204)+G119 -> 30.75 | I119: =(J119-H119)/J119 -> 0.1 | J119: =H119/(1-M119) -> 34.166667 | K119: =SUM(E119*J119) -> 34.166667 | L119: =SUM(E119*H119) -> 30.75 | M119: 0.1 | O119: =1530-1530*0.4 -> 918 | P119: ='ALL DATA & IT4PROFIT'!H167 | Q119: ='ALL DATA & IT4PROFIT'!K167 | R119: ='ALL DATA & IT4PROFIT'!D167
B120: ='ALL DATA & IT4PROFIT'!A168 -> SOLAX | C120: ='ALL DATA & IT4PROFIT'!B168 -> X3-MIC-6.0K-G2 | D120: ='ALL DATA & IT4PROFIT'!C168 -> 3PH | E120: 1 | F120: ='ALL DATA & IT4PROFIT'!F168 | G120: =F120+$G$204 -> 30 | H120: =(G120*$E$204)+G120 -> 30.75 | I120: =(J120-H120)/J120 -> 0.1 | J120: =H120/(1-M120) -> 34.166667 | K120: =SUM(E120*J120) -> 34.166667 | L120: =SUM(E120*H120) -> 30.75 | M120: 0.1 | O120: =1625-1625*0.4 -> 975 | P120: ='ALL DATA & IT4PROFIT'!H168 | Q120: ='ALL DATA & IT4PROFIT'!K168 | R120: ='ALL DATA & IT4PROFIT'!D168
B121: ='ALL DATA & IT4PROFIT'!A169 -> SOLAX | C121: ='ALL DATA & IT4PROFIT'!B169 -> X3-MIC-8.0K-G2 | D121: ='ALL DATA & IT4PROFIT'!C169 -> 3PH | E121: 1 | F121: ='ALL DATA & IT4PROFIT'!F169 | G121: =F121+$G$204 -> 30 | H121: =(G121*$E$204)+G121 -> 30.75 | I121: =(J121-H121)/J121 -> 0.1 | J121: =H121/(1-M121) -> 34.166667 | K121: =SUM(E121*J121) -> 34.166667 | L121: =SUM(E121*H121) -> 30.75 | M121: 0.1 | O121: =1680-1680*0.4 -> 1008 | P121: ='ALL DATA & IT4PROFIT'!H169 | Q121: ='ALL DATA & IT4PROFIT'!K169 | R121: ='ALL DATA & IT4PROFIT'!D169
B122: ='ALL DATA & IT4PROFIT'!A170 -> SOLAX | C122: ='ALL DATA & IT4PROFIT'!B170 -> X3-MIC-10.0K-G2 | D122: ='ALL DATA & IT4PROFIT'!C170 -> 3PH | E122: 1 | F122: ='ALL DATA & IT4PROFIT'!F170 | G122: =F122+$G$204 -> 30 | H122: =(G122*$E$204)+G122 -> 30.75 | I122: =(J122-H122)/J122 -> 0.1 | J122: =H122/(1-M122) -> 34.166667 | K122: =SUM(E122*J122) -> 34.166667 | L122: =SUM(E122*H122) -> 30.75 | M122: 0.1 | O122: =1840-1840*0.4 -> 1104 | P122: ='ALL DATA & IT4PROFIT'!H170 | Q122: ='ALL DATA & IT4PROFIT'!K170 | R122: ='ALL DATA & IT4PROFIT'!D170
B123: ='ALL DATA & IT4PROFIT'!A171 -> SOLAX | C123: ='ALL DATA & IT4PROFIT'!B171 -> Pocket Wifi (2 years warranty) | D123: ='ALL DATA & IT4PROFIT'!C171 | E123: 1 | F123: ='ALL DATA & IT4PROFIT'!F171 | G123: =F123+$G$204 -> 30 | H123: =(G123*$E$204)+G123 -> 30.75 | I123: =(J123-H123)/J123 -> 0.1 | J123: =H123/(1-M123) -> 34.166667 | K123: =SUM(E123*J123) -> 34.166667 | L123: =SUM(E123*H123) -> 30.75 | M123: 0.1 | O123: =50-50*0.4 -> 30 | P123: ='ALL DATA & IT4PROFIT'!H171 | Q123: ='ALL DATA & IT4PROFIT'!K171 | R123: ='ALL DATA & IT4PROFIT'!D171
B124: ='ALL DATA & IT4PROFIT'!A172 -> SOLAX | C124: ='ALL DATA & IT4PROFIT'!B172 -> Pocket Lan 3.0 (2 years warranty) | D124: ='ALL DATA & IT4PROFIT'!C172 | E124: 1 | F124: ='ALL DATA & IT4PROFIT'!F172 | G124: =F124+$G$204 -> 30 | H124: =(G124*$E$204)+G124 -> 30.75 | I124: =(J124-H124)/J124 -> 0.1 | J124: =H124/(1-M124) -> 34.166667 | K124: =SUM(E124*J124) -> 34.166667 | L124: =SUM(E124*H124) -> 30.75 | M124: 0.1 | O124: =50-50*0.4 -> 30 | P124: ='ALL DATA & IT4PROFIT'!H172 | Q124: ='ALL DATA & IT4PROFIT'!K172 | R124: ='ALL DATA & IT4PROFIT'!D172
B125: ='ALL DATA & IT4PROFIT'!A173 | C125: ='ALL DATA & IT4PROFIT'!B173 | D125: ='ALL DATA & IT4PROFIT'!C173 | E125: 1 | F125: ='ALL DATA & IT4PROFIT'!F173 | G125: =F125+$G$204 -> 30 | H125: =(G125*$E$204)+G125 -> 30.75 | I125: =(J125-H125)/J125 -> 0.1 | J125: =H125/(1-M125) -> 34.166667 | K125: =SUM(E125*J125) -> 34.166667 | L125: =SUM(E125*H125) -> 30.75 | M125: 0.1 | P125: ='ALL DATA & IT4PROFIT'!H173 | Q125: ='ALL DATA & IT4PROFIT'!K173 | R125: ='ALL DATA & IT4PROFIT'!D173
B126: ='ALL DATA & IT4PROFIT'!A174 -> SMA | C126: ='ALL DATA & IT4PROFIT'!B174 -> SMA Hybrid Sunny Tripower 5.0 Smart Energy | D126: ='ALL DATA & IT4PROFIT'!C174 -> 3PH HYBRID | E126: 1 | F126: ='ALL DATA & IT4PROFIT'!F174 | G126: =F126+$G$204 -> 30 | H126: =(G126*$E$204)+G126 -> 30.75 | I126: =(J126-H126)/J126 -> 0.1 | J126: =H126/(1-M126) -> 34.166667 | K126: =SUM(E126*J126) -> 34.166667 | L126: =SUM(E126*H126) -> 30.75 | M126: 0.1 | P126: ='ALL DATA & IT4PROFIT'!H174 | Q126: ='ALL DATA & IT4PROFIT'!K174 | R126: ='ALL DATA & IT4PROFIT'!D174
B127: ='ALL DATA & IT4PROFIT'!A175 -> SMA | C127: ='ALL DATA & IT4PROFIT'!B175 -> SMA Hybrid Sunny Tripower 6.0 Smart Energy | D127: ='ALL DATA & IT4PROFIT'!C175 -> 3PH HYBRID | E127: 1 | F127: ='ALL DATA & IT4PROFIT'!F175 | G127: =F127+$G$204 -> 30 | H127: =(G127*$E$204)+G127 -> 30.75 | I127: =(J127-H127)/J127 -> 0.1 | J127: =H127/(1-M127) -> 34.166667 | K127: =SUM(E127*J127) -> 34.166667 | L127: =SUM(E127*H127) -> 30.75 | M127: 0.1 | P127: ='ALL DATA & IT4PROFIT'!H175 | Q127: ='ALL DATA & IT4PROFIT'!K175 | R127: ='ALL DATA & IT4PROFIT'!D175
B128: ='ALL DATA & IT4PROFIT'!A176 -> SMA | C128: ='ALL DATA & IT4PROFIT'!B176 -> SMA Hybrid Sunny Tripower 8.0 Smart Energy | D128: ='ALL DATA & IT4PROFIT'!C176 -> 3PH HYBRID | E128: 1 | F128: ='ALL DATA & IT4PROFIT'!F176 | G128: =F128+$G$204 -> 30 | H128: =(G128*$E$204)+G128 -> 30.75 | I128: =(J128-H128)/J128 -> 0.1 | J128: =H128/(1-M128) -> 34.166667 | K128: =SUM(E128*J128) -> 34.166667 | L128: =SUM(E128*H128) -> 30.75 | M128: 0.1 | P128: ='ALL DATA & IT4PROFIT'!H176 | Q128: ='ALL DATA & IT4PROFIT'!K176 | R128: ='ALL DATA & IT4PROFIT'!D176
B129: ='ALL DATA & IT4PROFIT'!A177 -> SMA | C129: ='ALL DATA & IT4PROFIT'!B177 -> SMA Hybrid Sunny Tripower 10.0 Smart Energy | D129: ='ALL DATA & IT4PROFIT'!C177 -> 3PH HYBRID | E129: 1 | F129: ='ALL DATA & IT4PROFIT'!F177 | G129: =F129+$G$204 -> 30 | H129: =(G129*$E$204)+G129 -> 30.75 | I129: =(J129-H129)/J129 -> 0.1 | J129: =H129/(1-M129) -> 34.166667 | K129: =SUM(E129*J129) -> 34.166667 | L129: =SUM(E129*H129) -> 30.75 | M129: 0.1 | P129: ='ALL DATA & IT4PROFIT'!H177 | Q129: ='ALL DATA & IT4PROFIT'!K177 | R129: ='ALL DATA & IT4PROFIT'!D177
B130: ='ALL DATA & IT4PROFIT'!A178 -> SMA | C130: ='ALL DATA & IT4PROFIT'!B178 -> SMA Sunny Boy 1.5 | D130: ='ALL DATA & IT4PROFIT'!C178 -> 1PH | E130: 1 | F130: ='ALL DATA & IT4PROFIT'!F178 | G130: =F130+$G$204 -> 30 | H130: =(G130*$E$204)+G130 -> 30.75 | I130: =(J130-H130)/J130 -> 0.1 | J130: =H130/(1-M130) -> 34.166667 | K130: =SUM(E130*J130) -> 34.166667 | L130: =SUM(E130*H130) -> 30.75 | M130: 0.1 | P130: ='ALL DATA & IT4PROFIT'!H178 | Q130: ='ALL DATA & IT4PROFIT'!K178 | R130: ='ALL DATA & IT4PROFIT'!D178
B131: ='ALL DATA & IT4PROFIT'!A179 -> SMA | C131: ='ALL DATA & IT4PROFIT'!B179 -> SMA Sunny Boy 2.5 | D131: ='ALL DATA & IT4PROFIT'!C179 -> 1PH | E131: 1 | F131: ='ALL DATA & IT4PROFIT'!F179 | G131: =F131+$G$204 -> 30 | H131: =(G131*$E$204)+G131 -> 30.75 | I131: =(J131-H131)/J131 -> 0.1 | J131: =H131/(1-M131) -> 34.166667 | K131: =SUM(E131*J131) -> 34.166667 | L131: =SUM(E131*H131) -> 30.75 | M131: 0.1 | P131: ='ALL DATA & IT4PROFIT'!H179 | Q131: ='ALL DATA & IT4PROFIT'!K179 | R131: ='ALL DATA & IT4PROFIT'!D179
B132: ='ALL DATA & IT4PROFIT'!A180 -> SMA | C132: ='ALL DATA & IT4PROFIT'!B180 -> SMA Sunny Boy 3.0 | D132: ='ALL DATA & IT4PROFIT'!C180 -> 1PH | E132: 1 | F132: ='ALL DATA & IT4PROFIT'!F180 -> 837 | G132: =F132+$G$204 -> 867 | H132: =(G132*$E$204)+G132 -> 888.675 | I132: =(J132-H132)/J132 -> 0.1 | J132: =H132/(1-M132) -> 987.41667 | K132: =SUM(E132*J132) -> 987.41667 | L132: =SUM(E132*H132) -> 888.675 | M132: 0.1 | P132: ='ALL DATA & IT4PROFIT'!H180 | Q132: ='ALL DATA & IT4PROFIT'!K180 | R132: ='ALL DATA & IT4PROFIT'!D180
B133: ='ALL DATA & IT4PROFIT'!A181 -> SMA | C133: ='ALL DATA & IT4PROFIT'!B181 -> SMA Sunny Boy 3.6 | D133: ='ALL DATA & IT4PROFIT'!C181 -> 1PH | E133: 1 | F133: ='ALL DATA & IT4PROFIT'!F181 -> 891.6 | G133: =F133+$G$204 -> 921.6 | H133: =(G133*$E$204)+G133 -> 944.64 | I133: =(J133-H133)/J133 -> 0.1 | J133: =H133/(1-M133) -> 1049.6 | K133: =SUM(E133*J133) -> 1049.6 | L133: =SUM(E133*H133) -> 944.64 | M133: 0.1 | P133: ='ALL DATA & IT4PROFIT'!H181 | Q133: ='ALL DATA & IT4PROFIT'!K181 | R133: ='ALL DATA & IT4PROFIT'!D181
...

Sheet Inverter price analysis Energy3
A1: BEU: | C1: Partner: | G1: Location: | P1: COMPETITION PRICES
G2: *distr.price+freight | J2: *devide (LCP CY)/(1-GM)
B3: Brand | C3: Description | D3: Type | E3: QTY | F3: Distributor Energy3000 Price | G3: LCP CY (€) | H3: Final LCP CY | I3: ASKY GM % | J3: Final Price to Customer | K3: Revenue | L3: LCP CY Revenue | M3: Desired GM | N3: CONERCON ENERGY | O3: BIG SOLAR | P3: DR. ENERGY | Q3: TRIKKIS ENERGY | R3: KAFKAS
B4: ='ALL DATA & IT4PROFIT'!A6 -> HUAWEI | C4: ='ALL DATA & IT4PROFIT'!B6 -> SUN2000-2KTL-L1 | D4: ='ALL DATA & IT4PROFIT'!C6 -> 1PH HYBRID | E4: 1 | F4: ='ALL DATA & IT4PROFIT'!R6 -> 449 | G4: =F4+$G$190 -> 539 | H4: =(G4*$E$190)+G4 -> 552.475 | I4: =(J4-H4)/J4 -> 0.07 | J4: =H4/(1-M4) -> 594.05914 | K4: =SUM(E4*J4) -> 594.05914 | L4: =SUM(E4*H4) -> 552.475 | M4: 0.07 | N4: ='ALL DATA & IT4PROFIT'!L6 -> 420 | P4: ='ALL DATA & IT4PROFIT'!H6 -> 557 | Q4: ='ALL DATA & IT4PROFIT'!K6 -> 344 | R4: ='ALL DATA & IT4PROFIT'!D6 -> 489
B5: ='ALL DATA & IT4PROFIT'!A7 -> HUAWEI | C5: ='ALL DATA & IT4PROFIT'!B7 -> SUN2000-3KTL-L1 | D5: ='ALL DATA & IT4PROFIT'!C7 -> 1PH HYBRID | E5: 1 | F5: ='ALL DATA & IT4PROFIT'!R7 -> 529 | G5: =F5+$G$190 -> 619 | H5: =(G5*$E$190)+G5 -> 634.475 | I5: =(J5-H5)/J5 -> 0.07 | J5: =H5/(1-M5) -> 682.23118 | K5: =SUM(E5*J5) -> 682.23118 | L5: =SUM(E5*H5) -> 634.475 | M5: 0.07 | N5: ='ALL DATA & IT4PROFIT'!L7 -> 510 | P5: ='ALL DATA & IT4PROFIT'!H7 -> 545 | Q5: ='ALL DATA & IT4PROFIT'!K7 -> 432 | R5: ='ALL DATA & IT4PROFIT'!D7 -> 575
B6: ='ALL DATA & IT4PROFIT'!A8 -> HUAWEI | C6: ='ALL DATA & IT4PROFIT'!B8 -> SUN2000-3.68KTL-L1 | D6: ='ALL DATA & IT4PROFIT'!C8 -> 1PH HYBRID | E6: 1 | F6: ='ALL DATA & IT4PROFIT'!R8 -> 523 | G6: =F6+$G$190 -> 613 | H6: =(G6*$E$190)+G6 -> 628.325 | I6: =(J6-H6)/J6 -> 0.07 | J6: =H6/(1-M6) -> 675.61828 | K6: =SUM(E6*J6) -> 675.61828 | L6: =SUM(E6*H6) -> 628.325 | M6: 0.07 | N6: ='ALL DATA & IT4PROFIT'!L8 -> 580 | P6: ='ALL DATA & IT4PROFIT'!H8 | Q6: ='ALL DATA & IT4PROFIT'!K8 | R6: ='ALL DATA & IT4PROFIT'!D8 -> 677
B7: ='ALL DATA & IT4PROFIT'!A9 -> HUAWEI | C7: ='ALL DATA & IT4PROFIT'!B9 -> SUN2000-4KTL-L1 | D7: ='ALL DATA & IT4PROFIT'!C9 -> 1PH HYBRID | E7: 1 | F7: ='ALL DATA & IT4PROFIT'!R9 -> 648 | G7: =F7+$G$190 -> 738 | H7: =(G7*$E$190)+G7 -> 756.45 | I7: =(J7-H7)/J7 -> 0.07 | J7: =H7/(1-M7) -> 813.3871 | K7: =SUM(E7*J7) -> 813.3871 | L7: =SUM(E7*H7) -> 756.45 | M7: 0.07 | N7: ='ALL DATA & IT4PROFIT'!L9 -> 620 | P7: ='ALL DATA & IT4PROFIT'!H9 -> 580 | Q7: ='ALL DATA & IT4PROFIT'!K9 -> 563 | R7: ='ALL DATA & IT4PROFIT'!D9 -> 705
B8: ='ALL DATA & IT4PROFIT'!A10 -> HUAWEI | C8: ='ALL DATA & IT4PROFIT'!B10 -> SUN2000-4.6KTL-L1 | D8: ='ALL DATA & IT4PROFIT'!C10 -> 1PH HYBRID | E8: 1 | F8: ='ALL DATA & IT4PROFIT'!R10 -> 696 | G8: =F8+$G$190 -> 786 | H8: =(G8*$E$190)+G8 -> 805.65 | I8: =(J8-H8)/J8 -> 0.07 | J8: =H8/(1-M8) -> 866.29032 | K8: =SUM(E8*J8) -> 866.29032 | L8: =SUM(E8*H8) -> 805.65 | M8: 0.07 | N8: ='ALL DATA & IT4PROFIT'!L10 -> 645 | P8: ='ALL DATA & IT4PROFIT'!H10 -> 595 | Q8: ='ALL DATA & IT4PROFIT'!K10 -> 616 | R8: ='ALL DATA & IT4PROFIT'!D10 -> 756
B9: ='ALL DATA & IT4PROFIT'!A11 -> HUAWEI | C9: ='ALL DATA & IT4PROFIT'!B11 -> SUN2000-5KTL-L1 | D9: ='ALL DATA & IT4PROFIT'!C11 -> 1PH HYBRID | E9: 1 | F9: ='ALL DATA & IT4PROFIT'!R11 -> 703 | G9: =F9+$G$190 -> 793 | H9: =(G9*$E$190)+G9 -> 812.825 | I9: =(J9-H9)/J9 -> 0.07 | J9: =H9/(1-M9) -> 874.00538 | K9: =SUM(E9*J9) -> 874.00538 | L9: =SUM(E9*H9) -> 812.825 | M9: 0.07 | N9: ='ALL DATA & IT4PROFIT'!L11 -> 660 | P9: ='ALL DATA & IT4PROFIT'!H11 -> 620 | Q9: ='ALL DATA & IT4PROFIT'!K11 -> 624 | R9: ='ALL DATA & IT4PROFIT'!D11 -> 764
B10: ='ALL DATA & IT4PROFIT'!A12 -> HUAWEI | C10: ='ALL DATA & IT4PROFIT'!B12 -> SUN2000-6KTL-L1 | D10: ='ALL DATA & IT4PROFIT'!C12 -> 1PH HYBRID | E10: 1 | F10: ='ALL DATA & IT4PROFIT'!R12 -> 799 | G10: =F10+$G$190 -> 889 | H10: =(G10*$E$190)+G10 -> 911.225 | I10: =(J10-H10)/J10 -> 0.07 | J10: =H10/(1-M10) -> 979.81183 | K10: =SUM(E10*J10) -> 979.81183 | L10: =SUM(E10*H10) -> 911.225 | M10: 0.07 | N10: ='ALL DATA & IT4PROFIT'!L12 | P10: ='ALL DATA & IT4PROFIT'!H12 | Q10: ='ALL DATA & IT4PROFIT'!K12 | R10: ='ALL DATA & IT4PROFIT'!D12 -> 868
B11: ='ALL DATA & IT4PROFIT'!A13 -> HUAWEI | C11: ='ALL DATA & IT4PROFIT'!B13 -> SUN2000-3KTL-M1 | D11: ='ALL DATA & IT4PROFIT'!C13 -> 3PH HYBRID | E11: 1 | F11: ='ALL DATA & IT4PROFIT'!R13 -> 794 | G11: =F11+$G$190 -> 884 | H11: =(G11*$E$190)+G11 -> 906.1 | I11: =(J11-H11)/J11 -> 0.07 | J11: =H11/(1-M11) -> 974.30108 | K11: =SUM(E11*J11) -> 974.30108 | L11: =SUM(E11*H11) -> 906.1 | M11: 0.07 | N11: ='ALL DATA & IT4PROFIT'!L13 -> 845 | P11: ='ALL DATA & IT4PROFIT'!H13 -> 907 | Q11: ='ALL DATA & IT4PROFIT'!K13 -> 832 | R11: ='ALL DATA & IT4PROFIT'!D13 -> 880
B12: ='ALL DATA & IT4PROFIT'!A14 -> HUAWEI | C12: ='ALL DATA & IT4PROFIT'!B14 -> SUN2000-4KTL-M1 | D12: ='ALL DATA & IT4PROFIT'!C14 -> 3PH HYBRID | E12: 1 | F12: ='ALL DATA & IT4PROFIT'!R14 -> 830 | G12: =F12+$G$190 -> 920 | H12: =(G12*$E$190)+G12 -> 943 | I12: =(J12-H12)/J12 -> 0.07 | J12: =H12/(1-M12) -> 1013.9785 | K12: =SUM(E12*J12) -> 1013.9785 | L12: =SUM(E12*H12) -> 943 | M12: 0.07 | N12: ='ALL DATA & IT4PROFIT'!L14 -> 880 | P12: ='ALL DATA & IT4PROFIT'!H14 -> 906 | Q12: ='ALL DATA & IT4PROFIT'!K14 -> 871 | R12: ='ALL DATA & IT4PROFIT'!D14 -> 920
B13: ='ALL DATA & IT4PROFIT'!A15 -> HUAWEI | C13: ='ALL DATA & IT4PROFIT'!B15 -> SUN2000-5KTL-M1 | D13: ='ALL DATA & IT4PROFIT'!C15 -> 3PH HYBRID | E13: 1 | F13: ='ALL DATA & IT4PROFIT'!R15 -> 876 | G13: =F13+$G$190 -> 966 | H13: =(G13*$E$190)+G13 -> 990.15 | I13: =(J13-H13)/J13 -> 0.07 | J13: =H13/(1-M13) -> 1064.6774 | K13: =SUM(E13*J13) -> 1064.6774 | L13: =SUM(E13*H13) -> 990.15 | M13: 0.07 | N13: ='ALL DATA & IT4PROFIT'!L15 -> 930 | P13: ='ALL DATA & IT4PROFIT'!H15 -> 930 | Q13: ='ALL DATA & IT4PROFIT'!K15 -> 919 | R13: ='ALL DATA & IT4PROFIT'!D15 -> 971
B14: ='ALL DATA & IT4PROFIT'!A16 -> HUAWEI | C14: ='ALL DATA & IT4PROFIT'!B16 -> SUN2000-6KTL-M1 | D14: ='ALL DATA & IT4PROFIT'!C16 -> 3PH HYBRID | E14: 1 | F14: ='ALL DATA & IT4PROFIT'!R16 -> 980 | G14: =F14+$G$190 -> 1070 | H14: =(G14*$E$190)+G14 -> 1096.75 | I14: =(J14-H14)/J14 -> 0.07 | J14: =H14/(1-M14) -> 1179.3011 | K14: =SUM(E14*J14) -> 1179.3011 | L14: =SUM(E14*H14) -> 1096.75 | M14: 0.07 | N14: ='ALL DATA & IT4PROFIT'!L16 -> 1040 | P14: ='ALL DATA & IT4PROFIT'!H16 -> 1090 | Q14: ='ALL DATA & IT4PROFIT'!K16 -> 1028 | R14: ='ALL DATA & IT4PROFIT'!D16 -> 1086
B15: ='ALL DATA & IT4PROFIT'!A17 -> HUAWEI | C15: ='ALL DATA & IT4PROFIT'!B17 -> SUN2000-8KTL-M1 | D15: ='ALL DATA & IT4PROFIT'!C17 -> 3PH HYBRID | E15: 1 | F15: ='ALL DATA & IT4PROFIT'!R17 -> 1162 | G15: =F15+$G$190 -> 1252 | H15: =(G15*$E$190)+G15 -> 1283.3 | I15: =(J15-H15)/J15 -> 0.07 | J15: =H15/(1-M15) -> 1379.8925 | K15: =SUM(E15*J15) -> 1379.8925 | L15: =SUM(E15*H15) -> 1283.3 | M15: 0.07 | N15: ='ALL DATA & IT4PROFIT'!L17 -> 1235 | P15: ='ALL DATA & IT4PROFIT'!H17 -> 1260 | Q15: ='ALL DATA & IT4PROFIT'!K17 -> 1219 | R15: ='ALL DATA & IT4PROFIT'!D17 -> 1289
... B30: ='ALL DATA & IT4PROFIT'!A32 -> HUAWEI | C30: ='ALL DATA & IT4PROFIT'!B32 -> IV HU SUN2000-330KTL-H1 (1500V) | D30: ='ALL DATA & IT4PROFIT'!C32 | E30: 1 | F30: ='ALL DATA & IT4PROFIT'!R32 | G30: =F30+$G$190 -> 90 | H30: =(G30*$E$190)+G30 -> 92.25 | I30: =(J30-H30)/J30 -> 0.07 | J30: =H30/(1-M30) -> 99.193548 | K30: =SUM(E30*J30) -> 99.193548 | L30: =SUM(E30*H30) -> 92.25 | M30: 0.07 | N30: ='ALL DATA & IT4PROFIT'!L32 | P30: ='ALL DATA & IT4PROFIT'!H32 | Q30: ='ALL DATA & IT4PROFIT'!K32 | R30: ='ALL DATA & IT4PROFIT'!D32
B31: ='ALL DATA & IT4PROFIT'!A34 | C31: ='ALL DATA & IT4PROFIT'!B34 | D31: ='ALL DATA & IT4PROFIT'!C34 | E31: 1 | F31: ='ALL DATA & IT4PROFIT'!R34 | G31: =F31+$G$190 -> 90 | H31: =(G31*$E$190)+G31 -> 92.25 | I31: =(J31-H31)/J31 -> 0.07 | J31: =H31/(1-M31) -> 99.193548 | K31: =SUM(E31*J31) -> 99.193548 | L31: =SUM(E31*H31) -> 92.25 | M31: 0.07 | N31: ='ALL DATA & IT4PROFIT'!L34 | P31: ='ALL DATA & IT4PROFIT'!H34 | Q31: ='ALL DATA & IT4PROFIT'!K34 | R31: ='ALL DATA & IT4PROFIT'!D34
B32: ='ALL DATA & IT4PROFIT'!A35 -> HUAWEI | C32: ='ALL DATA & IT4PROFIT'!B35 -> SUN2000-450W-P2 | D32: ='ALL DATA & IT4PROFIT'!C35 -> OPTIMIZER | E32: 1 | F32: ='ALL DATA & IT4PROFIT'!R35 -> 35 | G32: =F32+$G$191 -> 40 | H32: =(G32*$E$190)+G32 -> 41 | I32: =(J32-H32)/J32 -> 0.07 | J32: =H32/(1-M32) -> 44.086022 | K32: =SUM(E32*J32) -> 44.086022 | L32: =SUM(E32*H32) -> 41 | M32: 0.07 | N32: ='ALL DATA & IT4PROFIT'!L35 -> 40 | P32: ='ALL DATA & IT4PROFIT'!H35 | Q32: ='ALL DATA & IT4PROFIT'!K35 -> 38.5 | R32: ='ALL DATA & IT4PROFIT'!D35 -> 41
B33: ='ALL DATA & IT4PROFIT'!A36 -> HUAWEI | C33: ='ALL DATA & IT4PROFIT'!B36 -> SUN2000-600W-P | D33: ='ALL DATA & IT4PROFIT'!C36 -> OPTIMIZER | E33: 1 | F33: ='ALL DATA & IT4PROFIT'!R36 -> 36.4 | G33: =F33+$G$191 -> 41.4 | H33: =(G33*$E$190)+G33 -> 42.435 | I33: =(J33-H33)/J33 -> 0.07 | J33: =H33/(1-M33) -> 45.629032 | K33: =SUM(E33*J33) -> 45.629032 | L33: =SUM(E33*H33) -> 42.435 | M33: 0.07 | N33: ='ALL DATA & IT4PROFIT'!L36 -> 40 | P33: ='ALL DATA & IT4PROFIT'!H36 | Q33: ='ALL DATA & IT4PROFIT'!K36 -> 39 | R33: ='ALL DATA & IT4PROFIT'!D36 -> 41
B34: ='ALL DATA & IT4PROFIT'!A37 | C34: ='ALL DATA & IT4PROFIT'!B37 | D34: ='ALL DATA & IT4PROFIT'!C37 | E34: 1 | F34: ='ALL DATA & IT4PROFIT'!R37 | G34: =F34+$G$190 -> 90 | H34: =(G34*$E$190)+G34 -> 92.25 | I34: =(J34-H34)/J34 -> 0.07 | J34: =H34/(1-M34) -> 99.193548 | K34: =SUM(E34*J34) -> 99.193548 | L34: =SUM(E34*H34) -> 92.25 | M34: 0.07 | N34: ='ALL DATA & IT4PROFIT'!L37 | P34: ='ALL DATA & IT4PROFIT'!H37 | Q34: ='ALL DATA & IT4PROFIT'!K37 | R34: ='ALL DATA & IT4PROFIT'!D37
B35: ='ALL DATA & IT4PROFIT'!A38 | C35: ='ALL DATA & IT4PROFIT'!B38 | D35: ='ALL DATA & IT4PROFIT'!C38 | E35: 1 | F35: ='ALL DATA & IT4PROFIT'!R38 | G35: =F35+$G$190 -> 90 | H35: =(G35*$E$190)+G35 -> 92.25 | I35: =(J35-H35)/J35 -> 0.07 | J35: =H35/(1-M35) -> 99.193548 | K35: =SUM(E35*J35) -> 99.193548 | L35: =SUM(E35*H35) -> 92.25 | M35: 0.07 | N35: ='ALL DATA & IT4PROFIT'!L38 | P35: ='ALL DATA & IT4PROFIT'!H38 | Q35: ='ALL DATA & IT4PROFIT'!K38 | R35: ='ALL DATA & IT4PROFIT'!D38
B36: ='ALL DATA & IT4PROFIT'!A39 -> SUNGROW | C36: ='ALL DATA & IT4PROFIT'!B39 -> IV SUNG SG2.0RS | D36: ='ALL DATA & IT4PROFIT'!C39 -> 1PH | E36: 1 | F36: ='ALL DATA & IT4PROFIT'!R39 | G36: =F36+$G$190 -> 90 | H36: =(G36*$E$190)+G36 -> 92.25 | I36: =(J36-H36)/J36 -> 0.07 | J36: =H36/(1-M36) -> 99.193548 | K36: =SUM(E36*J36) -> 99.193548 | L36: =SUM(E36*H36) -> 92.25 | M36: 0.07 | N36: ='ALL DATA & IT4PROFIT'!L39 | P36: ='ALL DATA & IT4PROFIT'!H39 | Q36: ='ALL DATA & IT4PROFIT'!K39 | R36: ='ALL DATA & IT4PROFIT'!D39
B37: ='ALL DATA & IT4PROFIT'!A40 -> SUNGROW | C37: ='ALL DATA & IT4PROFIT'!B40 -> IV SUNG SG3.0RS | D37: ='ALL DATA & IT4PROFIT'!C40 -> 1PH | E37: 1 | F37: ='ALL DATA & IT4PROFIT'!R40 | G37: =F37+$G$190 -> 90 | H37: =(G37*$E$190)+G37 -> 92.25 | I37: =(J37-H37)/J37 -> 0.07 | J37: =H37/(1-M37) -> 99.193548 | K37: =SUM(E37*J37) -> 99.193548 | L37: =SUM(E37*H37) -> 92.25 | M37: 0.07 | N37: ='ALL DATA & IT4PROFIT'!L40 | P37: ='ALL DATA & IT4PROFIT'!H40 | Q37: ='ALL DATA & IT4PROFIT'!K40 | R37: ='ALL DATA & IT4PROFIT'!D40
B38: ='ALL DATA & IT4PROFIT'!A41 -> SUNGROW | C38: ='ALL DATA & IT4PROFIT'!B41 -> IV SUNG SG4.0RS | D38: ='ALL DATA & IT4PROFIT'!C41 -> 1PH | E38: 1 | F38: ='ALL DATA & IT4PROFIT'!R41 | G38: =F38+$G$190 -> 90 | H38: =(G38*$E$190)+G38 -> 92.25 | I38: =(J38-H38)/J38 -> 0.07 | J38: =H38/(1-M38) -> 99.193548 | K38: =SUM(E38*J38) -> 99.193548 | L38: =SUM(E38*H38) -> 92.25 | M38: 0.07 | N38: ='ALL DATA & IT4PROFIT'!L41 | P38: ='ALL DATA & IT4PROFIT'!H41 | Q38: ='ALL DATA & IT4PROFIT'!K41 | R38: ='ALL DATA & IT4PROFIT'!D41
B39: ='ALL DATA & IT4PROFIT'!A42 -> SUNGROW | C39: ='ALL DATA & IT4PROFIT'!B42 -> IV SUNG SG5.0RS | D39: ='ALL DATA & IT4PROFIT'!C42 -> 1PH | E39: 1 | F39: ='ALL DATA & IT4PROFIT'!R42 | G39: =F39+$G$190 -> 90 | H39: =(G39*$E$190)+G39 -> 92.25 | I39: =(J39-H39)/J39 -> 0.07 | J39: =H39/(1-M39) -> 99.193548 | K39: =SUM(E39*J39) -> 99.193548 | L39: =SUM(E39*H39) -> 92.25 | M39: 0.07 | N39: ='ALL DATA & IT4PROFIT'!L42 | P39: ='ALL DATA & IT4PROFIT'!H42 | Q39: ='ALL DATA & IT4PROFIT'!K42 | R39: ='ALL DATA & IT4PROFIT'!D42
B40: ='ALL DATA & IT4PROFIT'!A43 -> SUNGROW | C40: ='ALL DATA & IT4PROFIT'!B43 -> IV SUNG SG3.0RT | D40: ='ALL DATA & IT4PROFIT'!C43 -> 3PH | E40: 1 | F40: ='ALL DATA & IT4PROFIT'!R43 | G40: =F40+$G$190 -> 90 | H40: =(G40*$E$190)+G40 -> 92.25 | I40: =(J40-H40)/J40 -> 0.07 | J40: =H40/(1-M40) -> 99.193548 | K40: =SUM(E40*J40) -> 99.193548 | L40: =SUM(E40*H40) -> 92.25 | M40: 0.07 | N40: ='ALL DATA & IT4PROFIT'!L43 | P40: ='ALL DATA & IT4PROFIT'!H43 | Q40: ='ALL DATA & IT4PROFIT'!K43 | R40: ='ALL DATA & IT4PROFIT'!D43
B41: ='ALL DATA & IT4PROFIT'!A44 -> SUNGROW | C41: ='ALL DATA & IT4PROFIT'!B44 -> IV SUNG SG4.0RT | D41: ='ALL DATA & IT4PROFIT'!C44 -> 3PH | E41: 1 | F41: ='ALL DATA & IT4PROFIT'!R44 | G41: =F41+$G$190 -> 90 | H41: =(G41*$E$190)+G41 -> 92.25 | I41: =(J41-H41)/J41 -> 0.07 | J41: =H41/(1-M41) -> 99.193548 | K41: =SUM(E41*J41) -> 99.193548 | L41: =SUM(E41*H41) -> 92.25 | M41: 0.07 | N41: ='ALL DATA & IT4PROFIT'!L44 | P41: ='ALL DATA & IT4PROFIT'!H44 | Q41: ='ALL DATA & IT4PROFIT'!K44 | R41: ='ALL DATA & IT4PROFIT'!D44
B42: ='ALL DATA & IT4PROFIT'!A45 -> SUNGROW | C42: ='ALL DATA & IT4PROFIT'!B45 -> IV SUNG SG5.0RT | D42: ='ALL DATA & IT4PROFIT'!C45 -> 3PH | E42: 1 | F42: ='ALL DATA & IT4PROFIT'!R45 | G42: =F42+$G$190 -> 90 | H42: =(G42*$E$190)+G42 -> 92.25 | I42: =(J42-H42)/J42 -> 0.07 | J42: =H42/(1-M42) -> 99.193548 | K42: =SUM(E42*J42) -> 99.193548 | L42: =SUM(E42*H42) -> 92.25 | M42: 0.07 | N42: ='ALL DATA & IT4PROFIT'!L45 | P42: ='ALL DATA & IT4PROFIT'!H45 | Q42: ='ALL DATA & IT4PROFIT'!K45 | R42: ='ALL DATA & IT4PROFIT'!D45
B43: ='ALL DATA & IT4PROFIT'!A46 -> SUNGROW | C43: ='ALL DATA & IT4PROFIT'!B46 -> IV SUNG SG6.0RT | D43: ='ALL DATA & IT4PROFIT'!C46 -> 3PH | E43: 1 | F43: ='ALL DATA & IT4PROFIT'!R46 | G43: =F43+$G$190 -> 90 | H43: =(G43*$E$190)+G43 -> 92.25 | I43: =(J43-H43)/J43 -> 0.07 | J43: =H43/(1-M43) -> 99.193548 | K43: =SUM(E43*J43) -> 99.193548 | L43: =SUM(E43*H43) -> 92.25 | M43: 0.07 | N43: ='ALL DATA & IT4PROFIT'!L46 | P43: ='ALL DATA & IT4PROFIT'!H46 | Q43: ='ALL DATA & IT4PROFIT'!K46 | R43: ='ALL DATA & IT4PROFIT'!D46
B44: ='ALL DATA & IT4PROFIT'!A47 -> SUNGROW | C44: ='ALL DATA & IT4PROFIT'!B47 -> IV SUNG SG8.0RT | D44: ='ALL DATA & IT4PROFIT'!C47 -> 3PH | E44: 1 | F44: ='ALL DATA & IT4PROFIT'!R47 | G44: =F44+$G$190 -> 90 | H44: =(G44*$E$190)+G44 -> 92.25 | I44: =(J44-H44)/J44 -> 0.07 | J44: =H44/(1-M44) -> 99.193548 | K44: =SUM(E44*J44) -> 99.193548 | L44: =SUM(E44*H44) -> 92.25 | M44: 0.07 | N44: ='ALL DATA & IT4PROFIT'!L47 | P44: ='ALL DATA & IT4PROFIT'!H47 | Q44: ='ALL DATA & IT4PROFIT'!K47 | R44: ='ALL DATA & IT4PROFIT'!D47
B45: ='ALL DATA & IT4PROFIT'!A48 -> SUNGROW | C45: ='ALL DATA & IT4PROFIT'!B48 -> IV SUNG SG10.0RT | D45: ='ALL DATA & IT4PROFIT'!C48 -> 3PH | E45: 1 | F45: ='ALL DATA & IT4PROFIT'!R48 | G45: =F45+$G$190 -> 90 | H45: =(G45*$E$190)+G45 -> 92.25 | I45: =(J45-H45)/J45 -> 0.07 | J45: =H45/(1-M45) -> 99.193548 | K45: =SUM(E45*J45) -> 99.193548 | L45: =SUM(E45*H45) -> 92.25 | M45: 0.07 | N45: ='ALL DATA & IT4PROFIT'!L48 | P45: ='ALL DATA & IT4PROFIT'!H48 | Q45: ='ALL DATA & IT4PROFIT'!K48 | R45: ='ALL DATA & IT4PROFIT'!D48
... B59: ='ALL DATA & IT4PROFIT'!A62 | C59: ='ALL DATA & IT4PROFIT'!B62 | D59: ='ALL DATA & IT4PROFIT'!C62 | E59: 1 | F59: ='ALL DATA & IT4PROFIT'!R62 | G59: =F59+$G$190 -> 90 | H59: =(G59*$E$190)+G59 -> 92.25 | I59: =(J59-H59)/J59 -> 0.07 | J59: =H59/(1-M59) -> 99.193548 | K59: =SUM(E59*J59) -> 99.193548 | L59: =SUM(E59*H59) -> 92.25 | M59: 0.07 | N59: ='ALL DATA & IT4PROFIT'!L62 | P59: ='ALL DATA & IT4PROFIT'!H62 | Q59: ='ALL DATA & IT4PROFIT'!K62 | R59: ='ALL DATA & IT4PROFIT'!D62
B60: ='ALL DATA & IT4PROFIT'!A63 -> FRONIUS | C60: ='ALL DATA & IT4PROFIT'!B63 -> PRIMO 3.0 | D60: ='ALL DATA & IT4PROFIT'!C63 -> 1PH | E60: 1 | F60: ='ALL DATA & IT4PROFIT'!R63 | G60: =F60+$G$190 -> 90 | H60: =(G60*$E$190)+G60 -> 92.25 | I60: =(J60-H60)/J60 -> 0.07 | J60: =H60/(1-M60) -> 99.193548 | K60: =SUM(E60*J60) -> 99.193548 | L60: =SUM(E60*H60) -> 92.25 | M60: 0.07 | N60: ='ALL DATA & IT4PROFIT'!L63 | O60: =1570-1570*0.42 -> 910.6 | P60: ='ALL DATA & IT4PROFIT'!H63 -> 950 | Q60: ='ALL DATA & IT4PROFIT'!K63 | R60: ='ALL DATA & IT4PROFIT'!D63
B61: ='ALL DATA & IT4PROFIT'!A64 -> FRONIUS | C61: ='ALL DATA & IT4PROFIT'!B64 -> Fronius Primo 3.6-1 | D61: ='ALL DATA & IT4PROFIT'!C64 | E61: 1 | F61: ='ALL DATA & IT4PROFIT'!R64 | G61: =F61+$G$190 -> 90 | H61: =(G61*$E$190)+G61 -> 92.25 | I61: =(J61-H61)/J61 -> 0.07 | J61: =H61/(1-M61) -> 99.193548 | K61: =SUM(E61*J61) -> 99.193548 | L61: =SUM(E61*H61) -> 92.25 | M61: 0.07 | N61: ='ALL DATA & IT4PROFIT'!L64 | P61: ='ALL DATA & IT4PROFIT'!H64 | Q61: ='ALL DATA & IT4PROFIT'!K64 | R61: ='ALL DATA & IT4PROFIT'!D64
B62: ='ALL DATA & IT4PROFIT'!A65 -> FRONIUS | C62: ='ALL DATA & IT4PROFIT'!B65 -> PRIMO 4.0 | D62: ='ALL DATA & IT4PROFIT'!C65 -> 1PH | E62: 1 | F62: ='ALL DATA & IT4PROFIT'!R65 | G62: =F62+$G$190 -> 90 | H62: =(G62*$E$190)+G62 -> 92.25 | I62: =(J62-H62)/J62 -> 0.07 | J62: =H62/(1-M62) -> 99.193548 | K62: =SUM(E62*J62) -> 99.193548 | L62: =SUM(E62*H62) -> 92.25 | M62: 0.07 | N62: ='ALL DATA & IT4PROFIT'!L65 | O62: =1740-1740*0.42 -> 1009.2 | P62: ='ALL DATA & IT4PROFIT'!H65 -> 1026 | Q62: ='ALL DATA & IT4PROFIT'!K65 | R62: ='ALL DATA & IT4PROFIT'!D65
B63: ='ALL DATA & IT4PROFIT'!A66 -> FRONIUS | C63: ='ALL DATA & IT4PROFIT'!B66 -> Fronius Primo 4.6-1 | D63: ='ALL DATA & IT4PROFIT'!C66 | E63: 1 | F63: ='ALL DATA & IT4PROFIT'!R66 | G63: =F63+$G$190 -> 90 | H63: =(G63*$E$190)+G63 -> 92.25 | I63: =(J63-H63)/J63 -> 0.07 | J63: =H63/(1-M63) -> 99.193548 | K63: =SUM(E63*J63) -> 99.193548 | L63: =SUM(E63*H63) -> 92.25 | M63: 0.07 | N63: ='ALL DATA & IT4PROFIT'!L66 | P63: ='ALL DATA & IT4PROFIT'!H66 | Q63: ='ALL DATA & IT4PROFIT'!K66 | R63: ='ALL DATA & IT4PROFIT'!D66
B64: ='ALL DATA & IT4PROFIT'!A67 -> FRONIUS | C64: ='ALL DATA & IT4PROFIT'!B67 -> PRIMO 5.0 | D64: ='ALL DATA & IT4PROFIT'!C67 -> 1PH | E64: 1 | F64: ='ALL DATA & IT4PROFIT'!R67 | G64: =F64+$G$190 -> 90 | H64: =(G64*$E$190)+G64 -> 92.25 | I64: =(J64-H64)/J64 -> 0.07 | J64: =H64/(1-M64) -> 99.193548 | K64: =SUM(E64*J64) -> 99.193548 | L64: =SUM(E64*H64) -> 92.25 | M64: 0.07 | N64: ='ALL DATA & IT4PROFIT'!L67 | O64: =1905-1905*0.42 -> 1104.9 | P64: ='ALL DATA & IT4PROFIT'!H67 -> 1124 | Q64: ='ALL DATA & IT4PROFIT'!K67 | R64: ='ALL DATA & IT4PROFIT'!D67
B65: ='ALL DATA & IT4PROFIT'!A68 | C65: ='ALL DATA & IT4PROFIT'!B68 | D65: ='ALL DATA & IT4PROFIT'!C68 | E65: 1 | F65: ='ALL DATA & IT4PROFIT'!R68 | G65: =F65+$G$190 -> 90 | H65: =(G65*$E$190)+G65 -> 92.25 | I65: =(J65-H65)/J65 -> 0.07 | J65: =H65/(1-M65) -> 99.193548 | K65: =SUM(E65*J65) -> 99.193548 | L65: =SUM(E65*H65) -> 92.25 | M65: 0.07 | N65: ='ALL DATA & IT4PROFIT'!L68 | P65: ='ALL DATA & IT4PROFIT'!H68 | Q65: ='ALL DATA & IT4PROFIT'!K68 | R65: ='ALL DATA & IT4PROFIT'!D68
B66: ='ALL DATA & IT4PROFIT'!A69 -> FRONIUS | C66: ='ALL DATA & IT4PROFIT'!B69 -> SYMO 3.0-S | D66: ='ALL DATA & IT4PROFIT'!C69 -> 3PH | E66: 1 | F66: ='ALL DATA & IT4PROFIT'!R69 | G66: =F66+$G$190 -> 90 | H66: =(G66*$E$190)+G66 -> 92.25 | I66: =(J66-H66)/J66 -> 0.07 | J66: =H66/(1-M66) -> 99.193548 | K66: =SUM(E66*J66) -> 99.193548 | L66: =SUM(E66*H66) -> 92.25 | M66: 0.07 | N66: ='ALL DATA & IT4PROFIT'!L69 | O66: =1630-1630*0.42 -> 945.4 | P66: ='ALL DATA & IT4PROFIT'!H69 -> 955 | Q66: ='ALL DATA & IT4PROFIT'!K69 | R66: ='ALL DATA & IT4PROFIT'!D69
B67: ='ALL DATA & IT4PROFIT'!A70 -> FRONIUS | C67: ='ALL DATA & IT4PROFIT'!B70 -> SYMO 3.7-S | D67: ='ALL DATA & IT4PROFIT'!C70 -> 3PH | E67: 1 | F67: ='ALL DATA & IT4PROFIT'!R70 | G67: =F67+$G$190 -> 90 | H67: =(G67*$E$190)+G67 -> 92.25 | I67: =(J67-H67)/J67 -> 0.07 | J67: =H67/(1-M67) -> 99.193548 | K67: =SUM(E67*J67) -> 99.193548 | L67: =SUM(E67*H67) -> 92.25 | M67: 0.07 | N67: ='ALL DATA & IT4PROFIT'!L70 | O67: =1790-1790*0.42 -> 1038.2 | P67: ='ALL DATA & IT4PROFIT'!H70 -> 960 | Q67: ='ALL DATA & IT4PROFIT'!K70 | R67: ='ALL DATA & IT4PROFIT'!D70
B68: ='ALL DATA & IT4PROFIT'!A71 -> FRONIUS | C68: ='ALL DATA & IT4PROFIT'!B71 -> SYMO 4.5-S | D68: ='ALL DATA & IT4PROFIT'!C71 -> 3PH | E68: 1 | F68: ='ALL DATA & IT4PROFIT'!R71 | G68: =F68+$G$190 -> 90 | H68: =(G68*$E$190)+G68 -> 92.25 | I68: =(J68-H68)/J68 -> 0.07 | J68: =H68/(1-M68) -> 99.193548 | K68: =SUM(E68*J68) -> 99.193548 | L68: =SUM(E68*H68) -> 92.25 | M68: 0.07 | N68: ='ALL DATA & IT4PROFIT'!L71 | O68: =1980-1980*0.42 -> 1148.4 | P68: ='ALL DATA & IT4PROFIT'!H71 | Q68: ='ALL DATA & IT4PROFIT'!K71 | R68: ='ALL DATA & IT4PROFIT'!D71
B69: ='ALL DATA & IT4PROFIT'!A72 -> FRONIUS | C69: ='ALL DATA & IT4PROFIT'!B72 -> SYMO 3.0-M | D69: ='ALL DATA & IT4PROFIT'!C72 -> 3PH | E69: 1 | F69: ='ALL DATA & IT4PROFIT'!R72 -> 885.89 | G69: =F69+$G$190 -> 975.89 | H69: =(G69*$E$190)+G69 -> 1000.2872 | I69: =(J69-H69)/J69 -> 0.07 | J69: =H69/(1-M69) -> 1075.5777 | K69: =SUM(E69*J69) -> 1075.5777 | L69: =SUM(E69*H69) -> 1000.2872 | M69: 0.07 | N69: ='ALL DATA & IT4PROFIT'!L72 | O69: =1800-1800*0.42 -> 1044 | P69: ='ALL DATA & IT4PROFIT'!H72 -> 1040 | Q69: ='ALL DATA & IT4PROFIT'!K72 | R69: ='ALL DATA & IT4PROFIT'!D72
B70: ='ALL DATA & IT4PROFIT'!A73 -> FRONIUS | C70: ='ALL DATA & IT4PROFIT'!B73 -> SYMO 3.7-M | D70: ='ALL DATA & IT4PROFIT'!C73 -> 3PH | E70: 1 | F70: ='ALL DATA & IT4PROFIT'!R73 | G70: =F70+$G$190 -> 90 | H70: =(G70*$E$190)+G70 -> 92.25 | I70: =(J70-H70)/J70 -> 0.07 | J70: =H70/(1-M70) -> 99.193548 | K70: =SUM(E70*J70) -> 99.193548 | L70: =SUM(E70*H70) -> 92.25 | M70: 0.07 | N70: ='ALL DATA & IT4PROFIT'!L73 | O70: =1980-1980*0.42 -> 1148.4 | P70: ='ALL DATA & IT4PROFIT'!H73 -> 1168 | Q70: ='ALL DATA & IT4PROFIT'!K73 | R70: ='ALL DATA & IT4PROFIT'!D73
B71: ='ALL DATA & IT4PROFIT'!A74 -> FRONIUS | C71: ='ALL DATA & IT4PROFIT'!B74 -> SYMO 4.5-M | D71: ='ALL DATA & IT4PROFIT'!C74 -> 3PH | E71: 1 | F71: ='ALL DATA & IT4PROFIT'!R74 -> 1033 | G71: =F71+$G$190 -> 1123 | H71: =(G71*$E$190)+G71 -> 1151.075 | I71: =(J71-H71)/J71 -> 0.07 | J71: =H71/(1-M71) -> 1237.7151 | K71: =SUM(E71*J71) -> 1237.7151 | L71: =SUM(E71*H71) -> 1151.075 | M71: 0.07 | N71: ='ALL DATA & IT4PROFIT'!L74 | O71: =2090-2090*0.42 -> 1212.2 | P71: ='ALL DATA & IT4PROFIT'!H74 -> 1240 | Q71: ='ALL DATA & IT4PROFIT'!K74 | R71: ='ALL DATA & IT4PROFIT'!D74
B72: ='ALL DATA & IT4PROFIT'!A75 -> FRONIUS | C72: ='ALL DATA & IT4PROFIT'!B75 -> SYMO 5.0-M | D72: ='ALL DATA & IT4PROFIT'!C75 -> 3PH | E72: 1 | F72: ='ALL DATA & IT4PROFIT'!R75 -> 1033 | G72: =F72+$G$190 -> 1123 | H72: =(G72*$E$190)+G72 -> 1151.075 | I72: =(J72-H72)/J72 -> 0.07 | J72: =H72/(1-M72) -> 1237.7151 | K72: =SUM(E72*J72) -> 1237.7151 | L72: =SUM(E72*H72) -> 1151.075 | M72: 0.07 | N72: ='ALL DATA & IT4PROFIT'!L75 | O72: =2120-2120*0.42 -> 1229.6 | P72: ='ALL DATA & IT4PROFIT'!H75 -> 1250 | Q72: ='ALL DATA & IT4PROFIT'!K75 | R72: ='ALL DATA & IT4PROFIT'!D75
B73: ='ALL DATA & IT4PROFIT'!A76 -> FRONIUS | C73: ='ALL DATA & IT4PROFIT'!B76 -> SYMO 6.0-M | D73: ='ALL DATA & IT4PROFIT'!C76 -> 3PH | E73: 1 | F73: ='ALL DATA & IT4PROFIT'!R76 -> 1055 | G73: =F73+$G$190 -> 1145 | H73: =(G73*$E$190)+G73 -> 1173.625 | I73: =(J73-H73)/J73 -> 0.07 | J73: =H73/(1-M73) -> 1261.9624 | K73: =SUM(E73*J73) -> 1261.9624 | L73: =SUM(E73*H73) -> 1173.625 | M73: 0.07 | N73: ='ALL DATA & IT4PROFIT'!L76 | O73: =2160-2160*0.42 -> 1252.8 | P73: ='ALL DATA & IT4PROFIT'!H76 -> 1274 | Q73: ='ALL DATA & IT4PROFIT'!K76 | R73: ='ALL DATA & IT4PROFIT'!D76
B74: ='ALL DATA & IT4PROFIT'!A77 -> FRONIUS | C74: ='ALL DATA & IT4PROFIT'!B77 -> SYMO 7.0-M | D74: ='ALL DATA & IT4PROFIT'!C77 -> 3PH | E74: 1 | F74: ='ALL DATA & IT4PROFIT'!R77 -> 1309 | G74: =F74+$G$190 -> 1399 | H74: =(G74*$E$190)+G74 -> 1433.975 | I74: =(J74-H74)/J74 -> 0.07 | J74: =H74/(1-M74) -> 1541.9086 | K74: =SUM(E74*J74) -> 1541.9086 | L74: =SUM(E74*H74) -> 1433.975 | M74: 0.07 | N74: ='ALL DATA & IT4PROFIT'!L77 | O74: =2670-2670*0.42 -> 1548.6 | P74: ='ALL DATA & IT4PROFIT'!H77 -> 1580 | Q74: ='ALL DATA & IT4PROFIT'!K77 | R74: ='ALL DATA & IT4PROFIT'!D77
B75: ='ALL DATA & IT4PROFIT'!A78 -> FRONIUS | C75: ='ALL DATA & IT4PROFIT'!B78 -> SYMO 8.2-M | D75: ='ALL DATA & IT4PROFIT'!C78 -> 3PH | E75: 1 | F75: ='ALL DATA & IT4PROFIT'!R78 -> 1448 | G75: =F75+$G$190 -> 1538 | H75: =(G75*$E$190)+G75 -> 1576.45 | I75: =(J75-H75)/J75 -> 0.07 | J75: =H75/(1-M75) -> 1695.1075 | K75: =SUM(E75*J75) -> 1695.1075 | L75: =SUM(E75*H75) -> 1576.45 | M75: 0.07 | N75: ='ALL DATA & IT4PROFIT'!L78 | O75: =2950-2950*0.42 -> 1711 | P75: ='ALL DATA & IT4PROFIT'!H78 -> 1740 | Q75: ='ALL DATA & IT4PROFIT'!K78 | R75: ='ALL DATA & IT4PROFIT'!D78
B76: ='ALL DATA & IT4PROFIT'!A79 -> FRONIUS | C76: ='ALL DATA & IT4PROFIT'!B79 -> SYMO 10.0-M | D76: ='ALL DATA & IT4PROFIT'!C79 -> 3PH | E76: 1 | F76: ='ALL DATA & IT4PROFIT'!R79 -> 1491 | G76: =F76+$G$190 -> 1581 | H76: =(G76*$E$190)+G76 -> 1620.525 | I76: =(J76-H76)/J76 -> 0.07 | J76: =H76/(1-M76) -> 1742.5 | K76: =SUM(E76*J76) -> 1742.5 | L76: =SUM(E76*H76) -> 1620.525 | M76: 0.07 | N76: ='ALL DATA & IT4PROFIT'!L79 | O76: =3100-3100*0.42 -> 1798 | P76: ='ALL DATA & IT4PROFIT'!H79 -> 1895 | Q76: ='ALL DATA & IT4PROFIT'!K79 | R76: ='ALL DATA & IT4PROFIT'!D79
B77: ='ALL DATA & IT4PROFIT'!A80 -> FRONIUS | C77: ='ALL DATA & IT4PROFIT'!B80 -> SYMO 12.5-3-M | D77: ='ALL DATA & IT4PROFIT'!C80 -> 3PH | E77: 1 | F77: ='ALL DATA & IT4PROFIT'!R80 -> 1696 | G77: =F77+$G$190 -> 1786 | H77: =(G77*$E$190)+G77 -> 1830.65 | I77: =(J77-H77)/J77 -> 0.07 | J77: =H77/(1-M77) -> 1968.4409 | K77: =SUM(E77*J77) -> 1968.4409 | L77: =SUM(E77*H77) -> 1830.65 | M77: 0.07 | N77: ='ALL DATA & IT4PROFIT'!L80 | P77: ='ALL DATA & IT4PROFIT'!H80 | Q77: ='ALL DATA & IT4PROFIT'!K80 | R77: ='ALL DATA & IT4PROFIT'!D80
B78: ='ALL DATA & IT4PROFIT'!A81 -> FRONIUS | C78: ='ALL DATA & IT4PROFIT'!B81 -> SYMO 15.0-3-M | D78: ='ALL DATA & IT4PROFIT'!C81 -> 3PH | E78: 1 | F78: ='ALL DATA & IT4PROFIT'!R81 -> 1703 | G78: =F78+$G$190 -> 1793 | H78: =(G78*$E$190)+G78 -> 1837.825 | I78: =(J78-H78)/J78 -> 0.07 | J78: =H78/(1-M78) -> 1976.1559 | K78: =SUM(E78*J78) -> 1976.1559 | L78: =SUM(E78*H78) -> 1837.825 | M78: 0.07 | N78: ='ALL DATA & IT4PROFIT'!L81 | P78: ='ALL DATA & IT4PROFIT'!H81 | Q78: ='ALL DATA & IT4PROFIT'!K81 | R78: ='ALL DATA & IT4PROFIT'!D81
B79: ='ALL DATA & IT4PROFIT'!A82 -> FRONIUS | C79: ='ALL DATA & IT4PROFIT'!B82 -> SYMO 17.5-3-M | D79: ='ALL DATA & IT4PROFIT'!C82 -> 3PH | E79: 1 | F79: ='ALL DATA & IT4PROFIT'!R82 -> 1835 | G79: =F79+$G$190 -> 1925 | H79: =(G79*$E$190)+G79 -> 1973.125 | I79: =(J79-H79)/J79 -> 0.07 | J79: =H79/(1-M79) -> 2121.6398 | K79: =SUM(E79*J79) -> 2121.6398 | L79: =SUM(E79*H79) -> 1973.125 | M79: 0.07 | N79: ='ALL DATA & IT4PROFIT'!L82 | P79: ='ALL DATA & IT4PROFIT'!H82 | Q79: ='ALL DATA & IT4PROFIT'!K82 | R79: ='ALL DATA & IT4PROFIT'!D82
B80: ='ALL DATA & IT4PROFIT'!A83 -> FRONIUS | C80: ='ALL DATA & IT4PROFIT'!B83 -> SYMO 20.0-3-M | D80: ='ALL DATA & IT4PROFIT'!C83 -> 3PH | E80: 1 | F80: ='ALL DATA & IT4PROFIT'!R83 | G80: =F80+$G$190 -> 90 | H80: =(G80*$E$190)+G80 -> 92.25 | I80: =(J80-H80)/J80 -> 0.07 | J80: =H80/(1-M80) -> 99.193548 | K80: =SUM(E80*J80) -> 99.193548 | L80: =SUM(E80*H80) -> 92.25 | M80: 0.07 | N80: ='ALL DATA & IT4PROFIT'!L83 | P80: ='ALL DATA & IT4PROFIT'!H83 | Q80: ='ALL DATA & IT4PROFIT'!K83 | R80: ='ALL DATA & IT4PROFIT'!D83
B81: ='ALL DATA & IT4PROFIT'!A84 | C81: ='ALL DATA & IT4PROFIT'!B84 | D81: ='ALL DATA & IT4PROFIT'!C84 | E81: 1 | F81: ='ALL DATA & IT4PROFIT'!R84 | G81: =F81+$G$190 -> 90 | H81: =(G81*$E$190)+G81 -> 92.25 | I81: =(J81-H81)/J81 -> 0.07 | J81: =H81/(1-M81) -> 99.193548 | K81: =SUM(E81*J81) -> 99.193548 | L81: =SUM(E81*H81) -> 92.25 | M81: 0.07 | N81: ='ALL DATA & IT4PROFIT'!L84 | P81: ='ALL DATA & IT4PROFIT'!H84 | Q81: ='ALL DATA & IT4PROFIT'!K84 | R81: ='ALL DATA & IT4PROFIT'!D84
B82: ='ALL DATA & IT4PROFIT'!A85 -> FRONIUS | C82: ='ALL DATA & IT4PROFIT'!B85 -> Fronius Symo GEN24 3.0 | D82: ='ALL DATA & IT4PROFIT'!C85 -> 3PH H lock | E82: 1 | F82: ='ALL DATA & IT4PROFIT'!R85 -> 933 | G82: =F82+$G$190 -> 1023 | H82: =(G82*$E$190)+G82 -> 1048.575 | I82: =(J82-H82)/J82 -> 0.07 | J82: =H82/(1-M82) -> 1127.5 | K82: =SUM(E82*J82) -> 1127.5 | L82: =SUM(E82*H82) -> 1048.575 | M82: 0.07 | N82: ='ALL DATA & IT4PROFIT'!L85 | P82: ='ALL DATA & IT4PROFIT'!H85 | Q82: ='ALL DATA & IT4PROFIT'!K85 | R82: ='ALL DATA & IT4PROFIT'!D85
B83: ='ALL DATA & IT4PROFIT'!A86 -> FRONIUS | C83: ='ALL DATA & IT4PROFIT'!B86 -> Fronius Symo GEN24 4.0 | D83: ='ALL DATA & IT4PROFIT'!C86 -> 3PH H lock | E83: 1 | F83: ='ALL DATA & IT4PROFIT'!R86 -> 1068 | G83: =F83+$G$190 -> 1158 | H83: =(G83*$E$190)+G83 -> 1186.95 | I83: =(J83-H83)/J83 -> 0.07 | J83: =H83/(1-M83) -> 1276.2903 | K83: =SUM(E83*J83) -> 1276.2903 | L83: =SUM(E83*H83) -> 1186.95 | M83: 0.07 | N83: ='ALL DATA & IT4PROFIT'!L86 | P83: ='ALL DATA & IT4PROFIT'!H86 | Q83: ='ALL DATA & IT4PROFIT'!K86 | R83: ='ALL DATA & IT4PROFIT'!D86
B84: ='ALL DATA & IT4PROFIT'!A87 -> FRONIUS | C84: ='ALL DATA & IT4PROFIT'!B87 -> Fronius Symo GEN24 5.0 | D84: ='ALL DATA & IT4PROFIT'!C87 -> 3PH H lock | E84: 1 | F84: ='ALL DATA & IT4PROFIT'!R87 -> 1099 | G84: =F84+$G$190 -> 1189 | H84: =(G84*$E$190)+G84 -> 1218.725 | I84: =(J84-H84)/J84 -> 0.07 | J84: =H84/(1-M84) -> 1310.457 | K84: =SUM(E84*J84) -> 1310.457 | L84: =SUM(E84*H84) -> 1218.725 | M84: 0.07 | N84: ='ALL DATA & IT4PROFIT'!L87 | P84: ='ALL DATA & IT4PROFIT'!H87 | Q84: ='ALL DATA & IT4PROFIT'!K87 | R84: ='ALL DATA & IT4PROFIT'!D87
B85: ='ALL DATA & IT4PROFIT'!A88 -> FRONIUS | C85: ='ALL DATA & IT4PROFIT'!B88 -> Fronius Symo GEN24 6.0 | D85: ='ALL DATA & IT4PROFIT'!C88 -> 3PH H lock | E85: 1 | F85: ='ALL DATA & IT4PROFIT'!R88 -> 1266 | G85: =F85+$G$190 -> 1356 | H85: =(G85*$E$190)+G85 -> 1389.9 | I85: =(J85-H85)/J85 -> 0.07 | J85: =H85/(1-M85) -> 1494.5161 | K85: =SUM(E85*J85) -> 1494.5161 | L85: =SUM(E85*H85) -> 1389.9 | M85: 0.07 | N85: ='ALL DATA & IT4PROFIT'!L88 | P85: ='ALL DATA & IT4PROFIT'!H88 | Q85: ='ALL DATA & IT4PROFIT'!K88 | R85: ='ALL DATA & IT4PROFIT'!D88
B86: ='ALL DATA & IT4PROFIT'!A89 -> FRONIUS | C86: ='ALL DATA & IT4PROFIT'!B89 -> Fronius Symo GEN24 8.0 | D86: ='ALL DATA & IT4PROFIT'!C89 -> 3PH H lock | E86: 1 | F86: ='ALL DATA & IT4PROFIT'!R89 -> 1531 | G86: =F86+$G$190 -> 1621 | H86: =(G86*$E$190)+G86 -> 1661.525 | I86: =(J86-H86)/J86 -> 0.07 | J86: =H86/(1-M86) -> 1786.586 | K86: =SUM(E86*J86) -> 1786.586 | L86: =SUM(E86*H86) -> 1661.525 | M86: 0.07 | N86: ='ALL DATA & IT4PROFIT'!L89 | P86: ='ALL DATA & IT4PROFIT'!H89 | Q86: ='ALL DATA & IT4PROFIT'!K89 | R86: ='ALL DATA & IT4PROFIT'!D89
B87: ='ALL DATA & IT4PROFIT'!A90 -> FRONIUS | C87: ='ALL DATA & IT4PROFIT'!B90 -> Fronius Symo GEN24 10.0 | D87: ='ALL DATA & IT4PROFIT'!C90 -> 3PH H lock | E87: 1 | F87: ='ALL DATA & IT4PROFIT'!R90 -> 1625 | G87: =F87+$G$190 -> 1715 | H87: =(G87*$E$190)+G87 -> 1757.875 | I87: =(J87-H87)/J87 -> 0.07 | J87: =H87/(1-M87) -> 1890.1882 | K87: =SUM(E87*J87) -> 1890.1882 | L87: =SUM(E87*H87) -> 1757.875 | M87: 0.07 | N87: ='ALL DATA & IT4PROFIT'!L90 | P87: ='ALL DATA & IT4PROFIT'!H90 | Q87: ='ALL DATA & IT4PROFIT'!K90 | R87: ='ALL DATA & IT4PROFIT'!D90
B88: ='ALL DATA & IT4PROFIT'!A91 | C88: ='ALL DATA & IT4PROFIT'!B91 | D88: ='ALL DATA & IT4PROFIT'!C91 | E88: 1 | F88: ='ALL DATA & IT4PROFIT'!R91 | G88: =F88+$G$190 -> 90 | H88: =(G88*$E$190)+G88 -> 92.25 | I88: =(J88-H88)/J88 -> 0.07 | J88: =H88/(1-M88) -> 99.193548 | K88: =SUM(E88*J88) -> 99.193548 | L88: =SUM(E88*H88) -> 92.25 | M88: 0.07 | N88: ='ALL DATA & IT4PROFIT'!L91 | P88: ='ALL DATA & IT4PROFIT'!H91 | Q88: ='ALL DATA & IT4PROFIT'!K91 | R88: ='ALL DATA & IT4PROFIT'!D91
... B102: ='ALL DATA & IT4PROFIT'!A105 | C102: ='ALL DATA & IT4PROFIT'!B105 | D102: ='ALL DATA & IT4PROFIT'!C105 | E102: 1 | F102: ='ALL DATA & IT4PROFIT'!R105 | G102: =F102+$G$190 -> 90 | H102: =(G102*$E$190)+G102 -> 92.25 | I102: =(J102-H102)/J102 -> 0.07 | J102: =H102/(1-M102) -> 99.193548 | K102: =SUM(E102*J102) -> 99.193548 | L102: =SUM(E102*H102) -> 92.25 | M102: 0.07 | N102: ='ALL DATA & IT4PROFIT'!L105 | P102: ='ALL DATA & IT4PROFIT'!H105 | Q102: ='ALL DATA & IT4PROFIT'!K105 | R102: ='ALL DATA & IT4PROFIT'!D105
B103: ='ALL DATA & IT4PROFIT'!A125 -> SOLAREDGE | C103: ='ALL DATA & IT4PROFIT'!B125 -> SE 17 k SETAPP WITH PLASTIC COVER | D103: ='ALL DATA & IT4PROFIT'!C125 -> 3PH | E103: 1 | F103: ='ALL DATA & IT4PROFIT'!R125 | G103: =F103+$G$190 -> 90 | H103: =(G103*$E$190)+G103 -> 92.25 | I103: =(J103-H103)/J103 -> 0.07 | J103: =H103/(1-M103) -> 99.193548 | K103: =SUM(E103*J103) -> 99.193548 | L103: =SUM(E103*H103) -> 92.25 | M103: 0.07 | N103: ='ALL DATA & IT4PROFIT'!L125 | P103: ='ALL DATA & IT4PROFIT'!H125 | Q103: ='ALL DATA & IT4PROFIT'!K125 | R103: ='ALL DATA & IT4PROFIT'!D125
B104: ='ALL DATA & IT4PROFIT'!A126 -> SOLAREDGE | C104: ='ALL DATA & IT4PROFIT'!B126 -> SE20 k SETAPP | D104: ='ALL DATA & IT4PROFIT'!C126 -> 3PH | E104: 1 | F104: ='ALL DATA & IT4PROFIT'!R126 | G104: =F104+$G$190 -> 90 | H104: =(G104*$E$190)+G104 -> 92.25 | I104: =(J104-H104)/J104 -> 0.07 | J104: =H104/(1-M104) -> 99.193548 | K104: =SUM(E104*J104) -> 99.193548 | L104: =SUM(E104*H104) -> 92.25 | M104: 0.07 | N104: ='ALL DATA & IT4PROFIT'!L126 | P104: ='ALL DATA & IT4PROFIT'!H126 | Q104: ='ALL DATA & IT4PROFIT'!K126 | R104: ='ALL DATA & IT4PROFIT'!D126
B105: ='ALL DATA & IT4PROFIT'!A144 -> SOLAREDGE | C105: ='ALL DATA & IT4PROFIT'!B144 | D105: ='ALL DATA & IT4PROFIT'!C144 | E105: 1 | F105: ='ALL DATA & IT4PROFIT'!R144 | G105: =F105+$G$190 -> 90 | H105: =(G105*$E$190)+G105 -> 92.25 | I105: =(J105-H105)/J105 -> 0.07 | J105: =H105/(1-M105) -> 99.193548 | K105: =SUM(E105*J105) -> 99.193548 | L105: =SUM(E105*H105) -> 92.25 | M105: 0.07 | N105: ='ALL DATA & IT4PROFIT'!L144 | P105: ='ALL DATA & IT4PROFIT'!H144 | Q105: ='ALL DATA & IT4PROFIT'!K144 | R105: ='ALL DATA & IT4PROFIT'!D144
B106: ='ALL DATA & IT4PROFIT'!A159 | C106: ='ALL DATA & IT4PROFIT'!B159 | D106: ='ALL DATA & IT4PROFIT'!C159 | E106: 1 | F106: ='ALL DATA & IT4PROFIT'!R159 | G106: =F106+$G$190 -> 90 | H106: =(G106*$E$190)+G106 -> 92.25 | I106: =(J106-H106)/J106 -> 0.07 | J106: =H106/(1-M106) -> 99.193548 | K106: =SUM(E106*J106) -> 99.193548 | L106: =SUM(E106*H106) -> 92.25 | M106: 0.07 | N106: ='ALL DATA & IT4PROFIT'!L159 | P106: ='ALL DATA & IT4PROFIT'!H159 | Q106: ='ALL DATA & IT4PROFIT'!K159 | R106: ='ALL DATA & IT4PROFIT'!D159
B107: ='ALL DATA & IT4PROFIT'!A160 | C107: ='ALL DATA & IT4PROFIT'!B160 | D107: ='ALL DATA & IT4PROFIT'!C160 | E107: 1 | F107: ='ALL DATA & IT4PROFIT'!R160 | G107: =F107+$G$190 -> 90 | H107: =(G107*$E$190)+G107 -> 92.25 | I107: =(J107-H107)/J107 -> 0.07 | J107: =H107/(1-M107) -> 99.193548 | K107: =SUM(E107*J107) -> 99.193548 | L107: =SUM(E107*H107) -> 92.25 | M107: 0.07 | N107: ='ALL DATA & IT4PROFIT'!L160 | P107: ='ALL DATA & IT4PROFIT'!H160 | Q107: ='ALL DATA & IT4PROFIT'!K160 | R107: ='ALL DATA & IT4PROFIT'!D160
B108: ='ALL DATA & IT4PROFIT'!A161 | C108: ='ALL DATA & IT4PROFIT'!B161 | D108: ='ALL DATA & IT4PROFIT'!C161 | E108: 1 | F108: ='ALL DATA & IT4PROFIT'!R161 | G108: =F108+$G$190 -> 90 | H108: =(G108*$E$190)+G108 -> 92.25 | I108: =(J108-H108)/J108 -> 0.07 | J108: =H108/(1-M108) -> 99.193548 | K108: =SUM(E108*J108) -> 99.193548 | L108: =SUM(E108*H108) -> 92.25 | M108: 0.07 | N108: ='ALL DATA & IT4PROFIT'!L161 | P108: ='ALL DATA & IT4PROFIT'!H161 | Q108: ='ALL DATA & IT4PROFIT'!K161 | R108: ='ALL DATA & IT4PROFIT'!D161
B109: ='ALL DATA & IT4PROFIT'!A162 -> SOLAX | C109: ='ALL DATA & IT4PROFIT'!B162 -> X1 2.0-S-D(L) Mini G3 | D109: ='ALL DATA & IT4PROFIT'!C162 -> 1PH | E109: 1 | F109: ='ALL DATA & IT4PROFIT'!R162 | G109: =F109+$G$190 -> 90 | H109: =(G109*$E$190)+G109 -> 92.25 | I109: =(J109-H109)/J109 -> 0.07 | J109: =H109/(1-M109) -> 99.193548 | K109: =SUM(E109*J109) -> 99.193548 | L109: =SUM(E109*H109) -> 92.25 | M109: 0.07 | N109: ='ALL DATA & IT4PROFIT'!L162 | O109: =615-615*0.4 -> 369 | P109: ='ALL DATA & IT4PROFIT'!H162 | Q109: ='ALL DATA & IT4PROFIT'!K162 | R109: ='ALL DATA & IT4PROFIT'!D162
B110: ='ALL DATA & IT4PROFIT'!A163 -> SOLAX | C110: ='ALL DATA & IT4PROFIT'!B163 -> X1 3.3-T-D(L) BOOST | D110: ='ALL DATA & IT4PROFIT'!C163 -> 1PH | E110: 1 | F110: ='ALL DATA & IT4PROFIT'!R163 | G110: =F110+$G$190 -> 90 | H110: =(G110*$E$190)+G110 -> 92.25 | I110: =(J110-H110)/J110 -> 0.07 | J110: =H110/(1-M110) -> 99.193548 | K110: =SUM(E110*J110) -> 99.193548 | L110: =SUM(E110*H110) -> 92.25 | M110: 0.07 | N110: ='ALL DATA & IT4PROFIT'!L163 | O110: =920-920*0.4 -> 552 | P110: ='ALL DATA & IT4PROFIT'!H163 | Q110: ='ALL DATA & IT4PROFIT'!K163 | R110: ='ALL DATA & IT4PROFIT'!D163
B111: ='ALL DATA & IT4PROFIT'!A164 -> SOLAX | C111: ='ALL DATA & IT4PROFIT'!B164 -> X1 4.2-T-D(L) BOOST | D111: ='ALL DATA & IT4PROFIT'!C164 -> 1PH | E111: 1 | F111: ='ALL DATA & IT4PROFIT'!R164 | G111: =F111+$G$190 -> 90 | H111: =(G111*$E$190)+G111 -> 92.25 | I111: =(J111-H111)/J111 -> 0.07 | J111: =H111/(1-M111) -> 99.193548 | K111: =SUM(E111*J111) -> 99.193548 | L111: =SUM(E111*H111) -> 92.25 | M111: 0.07 | N111: ='ALL DATA & IT4PROFIT'!L164 | O111: =985-985*0.4 -> 591 | P111: ='ALL DATA & IT4PROFIT'!H164 | Q111: ='ALL DATA & IT4PROFIT'!K164 | R111: ='ALL DATA & IT4PROFIT'!D164
B112: ='ALL DATA & IT4PROFIT'!A165 -> SOLAX | C112: ='ALL DATA & IT4PROFIT'!B165 -> X1 5.0-T-D(L) BOOST | D112: ='ALL DATA & IT4PROFIT'!C165 -> 1PH | E112: 1 | F112: ='ALL DATA & IT4PROFIT'!R165 | G112: =F112+$G$190 -> 90 | H112: =(G112*$E$190)+G112 -> 92.25 | I112: =(J112-H112)/J112 -> 0.07 | J112: =H112/(1-M112) -> 99.193548 | K112: =SUM(E112*J112) -> 99.193548 | L112: =SUM(E112*H112) -> 92.25 | M112: 0.07 | N112: ='ALL DATA & IT4PROFIT'!L165 | O112: =1055-1055*0.4 -> 633 | P112: ='ALL DATA & IT4PROFIT'!H165 | Q112: ='ALL DATA & IT4PROFIT'!K165 | R112: ='ALL DATA & IT4PROFIT'!D165
B113: ='ALL DATA & IT4PROFIT'!A166 -> SOLAX | C113: ='ALL DATA & IT4PROFIT'!B166 -> X3-MIC-4.0K-G2 | D113: ='ALL DATA & IT4PROFIT'!C166 -> 3PH | E113: 1 | F113: ='ALL DATA & IT4PROFIT'!R166 | G113: =F113+$G$190 -> 90 | H113: =(G113*$E$190)+G113 -> 92.25 | I113: =(J113-H113)/J113 -> 0.07 | J113: =H113/(1-M113) -> 99.193548 | K113: =SUM(E113*J113) -> 99.193548 | L113: =SUM(E113*H113) -> 92.25 | M113: 0.07 | N113: ='ALL DATA & IT4PROFIT'!L166 | O113: =1465-1465*0.4 -> 879 | P113: ='ALL DATA & IT4PROFIT'!H166 | Q113: ='ALL DATA & IT4PROFIT'!K166 | R113: ='ALL DATA & IT4PROFIT'!D166
B114: ='ALL DATA & IT4PROFIT'!A167 -> SOLAX | C114: ='ALL DATA & IT4PROFIT'!B167 -> X3-MIC-5.0K-G2 | D114: ='ALL DATA & IT4PROFIT'!C167 -> 3PH | E114: 1 | F114: ='ALL DATA & IT4PROFIT'!R167 | G114: =F114+$G$190 -> 90 | H114: =(G114*$E$190)+G114 -> 92.25 | I114: =(J114-H114)/J114 -> 0.07 | J114: =H114/(1-M114) -> 99.193548 | K114: =SUM(E114*J114) -> 99.193548 | L114: =SUM(E114*H114) -> 92.25 | M114: 0.07 | N114: ='ALL DATA & IT4PROFIT'!L167 | O114: =1530-1530*0.4 -> 918 | P114: ='ALL DATA & IT4PROFIT'!H167 | Q114: ='ALL DATA & IT4PROFIT'!K167 | R114: ='ALL DATA & IT4PROFIT'!D167
B115: ='ALL DATA & IT4PROFIT'!A168 -> SOLAX | C115: ='ALL DATA & IT4PROFIT'!B168 -> X3-MIC-6.0K-G2 | D115: ='ALL DATA & IT4PROFIT'!C168 -> 3PH | E115: 1 | F115: ='ALL DATA & IT4PROFIT'!R168 | G115: =F115+$G$190 -> 90 | H115: =(G115*$E$190)+G115 -> 92.25 | I115: =(J115-H115)/J115 -> 0.07 | J115: =H115/(1-M115) -> 99.193548 | K115: =SUM(E115*J115) -> 99.193548 | L115: =SUM(E115*H115) -> 92.25 | M115: 0.07 | N115: ='ALL DATA & IT4PROFIT'!L168 | O115: =1625-1625*0.4 -> 975 | P115: ='ALL DATA & IT4PROFIT'!H168 | Q115: ='ALL DATA & IT4PROFIT'!K168 | R115: ='ALL DATA & IT4PROFIT'!D168
B116: ='ALL DATA & IT4PROFIT'!A169 -> SOLAX | C116: ='ALL DATA & IT4PROFIT'!B169 -> X3-MIC-8.0K-G2 | D116: ='ALL DATA & IT4PROFIT'!C169 -> 3PH | E116: 1 | F116: ='ALL DATA & IT4PROFIT'!R169 | G116: =F116+$G$190 -> 90 | H116: =(G116*$E$190)+G116 -> 92.25 | I116: =(J116-H116)/J116 -> 0.07 | J116: =H116/(1-M116) -> 99.193548 | K116: =SUM(E116*J116) -> 99.193548 | L116: =SUM(E116*H116) -> 92.25 | M116: 0.07 | N116: ='ALL DATA & IT4PROFIT'!L169 | O116: =1680-1680*0.4 -> 1008 | P116: ='ALL DATA & IT4PROFIT'!H169 | Q116: ='ALL DATA & IT4PROFIT'!K169 | R116: ='ALL DATA & IT4PROFIT'!D169
B117: ='ALL DATA & IT4PROFIT'!A170 -> SOLAX | C117: ='ALL DATA & IT4PROFIT'!B170 -> X3-MIC-10.0K-G2 | D117: ='ALL DATA & IT4PROFIT'!C170 -> 3PH | E117: 1 | F117: ='ALL DATA & IT4PROFIT'!R170 | G117: =F117+$G$190 -> 90 | H117: =(G117*$E$190)+G117 -> 92.25 | I117: =(J117-H117)/J117 -> 0.07 | J117: =H117/(1-M117) -> 99.193548 | K117: =SUM(E117*J117) -> 99.193548 | L117: =SUM(E117*H117) -> 92.25 | M117: 0.07 | N117: ='ALL DATA & IT4PROFIT'!L170 | O117: =1840-1840*0.4 -> 1104 | P117: ='ALL DATA & IT4PROFIT'!H170 | Q117: ='ALL DATA & IT4PROFIT'!K170 | R117: ='ALL DATA & IT4PROFIT'!D170
B118: ='ALL DATA & IT4PROFIT'!A171 -> SOLAX | C118: ='ALL DATA & IT4PROFIT'!B171 -> Pocket Wifi (2 years warranty) | D118: ='ALL DATA & IT4PROFIT'!C171 | E118: 1 | F118: ='ALL DATA & IT4PROFIT'!R171 | G118: =F118+$G$190 -> 90 | H118: =(G118*$E$190)+G118 -> 92.25 | I118: =(J118-H118)/J118 -> 0.07 | J118: =H118/(1-M118) -> 99.193548 | K118: =SUM(E118*J118) -> 99.193548 | L118: =SUM(E118*H118) -> 92.25 | M118: 0.07 | N118: ='ALL DATA & IT4PROFIT'!L171 | O118: =50-50*0.4 -> 30 | P118: ='ALL DATA & IT4PROFIT'!H171 | Q118: ='ALL DATA & IT4PROFIT'!K171 | R118: ='ALL DATA & IT4PROFIT'!D171
B119: ='ALL DATA & IT4PROFIT'!A172 -> SOLAX | C119: ='ALL DATA & IT4PROFIT'!B172 -> Pocket Lan 3.0 (2 years warranty) | D119: ='ALL DATA & IT4PROFIT'!C172 | E119: 1 | F119: ='ALL DATA & IT4PROFIT'!R172 | G119: =F119+$G$190 -> 90 | H119: =(G119*$E$190)+G119 -> 92.25 | I119: =(J119-H119)/J119 -> 0.07 | J119: =H119/(1-M119) -> 99.193548 | K119: =SUM(E119*J119) -> 99.193548 | L119: =SUM(E119*H119) -> 92.25 | M119: 0.07 | N119: ='ALL DATA & IT4PROFIT'!L172 | O119: =50-50*0.4 -> 30 | P119: ='ALL DATA & IT4PROFIT'!H172 | Q119: ='ALL DATA & IT4PROFIT'!K172 | R119: ='ALL DATA & IT4PROFIT'!D172
B120: ='ALL DATA & IT4PROFIT'!A173 | C120: ='ALL DATA & IT4PROFIT'!B173 | D120: ='ALL DATA & IT4PROFIT'!C173 | E120: 1 | F120: ='ALL DATA & IT4PROFIT'!R173 | G120: =F120+$G$190 -> 90 | H120: =(G120*$E$190)+G120 -> 92.25 | I120: =(J120-H120)/J120 -> 0.07 | J120: =H120/(1-M120) -> 99.193548 | K120: =SUM(E120*J120) -> 99.193548 | L120: =SUM(E120*H120) -> 92.25 | M120: 0.07 | N120: ='ALL DATA & IT4PROFIT'!L173 | P120: ='ALL DATA & IT4PROFIT'!H173 | Q120: ='ALL DATA & IT4PROFIT'!K173 | R120: ='ALL DATA & IT4PROFIT'!D173
B121: ='ALL DATA & IT4PROFIT'!A174 -> SMA | C121: ='ALL DATA & IT4PROFIT'!B174 -> SMA Hybrid Sunny Tripower 5.0 Smart Energy | D121: ='ALL DATA & IT4PROFIT'!C174 -> 3PH HYBRID | E121: 1 | F121: ='ALL DATA & IT4PROFIT'!R174 -> 1700 | G121: =F121+$G$190 -> 1790 | H121: =(G121*$E$190)+G121 -> 1834.75 | I121: =(J121-H121)/J121 -> 0.07 | J121: =H121/(1-M121) -> 1972.8495 | K121: =SUM(E121*J121) -> 1972.8495 | L121: =SUM(E121*H121) -> 1834.75 | M121: 0.07 | N121: ='ALL DATA & IT4PROFIT'!L174 | P121: ='ALL DATA & IT4PROFIT'!H174 | Q121: ='ALL DATA & IT4PROFIT'!K174 | R121: ='ALL DATA & IT4PROFIT'!D174
B122: ='ALL DATA & IT4PROFIT'!A175 -> SMA | C122: ='ALL DATA & IT4PROFIT'!B175 -> SMA Hybrid Sunny Tripower 6.0 Smart Energy | D122: ='ALL DATA & IT4PROFIT'!C175 -> 3PH HYBRID | E122: 1 | F122: ='ALL DATA & IT4PROFIT'!R175 -> 1850 | G122: =F122+$G$190 -> 1940 | H122: =(G122*$E$190)+G122 -> 1988.5 | I122: =(J122-H122)/J122 -> 0.07 | J122: =H122/(1-M122) -> 2138.172 | K122: =SUM(E122*J122) -> 2138.172 | L122: =SUM(E122*H122) -> 1988.5 | M122: 0.07 | N122: ='ALL DATA & IT4PROFIT'!L175 | P122: ='ALL DATA & IT4PROFIT'!H175 | Q122: ='ALL DATA & IT4PROFIT'!K175 | R122: ='ALL DATA & IT4PROFIT'!D175
B123: ='ALL DATA & IT4PROFIT'!A176 -> SMA | C123: ='ALL DATA & IT4PROFIT'!B176 -> SMA Hybrid Sunny Tripower 8.0 Smart Energy | D123: ='ALL DATA & IT4PROFIT'!C176 -> 3PH HYBRID | E123: 1 | F123: ='ALL DATA & IT4PROFIT'!R176 -> 2100 | G123: =F123+$G$190 -> 2190 | H123: =(G123*$E$190)+G123 -> 2244.75 | I123: =(J123-H123)/J123 -> 0.07 | J123: =H123/(1-M123) -> 2413.7097 | K123: =SUM(E123*J123) -> 2413.7097 | L123: =SUM(E123*H123) -> 2244.75 | M123: 0.07 | N123: ='ALL DATA & IT4PROFIT'!L176 | P123: ='ALL DATA & IT4PROFIT'!H176 | Q123: ='ALL DATA & IT4PROFIT'!K176 | R123: ='ALL DATA & IT4PROFIT'!D176
B124: ='ALL DATA & IT4PROFIT'!A177 -> SMA | C124: ='ALL DATA & IT4PROFIT'!B177 -> SMA Hybrid Sunny Tripower 10.0 Smart Energy | D124: ='ALL DATA & IT4PROFIT'!C177 -> 3PH HYBRID | E124: 1 | F124: ='ALL DATA & IT4PROFIT'!R177 -> 2350 | G124: =F124+$G$190 -> 2440 | H124: =(G124*$E$190)+G124 -> 2501 | I124: =(J124-H124)/J124 -> 0.07 | J124: =H124/(1-M124) -> 2689.2473 | K124: =SUM(E124*J124) -> 2689.2473 | L124: =SUM(E124*H124) -> 2501 | M124: 0.07 | N124: ='ALL DATA & IT4PROFIT'!L177 | P124: ='ALL DATA & IT4PROFIT'!H177 | Q124: ='ALL DATA & IT4PROFIT'!K177 | R124: ='ALL DATA & IT4PROFIT'!D177
B125: ='ALL DATA & IT4PROFIT'!A178 -> SMA | C125: ='ALL DATA & IT4PROFIT'!B178 -> SMA Sunny Boy 1.5 | D125: ='ALL DATA & IT4PROFIT'!C178 -> 1PH | E125: 1 | F125: ='ALL DATA & IT4PROFIT'!R178 -> 519 | G125: =F125+$G$190 -> 609 | H125: =(G125*$E$190)+G125 -> 624.225 | I125: =(J125-H125)/J125 -> 0.07 | J125: =H125/(1-M125) -> 671.20968 | K125: =SUM(E125*J125) -> 671.20968 | L125: =SUM(E125*H125) -> 624.225 | M125: 0.07 | N125: ='ALL DATA & IT4PROFIT'!L178 | P125: ='ALL DATA & IT4PROFIT'!H178 | Q125: ='ALL DATA & IT4PROFIT'!K178 | R125: ='ALL DATA & IT4PROFIT'!D178
B126: ='ALL DATA & IT4PROFIT'!A179 -> SMA | C126: ='ALL DATA & IT4PROFIT'!B179 -> SMA Sunny Boy 2.5 | D126: ='ALL DATA & IT4PROFIT'!C179 -> 1PH | E126: 1 | F126: ='ALL DATA & IT4PROFIT'!R179 -> 756 | G126: =F126+$G$190 -> 846 | H126: =(G126*$E$190)+G126 -> 867.15 | I126: =(J126-H126)/J126 -> 0.07 | J126: =H126/(1-M126) -> 932.41935 | K126: =SUM(E126*J126) -> 932.41935 | L126: =SUM(E126*H126) -> 867.15 | M126: 0.07 | N126: ='ALL DATA & IT4PROFIT'!L179 | P126: ='ALL DATA & IT4PROFIT'!H179 | Q126: ='ALL DATA & IT4PROFIT'!K179 | R126: ='ALL DATA & IT4PROFIT'!D179
B127: ='ALL DATA & IT4PROFIT'!A180 -> SMA | C127: ='ALL DATA & IT4PROFIT'!B180 -> SMA Sunny Boy 3.0 | D127: ='ALL DATA & IT4PROFIT'!C180 -> 1PH | E127: 1 | F127: ='ALL DATA & IT4PROFIT'!R180 -> 845 | G127: =F127+$G$190 -> 935 | H127: =(G127*$E$190)+G127 -> 958.375 | I127: =(J127-H127)/J127 -> 0.07 | J127: =H127/(1-M127) -> 1030.5108 | K127: =SUM(E127*J127) -> 1030.5108 | L127: =SUM(E127*H127) -> 958.375 | M127: 0.07 | N127: ='ALL DATA & IT4PROFIT'!L180 | P127: ='ALL DATA & IT4PROFIT'!H180 | Q127: ='ALL DATA & IT4PROFIT'!K180 | R127: ='ALL DATA & IT4PROFIT'!D180
B128: ='ALL DATA & IT4PROFIT'!A181 -> SMA | C128: ='ALL DATA & IT4PROFIT'!B181 -> SMA Sunny Boy 3.6 | D128: ='ALL DATA & IT4PROFIT'!C181 -> 1PH | E128: 1 | F128: ='ALL DATA & IT4PROFIT'!R181 -> 900 | G128: =F128+$G$190 -> 990 | H128: =(G128*$E$190)+G128 -> 1014.75 | I128: =(J128-H128)/J128 -> 0.07 | J128: =H128/(1-M128) -> 1091.129 | K128: =SUM(E128*J128) -> 1091.129 | L128: =SUM(E128*H128) -> 1014.75 | M128: 0.07 | N128: ='ALL DATA & IT4PROFIT'!L181 | P128: ='ALL DATA & IT4PROFIT'!H181 | Q128: ='ALL DATA & IT4PROFIT'!K181 | R128: ='ALL DATA & IT4PROFIT'!D181
B129: ='ALL DATA & IT4PROFIT'!A182 -> SMA | C129: ='ALL DATA & IT4PROFIT'!B182 -> SMA Sunny Boy 4.0 | D129: ='ALL DATA & IT4PROFIT'!C182 -> 1PH | E129: 1 | F129: ='ALL DATA & IT4PROFIT'!R182 -> 944 | G129: =F129+$G$190 -> 1034 | H129: =(G129*$E$190)+G129 -> 1059.85 | I129: =(J129-H129)/J129 -> 0.07 | J129: =H129/(1-M129) -> 1139.6237 | K129: =SUM(E129*J129) -> 1139.6237 | L129: =SUM(E129*H129) -> 1059.85 | M129: 0.07 | N129: ='ALL DATA & IT4PROFIT'!L182 | P129: ='ALL DATA & IT4PROFIT'!H182 | Q129: ='ALL DATA & IT4PROFIT'!K182 | R129: ='ALL DATA & IT4PROFIT'!D182
B130: ='ALL DATA & IT4PROFIT'!A183 -> SMA | C130: ='ALL DATA & IT4PROFIT'!B183 -> SMA Sunny Boy 5.0 | D130: ='ALL DATA & IT4PROFIT'!C183 -> 1PH | E130: 1 | F130: ='ALL DATA & IT4PROFIT'!R183 -> 1013 | G130: =F130+$G$190 -> 1103 | H130: =(G130*$E$190)+G130 -> 1130.575 | I130: =(J130-H130)/J130 -> 0.07 | J130: =H130/(1-M130) -> 1215.672 | K130: =SUM(E130*J130) -> 1215.672 | L130: =SUM(E130*H130) -> 1130.575 | M130: 0.07 | N130: ='ALL DATA & IT4PROFIT'!L183 | P130: ='ALL DATA & IT4PROFIT'!H183 | Q130: ='ALL DATA & IT4PROFIT'!K183 | R130: ='ALL DATA & IT4PROFIT'!D183
B131: ='ALL DATA & IT4PROFIT'!A184 -> SMA | C131: ='ALL DATA & IT4PROFIT'!B184 -> SMA Sunny Tripower 3.0 | D131: ='ALL DATA & IT4PROFIT'!C184 -> 3PH | E131: 1 | F131: ='ALL DATA & IT4PROFIT'!R184 -> 1058 | G131: =F131+$G$190 -> 1148 | H131: =(G131*$E$190)+G131 -> 1176.7 | I131: =(J131-H131)/J131 -> 0.07 | J131: =H131/(1-M131) -> 1265.2688 | K131: =SUM(E131*J131) -> 1265.2688 | L131: =SUM(E131*H131) -> 1176.7 | M131: 0.07 | N131: ='ALL DATA & IT4PROFIT'!L184 | P131: ='ALL DATA & IT4PROFIT'!H184 | Q131: ='ALL DATA & IT4PROFIT'!K184 | R131: ='ALL DATA & IT4PROFIT'!D184
... B161: ='ALL DATA & IT4PROFIT'!A214 -> SMA | C161: ='ALL DATA & IT4PROFIT'!B214 -> SMA Sunny Highpower PEAK3 SHP 180-21 | D161: ='ALL DATA & IT4PROFIT'!C214 -> 3PH SUNNY | E161: 1 | F161: ='ALL DATA & IT4PROFIT'!R214 | G161: =F161+$G$190 -> 90 | H161: =(G161*$E$190)+G161 -> 92.25 | I161: =(J161-H161)/J161 -> 0.07 | J161: =H161/(1-M161) -> 99.193548 | K161: =SUM(E161*J161) -> 99.193548 | L161: =SUM(E161*H161) -> 92.25 | M161: 0.07 | N161: ='ALL DATA & IT4PROFIT'!L214 | P161: ='ALL DATA & IT4PROFIT'!H214 | Q161: ='ALL DATA & IT4PROFIT'!K214 | R161: ='ALL DATA & IT4PROFIT'!D214
B162: ='ALL DATA & IT4PROFIT'!A215 | C162: ='ALL DATA & IT4PROFIT'!B215 | D162: ='ALL DATA & IT4PROFIT'!C215 | E162: 1 | F162: ='ALL DATA & IT4PROFIT'!R215 | G162: =F162+$G$190 -> 90 | H162: =(G162*$E$190)+G162 -> 92.25 | I162: =(J162-H162)/J162 -> 0.07 | J162: =H162/(1-M162) -> 99.193548 | K162: =SUM(E162*J162) -> 99.193548 | L162: =SUM(E162*H162) -> 92.25 | M162: 0.07 | N162: ='ALL DATA & IT4PROFIT'!L215
B163: ='ALL DATA & IT4PROFIT'!A216 | C163: ='ALL DATA & IT4PROFIT'!B216 | D163: ='ALL DATA & IT4PROFIT'!C216 | E163: 1 | F163: ='ALL DATA & IT4PROFIT'!R216 | G163: =F163+$G$190 -> 90 | H163: =(G163*$E$190)+G163 -> 92.25 | I163: =(J163-H163)/J163 -> 0.07 | J163: =H163/(1-M163) -> 99.193548 | K163: =SUM(E163*J163) -> 99.193548 | L163: =SUM(E163*H163) -> 92.25 | M163: 0.07 | N163: ='ALL DATA & IT4PROFIT'!L216
B164: ='ALL DATA & IT4PROFIT'!A217 | C164: ='ALL DATA & IT4PROFIT'!B217 | D164: ='ALL DATA & IT4PROFIT'!C217 | E164: 1 | F164: ='ALL DATA & IT4PROFIT'!R217 | G164: =F164+$G$190 -> 90 | H164: =(G164*$E$190)+G164 -> 92.25 | I164: =(J164-H164)/J164 -> 0.07 | J164: =H164/(1-M164) -> 99.193548 | K164: =SUM(E164*J164) -> 99.193548 | L164: =SUM(E164*H164) -> 92.25 | M164: 0.07 | N164: ='ALL DATA & IT4PROFIT'!L217
E165: 1 | G165: =F165+$G$190 -> 90 | H165: =(G165*$E$190)+G165 -> 92.25 | I165: =(J165-H165)/J165 -> 0.07 | J165: =H165/(1-M165) -> 99.193548 | K165: =SUM(E165*J165) -> 99.193548 | L165: =SUM(E165*H165) -> 92.25 | M165: 0.07 | N165: ='ALL DATA & IT4PROFIT'!L218
E166: 1 | G166: =F166+$G$190 -> 90 | H166: =(G166*$E$190)+G166 -> 92.25 | I166: =(J166-H166)/J166 -> 0.07 | J166: =H166/(1-M166) -> 99.193548 | K166: =SUM(E166*J166) -> 99.193548 | L166: =SUM(E166*H166) -> 92.25 | M166: 0.07 | N166: ='ALL DATA & IT4PROFIT'!L219
E167: 1 | G167: =F167+$G$190 -> 90 | H167: =(G167*$E$190)+G167 -> 92.25 | I167: =(J167-H167)/J167 -> 0.07 | J167: =H167/(1-M167) -> 99.193548 | K167: =SUM(E167*J167) -> 99.193548 | L167: =SUM(E167*H167) -> 92.25 | M167: 0.07 | N167: ='ALL DATA & IT4PROFIT'!L220
E168: 1 | G168: =F168+$G$190 -> 90 | H168: =(G168*$E$190)+G168 -> 92.25 | I168: =(J168-H168)/J168 -> 0.07 | J168: =H168/(1-M168) -> 99.193548 | K168: =SUM(E168*J168) -> 99.193548 | L168: =SUM(E168*H168) -> 92.25 | M168: 0.07 | N168: ='ALL DATA & IT4PROFIT'!L221
E169: 1 | G169: =F169+$G$190 -> 90 | H169: =(G169*$E$190)+G169 -> 92.25 | I169: =(J169-H169)/J169 -> 0.07 | J169: =H169/(1-M169) -> 99.193548 | K169: =SUM(E169*J169) -> 99.193548 | L169: =SUM(E169*H169) -> 92.25 | M169: 0.07 | N169: ='ALL DATA & IT4PROFIT'!L222
...

Sheet Panels GM calculation for CY
H1: Freight to CY (€/container) | I1: 2650 | J1: POSR (%) | K1: 0.025
A2: PV Modules - container | J2: *has to be decided | N2: *devide (LCP CY)/(1-GM)
A3: Brand | B3: Model | C3: Type | D3: Distributor | E3: Price in EU | F3: Wp/panel | H3: panels /container | I3: Freight to CY | J3: LCP CY | K3: FINAL LCP CY | L3: Desired GM(%) | M3: GM (%) | N3: Final Price to Customer | O3: Customer Price (c/Wp) | Q3: GP per container
A5: Axitec | B5: BLK AC-400MH/108VAU | C5: Monofacial | E5: 60 | F5: 400 | G5: =E5/F5 -> 0.15 | H5: 780 | I5: =$I$1/H5 -> 3.3974359 | J5: =E5+I5 -> 63.397436 | K5: =(J5*$K$1)+J5 -> 64.982372 | L5: 0.125 | M5: =(N5-K5)/N5 -> 0.125 | N5: =K5/(1-L5) -> 74.265568 | O5: =N5/F5 -> 0.18566392 | Q5: =(N5-K5)*H5 -> 7240.8929
A6: Axitec | B6: FXXL AC-420TFM/108BB | C6: Monofacial | E6: 75 | F6: 420 | G6: =E6/F6 -> 0.17857143 | H6: 936 | I6: =$I$1/H6 -> 2.8311966 | J6: =E6+I6 -> 77.831197 | K6: =(J6*$K$1)+J6 -> 79.776977 | L6: 0.125 | M6: =(N6-K6)/N6 -> 0.125 | N6: =K6/(1-L6) -> 91.173687 | O6: =N6/F6 -> 0.21708021 | Q6: =(N6-K6)*H6 -> 10667.321
A7: Axitec | B7: GL AC-430TGB/108BB | C7: Bifacial | E7: 86 | F7: 430 | G7: =E7/F7 -> 0.2 | H7: 864 | I7: =$I$1/H7 -> 3.0671296 | J7: =E7+I7 -> 89.06713 | K7: =(J7*$K$1)+J7 -> 91.293808 | L7: 0.125 | M7: =(N7-K7)/N7 -> 0.125 | N7: =K7/(1-L7) -> 104.33578 | O7: =N7/F7 -> 0.24264135 | Q7: =(N7-K7)*H7 -> 11268.264
A8: Axitec | B8: HC AC-540MH/144V | C8: Monofacial | E8: 86.4 | F8: 540 | G8: =E8/F8 -> 0.16 | H8: 620 | I8: =$I$1/H8 -> 4.2741935 | J8: =E8+I8 -> 90.674194 | K8: =(J8*$K$1)+J8 -> 92.941048 | L8: 0.125 | M8: =(N8-K8)/N8 -> 0.125 | N8: =K8/(1-L8) -> 106.21834 | O8: =N8/F8 -> 0.19670063 | Q8: =(N8-K8)*H8 -> 8231.9214
A9: JA Solar | B9: JAM54S31-410W | C9: Monofacial | E9: 61.5 | F9: 410 | G9: =E9/F9 -> 0.15 | H9: 936 | I9: =$I$1/H9 -> 2.8311966 | J9: =E9+I9 -> 64.331197 | K9: =(J9*$K$1)+J9 -> 65.939476 | L9: 0.125 | M9: =(N9-K9)/N9 -> 0.125 | N9: =K9/(1-L9) -> 75.359402 | O9: =N9/F9 -> 0.18380342 | Q9: =(N9-K9)*H9 -> 8817.05
A10: JA Solar | B10: JAM54D41-435/LB | C10: Bifacial | E10: 87 | F10: 435 | G10: =E10/F10 -> 0.2 | H10: 936 | I10: =$I$1/H10 -> 2.8311966 | J10: =E10+I10 -> 89.831197 | K10: =(J10*$K$1)+J10 -> 92.076977 | L10: 0.125 | M10: =(N10-K10)/N10 -> 0.125 | N10: =K10/(1-L10) -> 105.23083 | O10: =N10/F10 -> 0.24190995 | Q10: =(N10-K10)*H10 -> 12312.007
A11: JA Solar | B11: JAM54D40-440/LB | C11: Bifacial | E11: 96.8 | F11: 440 | G11: =E11/F11 -> 0.22 | H11: 936 | I11: =$I$1/H11 -> 2.8311966 | J11: =E11+I11 -> 99.631197 | K11: =(J11*$K$1)+J11 -> 102.12198 | L11: 0.125 | M11: =(N11-K11)/N11 -> 0.125 | N11: =K11/(1-L11) -> 116.71083 | O11: =N11/F11 -> 0.26525189 | Q11: =(N11-K11)*H11 -> 13655.167
A12: JA Solar | B12: JAM72S30-555/GR | C12: Monofacial | E12: 91.5 | F12: 555 | G12: =E12/F12 -> 0.16486486 | H12: 720 | I12: =$I$1/H12 -> 3.6805556 | J12: =E12+I12 -> 95.180556 | K12: =(J12*$K$1)+J12 -> 97.560069 | L12: 0.125 | M12: =(N12-K12)/N12 -> 0.125 | N12: =K12/(1-L12) -> 111.49722 | O12: =N12/F12 -> 0.2008959 | Q12: =(N12-K12)*H12 -> 10034.75
A13: Trina Solar | B13: TSM-410DE09R.05 | C13: Monofacial | E13: 65.6 | F13: 410 | G13: =E13/F13 -> 0.16 | H13: 936 | I13: =$I$1/H13 -> 2.8311966 | J13: =E13+I13 -> 68.431197 | K13: =(J13*$K$1)+J13 -> 70.141976 | L13: 0.125 | M13: =(N13-K13)/N13 -> 0.125 | N13: =K13/(1-L13) -> 80.162259 | O13: =N13/F13 -> 0.1955177 | Q13: =(N13-K13)*H13 -> 9378.9843
A14: Trina Solar | B14: TSM-420DE09R.05 | C14: Monofacial | E14: 71.4 | F14: 420 | G14: =E14/F14 -> 0.17 | H14: 936 | I14: =$I$1/H14 -> 2.8311966 | J14: =E14+I14 -> 74.231197 | K14: =(J14*$K$1)+J14 -> 76.086977 | L14: 0.125 | M14: =(N14-K14)/N14 -> 0.125 | N14: =K14/(1-L14) -> 86.956545 | O14: =N14/F14 -> 0.20703939 | Q14: =(N14-K14)*H14 -> 10173.916
A15: Trina Solar | B15: TSM-430NEG9RC.27 | C15: Monofacial | E15: 84 | F15: 430 | G15: =E15/F15 -> 0.19534884 | H15: 936 | I15: =$I$1/H15 -> 2.8311966 | J15: =E15+I15 -> 86.831197 | K15: =(J15*$K$1)+J15 -> 89.001976 | L15: 0.125 | M15: =(N15-K15)/N15 -> 0.125 | N15: =K15/(1-L15) -> 101.71654 | O15: =N15/F15 -> 0.2365501 | Q15: =(N15-K15)*H15 -> 11900.836
A16: jinko | B16: 440 | C16: Monofacial | D16: BayWa | E16: 58.96 | F16: 440 | G16: =E16/F16 -> 0.134 | H16: 936 | I16: =$I$1/H16 -> 2.8311966 | J16: =E16+I16 -> 61.791197 | K16: =(J16*$K$1)+J16 -> 63.335977 | L16: 0.15 | M16: =(N16-K16)/N16 -> 0.15 | N16: =K16/(1-L16) -> 74.512914 | O16: =N16/F16 -> 0.16934753 | P16: =N16*H16 -> 69744.087 | Q16: =(N16-K16)*H16 -> 10461.613
A17: LONGI | B17: 585 | C17: Monofacial | D17: BayWa | E17: 86.58 | F17: 585 | G17: =E17/F17 -> 0.148 | H17: 620 | I17: =$I$1/H17 -> 4.2741935 | J17: =E17+I17 -> 90.854194 | K17: =(J17*$K$1)+J17 -> 93.125548 | L17: 0.125 | M17: =(N17-K17)/N17 -> 0.125 | N17: =K17/(1-L17) -> 106.4292 | O17: =N17/F17 -> 0.18193025 | Q17: =(N17-K17)*H17 -> 8248.2629
A18: JINKO | B18: 585 | C18: Monofacial | D18: ENERGY EXPERTS | E18: 74.295 | F18: 585 | G18: =E18/F18 -> 0.127 | H18: 720 | I18: =$I$1/H18 -> 3.6805556 | J18: =E18+I18 -> 77.975556 | K18: =(J18*$K$1)+J18 -> 79.924944 | L18: 0.0575 | M18: =(N18-K18)/N18 -> 0.0575 | N18: =K18/(1-L18) -> 84.801002 | O18: =N18/F18 -> 0.14495898 | Q18: =(N18-K18)*H18 -> 3510.7615
A20: * the landing price of a panel in Europe must be less that 0.13€/Wp in order the final Customer Price to be able to compare with other Competitor suppliers and give a bigger profit
A22: test | H22: Freight to CY (€/pallet) | I22: 200 | J22: POSR (%) | K22: 0.025
A23: PV Modules - pallet | J23: *has to be decided | N23: *devide (LCP CY)/(1-GM)
A24: Brand | B24: Model | C24: Type | D24: Distributor | E24: Price in EU | F24: Wp/panel | H24: panels /pallet | I24: Freight to CY | J24: LCP CY | K24: FINAL LCP CY | L24: Disired GM(%) | M24: GM (%) | N24: Final Price to Customer | O24: Customer Price (c/Wp) | Q24: GP per pallet
A26: Axitec | B26: BLK AC-400MH/108VAU | C26: Monofacial | E26: 60 | F26: 400 | G26: =E26/F26 -> 0.15 | I26: =$I$22/H26 -> #DIV/0! | J26: =E26+I26 -> #DIV/0! | K26: =(J26*$K$22)+J26 -> #DIV/0! | L26: 0.125 | M26: =(N26-K26)/N26 -> #DIV/0! | N26: =K26/(1-L26) -> #DIV/0! | O26: =N26/F26 -> #DIV/0! | Q26: =(N26-K26)*H26 -> #DIV/0!
A27: Axitec | B27: FXXL AC-420TFM/108BB | C27: Monofacial | E27: 75 | F27: 420 | G27: =E27/F27 -> 0.17857143 | I27: =$I$22/H27 -> #DIV/0! | J27: =E27+I27 -> #DIV/0! | K27: =(J27*$K$22)+J27 -> #DIV/0! | M27: =(N27-K27)/N27 -> #DIV/0! | N27: =K27/(1-L27) -> #DIV/0! | O27: =N27/F27 -> #DIV/0! | Q27: =(N27-K27)*H27 -> #DIV/0!
A28: Axitec | B28: GL AC-430TGB/108BB | C28: Bifacial | E28: 86 | F28: 430 | G28: =E28/F28 -> 0.2 | I28: =$I$22/H28 -> #DIV/0! | J28: =E28+I28 -> #DIV/0! | K28: =(J28*$K$22)+J28 -> #DIV/0! | M28: =(N28-K28)/N28 -> #DIV/0! | N28: =K28/(1-L28) -> #DIV/0! | O28: =N28/F28 -> #DIV/0! | Q28: =(N28-K28)*H28 -> #DIV/0!
A29: Axitec | B29: HC AC-540MH/144V | C29: Monofacial | E29: 86.4 | F29: 540 | G29: =E29/F29 -> 0.16 | I29: =$I$22/H29 -> #DIV/0! | J29: =E29+I29 -> #DIV/0! | K29: =(J29*$K$22)+J29 -> #DIV/0! | M29: =(N29-K29)/N29 -> #DIV/0! | N29: =K29/(1-L29) -> #DIV/0! | O29: =N29/F29 -> #DIV/0! | Q29: =(N29-K29)*H29 -> #DIV/0!
A30: JA Solar | B30: JAM54S31-410W | C30: Monofacial | E30: 61.5 | F30: 410 | G30: =E30/F30 -> 0.15 | H30: 36 | I30: =$I$22/H30 -> 5.5555556 | J30: =E30+I30 -> 67.055556 | K30: =(J30*$K$22)+J30 -> 68.731944 | M30: =(N30-K30)/N30 -> 0 | N30: =K30/(1-L30) -> 68.731944 | O30: =N30/F30 -> 0.16763889 | Q30: =(N30-K30)*H30 -> 0
A31: JA Solar | B31: JAM54S31-410W | C31: Monofacial | D31: solarity | E31: 60 | F31: 415 | G31: =E31/F31 -> 0.14457831 | H31: 36 | I31: =$I$22/H31 -> 5.5555556 | J31: =E31+I31 -> 65.555556 | K31: =(J31*$K$22)+J31 -> 67.194444 | M31: =(N31-K31)/N31 -> 0 | N31: =K31/(1-L31) -> 67.194444 | O31: =N31/F31 -> 0.16191432 | Q31: =(N31-K31)*H31 -> 0
A32: JA Solar | B32: JAM54D41-435/LB | C32: Bifacial | E32: 87 | F32: 435 | G32: =E32/F32 -> 0.2 | I32: =$I$22/H32 -> #DIV/0! | J32: =E32+I32 -> #DIV/0! | K32: =(J32*$K$22)+J32 -> #DIV/0! | M32: =(N32-K32)/N32 -> #DIV/0! | N32: =K32/(1-L32) -> #DIV/0! | O32: =N32/F32 -> #DIV/0! | Q32: =(N32-K32)*H32 -> #DIV/0!
A33: JA Solar | B33: JAM54D40-440/LB | C33: Bifacial | E33: 96.8 | F33: 440 | G33: =E33/F33 -> 0.22 | I33: =$I$22/H33 -> #DIV/0! | J33: =E33+I33 -> #DIV/0! | K33: =(J33*$K$22)+J33 -> #DIV/0! | M33: =(N33-K33)/N33 -> #DIV/0! | N33: =K33/(1-L33) -> #DIV/0! | O33: =N33/F33 -> #DIV/0! | Q33: =(N33-K33)*H33 -> #DIV/0!
A34: JA Solar | B34: JAM72S30-555/GR | C34: Monofacial | E34: 91.5 | F34: 555 | G34: =E34/F34 -> 0.16486486 | I34: =$I$22/H34 -> #DIV/0! | J34: =E34+I34 -> #DIV/0! | K34: =(J34*$K$22)+J34 -> #DIV/0! | M34: =(N34-K34)/N34 -> #DIV/0! | N34: =K34/(1-L34) -> #DIV/0! | O34: =N34/F34 -> #DIV/0! | Q34: =(N34-K34)*H34 -> #DIV/0!
A35: Trina Solar | B35: TSM-410DE09R.05 | C35: Monofacial | E35: 65.6 | F35: 410 | G35: =E35/F35 -> 0.16 | I35: =$I$22/H35 -> #DIV/0! | J35: =E35+I35 -> #DIV/0! | K35: =(J35*$K$22)+J35 -> #DIV/0! | M35: =(N35-K35)/N35 -> #DIV/0! | N35: =K35/(1-L35) -> #DIV/0! | O35: =N35/F35 -> #DIV/0! | Q35: =(N35-K35)*H35 -> #DIV/0!
A36: Trina Solar | B36: TSM-415DE09R.05 | C36: Monofacial | D36: Energy3000 | E36: 69 | F36: 415 | G36: =E36/F36 -> 0.16626506 | H36: 36 | I36: =$I$22/H36 -> 5.5555556 | J36: =E36+I36 -> 74.555556 | K36: =(J36*$K$22)+J36 -> 76.419444 | M36: =(N36-K36)/N36 -> 0 | N36: =K36/(1-L36) -> 76.419444 | O36: =N36/F36 -> 0.18414324 | Q36: =(N36-K36)*H36 -> 0
A37: Trina Solar | B37: TSM-420DE09R.05 | C37: Monofacial | E37: 71.4 | F37: 420 | G37: =E37/F37 -> 0.17 | I37: =$I$22/H37 -> #DIV/0! | J37: =E37+I37 -> #DIV/0! | K37: =(J37*$K$22)+J37 -> #DIV/0! | M37: =(N37-K37)/N37 -> #DIV/0! | N37: =K37/(1-L37) -> #DIV/0! | O37: =N37/F37 -> #DIV/0! | Q37: =(N37-K37)*H37 -> #DIV/0!
A38: Trina Solar | B38: TSM-430NEG9RC.27 | C38: Monofacial | E38: 84 | F38: 430 | G38: =E38/F38 -> 0.19534884 | H38: 36 | I38: =$I$22/H38 -> 5.5555556 | J38: =E38+I38 -> 89.555556 | K38: =(J38*$K$22)+J38 -> 91.794444 | M38: =(N38-K38)/N38 -> 0 | N38: =K38/(1-L38) -> 91.794444 | O38: =N38/F38 -> 0.21347545 | Q38: =(N38-K38)*H38 -> 0
A39: jinko | B39: Tiger neo 435Wp | C39: Monofacial | D39: BayWa | E39: =0.144*435 -> 62.64 | F39: 435 | G39: =E39/F39 -> 0.144 | H39: 36 | I39: =$I$22/H39 -> 5.5555556 | J39: =E39+I39 -> 68.195556 | K39: =(J39*$K$22)+J39 -> 69.900444 | L39: 0.07 | M39: =(N39-K39)/N39 -> 0.07 | N39: =K39/(1-L39) -> 75.161768 | O39: =N39/F39 -> 0.17278567 | Q39: =(N39-K39)*H39 -> 189.40766 | T39: https://www.mg-solar-shop.com/media/pdf/43/30/25/datasheet_jkm425-450n-54hl4r-v.pdf | U39: 1762*1134*30mm
A40: jinko | B40: Tiger neo 440Wp | C40: Monofacial | D40: BayWa | E40: 63.36 | F40: 440 | G40: =E40/F40 -> 0.144 | H40: 36 | I40: =$I$22/H40 -> 5.5555556 | J40: =E40+I40 -> 68.915556 | K40: =(J40*$K$22)+J40 -> 70.638444 | L40: 0.1 | M40: =(N40-K40)/N40 -> 0.1 | N40: =K40/(1-L40) -> 78.48716 | O40: =N40/F40 -> 0.17837991 | Q40: =(N40-K40)*H40 -> 282.55378 | T40: https://www.mg-solar-shop.com/media/pdf/43/30/25/datasheet_jkm425-450n-54hl4r-v.pdf | U40: 1762*1134*30mm
A41: LONGI | B41: Scientist 585Wp | C41: Monofacial | D41: BayWa | E41: 86.58 | F41: 585 | G41: =E41/F41 -> 0.148 | H41: 31 | I41: =$I$22/H41 -> 6.4516129 | J41: =E41+I41 -> 93.031613 | K41: =(J41*$K$22)+J41 -> 95.357403 | L41: 0.1 | M41: =(N41-K41)/N41 -> 0.1 | N41: =K41/(1-L41) -> 105.95267 | O41: =N41/F41 -> 0.18111568 | Q41: =(N41-K41)*H41 -> 328.45328 | T41: https://5qrorwxhmlijjij.leadongcdn.com/LONGI+Hi-MO+6+Scientist+LR5-72HTH+585-600M-aidjrBpjKokRijSmmkrnplmk.pdf?dp= | U41: 2278*1134*35mm
A42: jinko | B42: Tiger neo 440Wp | C42: Monofacial | D42: BayWa | E42: 63.36 | F42: 440 | G42: =E42/F42 -> 0.144 | H42: 36 | I42: =$I$22/H42 -> 5.5555556 | J42: =E42+I42 -> 68.915556 | K42: =(J42*$K$22)+J42 -> 70.638444 | L42: 0.1 | M42: =(N42-K42)/N42 -> 0.1 | N42: =K42/(1-L42) -> 78.48716 | O42: =N42/F42 -> 0.17837991 | Q42: =(N42-K42)*H42 -> 282.55378 | T42: https://www.mg-solar-shop.com/media/pdf/43/30/25/datasheet_jkm425-450n-54hl4r-v.pdf | U42: 1762*1134*30mm
A43: sunpower | B43: p6 xs 405 | C43: Monofacial | D43: BayWa | E43: =405*0.155 -> 62.775 | F43: 405 | G43: =E43/F43 -> 0.155 | H43: 36 | I43: =$I$22/H43 -> 5.5555556 | J43: =E43+I43 -> 68.330556 | K43: =(J43*$K$22)+J43 -> 70.038819 | L43: 0.1 | M43: =(N43-K43)/N43 -> 0.1 | N43: =K43/(1-L43) -> 77.82091 | O43: =N43/F43 -> 0.1921504 | Q43: =(N43-K43)*H43 -> 280.15528 | U43: 1762*1134*30mm
A44: LUXOR | B44: LX-575TC-M/144/N TYPE/B | C44: Bifacial | D44: KRANNICH | E44: 89.12 | F44: 575 | G44: =E44/F44 -> 0.1549913 | H44: 31 | I44: =$I$22/H44 -> 6.4516129 | J44: =E44+I44 -> 95.571613 | K44: =(J44*$K$22)+J44 -> 97.960903 | L44: 0.15 | M44: =(N44-K44)/N44 -> 0.15 | N44: =K44/(1-L44) -> 115.24812 | O44: =N44/F44 -> 0.20043152 | Q44: =(N44-K44)*H44 -> 535.90376 | T44: https://www.luxor.solar/files/luxor/download/datasheets/LX_EL_N-Type_GG_BIF_SW_M144_555-575W_182_EN.pdf | U44: 2279*1134*35mm | V44: 32.7kg
A45: LUXOR | B45: ECO LINE LX-430 M108 G-G | C45: Monofacial | D45: KRANNICH | E45: =2399.4/36 -> 66.65 | F45: 430 | G45: =E45/F45 -> 0.155 | H45: 36 | I45: =$I$22/H45 -> 5.5555556 | J45: =E45+I45 -> 72.205556 | K45: =(J45*$K$22)+J45 -> 74.010694 | L45: 0.13 | M45: =(N45-K45)/N45 -> 0.13 | N45: =K45/(1-L45) -> 85.069764 | O45: =N45/F45 -> 0.19783666 | Q45: =(N45-K45)*H45 -> 398.12649 | T45: https://www.luxor.solar/files/luxor/download/datasheets/LX_EL_N-Type_GG_BIF_SW_M144_555-575W_182_EN.pdf | U45: 2279*1134*35mm | V45: 32.7kg
A46: LUXOR | B46: ECO LINE LX-440 M108 G-G | C46: Monofacial | D46: KRANNICH | E46: =2455.2/36 -> 68.2 | F46: 440 | G46: =E46/F46 -> 0.155 | H46: 36 | I46: =$I$22/H46 -> 5.5555556 | J46: =E46+I46 -> 73.755556 | K46: =(J46*$K$22)+J46 -> 75.599444 | L46: 0.1409 | M46: =(N46-K46)/N46 -> 0.1409 | N46: =K46/(1-L46) -> 87.998422 | O46: =N46/F46 -> 0.19999641 | Q46: =(N46-K46)*H46 -> 446.3632 | T46: https://www.luxor.solar/files/luxor/download/datasheets/LX_EL_N-Type_GG_BIF_SW_M144_555-575W_182_EN.pdf | U46: 2279*1134*35mm | V46: 32.7kg
A47: SUNPOWER | B47: SPR-P6-405-BLK | C47: *container price | D47: baywa | E47: 58.725 | F47: 405 | G47: 0.145 | H47: 36 | I47: =$I$22/H47 -> 5.5555556 | J47: =E47+I47 -> 64.280556 | K47: =(J47*$K$22)+J47 -> 65.887569 | L47: 0.1421 | M47: =(N47-K47)/N47 -> 0.1421 | N47: =K47/(1-L47) -> 76.80099 | O47: =N47/F47 -> 0.18963207 | Q47: =(N47-K47)*H47 -> 392.88315
A48: LUXOR | B48: LX-610TC-M/132/N TYPE/Bifacial/Glass Glass | C48: Bifacial | D48: KRANNICH | E48: 94.55 | F48: 575 | G48: =E48/F48 -> 0.16443478 | H48: 31 | I48: =$I$22/H48 -> 6.4516129 | J48: =E48+I48 -> 101.00161 | K48: =(J48*$K$22)+J48 -> 103.52665 | L48: 0.144 | M48: =(N48-K48)/N48 -> 0.144 | N48: =K48/(1-L48) -> 120.94235 | O48: =N48/F48 -> 0.21033452 | Q48: =(N48-K48)*H48 -> 539.88666 | T48: https://www.luxor.solar/files/luxor/download/datasheets/LX_EL_N-Type_GG_BIF_SW_M144_555-575W_182_EN.pdf | U48: 2279*1134*35mm | V48: 32.7kg
A49: jinko | B49: Tiger neo 445Wp | C49: Monofacial | D49: BayWa | E49: 64.08 | F49: 445 | G49: =E49/F49 -> 0.144 | H49: 36 | I49: =180/H49 -> 5 | J49: =E49+I49 -> 69.08 | K49: =(J49*$K$22)+J49 -> 70.807 | L49: 0.115 | M49: =(N49-K49)/N49 -> 0.115 | N49: =K49/(1-L49) -> 80.00791 | O49: =N49/F49 -> 0.17979306 | Q49: =(N49-K49)*H49 -> 331.23275 | T49: https://www.mg-solar-shop.com/media/pdf/43/30/25/datasheet_jkm425-450n-54hl4r-v.pdf | U49: 1762*1134*30mm
A52: baywa 9/4
A53: 1. For PV panels:
A54: For full container (can be a full container with or panels or mixed with inverters):
A55: Jinko Tiger neo 440Wp à 0.134 €/Wp
A56: Sunpower 405Wp P6 XS à 0.145 €/Wp
A58: For full pallets
A59: Jinko Tiger neo 440Wp à 0.144 €/Wp
A60: Sunpower 405Wp P6 XS à 0.155 €/Wp
A61: Prices are delivered to transport agency in Cyprus.
A63: energy experts 9/7/24
A64: JINKO Tiger Neo N-type bifacial μονοκρυσταλλικά πλαίσια 144 κυττάρων multi busbar half cut technology, μεγαλύτερη απόδοση 22,09% και καλύτερη 30ετή γραμμική απόδοση, 585W (τύπος JKM585N-72HL4-BDV), 0,13 ευρώ/Wp
A65: JINKO Tiger Pro bifacial μονοκρυσταλλικά πλαίσια 144 κυττάρων multi busbar half cut technology, απόδοση 20,94% και 30ετή γραμμική απόδοση, 540W (τύπος JKM540M-72HL4-TV), 0,125 ευρώ/Wp
... A67: JINKO Tiger Neo N-type BLACK FRAME 440W (τύπος JKM440N-54HL4R-V), 0,14 ευρώ/Wp μονοκρυσταλλικά πλαισια 108 κυττάρων multi busbar half cut technology με 5% μεγαλύτερη παραγωγή λόγω καλύτερου θερμοκρασιακού συντελεστή -0,29%/C, μεγαλύτερη απόδοση και καλύτερη 30ετή γραμμική απόδοση,

Sheet Shipping Costs
A1: Krannich
A2: Aspropyrgos - Limassol port | B2: 40ft HQ Container | C2: 2300 | F2: HUAWEI μονοφασικά : 24τμχ ανά παλέτα
A3: Thessaloniki - Limassol | B3: 40ft HQ Container | C3: 2515 | F3: HUAWEI τριφασικά : 16τμχ ανά παλέτα ( ειδικές κατηγοριοποιήσεις ανά μοντέλο Μ1, Μ2, Μ3 & Μ5)
B4: PV panel Pallet | C4: 200 | F4: Fronius έως 8KW : 12τμχ ανά παλέτα
B5: Inverter normal pallet | C5: 150 | F5: Fronius 10KW – 20KW : 8 τμχ ανά παλέτα
B6: Package (eg. 1 inverter) | C6: 25
A7: Polyfreight
A8: Exw Aspropyrgos-Limassol | B8: 40' DC- 7 days EVERGREEN | C8: 1820 | D8: +200euro για HD
A9: Exw Aspropyrgos-Limassol | B9: 40' DC - 3 days - Salamis Shipping Line | C9: 2140 | G9: ~ 3 euros per panel
A10: Exw Aspropyrgos-Limassol | B10: 40' DC - 3 days - CMA-CGM | C10: 1900 | G10: ~ 108 euros per panel box
A11: Stuttgard via Koper-Limassol | B11: 40'HC - 10 days COSCO SHIPPING | C11: 3640 | G11: ~ 25 euros per inverter
A12: Rotterdam city - Limassol | B12: 40' DC - 20 days | C12: 2610
A13: Budapest via Koper-Limassol | B13: 40' DC - 10 days | C13: 3100
A14: Thessaloniki - Limassol | B14: 1 pallet PV - 3days | C14: 290
A15: Aspropyrgos - Limassol | B15: 1 pallet PV - 3days | C15: 300
A16: Aspropyrgos - Limassol | B16: 1 normal pallet - 3days | C16: 145
A17: Thessaloniki - Limassol | B17: 1 normal pallet - 3days | C17: 135
A18: BayWa r.e.
A19: Athens-Limassol | B19: 1 normal pallet | C19: 110
A20: Energy3000 | D20: Industriestraße V/1, 7052 Müllendorf, Austria
A21: Austria-Athens | B21: 1 piece | C21: 79 | D21: +5e every inverter
A22: Austria-Thessaloniki | B22: 1 piece | C22: 76
A23: Austria-Athens | B23: 1 pallet inverters | C23: 280 | F23: +200euros from Greece to Cyprus
A24: Austria-Thessaloniki | B24: 1 pallet inverters | C24: 250
A25: Austria-Athens | B25: 1 pallet PV | C25: 440 | D25: ~13e per panel
A26: Austria-Thessaloniki | B26: 1 pallet PV | C26: 508 | D26: ~15e
A27: SOLARITY
A28: CZ-CY | B28: 1 pallet | C28: 300
A29: CZ-CY | B29: 1 pallet PV | C29: 520
A30: CZ-CY | B30: container | C30: 3155

Sheet ALL DATA & IT4PROFIT
Z1: Required product data for IT4
A2: Brand | B2: Model | D2: Price KAFKAS | E2: PRICE KRANNICH GR WITHOUT 27-34% discount | F2: PRICE KRANNICH GR *27-34% discount | G2: BIG SOLAR | H2: PRICE DR. ENERGY | I2: PRICE BayWa r.e Greece | J2: *REDUSED* BayWa r.e Greece | K2: TRIKKIS ENERGY | L2: CONERCON (Lanitis) | M2: MEMODO | N2: SOLARITY | O2: SUN.STORE | P2: MERXU | Q2: SOLAR DISTRIBUTION | R2: ENERGY3000 | Z2: Article | AA2: Manufacturer (Manufacturer site) | AB2: Product type | AC2: Description | AD2: Package Type | AE2: Color | AF2: Warranty (month) | AG2: URL | AH2: Q-ty in Pack | AI2: Dimensions w/o package (WxHxD) | AJ2: Weight w/o package | AK2: Dimensions with package (WxHxD) | AL2: Pack Weight Brutto | AM2: Pack Weight Netto | AN2: Box Dimensions (WxHxD) | AO2: Box Weight Brutto | AP2: Packs in Box
E3: + ~100€ SHIPPING | F3: + ~100€ SHIPPING
E4: 0.3 | F4: 0.4
A5: INVERTERS | C5: TYPE
A6: HUAWEI | B6: SUN2000-2KTL-L1 | C6: 1PH HYBRID | D6: 489 | F6: =E6-(E6*$F$4) -> 0 | H6: 557 | J6: *se container | K6: 344 | L6: 420 | N6: 494.54 | O6: 426 | P6: 406 | Q6: 385 | R6: 449 | Z6: SUN2000-2KTL-L1 | AA6: HUAWEI | AB6: Inverter | AC6: Hybrid, 1 phase Inverter, 2kW | AD6: Box | AF6: 120 | AG6: https://solar.huawei.com/en-GB/download?p=/-/media/Solar/attachment/pdf/apac/datasheet/SUN2000-2-5KTL-L1.pdf | AH6: 1 | AI6: 365mm * 365mm * 156 mm | AJ6: 12
A7: HUAWEI | B7: SUN2000-3KTL-L1 | C7: 1PH HYBRID | D7: 575 | E7: 843 | F7: =E7-(E7*$F$4)-150 -> 355.8 | H7: 545 | I7: 605 | J7: 550 | K7: 432 | L7: 510 | N7: 581.5 | O7: 483 | P7: 409 | R7: 529 | Z7: SUN2000-3KTL-L1 | AA7: HUAWEI | AB7: Inverter | AC7: Hybrid, 1 phase Inverter, 3kW | AD7: Box | AF7: 120 | AG7: https://solar.huawei.com/en-GB/download?p=/-/media/Solar/attachment/pdf/apac/datasheet/SUN2000-2-5KTL-L1.pdf | AH7: 1 | AI7: 365mm * 365mm * 156 mm | AJ7: 12
A8: HUAWEI | B8: SUN2000-3.68KTL-L1 | C8: 1PH HYBRID | D8: 677 | F8: =E8-(E8*$F$4) -> 0 | L8: 580 | N8: 663 | O8: 567 | P8: 456 | Q8: 579 | R8: 523 | Z8: SUN2000-3.68KTL-L1 | AA8: HUAWEI | AB8: Inverter | AC8: Hybrid, 1 phase Inverter, 3.6kW | AD8: Box
A9: HUAWEI | B9: SUN2000-4KTL-L1 | C9: 1PH HYBRID | D9: 705 | E9: 946 | F9: =E9-(E9*$F$4)-150 -> 417.6 | H9: 580 | I9: 741 | J9: 674 | K9: 563 | L9: 620 | N9: 710.84 | O9: 616 | P9: 665 | R9: 648 | Z9: SUN2000-4KTL-L1 | AA9: HUAWEI | AB9: Inverter | AC9: Hybrid, 1 phase Inverter, 4kW | AD9: Box | AF9: 120 | AG9: https://solar.huawei.com/en-GB/download?p=/-/media/Solar/attachment/pdf/apac/datasheet/SUN2000-2-5KTL-L1.pdf | AH9: 1 | AI9: 365mm * 365mm * 156 mm | AJ9: 12
A10: HUAWEI | B10: SUN2000-4.6KTL-L1 | C10: 1PH HYBRID | D10: 756 | E10: 1114 | F10: =E10-(E10*$F$4)-150 -> 518.4 | H10: 595 | K10: 616 | L10: 645 | N10: 734.35 | O10: 582 | P10: 685 | Q10: 650 | R10: 696 | Z10: SUN2000-4.6KTL-L1 | AA10: HUAWEI | AB10: Inverter | AC10: Hybrid, 1 phase Inverter, 4.6kW | AD10: Box
A11: HUAWEI | B11: SUN2000-5KTL-L1 | C11: 1PH HYBRID | D11: 764 | E11: 1026 | F11: =E11-(E11*$F$4)-150 -> 465.6 | H11: 620 | I11: 803 | J11: 731 | K11: 624 | L11: 660 | N11: 770.63 | O11: 658 | P11: 561 | R11: 703 | Z11: SUN2000-5KTL-L1 | AA11: HUAWEI | AB11: Inverter | AC11: Hybrid, 1 phase Inverter, 5kW | AD11: Box | AF11: 120 | AG11: https://solar.huawei.com/en-GB/download?p=/-/media/Solar/attachment/pdf/apac/datasheet/SUN2000-2-5KTL-L1.pdf | AH11: 1 | AI11: 365mm * 365mm * 156 mm | AJ11: 12
A12: HUAWEI | B12: SUN2000-6KTL-L1 | C12: 1PH HYBRID | D12: 868 | E12: 993 | F12: =E12-(E12*$F$4)-150 -> 445.8 | O12: 814 | P12: 669 | R12: 799
A13: HUAWEI | B13: SUN2000-3KTL-M1 | C13: 3PH HYBRID | D13: 880 | E13: 1347 | F13: =E13-(E13*$F$4) -> 808.2 | H13: 907 | I13: 873 | J13: 794 | K13: 832 | L13: 845 | N13: 881 | O13: 772 | P13: 760 | R13: 794 | Z13: SUN2000-3KTL-M1 | AA13: HUAWEI | AB13: Inverter | AC13: Hybrid, 3 phase Inverter, 3kW | AD13: Box | AF13: 120 | AG13: https://solar.huawei.com/download?p=%2F-%2Fmedia%2FSolar%2Fdatasheet%2FSUN2000-3_4_5_6_8_10KTL-M1_High_Current_Version.pdf | AH13: 1 | AI13: 525 mm x 492.5 mm x 166 mm | AJ13: 17
A14: HUAWEI | B14: SUN2000-4KTL-M1 | C14: 3PH HYBRID | D14: 920 | E14: 1408 | F14: =E14-(E14*$F$4) -> 844.8 | H14: 906 | I14: 913 | J14: 830 | K14: 871 | L14: 880 | N14: 919 | O14: 842 | P14: 750 | R14: 830 | Z14: SUN2000-4KTL-M1 | AA14: HUAWEI | AB14: Inverter | AC14: Hybrid, 3 phase Inverter, 4kW | AD14: Box | AF14: 120 | AG14: https://solar.huawei.com/download?p=%2F-%2Fmedia%2FSolar%2Fdatasheet%2FSUN2000-3_4_5_6_8_10KTL-M1_High_Current_Version.pdf | AH14: 1 | AI14: 526 mm x 492.5 mm x 166 mm | AJ14: 17
A15: HUAWEI | B15: SUN2000-5KTL-M1 | C15: 3PH HYBRID | D15: 971 | E15: 1485 | F15: =E15-(E15*$F$4) -> 891 | H15: 930 | I15: 963 | J15: 876 | K15: 919 | L15: 930 | N15: 963.67 | O15: 887 | P15: 860 | R15: 876 | Z15: SUN2000-5KTL-M1 | AA15: HUAWEI | AB15: Inverter | AC15: Hybrid, 3 phase Inverter, 5kW | AD15: Box | AF15: 120 | AG15: https://solar.huawei.com/download?p=%2F-%2Fmedia%2FSolar%2Fdatasheet%2FSUN2000-3_4_5_6_8_10KTL-M1_High_Current_Version.pdf | AH15: 1 | AI15: 527 mm x 492.5 mm x 166 mm | AJ15: 17
A16: HUAWEI | B16: SUN2000-6KTL-M1 | C16: 3PH HYBRID | D16: 1086 | E16: 1660 | F16: =E16-(E16*$F$4) -> 996 | H16: 1090 | I16: 1078 | J16: 980 | K16: 1028 | L16: 1040 | N16: 1083 | O16: 980 | P16: 849 | R16: 980 | Z16: SUN2000-6KTL-M1 | AA16: HUAWEI | AB16: Inverter | AC16: Hybrid, 3 phase Inverter, 6kW | AD16: Box | AF16: 120 | AG16: https://solar.huawei.com/download?p=%2F-%2Fmedia%2FSolar%2Fdatasheet%2FSUN2000-3_4_5_6_8_10KTL-M1_High_Current_Version.pdf | AH16: 1 | AI16: 528 mm x 492.5 mm x 166 mm | AJ16: 17
A17: HUAWEI | B17: SUN2000-8KTL-M1 | C17: 3PH HYBRID | D17: 1289 | E17: 1966 | F17: =E17-(E17*$F$4) -> 1179.6 | H17: 1260 | I17: 1278 | J17: 1162 | K17: 1219 | L17: 1235 | N17: 1276 | O17: 1177 | P17: 1043 | R17: 1162 | Z17: SUN2000-8KTL-M1 | AA17: HUAWEI | AB17: Inverter | AC17: Hybrid, 3 phase Inverter, 8kW | AD17: Box | AF17: 120 | AG17: https://solar.huawei.com/download?p=%2F-%2Fmedia%2FSolar%2Fdatasheet%2FSUN2000-3_4_5_6_8_10KTL-M1_High_Current_Version.pdf | AH17: 1 | AI17: 529 mm x 492.5 mm x 166 mm | AJ17: 17
A18: HUAWEI | B18: SUN2000-10KTL-M1 | C18: 3PH HYBRID | D18: 1448 | E18: 2207 | F18: =E18-(E18*$F$4) -> 1324.2 | H18: 1385 | I18: 1435 | J18: 1306 | K18: 1369 | L18: 1385 | N18: 1442 | O18: 1275 | P18: 1239 | R18: 1306 | Z18: SUN2000-10KTL-M1 | AA18: HUAWEI | AB18: Inverter | AC18: Hybrid, 3 phase Inverter, 10kW | AD18: Box | AF18: 120 | AG18: https://solar.huawei.com/download?p=%2F-%2Fmedia%2FSolar%2Fdatasheet%2FSUN2000-3_4_5_6_8_10KTL-M1_High_Current_Version.pdf | AH18: 1 | AI18: 530 mm x 492.5 mm x 166 mm | AJ18: 17
A19: HUAWEI | B19: SUN2000-12KTL-M5 | C19: 3PH HYBRID | D19: 1515 | E19: 2312 | F19: =E19-(E19*$F$4) -> 1387.2 | I19: 1504 | J19: 1420 | K19: 947.6 | L19: 1450 | N19: 1508 | O19: 1350 | P19: 1347 | R19: 1375 | Z19: SUN2000-12KTL-M5 | AA19: HUAWEI | AB19: Inverter | AC19: Hybrid, 3 phase Inverter, 12kW | AD19: Box | AF19: 120 | AG19: https://solar.huawei.com/download?p=%2F-%2Fmedia%2FSolar%2Fdatasheet%2FSUN2000-12_15_17_20_25KTL-M5.pdf | AH19: 1 | AI19: 546 mm x 460 mm x 241.5 mm | AJ19: 21
A20: HUAWEI | B20: SUN2000-15KTL-M5 | C20: 3PH HYBRID | D20: 1710 | E20: 2607 | F20: =E20-(E20*$F$4) -> 1564.2 | I20: 1697 | J20: 1580 | K20: 1133.5 | L20: 1640 | N20: 1703 | O20: 1547 | P20: 1351 | R20: 1552 | Z20: SUN2000-15KTL-M5 | AA20: HUAWEI | AB20: Inverter | AC20: Hybrid, 3 phase Inverter, 15kW | AD20: Box | AF20: 120 | AG20: https://solar.huawei.com/download?p=%2F-%2Fmedia%2FSolar%2Fdatasheet%2FSUN2000-12_15_17_20_25KTL-M5.pdf | AH20: 1 | AI20: 547 mm x 460 mm x 241.5 mm | AJ20: 21
A21: HUAWEI | B21: SUN2000-17KTL-M5 | C21: 3PH HYBRID | D21: 1447 | E21: 2662 | F21: =E21-(E21*$F$4) -> 1597.2 | I21: 1733 | J21: 1615 | K21: 1167.6 | L21: 1675 | N21: 1737 | O21: 1596 | P21: 1285 | Q21: 1257 | R21: 1585 | Z21: SUN2000-17KTL-M5 | AA21: HUAWEI | AB21: Inverter | AC21: Hybrid, 3 phase Inverter, 17kW | AD21: Box | AF21: 120 | AG21: https://solar.huawei.com/download?p=%2F-%2Fmedia%2FSolar%2Fdatasheet%2FSUN2000-12_15_17_20_25KTL-M5.pdf | AH21: 1 | AI21: 548 mm x 460 mm x 241.5 mm | AJ21: 21
A22: HUAWEI | B22: SUN2000-20KTL-M5 | C22: 3PH HYBRID | D22: 1844 | E22: 2812 | F22: =E22-(E22*$F$4) -> 1687.2 | I22: 1831 | J22: 1704 | K22: 1262.2 | L22: 1790 | N22: 1829 | O22: 1650 | P22: 1452 | Q22: 1352 | R22: 1674 | Z22: SUN2000-20KTL-M5 | AA22: HUAWEI | AB22: Inverter | AC22: Hybrid, 3 phase Inverter, 20kW | AD22: Box | AF22: 120 | AG22: https://solar.huawei.com/download?p=%2F-%2Fmedia%2FSolar%2Fdatasheet%2FSUN2000-12_15_17_20_25KTL-M5.pdf | AH22: 1 | AI22: 549 mm x 460 mm x 241.5 mm | AJ22: 21
A23: HUAWEI | B23: SUN2000-25KTL-M5 | C23: 3PH HYBRID | D23: 1906 | E23: 2904 | F23: =E23-(E23*$F$4) -> 1742.4 | I23: 1891 | K23: 1320.5 | L23: 1825 | O23: 1690 | P23: 1750 | R23: 1730 | Z23: SUN2000-25KTL-M5 | AA23: HUAWEI | AB23: Inverter | AC23: Hybrid, 3 phase Inverter, 25kW | AD23: Box | AF23: 120 | AG23: https://solar.huawei.com/download?p=%2F-%2Fmedia%2FSolar%2Fdatasheet%2FSUN2000-12_15_17_20_25KTL-M5.pdf | AH23: 1 | AI23: 550 mm x 460 mm x 241.5 mm | AJ23: 21
A24: HUAWEI | B24: SUN2000-30KTL-M3 | C24: 3PH HYBRID | D24: 2106 | E24: 3210 | F24: =E24-(E24*$F$4) -> 1926 | J24: 1945 | K24: 1993 | L24: 2080 | N24: 2083 | O24: 1766 | P24: 1700 | Q24: 1863 | R24: 1881 | Z24: SUN2000-30KTL-M3 | AA24: HUAWEI | AB24: Inverter | AC24: Hybrid, 3 phase Inverter, 30kW | AD24: Box | AF24: 120 | AG24: https://solar.huawei.com/en-GB/download?p=%2F-%2Fmedia%2FSolar%2Fattachment%2Fpdf%2Feu%2Fdatasheet%2FSUN2000-30-40KTL-M3.pdf | AH24: 1 | AI24: 640 x 530 x 270 mm | AJ24: 43
A25: HUAWEI | B25: SUN2000-36KTL-M3 | C25: 3PH HYBRID | D25: 2405 | E25: 3663 | F25: =E25-(E25*$F$4) -> 2197.8 | J25: 2220 | K25: 2274 | L25: 2250 | N25: 2377 | O25: 1700 | P25: 2095 | Q25: 1759 | R25: 2170 | Z25: SUN2000-36KTL-M3 | AA25: HUAWEI | AB25: Inverter | AC25: Hybrid, 3 phase Inverter, 36kW | AD25: Box | AF25: 120 | AG25: https://solar.huawei.com/en-GB/download?p=%2F-%2Fmedia%2FSolar%2Fattachment%2Fpdf%2Feu%2Fdatasheet%2FSUN2000-30-40KTL-M3.pdf | AH25: 1 | AI25: 641 x 530 x 270 mm | AJ25: 44
A26: HUAWEI | B26: SUN2000-40KTL-M3 | C26: 3PH HYBRID | D26: 2536 | E26: 3862 | F26: =E26-(E26*$F$4) -> 2317.2 | J26: 2348 | K26: 2399 | L26: 2380 | N26: 2506 | O26: 1950 | P26: 1800 | R26: 2289 | Z26: SUN2000-40KTL-M3 | AA26: HUAWEI | AB26: Inverter | AC26: Hybrid, 3 phase Inverter, 40kW | AD26: Box | AF26: 120 | AG26: https://solar.huawei.com/en-GB/download?p=%2F-%2Fmedia%2FSolar%2Fattachment%2Fpdf%2Feu%2Fdatasheet%2FSUN2000-30-40KTL-M3.pdf | AH26: 1 | AI26: 642 x 530 x 270 mm | AJ26: 45
A27: HUAWEI | B27: SUN2000-50KTL-M3 | C27: 3PH HYBRID | D27: 2543 | E27: 4000 | F27: =E27-(E27*$F$4) -> 2400 | J27: 2350 | K27: 2405 | L27: 2400 | N27: 2513 | O27: 1750 | P27: 1800 | R27: 2319 | Z27: SUN2000-50KTL-M3 | AA27: HUAWEI | AB27: Inverter | AC27: Hybrid, 3 phase Inverter, 50kW | AD27: Box | AF27: 120 | AG27: https://solar.huawei.com/en-GB/download?p=%2F-%2Fmedia%2FSolar%2Fattachment%2Fpdf%2Feu%2Fdatasheet%2FSUN2000-50kTL-M3-Datasheet.pdf | AH27: 1 | AI27: 640 x 530 x 270 mm | AJ27: 49
A28: HUAWEI | B28: SUN2000-100KTL-M2-AFCI | C28: 3PH HYBRID | D28: 4020 | K28: 3800 | N28: 3968 | P28: 3740 | R28: 3626 | Z28: SUN2000-100KTL-M2-AFCI | AA28: HUAWEI | AB28: Inverter | AC28: Hybrid, 3 phase Inverter, 100kW | AD28: Box | AF28: 120 | AG28: https://solar.huawei.com/download?p=%2F-%2Fmedia%2FSolarV4%2Fsolar-version2%2Fcommon%2Fprofessionals%2Fall-products%2Fci%2Fsmart-pv-controller%2Fsun2000-100ktl-m2%2Fsun2000-100ktl-m2-datasheet-20230506.pdf | AH28: 1 | AI28: 1035 x 700 x 365 mm | AJ28: 93
A29: HUAWEI | B29: IV HU SUN2000 115 KTL M2 | K29: 3842.6 | O29: 3699 | P29: 3810 | R29: 3998 | Z29: IV HU SUN2000 115 KTL M2 | AA29: HUAWEI | AB29: Inverter | AC29: String, 3 phase Inverter, 115kW | AD29: Box | AG29: https://solar.huawei.com/download?p=%2F-%2Fmedia%2FSolarV4%2Fsolar-version2%2Fcommon%2Fprofessionals%2Fall-products%2Fci%2Fsmart-pv-controller%2Fsun2000-115ktl-m2%2Fsun2000-115ktl-m2-datasheet-20230506.pdf | AH29: 1 | AI29: 1036 x 700 x 365 mm | AJ29: 93
A30: HUAWEI | B30: IV HU SUN2000 105 KTL H1 (1500V) | O30: 3690 | P30: 3595 | Z30: IV HU SUN2000 105 KTL H1 (1500V) | AA30: HUAWEI | AB30: Inverter | AC30: String, 3 phase Inverter 105kW | AD30: Box | AG30: https://solar.huawei.com/en-GB/download?p=%2F~%2Fmedia%2FSolar%2Fattachment%2Fpdf%2Feu%2Fdatasheet%2FSUN2000-105KTL-H1.pdf | AH30: 1 | AI30: 1075 x 605 x 310mm | AJ30: 79
A31: HUAWEI | B31: IV HU SUN2000 215 KTL-H3 (1500V) | O31: 5244 | P31: 5315 | Z31: IV HU SUN2000 215 KTL-H3 (1500V) | AA31: HUAWEI | AB31: Inverter | AC31: String, 3 phase Inverter, 215kW | AD31: Box | AG31: https://solar.huawei.com/en-GB/download?p=%2F-%2Fmedia%2FSolar%2Fattachment%2Fpdf%2Feu%2Fdatasheet%2FSUN2000-215KTL-H3.pdf | AH31: 1 | AI31: 1035 x 700 x 365 mm | AJ31: 86
A32: HUAWEI | B32: IV HU SUN2000-330KTL-H1 (1500V) | N32: 9400 | O32: 6800 | P32: 7219 | Z32: IV HU SUN2000-330KTL-H1 (1500V) | AA32: HUAWEI | AB32: Inverter | AC32: String, 3 phase Inverter, 330kW | AD32: Box | AG32: https://solar.huawei.com/download?p=%2F-%2Fmedia%2FSolarV4%2Fsolar-version2%2Fcommon%2Fprofessionals%2Fall-products%2Futility-smart-pv%2Fsmart-pv-controller%2FSUN2000-330KTL-H1%2Fsun2000-330ktl-h1-datasheet-20230515.pdf | AH32: 1 | AI32: 1,048 x 732 x 395 mm | AJ32: 112
A33: HUAWEI | B33: SUN2000-20KTL-MBO | C33: 3PH HYBRID | E33: 3390 | F33: =E33-(E33*$F$4) -> 2034 | L33: 2150 | Z33: SUN2000-20KTL-MBO | AA33: HUAWEI | AB33: Inverter | AC33: Hybrid, 3 phase Inverter, 20kW | AD33: Box
A35: HUAWEI | B35: SUN2000-450W-P2 | C35: OPTIMIZER | D35: 41 | E35: 60 | F35: =E35-(E35*$F$4) -> 36 | J35: 45 | K35: 38.5 | L35: 40 | P35: 38.74 | Q35: 31 | R35: 35 | Z35: SUN2000-450W-P2 | AA35: HUAWEI | AB35: Optimizer | AC35: Power optimizer | AD35: Box | AF35: 300 | AG35: https://solar.huawei.com/en-GB/download?p=%2F-%2Fmedia%2FSolar%2Fattachment%2Fpdf%2Feu%2Fdatasheet%2FSUN2000-600W-P.pdf | AH35: 20 | AI35: 75 x 140 x 28 mm | AJ35: 0.6
A36: HUAWEI | B36: SUN2000-600W-P | C36: OPTIMIZER | D36: 41 | E36: 65 | F36: =E36-(E36*$F$4) -> 39 | J36: 45 | K36: 39 | L36: 40 | P36: 39.63 | R36: 36.4 | Z36: SUN2000-600W-P | AA36: HUAWEI | AB36: Optimizer | AC36: Power optimizer | AD36: Box | AF36: 120 | AG36: https://solar.huawei.com/en-GB/download?p=%2F-%2Fmedia%2FSolar%2Fattachment%2Fpdf%2Feu%2Fdatasheet%2FSUN2000-600W-P.pdf | AH36: 20 | AI36: 75 x 140 x 28 mm | AJ36: 0.6
A39: SUNGROW | B39: IV SUNG SG2.0RS | C39: 1PH | E39: 655 | F39: =E39-(E39*$F$4) -> 393 | Z39: IV SUNG SG2.0RS | AA39: SUNGROW | AB39: Inverter | AC39: String 1phase inverter, 2kW | AD39: Box | AG39: https://en.sungrowpower.com/upload/file/20211012/DS_20210720_SG2.0~3.0RS-S_V1.2.3_EN.pdf | AH39: 1 | AI39: 320 * 225 * 120 mm | AJ39: 6
A40: SUNGROW | B40: IV SUNG SG3.0RS | C40: 1PH | E40: 770 | F40: =E40-(E40*$F$4) -> 462 | Z40: IV SUNG SG3.0RS | AA40: SUNGROW | AB40: Inverter | AC40: String 1phase inverter, 3kW | AD40: Box | AG40: https://en.sungrowpower.com/upload/file/20211012/DS_20210720_SG2.0~3.0RS-S_V1.2.3_EN.pdf | AH40: 1 | AI40: 320 * 225 * 120 mm | AJ40: 6
A41: SUNGROW | B41: IV SUNG SG4.0RS | C41: 1PH | E41: 916 | F41: =E41-(E41*$F$4) -> 549.6 | Z41: IV SUNG SG4.0RS | AA41: SUNGROW | AB41: Inverter | AC41: String 1phase inverter, 4kW | AD41: Box | AG41: https://uk.sungrowpower.com/upload/file/20210927/EN%20DS%20SG3.0-6.0RS%20Datasheet.pdf | AH41: 1 | AI41: 410 * 270* 150 mm | AJ41: 10
A42: SUNGROW | B42: IV SUNG SG5.0RS | C42: 1PH | E42: 989 | F42: =E42-(E42*$F$4) -> 593.4 | Z42: IV SUNG SG5.0RS | AA42: SUNGROW | AB42: Inverter | AC42: String 1phase inverter, 5kW | AD42: Box | AG42: https://uk.sungrowpower.com/upload/file/20210927/EN%20DS%20SG3.0-6.0RS%20Datasheet.pdf | AH42: 1 | AI42: 410 * 270* 150 mm | AJ42: 10
A43: SUNGROW | B43: IV SUNG SG3.0RT | C43: 3PH | E43: 1080 | F43: =E43-(E43*$F$4) -> 648 | Z43: IV SUNG SG3.0RT | AA43: SUNGROW | AB43: Inverter | AC43: String 3phase inverter, 3kW | AD43: Box | AG43: https://uk.sungrowpower.com/upload/file/20220808/EN%20DS%20SG3.0RT%20SG4.0RT%20Datasheet.pdf | AH43: 1 | AI43: 370*480*195 mm | AJ43: 18
A44: SUNGROW | B44: IV SUNG SG4.0RT | C44: 3PH | E44: 1139 | F44: =E44-(E44*$F$4) -> 683.4 | Z44: IV SUNG SG4.0RT | AA44: SUNGROW | AB44: Inverter | AC44: String 3phase inverter, 4kW | AD44: Box | AG44: https://uk.sungrowpower.com/upload/file/20220808/EN%20DS%20SG3.0RT%20SG4.0RT%20Datasheet.pdf | AH44: 1 | AI44: 370*480*195 mm | AJ44: 18
A45: SUNGROW | B45: IV SUNG SG5.0RT | C45: 3PH | E45: 1215 | F45: =E45-(E45*$F$4) -> 729 | Q45: 586 | Z45: IV SUNG SG5.0RT | AA45: SUNGROW | AB45: Inverter | AC45: String 3phase inverter, 5kW | AD45: Box | AG45: https://uk.sungrowpower.com/upload/file/20220607/EN%20DS%20SG5.0%206.0%207.0%208.0%2010%2012RT%20Datasheet.pdf | AH45: 1 | AI45: 370*480*195 mm | AJ45: 18
A46: SUNGROW | B46: IV SUNG SG6.0RT | C46: 3PH | E46: 1245 | F46: =E46-(E46*$F$4) -> 747 | Q46: 544 | Z46: IV SUNG SG6.0RT | AA46: SUNGROW | AB46: Inverter | AC46: String 3phase inverter, 6kW | AD46: Box | AG46: https://uk.sungrowpower.com/upload/file/20220607/EN%20DS%20SG5.0%206.0%207.0%208.0%2010%2012RT%20Datasheet.pdf | AH46: 1 | AI46: 370*480*195 mm | AJ46: 18
A47: SUNGROW | B47: IV SUNG SG8.0RT | C47: 3PH | E47: 1259 | F47: =E47-(E47*$F$4) -> 755.4 | Q47: 617 | Z47: IV SUNG SG8.0RT | AA47: SUNGROW | AB47: Inverter | AC47: String 3phase inverter, 8kW | AD47: Box | AG47: https://uk.sungrowpower.com/upload/file/20220607/EN%20DS%20SG5.0%206.0%207.0%208.0%2010%2012RT%20Datasheet.pdf | AH47: 1 | AI47: 370*480*195 mm | AJ47: 18
A48: SUNGROW | B48: IV SUNG SG10.0RT | C48: 3PH | E48: 1450 | F48: =E48-(E48*$F$4) -> 870 | Q48: 709 | Z48: IV SUNG SG10.0RT | AA48: SUNGROW | AB48: Inverter | AC48: String 3phase inverter, 10kW | AD48: Box | AG48: https://uk.sungrowpower.com/upload/file/20220607/EN%20DS%20SG5.0%206.0%207.0%208.0%2010%2012RT%20Datasheet.pdf | AH48: 1 | AI48: 370*480*195 mm | AJ48: 18
A49: SUNGROW | B49: IV SUNG SG12.0RT | C49: 3PH | E49: 1509 | F49: =E49-(E49*$F$4) -> 905.4 | Q49: 736 | Z49: IV SUNG SG12.0RT | AA49: SUNGROW | AB49: Inverter | AC49: String 3phase inverter, 12kW | AD49: Box | AG49: https://uk.sungrowpower.com/upload/file/20220607/EN%20DS%20SG5.0%206.0%207.0%208.0%2010%2012RT%20Datasheet.pdf | AH49: 1 | AI49: 370*480*195 mm | AJ49: 18
A50: SUNGROW | B50: IV SUNG SG15.0RT | C50: 3PH | E50: 1799 | F50: =E50-(E50*$F$4) -> 1079.4 | Q50: 884 | Z50: IV SUNG SG15.0RT | AA50: SUNGROW | AB50: Inverter | AC50: String 3phase inverter, 15kW | AD50: Box | AG50: https://uk.sungrowpower.com/upload/file/20220607/EN%20DS%20SG15%2017%2020RT%20Datasheet.pdf | AH50: 1 | AI50: 370*480*195 mm | AJ50: 21
A51: SUNGROW | B51: IV SUNG SG20.0RT | C51: 3PH | E51: 1895 | F51: =E51-(E51*$F$4) -> 1137 | Q51: 932 | Z51: IV SUNG SG20.0RT | AA51: SUNGROW | AB51: Inverter | AC51: String 3phase inverter, 20kW | AD51: Box | AG51: https://uk.sungrowpower.com/upload/file/20220607/EN%20DS%20SG15%2017%2020RT%20Datasheet.pdf | AH51: 1 | AI51: 370*480*195 mm | AJ51: 21
A52: SUNGROW | B52: IV SUNG SG33CX | C52: 3PH | E52: 2835 | F52: =E52-(E52*$F$4) -> 1701 | Z52: IV SUNG SG33CX | AA52: SUNGROW | AB52: Inverter | AC52: String 3phase inverter, 33kW | AD52: Box | AG52: https://info-support.sungrowpower.com/application/pdf/2022/04/25/DS_20210206_SG33CX%20SG40CX%20SG50CX(including%20Premium)%20Datasheet_V1.1.1_EN.pdf | AH52: 1 | AI52: 702*595*310mm | AJ52: 50
A53: SUNGROW | B53: IV SUNG SG50CX-P2 | C53: 3PH | E53: 3750 | F53: =E53-(E53*$F$4) -> 2250 | Q53: 2215 | Z53: IV SUNG SG50CX-P2 | AA53: SUNGROW | AB53: Inverter | AC53: String 3phase inverter, 50kW | AD53: Box | AG53: https://info-support.sungrowpower.com/application/pdf/2022/04/25/DS_20210206_SG33CX%20SG40CX%20SG50CX(including%20Premium)%20Datasheet_V1.1.1_EN.pdf | AH53: 1 | AI53: 782*645*310mm | AJ53: 62
A54: SUNGROW | B54: IV SUNG SG125-250-350CX-P2 | C54: 3PH | E54: UPON REQUEST
A55: SUNGROW | B55: IVH SUNG SH3.0RS | C55: 1PH HYBRID | E55: 1140 | F55: =E55-(E55*$F$4) -> 684 | Z55: IVH SUNG SH3.0RS | AA55: SUNGROW | AB55: Inverter | AC55: Hybrid, 1 phase Inverter, 3kW | AD55: Box | AG55: https://info-support.sungrowpower.com/application/pdf/2024/01/17/DS_20240111_SH3.0_3.6_4.0_5.0_6.0RS_Datasheet_V17_EN(IEC).pdf | AH55: 1 | AI55: 490 mm * 340 mm * 170 mm | AJ55: 18.5
A56: SUNGROW | B56: IVH SUNG SH4.0RS | C56: 1PH HYBRID | E56: 1349 | F56: =E56-(E56*$F$4) -> 809.4 | Z56: IVH SUNG SH4.0RS | AA56: SUNGROW | AB56: Inverter | AC56: Hybrid, 1 phase Inverter, 4kW | AD56: Box | AG56: https://info-support.sungrowpower.com/application/pdf/2024/01/17/DS_20240111_SH3.0_3.6_4.0_5.0_6.0RS_Datasheet_V17_EN(IEC).pdf | AH56: 1 | AI56: 490 mm * 340 mm * 170 mm | AJ56: 18.5
A57: SUNGROW | B57: IVH SUNG SH5.0RS | C57: 1PH HYBRID | E57: 1450 | F57: =E57-(E57*$F$4) -> 870 | M57: 1200 | Z57: IVH SUNG SH5.0RS | AA57: SUNGROW | AB57: Inverter | AC57: Hybrid, 1 phase Inverter, 5kW | AD57: Box | AG57: https://info-support.sungrowpower.com/application/pdf/2024/01/17/DS_20240111_SH3.0_3.6_4.0_5.0_6.0RS_Datasheet_V17_EN(IEC).pdf | AH57: 1 | AI57: 490 mm * 340 mm * 170 mm | AJ57: 18.5
A58: SUNGROW | B58: IVH SUNG SH5RT V112 S | C58: 3PH HYBRID | E58: 2158 | F58: =E58-(E58*$F$4) -> 1294.8 | M58: 1420 | Z58: IVH SUNG SH5RT V112 S | AA58: SUNGROW | AB58: Inverter | AC58: Hybrid, 3 phase Inverter, 5kW | AD58: Box | AG58: https://en.sungrowpower.com/upload/file/20210706/DS_20210703_SH5~10RT_V1.2.1_EN.pdf | AH58: 1 | AI58: 460 * 540 * 170 mm | AJ58: 27
A59: SUNGROW | B59: IVH SUNG SH6RT V112 S | C59: 3PH HYBRID | E59: 2268 | F59: =E59-(E59*$F$4) -> 1360.8 | M59: 1499 | Z59: IVH SUNG SH6RT V112 S | AA59: SUNGROW | AB59: Inverter | AC59: Hybrid, 3 phase Inverter, 6kW | AD59: Box | AG59: https://en.sungrowpower.com/upload/file/20210706/DS_20210703_SH5~10RT_V1.2.1_EN.pdf | AH59: 1 | AI59: 460 * 540 * 170 mm | AJ59: 27
A60: SUNGROW | B60: IVH SUNG SH8RT V112 S | C60: 3PH HYBRID | E60: 2369 | F60: =E60-(E60*$F$4) -> 1421.4 | M60: 1569 | Z60: IVH SUNG SH8RT V112 S | AA60: SUNGROW | AB60: Inverter | AC60: Hybrid, 3 phase Inverter, 8kW | AD60: Box | AG60: https://en.sungrowpower.com/upload/file/20210706/DS_20210703_SH5~10RT_V1.2.1_EN.pdf | AH60: 1 | AI60: 460 * 540 * 170 mm | AJ60: 27
A61: SUNGROW | B61: IVH SUNG SH10RT V112 S | C61: 3PH HYBRID | E61: 2534 | F61: =E61-(E61*$F$4) -> 1520.4 | M61: 1689 | Z61: IVH SUNG SH10RT V112 S | AA61: SUNGROW | AB61: Inverter | AC61: Hybrid, 3 phase Inverter, 10kW | AD61: Box
A63: FRONIUS | B63: PRIMO 3.0 | C63: 1PH | E63: 1357 | F63: =E63-(E63*$F$4) -> 814.2 | G63: =1570-1570*0.42 -> 910.6 | H63: 950 | I63: 872 | J63: 844 | M63: 839 | N63: 883.8 | P63: 884.74 | Z63: PRIMO 3.0 | AA63: FRONIUS | AB63: Inverter | AC63: String, 1 phase Inverter, 3kW | AD63: Box | AG63: https://www.fronius.com/~/downloads/Solar%20Energy/Datasheets/SE_DS_Fronius_Primo_EN.pdf | AH63: 1 | AI63: 645 x 431 x 204 mm | AJ63: 21.5
A64: FRONIUS | B64: Fronius Primo 3.6-1 | F64: =E64-(E64*$F$4) -> 0 | M64: 887 | N64: 977 | P64: 936 | Z64: Fronius Primo 3.6-1 | AA64: FRONIUS | AB64: Inverter | AC64: String, 1 phase Inverter, 3.6kW | AD64: Box | AG64: https://www.fronius.com/~/downloads/Solar%20Energy/Datasheets/SE_DS_Fronius_Primo_EN.pdf | AH64: 1 | AI64: 645 x 431 x 204 mm | AJ64: 21.5
A65: FRONIUS | B65: PRIMO 4.0 | C65: 1PH | E65: 1477 | F65: =E65-(E65*$F$4) -> 886.2 | G65: =1740-1740*0.42 -> 1009.2 | H65: 1026 | I65: 965 | J65: 934 | M65: 929 | N65: 978.71 | Z65: PRIMO 4.0 | AA65: FRONIUS | AB65: Inverter | AC65: String, 1 phase Inverter, 4kW | AD65: Box | AG65: https://www.fronius.com/~/downloads/Solar%20Energy/Datasheets/SE_DS_Fronius_Primo_EN.pdf | AH65: 1 | AI65: 645 x 431 x 204 mm | AJ65: 21.5
A66: FRONIUS | B66: Fronius Primo 4.6-1 | M66: 985 | N66: 1039 | Z66: Fronius Primo 4.6-1 | AA66: FRONIUS | AB66: Inverter | AC66: String, 1 phase Inverter, 4.6kW | AD66: Box | AG66: https://www.fronius.com/~/downloads/Solar%20Energy/Datasheets/SE_DS_Fronius_Primo_EN.pdf | AH66: 1 | AI66: 645 x 431 x 204 mm | AJ66: 21.5
A67: FRONIUS | B67: PRIMO 5.0 | C67: 1PH | E67: 1626 | F67: =E67-(E67*$F$4) -> 975.6 | G67: =1905-1905*0.42 -> 1104.9 | H67: 1124 | I67: 1061 | J67: 1027 | M67: 1022 | N67: 1076.83 | Z67: PRIMO 5.0 | AA67: FRONIUS | AB67: Inverter | AC67: String, 1 phase Inverter, 5kW | AD67: Box | AG67: https://www.fronius.com/~/downloads/Solar%20Energy/Datasheets/SE_DS_Fronius_Primo_EN.pdf | AH67: 1 | AI67: 645 x 431 x 204 mm | AJ67: 21.5
A69: FRONIUS | B69: SYMO 3.0-S | C69: 3PH | E69: 1390 | F69: =E69-(E69*$F$4) -> 834 | G69: =1630-1630*0.42 -> 945.4 | H69: 955 | I69: 864 | J69: 835 | N69: 868.78 | P69: 937 | Z69: SYMO 3.0-S | AA69: FRONIUS | AB69: Inverter | AC69: String, 3 phase Inverter, 3kW | AD69: Box | AG69: https://www.fronius.com/~/downloads/Solar%20Energy/Datasheets/SE_DS_Fronius_Symo_EN.pdf | AH69: 1 | AI69: 645 x 431 x 204 mm | AJ69: 16
A70: FRONIUS | B70: SYMO 3.7-S | C70: 3PH | E70: 1530 | F70: =E70-(E70*$F$4) -> 918 | G70: =1790-1790*0.42 -> 1038.2 | H70: 960 | I70: 950 | N70: 846.24 | P70: 930 | Z70: SYMO 3.7-S | AA70: FRONIUS | AB70: Inverter | AC70: String, 3 phase Inverter, 3.7kW | AD70: Box | AG70: https://www.fronius.com/~/downloads/Solar%20Energy/Datasheets/SE_DS_Fronius_Symo_EN.pdf | AH70: 1 | AI70: 646 x 431 x 204 mm | AJ70: 16
A71: FRONIUS | B71: SYMO 4.5-S | C71: 3PH | E71: 1696 | F71: =E71-(E71*$F$4) -> 1017.6 | G71: =1980-1980*0.42 -> 1148.4 | I71: 1052 | J71: 912 | N71: 1055.54 | P71: 1031 | Z71: SYMO 4.5-S | AA71: FRONIUS | AB71: Inverter | AC71: String, 3 phase Inverter, 4.5kW | AD71: Box | AG71: https://www.fronius.com/~/downloads/Solar%20Energy/Datasheets/SE_DS_Fronius_Symo_EN.pdf | AH71: 1 | AI71: 647 x 431 x 204 mm | AJ71: 16
A72: FRONIUS | B72: SYMO 3.0-M | C72: 3PH | E72: 1540 | F72: =E72-(E72*$F$4) -> 924 | G72: =1800-1800*0.42 -> 1044 | H72: 1040 | I72: 956 | J72: 925 | M72: 989 | N72: 959 | P72: 950 | R72: 885.89 | Z72: SYMO 3.0-M | AA72: FRONIUS | AB72: Inverter | AC72: String, 3 phase Inverter, 3kW | AD72: Box | AG72: https://www.fronius.com/~/downloads/Solar%20Energy/Datasheets/SE_DS_Fronius_Symo_EN.pdf | AH72: 1 | AI72: 648 x 431 x 204 mm | AJ72: 19.9
A73: FRONIUS | B73: SYMO 3.7-M | C73: 3PH | E73: 1690 | F73: =E73-(E73*$F$4) -> 1014 | G73: =1980-1980*0.42 -> 1148.4 | H73: 1168 | I73: 1048 | J73: 1015 | M73: 1088 | N73: 1051.76 | P73: 1032 | Z73: SYMO 3.7-M | AA73: FRONIUS | AB73: Inverter | AC73: String, 3 phase Inverter, 3.7kW | AD73: Box | AG73: https://www.fronius.com/~/downloads/Solar%20Energy/Datasheets/SE_DS_Fronius_Symo_EN.pdf | AH73: 1 | AI73: 649 x 431 x 204 mm | AJ73: 19.9
