Workbook

Sheet Inputs
A1: MINING CONTAINER MODEL — INPUTS
A2: Yellow cells are editable. All other sheets read from here.
A4: HASHRATE & MARKET
A5: Hashprice (BTC/PH/day) | B5: 0.00049578 | C5: BTC/PH/day | D5: Hashrate Index 14 Sep 2026, diff 127.45T
A6: Pool fee | B6: 0.02 | C6: % | D6: 2% (standard Braiins / Foundry)
A7: Daytime hours / day | B7: 8 | C7: h/day | D7: Cyprus solar, 8 productive sun hours
A8: BTC price — scenario 1 | B8: 60000 | C8: USD | D8: Low
A9: BTC price — scenario 2 | B9: 80000 | C9: USD | D9: Mid (near live $78,274)
A10: BTC price — scenario 3 | B10: 100000 | C10: USD | D10: Base
A11: BTC price — scenario 4 | B11: 120000 | C11: USD | D11: High
A13: MINER SPECS
A14: S19j Pro — hashrate | B14: 104 | C14: TH/s | D14: Bitmain spec
A15: S19j Pro — power | B15: 3068 | C15: W | D15: At wall, 25°C, Bitmain spec
A16: S19j Pro — unit price | B16: 300 | C16: USD | D16: Mid-market used: BitmainMiners $156-$312, Digital Bridge $312
A17: S21 200T — hashrate | B17: 200 | C17: TH/s | D17: Bitmain spec
A18: S21 200T — power | B18: 3500 | C18: W | D18: At wall, 25°C, Bitmain spec
A19: S21 200T — unit price | B19: 1000 | C19: USD | D19: Mid-market used: ECOS $900, Bitark $1,100 (Sep 2026)
A20: Container slots | B20: 168 | C20: miners | D20: OneMiners 20ft 168-slot S19/S21 compatible
A21: Container price | B21: 25118 | C21: USD | D21: OneMiners list price Sep 2026
A22: Container fans aux | B22: 25 | C22: kW | D22: ~4-5% of miner load
A23: Year-1 failure rate | B23: 0.15 | C23: % | D23: Used miners; not replaced
A24: Uptime Y2-Y5 | B24: 0.85 | C24: % | D24: 85% of fleet (15% dead, no replacement)
A26: IMPORT COSTS (CHINA → LIMASSOL)
A27: Ocean freight (per container) | B27: 4000 | C27: USD | D27: China–Limassol FCL 20ft; published range $2,250-$4,400
A28: Marine insurance rate | B28: 0.003 | C28: % | D28: 0.3% of FOB
A29: Customs duty rate | B29: 0 | C29: % | D29: 0% under EU TARIC 8471 (ITA/German BTI); 8543 alt = 3.7%
A30: Cyprus import VAT | B30: 0.19 | C30: % | D30: 19% on (CIF + duty + THC); reclaimable by VAT-reg entity
A31: Limassol terminal (THC) | B31: 300 | C31: USD | D31: EUROGATE €260.85 / 20ft (Feb 2026 tariff), converted
A32: Customs broker | B32: 287 | C32: USD | D32: ~€250 est.
A34: HALVING
A35: Halving date | B35: 13-Apr-2028 | D35: Block 1,050,000; subsidy 3.125 → 1.5625 BTC
A36: Y1 pre-halving factor | B36: 1 | D36: All 365 days pre-halving
A37: Y2 blended factor | B37: 0.784 | D37: 208 pre-halving + 158 post = 78.4% of pre-halving
A38: Y3-Y5 post-halving factor | B38: 0.5 | D38: All 365 days post-halving = 50%

Sheet Capex
A1: LANDED CAPEX — CHINA TO LIMASSOL
B2: S19j Pro ($300/unit) | C2: S21 200T ($1,000/unit) | D2: Notes
A3: Miners | B3: =Inputs!$B$19*Inputs!$B$15 | C3: =Inputs!$B$19*Inputs!$B$18 | D3: 168 × unit price
A4: Container (OneMiners 168-slot) | B4: =Inputs!$B$20 | C4: =Inputs!$B$20 | D4: Same box for both miner types
A5: FOB China | B5: =Capex!B3+Capex!B4 | C5: =Capex!C3+Capex!C4
A6: Ocean freight (China → Limassol) | B6: =Inputs!$B$25 | C6: =Inputs!$B$25 | D6: FCL 20ft; range $2,250–$4,400
A7: Marine insurance (0.3% of FOB) | B7: =Capex!B5*Inputs!$B$26 | C7: =Capex!C5*Inputs!$B$26 | D7: 0.3%
A8: CIF Limassol | B8: =Capex!B5+Capex!B6+Capex!B7 | C8: =Capex!C5+Capex!C6+Capex!C7
A9: Customs duty (EU TARIC 8471 ITA: 0%) | B9: =Capex!B8*Inputs!$B$27 | C9: =Capex!C8*Inputs!$B$27 | D9: Change to 3.7% in Inputs if customs reclassifies to 8543
A10: Cyprus import VAT 19% (reclaimable) | B10: =(Capex!B8+Capex!B9+Inputs!$B$29)*Inputs!$B$28 | C10: =(Capex!C8+Capex!C9+Inputs!$B$29)*Inputs!$B$28 | D10: Paid at port; reclaimed by VAT-registered importer
A11: EUROGATE Limassol THC | B11: =Inputs!$B$29 | C11: =Inputs!$B$29 | D11: €260.85/20ft effective Feb 2026, converted at 1.15
A12: Customs broker | B12: =Inputs!$B$30 | C12: =Inputs!$B$30 | D12: ~€250
A13: CASH TO CLEAR PORT | B13: =Capex!B8+Capex!B9+Capex!B10+Capex!B11+Capex!B12 | C13: =Capex!C8+Capex!C9+Capex!C10+Capex!C11+Capex!C12 | D13: Pay this to get the container
A14: Net after VAT reclaim | B14: =Capex!B13-Capex!B10 | C14: =Capex!C13-Capex!C10 | D14: Effective capex for VAT-registered entity
A16: CONTAINER SPECS
A17: Hashrate (168 units) | B17: =Inputs!$B$19*Inputs!$B$13/1000&" PH/s" | C17: =Inputs!$B$19*Inputs!$B$16/1000&" PH/s"
A18: Miner load (168 units) | B18: =Inputs!$B$19*Inputs!$B$14/1000&" kW" | C18: =Inputs!$B$19*Inputs!$B$17/1000&" kW"
A19: Peak draw incl. fans | B19: =(Inputs!$B$19*Inputs!$B$14+Inputs!$B$21*1000)/1000&" kW" | C19: =(Inputs!$B$19*Inputs!$B$17+Inputs!$B$21*1000)/1000&" kW"

Sheet S19j-Pro
A1: S19j Pro 104T — 5-YEAR DAYTIME MINING REVENUE
A2: Daytime only (8 h/day) · Pool fee 2% · 15% failure Y1 · Halving ~13 Apr 2028 · Difficulty flat
A3: BTC Price | B3: Year 1 | C3: Year 2 | D3: Year 3 | E3: Year 4 | F3: Year 5 | G3: 5-Yr Gross | H3: Payback (cash) | I3: Payback (net VAT)
A4: $60k | B4: =(Inputs!$B$19*Inputs!$B$13/1000)*Inputs!$B$5*(1-Inputs!$B$6)*Inputs!$B$8*365*(Inputs!$B$7/24)*(1-Inputs!$B$22)*Inputs!$B$33 | C4: =(Inputs!$B$19*Inputs!$B$13/1000)*Inputs!$B$5*(1-Inputs!$B$6)*Inputs!$B$8*365*(Inputs!$B$7/24)*Inputs!$B$23*Inputs!$B$34 | D4: =(Inputs!$B$19*Inputs!$B$13/1000)*Inputs!$B$5*(1-Inputs!$B$6)*Inputs!$B$8*365*(Inputs!$B$7/24)*Inputs!$B$23*Inputs!$B$35 | E4: =(Inputs!$B$19*Inputs!$B$13/1000)*Inputs!$B$5*(1-Inputs!$B$6)*Inputs!$B$8*365*(Inputs!$B$7/24)*Inputs!$B$23*Inputs!$B$35 | F4: =(Inputs!$B$19*Inputs!$B$13/1000)*Inputs!$B$5*(1-Inputs!$B$6)*Inputs!$B$8*365*(Inputs!$B$7/24)*Inputs!$B$23*Inputs!$B$35 | G4: =SUM(B4:F4) | H4: =Capex!B13/B4 | I4: =Capex!B14/B4
A5: $80k | B5: =(Inputs!$B$19*Inputs!$B$13/1000)*Inputs!$B$5*(1-Inputs!$B$6)*Inputs!$B$9*365*(Inputs!$B$7/24)*(1-Inputs!$B$22)*Inputs!$B$33 | C5: =(Inputs!$B$19*Inputs!$B$13/1000)*Inputs!$B$5*(1-Inputs!$B$6)*Inputs!$B$9*365*(Inputs!$B$7/24)*Inputs!$B$23*Inputs!$B$34 | D5: =(Inputs!$B$19*Inputs!$B$13/1000)*Inputs!$B$5*(1-Inputs!$B$6)*Inputs!$B$9*365*(Inputs!$B$7/24)*Inputs!$B$23*Inputs!$B$35 | E5: =(Inputs!$B$19*Inputs!$B$13/1000)*Inputs!$B$5*(1-Inputs!$B$6)*Inputs!$B$9*365*(Inputs!$B$7/24)*Inputs!$B$23*Inputs!$B$35 | F5: =(Inputs!$B$19*Inputs!$B$13/1000)*Inputs!$B$5*(1-Inputs!$B$6)*Inputs!$B$9*365*(Inputs!$B$7/24)*Inputs!$B$23*Inputs!$B$35 | G5: =SUM(B5:F5) | H5: =Capex!B13/B5 | I5: =Capex!B14/B5
A6: $100k | B6: =(Inputs!$B$19*Inputs!$B$13/1000)*Inputs!$B$5*(1-Inputs!$B$6)*Inputs!$B$10*365*(Inputs!$B$7/24)*(1-Inputs!$B$22)*Inputs!$B$33 | C6: =(Inputs!$B$19*Inputs!$B$13/1000)*Inputs!$B$5*(1-Inputs!$B$6)*Inputs!$B$10*365*(Inputs!$B$7/24)*Inputs!$B$23*Inputs!$B$34 | D6: =(Inputs!$B$19*Inputs!$B$13/1000)*Inputs!$B$5*(1-Inputs!$B$6)*Inputs!$B$10*365*(Inputs!$B$7/24)*Inputs!$B$23*Inputs!$B$35 | E6: =(Inputs!$B$19*Inputs!$B$13/1000)*Inputs!$B$5*(1-Inputs!$B$6)*Inputs!$B$10*365*(Inputs!$B$7/24)*Inputs!$B$23*Inputs!$B$35 | F6: =(Inputs!$B$19*Inputs!$B$13/1000)*Inputs!$B$5*(1-Inputs!$B$6)*Inputs!$B$10*365*(Inputs!$B$7/24)*Inputs!$B$23*Inputs!$B$35 | G6: =SUM(B6:F6) | H6: =Capex!B13/B6 | I6: =Capex!B14/B6
A7: $120k | B7: =(Inputs!$B$19*Inputs!$B$13/1000)*Inputs!$B$5*(1-Inputs!$B$6)*Inputs!$B$11*365*(Inputs!$B$7/24)*(1-Inputs!$B$22)*Inputs!$B$33 | C7: =(Inputs!$B$19*Inputs!$B$13/1000)*Inputs!$B$5*(1-Inputs!$B$6)*Inputs!$B$11*365*(Inputs!$B$7/24)*Inputs!$B$23*Inputs!$B$34 | D7: =(Inputs!$B$19*Inputs!$B$13/1000)*Inputs!$B$5*(1-Inputs!$B$6)*Inputs!$B$11*365*(Inputs!$B$7/24)*Inputs!$B$23*Inputs!$B$35 | E7: =(Inputs!$B$19*Inputs!$B$13/1000)*Inputs!$B$5*(1-Inputs!$B$6)*Inputs!$B$11*365*(Inputs!$B$7/24)*Inputs!$B$23*Inputs!$B$35 | F7: =(Inputs!$B$19*Inputs!$B$13/1000)*Inputs!$B$5*(1-Inputs!$B$6)*Inputs!$B$11*365*(Inputs!$B$7/24)*Inputs!$B$23*Inputs!$B$35 | G7: =SUM(B7:F7) | H7: =Capex!B13/B7 | I7: =Capex!B14/B7
A9: Hashrate: (Inputs!$B$19*Inputs!$B$13/1000) PH/s (=Inputs!$B$19 slots × Inputs!$B$13 TH ÷ 1,000)
A10: Payback = Cash-to-port ÷ Year-1 revenue (conservative: ignores Year-2+ cash in). Actual payback is faster.
A11: Year 2 blended factor 0.784 = 208 pre-halving days + 158 post-halving days (out of 365).
A12: Difficulty is held flat. A ~5% increase was queued for 19 Sep 2026 — subtract 5% from all figures if confirmed.

Sheet S21-200T
A1: S21 200T — 5-YEAR DAYTIME MINING REVENUE
A2: Daytime only (8 h/day) · Pool fee 2% · 15% failure Y1 · Halving ~13 Apr 2028 · Difficulty flat
A3: BTC Price | B3: Year 1 | C3: Year 2 | D3: Year 3 | E3: Year 4 | F3: Year 5 | G3: 5-Yr Gross | H3: Payback (cash) | I3: Payback (net VAT)
A4: $60k | B4: =(Inputs!$B$19*Inputs!$B$16/1000)*Inputs!$B$5*(1-Inputs!$B$6)*Inputs!$B$8*365*(Inputs!$B$7/24)*(1-Inputs!$B$22)*Inputs!$B$33 | C4: =(Inputs!$B$19*Inputs!$B$16/1000)*Inputs!$B$5*(1-Inputs!$B$6)*Inputs!$B$8*365*(Inputs!$B$7/24)*Inputs!$B$23*Inputs!$B$34 | D4: =(Inputs!$B$19*Inputs!$B$16/1000)*Inputs!$B$5*(1-Inputs!$B$6)*Inputs!$B$8*365*(Inputs!$B$7/24)*Inputs!$B$23*Inputs!$B$35 | E4: =(Inputs!$B$19*Inputs!$B$16/1000)*Inputs!$B$5*(1-Inputs!$B$6)*Inputs!$B$8*365*(Inputs!$B$7/24)*Inputs!$B$23*Inputs!$B$35 | F4: =(Inputs!$B$19*Inputs!$B$16/1000)*Inputs!$B$5*(1-Inputs!$B$6)*Inputs!$B$8*365*(Inputs!$B$7/24)*Inputs!$B$23*Inputs!$B$35 | G4: =SUM(B4:F4) | H4: =Capex!C13/B4 | I4: =Capex!C14/B4
A5: $80k | B5: =(Inputs!$B$19*Inputs!$B$16/1000)*Inputs!$B$5*(1-Inputs!$B$6)*Inputs!$B$9*365*(Inputs!$B$7/24)*(1-Inputs!$B$22)*Inputs!$B$33 | C5: =(Inputs!$B$19*Inputs!$B$16/1000)*Inputs!$B$5*(1-Inputs!$B$6)*Inputs!$B$9*365*(Inputs!$B$7/24)*Inputs!$B$23*Inputs!$B$34 | D5: =(Inputs!$B$19*Inputs!$B$16/1000)*Inputs!$B$5*(1-Inputs!$B$6)*Inputs!$B$9*365*(Inputs!$B$7/24)*Inputs!$B$23*Inputs!$B$35 | E5: =(Inputs!$B$19*Inputs!$B$16/1000)*Inputs!$B$5*(1-Inputs!$B$6)*Inputs!$B$9*365*(Inputs!$B$7/24)*Inputs!$B$23*Inputs!$B$35 | F5: =(Inputs!$B$19*Inputs!$B$16/1000)*Inputs!$B$5*(1-Inputs!$B$6)*Inputs!$B$9*365*(Inputs!$B$7/24)*Inputs!$B$23*Inputs!$B$35 | G5: =SUM(B5:F5) | H5: =Capex!C13/B5 | I5: =Capex!C14/B5
A6: $100k | B6: =(Inputs!$B$19*Inputs!$B$16/1000)*Inputs!$B$5*(1-Inputs!$B$6)*Inputs!$B$10*365*(Inputs!$B$7/24)*(1-Inputs!$B$22)*Inputs!$B$33 | C6: =(Inputs!$B$19*Inputs!$B$16/1000)*Inputs!$B$5*(1-Inputs!$B$6)*Inputs!$B$10*365*(Inputs!$B$7/24)*Inputs!$B$23*Inputs!$B$34 | D6: =(Inputs!$B$19*Inputs!$B$16/1000)*Inputs!$B$5*(1-Inputs!$B$6)*Inputs!$B$10*365*(Inputs!$B$7/24)*Inputs!$B$23*Inputs!$B$35 | E6: =(Inputs!$B$19*Inputs!$B$16/1000)*Inputs!$B$5*(1-Inputs!$B$6)*Inputs!$B$10*365*(Inputs!$B$7/24)*Inputs!$B$23*Inputs!$B$35 | F6: =(Inputs!$B$19*Inputs!$B$16/1000)*Inputs!$B$5*(1-Inputs!$B$6)*Inputs!$B$10*365*(Inputs!$B$7/24)*Inputs!$B$23*Inputs!$B$35 | G6: =SUM(B6:F6) | H6: =Capex!C13/B6 | I6: =Capex!C14/B6
A7: $120k | B7: =(Inputs!$B$19*Inputs!$B$16/1000)*Inputs!$B$5*(1-Inputs!$B$6)*Inputs!$B$11*365*(Inputs!$B$7/24)*(1-Inputs!$B$22)*Inputs!$B$33 | C7: =(Inputs!$B$19*Inputs!$B$16/1000)*Inputs!$B$5*(1-Inputs!$B$6)*Inputs!$B$11*365*(Inputs!$B$7/24)*Inputs!$B$23*Inputs!$B$34 | D7: =(Inputs!$B$19*Inputs!$B$16/1000)*Inputs!$B$5*(1-Inputs!$B$6)*Inputs!$B$11*365*(Inputs!$B$7/24)*Inputs!$B$23*Inputs!$B$35 | E7: =(Inputs!$B$19*Inputs!$B$16/1000)*Inputs!$B$5*(1-Inputs!$B$6)*Inputs!$B$11*365*(Inputs!$B$7/24)*Inputs!$B$23*Inputs!$B$35 | F7: =(Inputs!$B$19*Inputs!$B$16/1000)*Inputs!$B$5*(1-Inputs!$B$6)*Inputs!$B$11*365*(Inputs!$B$7/24)*Inputs!$B$23*Inputs!$B$35 | G7: =SUM(B7:F7) | H7: =Capex!C13/B7 | I7: =Capex!C14/B7
A9: Hashrate: (Inputs!$B$19*Inputs!$B$16/1000) PH/s (=Inputs!$B$19 slots × Inputs!$B$16 TH ÷ 1,000)
A10: Payback = Cash-to-port ÷ Year-1 revenue (conservative: ignores Year-2+ cash in). Actual payback is faster.
A11: Year 2 blended factor 0.784 = 208 pre-halving days + 158 post-halving days (out of 365).
A12: Difficulty is held flat. A ~5% increase was queued for 19 Sep 2026 — subtract 5% from all figures if confirmed.

Sheet Comparison
A1: S19j Pro vs S21 200T — COMPARISON @ $80k BTC
B2: S19j Pro | C2: S21 200T | D2: Notes
A3: Unit price | B3: =Inputs!$B$15 | C3: =Inputs!$B$18 | D3: USD, per miner
A4: Hashrate per container | B4: =Inputs!$B$19*Inputs!$B$13/1000 | C4: =Inputs!$B$19*Inputs!$B$16/1000 | D4: PH/s
A5: S21 : S19 hashrate ratio | B5: — | C5: =Inputs!$B$19*Inputs!$B$16/(Inputs!$B$19*Inputs!$B$13) | D5: ×
A6: Cash to clear Limassol | B6: =Capex!B13 | C6: =Capex!C13 | D6: USD
A7: Net after VAT reclaim | B7: =Capex!B14 | C7: =Capex!C14 | D7: USD
A8: S21 premium vs S19 (cash) | B8: — | C8: =Capex!C13-Capex!B13 | D8: USD extra
A9: Year 1 revenue @ $80k | B9: ='S19j-Pro'!B5 | C9: ='S21-200T'!B5 | D9: USD
A10: Year 2 revenue @ $80k | B10: ='S19j-Pro'!C5 | C10: ='S21-200T'!C5 | D10: USD
A11: 5-year gross @ $80k | B11: ='S19j-Pro'!G5 | C11: ='S21-200T'!G5 | D11: USD
A12: 5-year net profit @ $80k | B12: ='S19j-Pro'!G5-Capex!B13 | C12: ='S21-200T'!G5-Capex!C13 | D12: USD
A13: Payback — cash @ $80k | B13: =Capex!B13/'S19j-Pro'!B5 | C13: =Capex!C13/'S21-200T'!B5 | D13: years (Y1 basis)
A14: Payback — net VAT @ $80k | B14: =Capex!B14/'S19j-Pro'!B5 | C14: =Capex!C14/'S21-200T'!B5 | D14: years (Y1 basis)
A15: 5-yr ROI on cash @ $80k | B15: =('S19j-Pro'!G5-Capex!B13)/Capex!B13 | C15: =('S21-200T'!G5-Capex!C13)/Capex!C13 | D15: %
A17: ★ S19 wins on ROI %; S21 wins on absolute 5-yr profit. Two S19 cans (~$191k cash) outperform one S21 can ($236k) on absolute profit at every BTC scenario.

Sheet Price Sources
A1: MINER PRICE VERIFICATION — SOURCES (Sep 2026)
A2: Source | B2: Model | C2: Price (USD) | D2: Condition | E2: URL / Note
A3: — S19j Pro 104 TH/s —
A4: BitmainMiners (Delaware) | B4: S19j Pro 104T | C4: $156 | D4: Used, 60-day warranty | E4: bitmainminers.com — cheapest verifiable spot
A5: EndlessMining (Philadelphia) | B5: S19j Pro 104T | C5: $190 | D5: Used, listed serial numbers | E5: endlessmining.com — 23 units with s/n
A6: Digital Bridge Mining | B6: S19j Pro 104T | C6: $312 | D6: Used, in-slot | E6: digitalbridgemining.io
A7: IngListing sold-comp DB | B7: S19j Pro 104T | C7: $118 | D7: Median of 18 sold units | E7: inglisting.com — bare machines, auction data
A8: CryptoMiningHubs | B8: S19j Pro 104T | C8: $740 | D8: Used, manufacturer warranty | E8: cryptomininghubs.com — EU-priced
A9: NoxHash 2026 range | B9: S19j Pro 104T | C9: $5–9/TH → $520–935 | D9: Used, indicative | E9: noxhash.com — Luxor desk / Kaboomracks data
A10: ★ MODEL PRICE USED | B10: S19j Pro 104T | C10: $300 | D10: Mid of spot warehouse | E10: Midpoint $156–$312; tested, serial, minimal warranty
A12: — S21 200 TH/s —
A13: ECOS marketplace (Sep 2026) | B13: S21 200T | C13: $900 | D13: Used peer sale (9 Sep 2026) | E13: ecos.am marketplace — lowest Sep listing
A14: IngListing sold-comp | B14: S21 200T | C14: $999 | D14: 1 unit sold, thin data | E14: inglisting.com — single sold comp
A15: Bitark (ASIC Miner Value) | B15: S21 200T | C15: $1,100 | D15: Used, Hong Kong stock | E15: asicminervalue.com vendor list
A16: HSASICMiner | B16: S21 200T | C16: $716–$1,725 | D16: Used, PSU included | E16: hsasicminer.com
A17: EndlessMining (US stock) | B17: S21 200T | C17: $1,657 | D17: Used, 7-day DOA | E17: endlessmining.com
A18: MillionMiner | B18: S21 200T | C18: $1,755 | D18: Used | E18: millionminer.com
A19: NoxHash 2026 range | B19: S21 200T | C19: $16–19/TH → $3,200–$3,800 | D19: Used, indicative | E19: noxhash.com — newer gen retains value better
A20: ★ MODEL PRICE USED | B20: S21 200T | C20: $1,000 | D20: Mid ECOS $900 / Bitark $1,100 | E20: Minimum verifiable: $716; mid Asia/peer market: $1,000
