Workbook

Sheet Inputs
A1: ANARITA 10 MW — PV + BESS REFINANCING MODEL
A2: Prepared for: Muminjon (Spanercom) | Lighthief Cyprus Ltd | March 2026
A3: Yellow cells are modifiable inputs
A5: PV PARK | F5: SOH Data
A6: Parameter | B6: Value | C6: Unit | D6: Notes | F6: 1
A7: PV Installed Capacity | B7: 10 | C7: MW | D7: Client | F7: 0.9462
A8: PV Value per MW | B8: 1525000 | C8: EUR/MW | D8: Client estimate | F8: 0.9266
A9: Total PV Asset Value | B9: =B7*B8 | C9: EUR | D9: =B7*B8 | F9: 0.907
A10: Annual PV Production (PVSyst) | B10: 19320 | C10: MWh | D10: Verified May-24 to Oct-25 | F10: 0.8874
A11: PV Degradation | B11: 0.005 | D11: 0.5%/yr | F11: 0.8678
A12: PV Revenue Price (solar-hour avg) | B12: 140.88 | C12: EUR/MWh | D12: TSOC DAM 134-day verified (06:00-17:00) | F12: 0.8534
A13: PV Annual O&M (estimated) | B13: 90000 | C13: EUR/yr | D13: Industry estimate for 10 MW | F13: 0.839
F14: 0.8246
A15: BESS SYSTEM (Option B: 10 MW / 30 MWh) | F15: 0.8102
A16: BESS Power | B16: 10 | C16: MW | F16: 0.7958
A17: BESS Energy | B17: 30 | C17: MWh | D17: 6 x 5 MWh containers | F17: 0.7839
A18: BESS Duration | B18: 3 | C18: hours | F18: 0.772
A19: BESS EPC Price | B19: 4040500 | C19: EUR | D19: Offer LCY-OFFER-MUMINJON-2026-03-01 | F19: 0.7601
A20: Peak Discharge Price | B20: 182.99 | C20: EUR/MWh | D20: TSOC DAM 134-day avg (17:00-21:00) | F20: 0.7482
A21: Round-Trip Efficiency (RTE) | B21: 0.8632 | D21: Linyang AC-AC full system | F21: 0.7361
A22: Net Revenue per MWh Stored | B22: =B20*B21 | C22: EUR/MWh | D22: =B20*B21
A23: BESS Availability | B23: 0.97 | D23: 97% guaranteed (LTSA)
A24: Curtailment Rate | B24: 0.5 | D24: Current park baseline (modifiable)
A25: LTSA Cost Rate | B25: 2469.59 | C25: EUR/MWh/yr | D25: Confirmed Linyang RFI V3
A26: BESS Insurance | B26: 15000 | C26: EUR/yr | D26: Budget estimate
A27: BESS Annual O&M | B27: =B17*B25+B26 | C27: EUR/yr | D27: =B17*B25+B26
A29: FINANCING
A30: Existing PV Loan Balance | B30: 6000000 | C30: EUR | D30: Current: 10yr (2026-2035), 3.13%, semi-annual €400K installments
A31: BESS Investment | B31: =B19 | C31: EUR | D31: =B19
A32: Target LTV | B32: 0.7 | D32: Loan-to-Value target on combined PV+BESS assets
A33: Total New Facility | B33: =(B9+B19)*B32 | C33: EUR | D33: =(PV Value + BESS Value) x Target LTV
A34: Interest Rate | B34: 0.0313 | D34: 3.13% fixed
A35: Loan Term | B35: 15 | C35: years | D35: Matching BESS operational life
A36: Annual Annuity Payment | B36: =B33*(B34*(1+B34)^B35)/((1+B34)^B35-1) | C36: EUR | D36: PMT formula: P × r(1+r)^n / ((1+r)^n - 1)
A37: Cash Released to Client | B37: =B33-B30-B31 | C37: EUR | D37: =Total Facility - Old Loan Payoff - BESS Cost
A38: LTV (PV only) | B38: =B33/B9 | D38: Should be < 80% for most lenders
A39: LTV (PV + BESS combined) | B39: =B33/(B9+B19) | D39: =Target LTV (verification)

Sheet Combined Cashflow
A1: 15-YEAR COMBINED PV + BESS CASHFLOW
A2: All formulas reference the Inputs sheet
A4: Year | B4: PV Prod (MWh) | C4: PV Revenue (EUR) | D4: BESS Captured (MWh) | E4: BESS Dischgd (MWh) | F4: BESS Revenue (EUR) | G4: Total Revenue (EUR) | H4: PV O&M (EUR) | I4: BESS O&M (EUR) | J4: EBITDA (EUR) | K4: Debt Service (EUR) | L4: Net After Debt (EUR) | M4: DSCR
A5: 1 | B5: =Inputs!B10*(1-Inputs!B11)^(1-1) | C5: =B5*Inputs!B12 | D5: =MIN((Inputs!B17*Inputs!$F$7)*365*Inputs!B23,(B5*Inputs!B24)*IF((((B5*Inputs!B24)/365)/(Inputs!B17*Inputs!$F$7))>1.5,0.97,IF((((B5*Inputs!B24)/365)/(Inputs!B17*Inputs!$F$7))>1.2,0.95,IF((((B5*Inputs!B24)/365)/(Inputs!B17*Inputs!$F$7))>1.0,0.92,IF((((B5*Inputs!B24)/365)/(Inputs!B17*Inputs!$F$7))>0.8,0.88,IF((((B5*Inputs!B24)/365)/(Inputs!B17*Inputs!$F$7))>0.6,0.82,0.72)))))*Inputs!B23) | E5: =D5*Inputs!B21 | F5: =E5*Inputs!B20 | G5: =C5+F5 | H5: =Inputs!B13 | I5: =Inputs!B27 | J5: =G5-H5-I5 | K5: =Inputs!B36 | L5: =J5-K5 | M5: =J5/K5
A6: 2 | B6: =Inputs!B10*(1-Inputs!B11)^(2-1) | C6: =B6*Inputs!B12 | D6: =MIN((Inputs!B17*Inputs!$F$8)*365*Inputs!B23,(B6*Inputs!B24)*IF((((B6*Inputs!B24)/365)/(Inputs!B17*Inputs!$F$8))>1.5,0.97,IF((((B6*Inputs!B24)/365)/(Inputs!B17*Inputs!$F$8))>1.2,0.95,IF((((B6*Inputs!B24)/365)/(Inputs!B17*Inputs!$F$8))>1.0,0.92,IF((((B6*Inputs!B24)/365)/(Inputs!B17*Inputs!$F$8))>0.8,0.88,IF((((B6*Inputs!B24)/365)/(Inputs!B17*Inputs!$F$8))>0.6,0.82,0.72)))))*Inputs!B23) | E6: =D6*Inputs!B21 | F6: =E6*Inputs!B20 | G6: =C6+F6 | H6: =Inputs!B13 | I6: =Inputs!B27 | J6: =G6-H6-I6 | K6: =Inputs!B36 | L6: =J6-K6 | M6: =J6/K6
A7: 3 | B7: =Inputs!B10*(1-Inputs!B11)^(3-1) | C7: =B7*Inputs!B12 | D7: =MIN((Inputs!B17*Inputs!$F$9)*365*Inputs!B23,(B7*Inputs!B24)*IF((((B7*Inputs!B24)/365)/(Inputs!B17*Inputs!$F$9))>1.5,0.97,IF((((B7*Inputs!B24)/365)/(Inputs!B17*Inputs!$F$9))>1.2,0.95,IF((((B7*Inputs!B24)/365)/(Inputs!B17*Inputs!$F$9))>1.0,0.92,IF((((B7*Inputs!B24)/365)/(Inputs!B17*Inputs!$F$9))>0.8,0.88,IF((((B7*Inputs!B24)/365)/(Inputs!B17*Inputs!$F$9))>0.6,0.82,0.72)))))*Inputs!B23) | E7: =D7*Inputs!B21 | F7: =E7*Inputs!B20 | G7: =C7+F7 | H7: =Inputs!B13 | I7: =Inputs!B27 | J7: =G7-H7-I7 | K7: =Inputs!B36 | L7: =J7-K7 | M7: =J7/K7
A8: 4 | B8: =Inputs!B10*(1-Inputs!B11)^(4-1) | C8: =B8*Inputs!B12 | D8: =MIN((Inputs!B17*Inputs!$F$10)*365*Inputs!B23,(B8*Inputs!B24)*IF((((B8*Inputs!B24)/365)/(Inputs!B17*Inputs!$F$10))>1.5,0.97,IF((((B8*Inputs!B24)/365)/(Inputs!B17*Inputs!$F$10))>1.2,0.95,IF((((B8*Inputs!B24)/365)/(Inputs!B17*Inputs!$F$10))>1.0,0.92,IF((((B8*Inputs!B24)/365)/(Inputs!B17*Inputs!$F$10))>0.8,0.88,IF((((B8*Inputs!B24)/365)/(Inputs!B17*Inputs!$F$10))>0.6,0.82,0.72)))))*Inputs!B23) | E8: =D8*Inputs!B21 | F8: =E8*Inputs!B20 | G8: =C8+F8 | H8: =Inputs!B13 | I8: =Inputs!B27 | J8: =G8-H8-I8 | K8: =Inputs!B36 | L8: =J8-K8 | M8: =J8/K8
A9: 5 | B9: =Inputs!B10*(1-Inputs!B11)^(5-1) | C9: =B9*Inputs!B12 | D9: =MIN((Inputs!B17*Inputs!$F$11)*365*Inputs!B23,(B9*Inputs!B24)*IF((((B9*Inputs!B24)/365)/(Inputs!B17*Inputs!$F$11))>1.5,0.97,IF((((B9*Inputs!B24)/365)/(Inputs!B17*Inputs!$F$11))>1.2,0.95,IF((((B9*Inputs!B24)/365)/(Inputs!B17*Inputs!$F$11))>1.0,0.92,IF((((B9*Inputs!B24)/365)/(Inputs!B17*Inputs!$F$11))>0.8,0.88,IF((((B9*Inputs!B24)/365)/(Inputs!B17*Inputs!$F$11))>0.6,0.82,0.72)))))*Inputs!B23) | E9: =D9*Inputs!B21 | F9: =E9*Inputs!B20 | G9: =C9+F9 | H9: =Inputs!B13 | I9: =Inputs!B27 | J9: =G9-H9-I9 | K9: =Inputs!B36 | L9: =J9-K9 | M9: =J9/K9
A10: 6 | B10: =Inputs!B10*(1-Inputs!B11)^(6-1) | C10: =B10*Inputs!B12 | D10: =MIN((Inputs!B17*Inputs!$F$12)*365*Inputs!B23,(B10*Inputs!B24)*IF((((B10*Inputs!B24)/365)/(Inputs!B17*Inputs!$F$12))>1.5,0.97,IF((((B10*Inputs!B24)/365)/(Inputs!B17*Inputs!$F$12))>1.2,0.95,IF((((B10*Inputs!B24)/365)/(Inputs!B17*Inputs!$F$12))>1.0,0.92,IF((((B10*Inputs!B24)/365)/(Inputs!B17*Inputs!$F$12))>0.8,0.88,IF((((B10*Inputs!B24)/365)/(Inputs!B17*Inputs!$F$12))>0.6,0.82,0.72)))))*Inputs!B23) | E10: =D10*Inputs!B21 | F10: =E10*Inputs!B20 | G10: =C10+F10 | H10: =Inputs!B13 | I10: =Inputs!B27 | J10: =G10-H10-I10 | K10: =Inputs!B36 | L10: =J10-K10 | M10: =J10/K10
A11: 7 | B11: =Inputs!B10*(1-Inputs!B11)^(7-1) | C11: =B11*Inputs!B12 | D11: =MIN((Inputs!B17*Inputs!$F$13)*365*Inputs!B23,(B11*Inputs!B24)*IF((((B11*Inputs!B24)/365)/(Inputs!B17*Inputs!$F$13))>1.5,0.97,IF((((B11*Inputs!B24)/365)/(Inputs!B17*Inputs!$F$13))>1.2,0.95,IF((((B11*Inputs!B24)/365)/(Inputs!B17*Inputs!$F$13))>1.0,0.92,IF((((B11*Inputs!B24)/365)/(Inputs!B17*Inputs!$F$13))>0.8,0.88,IF((((B11*Inputs!B24)/365)/(Inputs!B17*Inputs!$F$13))>0.6,0.82,0.72)))))*Inputs!B23) | E11: =D11*Inputs!B21 | F11: =E11*Inputs!B20 | G11: =C11+F11 | H11: =Inputs!B13 | I11: =Inputs!B27 | J11: =G11-H11-I11 | K11: =Inputs!B36 | L11: =J11-K11 | M11: =J11/K11
A12: 8 | B12: =Inputs!B10*(1-Inputs!B11)^(8-1) | C12: =B12*Inputs!B12 | D12: =MIN((Inputs!B17*Inputs!$F$14)*365*Inputs!B23,(B12*Inputs!B24)*IF((((B12*Inputs!B24)/365)/(Inputs!B17*Inputs!$F$14))>1.5,0.97,IF((((B12*Inputs!B24)/365)/(Inputs!B17*Inputs!$F$14))>1.2,0.95,IF((((B12*Inputs!B24)/365)/(Inputs!B17*Inputs!$F$14))>1.0,0.92,IF((((B12*Inputs!B24)/365)/(Inputs!B17*Inputs!$F$14))>0.8,0.88,IF((((B12*Inputs!B24)/365)/(Inputs!B17*Inputs!$F$14))>0.6,0.82,0.72)))))*Inputs!B23) | E12: =D12*Inputs!B21 | F12: =E12*Inputs!B20 | G12: =C12+F12 | H12: =Inputs!B13 | I12: =Inputs!B27 | J12: =G12-H12-I12 | K12: =Inputs!B36 | L12: =J12-K12 | M12: =J12/K12
A13: 9 | B13: =Inputs!B10*(1-Inputs!B11)^(9-1) | C13: =B13*Inputs!B12 | D13: =MIN((Inputs!B17*Inputs!$F$15)*365*Inputs!B23,(B13*Inputs!B24)*IF((((B13*Inputs!B24)/365)/(Inputs!B17*Inputs!$F$15))>1.5,0.97,IF((((B13*Inputs!B24)/365)/(Inputs!B17*Inputs!$F$15))>1.2,0.95,IF((((B13*Inputs!B24)/365)/(Inputs!B17*Inputs!$F$15))>1.0,0.92,IF((((B13*Inputs!B24)/365)/(Inputs!B17*Inputs!$F$15))>0.8,0.88,IF((((B13*Inputs!B24)/365)/(Inputs!B17*Inputs!$F$15))>0.6,0.82,0.72)))))*Inputs!B23) | E13: =D13*Inputs!B21 | F13: =E13*Inputs!B20 | G13: =C13+F13 | H13: =Inputs!B13 | I13: =Inputs!B27 | J13: =G13-H13-I13 | K13: =Inputs!B36 | L13: =J13-K13 | M13: =J13/K13
A14: 10 | B14: =Inputs!B10*(1-Inputs!B11)^(10-1) | C14: =B14*Inputs!B12 | D14: =MIN((Inputs!B17*Inputs!$F$16)*365*Inputs!B23,(B14*Inputs!B24)*IF((((B14*Inputs!B24)/365)/(Inputs!B17*Inputs!$F$16))>1.5,0.97,IF((((B14*Inputs!B24)/365)/(Inputs!B17*Inputs!$F$16))>1.2,0.95,IF((((B14*Inputs!B24)/365)/(Inputs!B17*Inputs!$F$16))>1.0,0.92,IF((((B14*Inputs!B24)/365)/(Inputs!B17*Inputs!$F$16))>0.8,0.88,IF((((B14*Inputs!B24)/365)/(Inputs!B17*Inputs!$F$16))>0.6,0.82,0.72)))))*Inputs!B23) | E14: =D14*Inputs!B21 | F14: =E14*Inputs!B20 | G14: =C14+F14 | H14: =Inputs!B13 | I14: =Inputs!B27 | J14: =G14-H14-I14 | K14: =Inputs!B36 | L14: =J14-K14 | M14: =J14/K14
A15: 11 | B15: =Inputs!B10*(1-Inputs!B11)^(11-1) | C15: =B15*Inputs!B12 | D15: =MIN((Inputs!B17*Inputs!$F$17)*365*Inputs!B23,(B15*Inputs!B24)*IF((((B15*Inputs!B24)/365)/(Inputs!B17*Inputs!$F$17))>1.5,0.97,IF((((B15*Inputs!B24)/365)/(Inputs!B17*Inputs!$F$17))>1.2,0.95,IF((((B15*Inputs!B24)/365)/(Inputs!B17*Inputs!$F$17))>1.0,0.92,IF((((B15*Inputs!B24)/365)/(Inputs!B17*Inputs!$F$17))>0.8,0.88,IF((((B15*Inputs!B24)/365)/(Inputs!B17*Inputs!$F$17))>0.6,0.82,0.72)))))*Inputs!B23) | E15: =D15*Inputs!B21 | F15: =E15*Inputs!B20 | G15: =C15+F15 | H15: =Inputs!B13 | I15: =Inputs!B27 | J15: =G15-H15-I15 | K15: =Inputs!B36 | L15: =J15-K15 | M15: =J15/K15
A16: 12 | B16: =Inputs!B10*(1-Inputs!B11)^(12-1) | C16: =B16*Inputs!B12 | D16: =MIN((Inputs!B17*Inputs!$F$18)*365*Inputs!B23,(B16*Inputs!B24)*IF((((B16*Inputs!B24)/365)/(Inputs!B17*Inputs!$F$18))>1.5,0.97,IF((((B16*Inputs!B24)/365)/(Inputs!B17*Inputs!$F$18))>1.2,0.95,IF((((B16*Inputs!B24)/365)/(Inputs!B17*Inputs!$F$18))>1.0,0.92,IF((((B16*Inputs!B24)/365)/(Inputs!B17*Inputs!$F$18))>0.8,0.88,IF((((B16*Inputs!B24)/365)/(Inputs!B17*Inputs!$F$18))>0.6,0.82,0.72)))))*Inputs!B23) | E16: =D16*Inputs!B21 | F16: =E16*Inputs!B20 | G16: =C16+F16 | H16: =Inputs!B13 | I16: =Inputs!B27 | J16: =G16-H16-I16 | K16: =Inputs!B36 | L16: =J16-K16 | M16: =J16/K16
A17: 13 | B17: =Inputs!B10*(1-Inputs!B11)^(13-1) | C17: =B17*Inputs!B12 | D17: =MIN((Inputs!B17*Inputs!$F$19)*365*Inputs!B23,(B17*Inputs!B24)*IF((((B17*Inputs!B24)/365)/(Inputs!B17*Inputs!$F$19))>1.5,0.97,IF((((B17*Inputs!B24)/365)/(Inputs!B17*Inputs!$F$19))>1.2,0.95,IF((((B17*Inputs!B24)/365)/(Inputs!B17*Inputs!$F$19))>1.0,0.92,IF((((B17*Inputs!B24)/365)/(Inputs!B17*Inputs!$F$19))>0.8,0.88,IF((((B17*Inputs!B24)/365)/(Inputs!B17*Inputs!$F$19))>0.6,0.82,0.72)))))*Inputs!B23) | E17: =D17*Inputs!B21 | F17: =E17*Inputs!B20 | G17: =C17+F17 | H17: =Inputs!B13 | I17: =Inputs!B27 | J17: =G17-H17-I17 | K17: =Inputs!B36 | L17: =J17-K17 | M17: =J17/K17
A18: 14 | B18: =Inputs!B10*(1-Inputs!B11)^(14-1) | C18: =B18*Inputs!B12 | D18: =MIN((Inputs!B17*Inputs!$F$20)*365*Inputs!B23,(B18*Inputs!B24)*IF((((B18*Inputs!B24)/365)/(Inputs!B17*Inputs!$F$20))>1.5,0.97,IF((((B18*Inputs!B24)/365)/(Inputs!B17*Inputs!$F$20))>1.2,0.95,IF((((B18*Inputs!B24)/365)/(Inputs!B17*Inputs!$F$20))>1.0,0.92,IF((((B18*Inputs!B24)/365)/(Inputs!B17*Inputs!$F$20))>0.8,0.88,IF((((B18*Inputs!B24)/365)/(Inputs!B17*Inputs!$F$20))>0.6,0.82,0.72)))))*Inputs!B23) | E18: =D18*Inputs!B21 | F18: =E18*Inputs!B20 | G18: =C18+F18 | H18: =Inputs!B13 | I18: =Inputs!B27 | J18: =G18-H18-I18 | K18: =Inputs!B36 | L18: =J18-K18 | M18: =J18/K18
A19: 15 | B19: =Inputs!B10*(1-Inputs!B11)^(15-1) | C19: =B19*Inputs!B12 | D19: =MIN((Inputs!B17*Inputs!$F$21)*365*Inputs!B23,(B19*Inputs!B24)*IF((((B19*Inputs!B24)/365)/(Inputs!B17*Inputs!$F$21))>1.5,0.97,IF((((B19*Inputs!B24)/365)/(Inputs!B17*Inputs!$F$21))>1.2,0.95,IF((((B19*Inputs!B24)/365)/(Inputs!B17*Inputs!$F$21))>1.0,0.92,IF((((B19*Inputs!B24)/365)/(Inputs!B17*Inputs!$F$21))>0.8,0.88,IF((((B19*Inputs!B24)/365)/(Inputs!B17*Inputs!$F$21))>0.6,0.82,0.72)))))*Inputs!B23) | E19: =D19*Inputs!B21 | F19: =E19*Inputs!B20 | G19: =C19+F19 | H19: =Inputs!B13 | I19: =Inputs!B27 | J19: =G19-H19-I19 | K19: =Inputs!B36 | L19: =J19-K19 | M19: =J19/K19
A21: TOTAL | C21: =SUM(C5:C19) | F21: =SUM(F5:F19) | G21: =SUM(G5:G19) | H21: =SUM(H5:H19) | I21: =SUM(I5:I19) | J21: =SUM(J5:J19) | K21: =SUM(K5:K19) | L21: =SUM(L5:L19) | M21: =AVERAGE(M5:M19)
A22: MIN DSCR | M22: =MIN(M5:M19)

Sheet Debt Schedule
A1: DEBT AMORTISATION SCHEDULE
A3: Year | B3: Opening Balance | C3: Interest (3.13%) | D3: Principal | E3: Annuity Payment | F3: Closing Balance
A4: 1 | B4: =Inputs!B33 | C4: =B4*Inputs!B34 | D4: =E4-C4 | E4: =Inputs!B36 | F4: =B4-D4
A5: 2 | B5: =F4 | C5: =B5*Inputs!B34 | D5: =E5-C5 | E5: =Inputs!B36 | F5: =B5-D5
A6: 3 | B6: =F5 | C6: =B6*Inputs!B34 | D6: =E6-C6 | E6: =Inputs!B36 | F6: =B6-D6
A7: 4 | B7: =F6 | C7: =B7*Inputs!B34 | D7: =E7-C7 | E7: =Inputs!B36 | F7: =B7-D7
A8: 5 | B8: =F7 | C8: =B8*Inputs!B34 | D8: =E8-C8 | E8: =Inputs!B36 | F8: =B8-D8
A9: 6 | B9: =F8 | C9: =B9*Inputs!B34 | D9: =E9-C9 | E9: =Inputs!B36 | F9: =B9-D9
A10: 7 | B10: =F9 | C10: =B10*Inputs!B34 | D10: =E10-C10 | E10: =Inputs!B36 | F10: =B10-D10
A11: 8 | B11: =F10 | C11: =B11*Inputs!B34 | D11: =E11-C11 | E11: =Inputs!B36 | F11: =B11-D11
A12: 9 | B12: =F11 | C12: =B12*Inputs!B34 | D12: =E12-C12 | E12: =Inputs!B36 | F12: =B12-D12
A13: 10 | B13: =F12 | C13: =B13*Inputs!B34 | D13: =E13-C13 | E13: =Inputs!B36 | F13: =B13-D13
A14: 11 | B14: =F13 | C14: =B14*Inputs!B34 | D14: =E14-C14 | E14: =Inputs!B36 | F14: =B14-D14
A15: 12 | B15: =F14 | C15: =B15*Inputs!B34 | D15: =E15-C15 | E15: =Inputs!B36 | F15: =B15-D15
A16: 13 | B16: =F15 | C16: =B16*Inputs!B34 | D16: =E16-C16 | E16: =Inputs!B36 | F16: =B16-D16
A17: 14 | B17: =F16 | C17: =B17*Inputs!B34 | D17: =E17-C17 | E17: =Inputs!B36 | F17: =B17-D17
A18: 15 | B18: =F17 | C18: =B18*Inputs!B34 | D18: =E18-C18 | E18: =Inputs!B36 | F18: =B18-D18
A20: TOTAL | C20: =SUM(C4:C18) | D20: =SUM(D4:D18) | E20: =SUM(E4:E18)
A21: Total Interest Paid | B21: =C20

Sheet Sensitivity
A1: SENSITIVITY ANALYSIS
A3: DSCR BY CURTAILMENT RATE (Year 1)
A4: Curtailment Rate | B4: 0.45 | C4: 0.5 | D4: 0.55 | E4: 0.6 | F4: 0.7
A5: PV Revenue (EUR) | B5: =Inputs!B10*Inputs!B12 | C5: =Inputs!B10*Inputs!B12 | D5: =Inputs!B10*Inputs!B12 | E5: =Inputs!B10*Inputs!B12 | F5: =Inputs!B10*Inputs!B12
A6: Annual Curtailed (MWh) | B6: =Inputs!B10*B4 | C6: =Inputs!B10*C4 | D6: =Inputs!B10*D4 | E6: =Inputs!B10*E4 | F6: =Inputs!B10*F4
A7: BESS Revenue (EUR) | B7: =MIN((Inputs!B17*Inputs!$F$7)*365*Inputs!B23,B6*IF(((B6/365)/(Inputs!B17*Inputs!$F$7))>1.5,0.97,IF(((B6/365)/(Inputs!B17*Inputs!$F$7))>1.2,0.95,IF(((B6/365)/(Inputs!B17*Inputs!$F$7))>1.0,0.92,IF(((B6/365)/(Inputs!B17*Inputs!$F$7))>0.8,0.88,IF(((B6/365)/(Inputs!B17*Inputs!$F$7))>0.6,0.82,0.72)))))*Inputs!B23)*Inputs!B21*Inputs!B20 | C7: =MIN((Inputs!B17*Inputs!$F$7)*365*Inputs!B23,C6*IF(((C6/365)/(Inputs!B17*Inputs!$F$7))>1.5,0.97,IF(((C6/365)/(Inputs!B17*Inputs!$F$7))>1.2,0.95,IF(((C6/365)/(Inputs!B17*Inputs!$F$7))>1.0,0.92,IF(((C6/365)/(Inputs!B17*Inputs!$F$7))>0.8,0.88,IF(((C6/365)/(Inputs!B17*Inputs!$F$7))>0.6,0.82,0.72)))))*Inputs!B23)*Inputs!B21*Inputs!B20 | D7: =MIN((Inputs!B17*Inputs!$F$7)*365*Inputs!B23,D6*IF(((D6/365)/(Inputs!B17*Inputs!$F$7))>1.5,0.97,IF(((D6/365)/(Inputs!B17*Inputs!$F$7))>1.2,0.95,IF(((D6/365)/(Inputs!B17*Inputs!$F$7))>1.0,0.92,IF(((D6/365)/(Inputs!B17*Inputs!$F$7))>0.8,0.88,IF(((D6/365)/(Inputs!B17*Inputs!$F$7))>0.6,0.82,0.72)))))*Inputs!B23)*Inputs!B21*Inputs!B20 | E7: =MIN((Inputs!B17*Inputs!$F$7)*365*Inputs!B23,E6*IF(((E6/365)/(Inputs!B17*Inputs!$F$7))>1.5,0.97,IF(((E6/365)/(Inputs!B17*Inputs!$F$7))>1.2,0.95,IF(((E6/365)/(Inputs!B17*Inputs!$F$7))>1.0,0.92,IF(((E6/365)/(Inputs!B17*Inputs!$F$7))>0.8,0.88,IF(((E6/365)/(Inputs!B17*Inputs!$F$7))>0.6,0.82,0.72)))))*Inputs!B23)*Inputs!B21*Inputs!B20 | F7: =MIN((Inputs!B17*Inputs!$F$7)*365*Inputs!B23,F6*IF(((F6/365)/(Inputs!B17*Inputs!$F$7))>1.5,0.97,IF(((F6/365)/(Inputs!B17*Inputs!$F$7))>1.2,0.95,IF(((F6/365)/(Inputs!B17*Inputs!$F$7))>1.0,0.92,IF(((F6/365)/(Inputs!B17*Inputs!$F$7))>0.8,0.88,IF(((F6/365)/(Inputs!B17*Inputs!$F$7))>0.6,0.82,0.72)))))*Inputs!B23)*Inputs!B21*Inputs!B20
A8: Total Revenue (EUR) | B8: =B5+B7 | C8: =C5+C7 | D8: =D5+D7 | E8: =E5+E7 | F8: =F5+F7
A9: Total O&M (EUR) | B9: =Inputs!B13+Inputs!B27 | C9: =Inputs!B13+Inputs!B27 | D9: =Inputs!B13+Inputs!B27 | E9: =Inputs!B13+Inputs!B27 | F9: =Inputs!B13+Inputs!B27
A10: EBITDA (EUR) | B10: =B8-B9 | C10: =C8-C9 | D10: =D8-D9 | E10: =E8-E9 | F10: =F8-F9
A11: Annual Debt Service (EUR) | B11: =Inputs!B36 | C11: =Inputs!B36 | D11: =Inputs!B36 | E11: =Inputs!B36 | F11: =Inputs!B36
A12: DSCR | B12: =B10/B11 | C12: =C10/C11 | D12: =D10/D11 | E12: =E10/E11 | F12: =F10/F11
A13: Net Free Cash After Debt (EUR) | B13: =B10-B11 | C13: =C10-C11 | D13: =D10-D11 | E13: =E10-E11 | F13: =F10-F11
A16: WITHOUT BESS vs WITH BESS (at 50% curtailment)
B17: Without BESS | C17: With BESS | D17: Delta
A18: Loan Amount | B18: =Inputs!B30 | C18: =Inputs!B33 | D18: =C18-B18
A19: Annual Debt Service | B19: =Inputs!B30*(Inputs!B34*(1+Inputs!B34)^Inputs!B35)/((1+Inputs!B34)^Inputs!B35-1) | C19: =Inputs!B36 | D19: =C19-B19
A20: PV Revenue (Year 1) | B20: =Inputs!B10*Inputs!B12 | C20: =Inputs!B10*Inputs!B12 | D20: =C20-B20
A21: BESS Revenue (Year 1) | B21: 0 | C21: =MIN((Inputs!B17*Inputs!$F$7)*365*Inputs!B23,(Inputs!B10*0.5)*IF((((Inputs!B10*0.5)/365)/(Inputs!B17*Inputs!$F$7))>1.5,0.97,IF((((Inputs!B10*0.5)/365)/(Inputs!B17*Inputs!$F$7))>1.2,0.95,IF((((Inputs!B10*0.5)/365)/(Inputs!B17*Inputs!$F$7))>1.0,0.92,IF((((Inputs!B10*0.5)/365)/(Inputs!B17*Inputs!$F$7))>0.8,0.88,IF((((Inputs!B10*0.5)/365)/(Inputs!B17*Inputs!$F$7))>0.6,0.82,0.72)))))*Inputs!B23)*Inputs!B21*Inputs!B20 | D21: =C21-B21
A22: Total Revenue | B22: =B20+B21 | C22: =C20+C21 | D22: =C22-B22
A23: Total O&M | B23: =Inputs!B13 | C23: =Inputs!B13+Inputs!B27 | D23: =C23-B23
A24: EBITDA | B24: =B22-B23 | C24: =C22-C23 | D24: =C24-B24
A25: Net After Debt | B25: =B24-B19 | C25: =C24-C19 | D25: =C25-B25
A26: DSCR | B26: =B24/B19 | C26: =C24/C19

Sheet Bankability
A1: BANKABILITY SUMMARY — FOR LENDER REVIEW
A2: Spanercom / Anarita 10 MW PV + 30 MWh BESS Refinancing
A4: ASSET VALUATION
A5: PV Park (10 MW x EUR 1.4M/MW) | B5: =Inputs!B9
A6: BESS System (10 MW / 30 MWh EPC) | B6: =Inputs!B19
A7: Total Asset Value | B7: =B5+B6
A8: Total Loan Facility | B8: =Inputs!B33
A9: Cash Released to Client | B9: =Inputs!B37
A10: LTV (PV + BESS combined) | B10: =B8/B7
A12: BESS PERFORMANCE GUARANTEES
A13: OEM | B13: Linyang Energy (Shanghai-listed, revenue >US$3B)
A14: Performance Bond | B14: 5% corporate bank guarantee from Linyang Energy
A15: Base Warranty | B15: 5 years included in EPC price
A16: Extended Warranty | B16: Available to 15 years at confirmed OEM rates
A17: Availability Guarantee | B17: 97% annual system availability with LDs for shortfall
A18: SOH Guarantee | B18: Per Linyang degradation curve; shortfall = EUR 30/MWh/day LD
A19: Delay LDs | B19: 0.1-0.2% of contract value/day, capped at 10%
A20: Grid Code Certification | B20: TUV EN 50549-2:2019/A1:2023 (cert D 115067 0077)
A21: EPC Insurance | B21: CAR/EAR + Third Party Liability during construction
A22: Marine Cargo | B22: Covered by OEM under CIF Limassol terms
A23: Local O&M | B23: Lighthief Cyprus — 6 field engineers, Limassol spare parts warehouse
A24: Monitoring | B24: 24/7/365 via Voltus SCADA + Linyang Cloud EMS
... A29: End of Life | B29: Free collection and recycling/cashback by Lighthief at EOL
A31: KEY FINANCIAL METRICS
A32: Annual Debt Service | B32: =Inputs!B36
A33: Year 1 DSCR (at 50% curtailment) | B33: ='Combined Cashflow'!M5
A34: Average 15-Year DSCR | B34: =AVERAGE('Combined Cashflow'!M5:M19)
A35: Minimum DSCR (any year) | B35: =MIN('Combined Cashflow'!M5:M19)
A36: 15-Year Total Net Free Cash | B36: =SUM('Combined Cashflow'!L5:L19)

Sheet With vs Without BESS
A1: 15-YEAR COMPARISON: PV ONLY vs PV + BESS
A3: Year | B3: PV Revenue | C3: Debt (PV only) | D3: Net (PV only) | E3: Debt (PV+BESS) | F3: BESS Revenue | G3: Net (PV+BESS)
A4: 1 | B4: =Inputs!B10*(1-Inputs!B11)^(1-1)*Inputs!B12 | C4: =Inputs!B30*(Inputs!B34*(1+Inputs!B34)^Inputs!B35)/((1+Inputs!B34)^Inputs!B35-1) | D4: =B4-Inputs!B13-C4 | E4: =Inputs!B36 | F4: ='Combined Cashflow'!F5 | G4: =B4+F4-Inputs!B13-Inputs!B27-E4
A5: 2 | B5: =Inputs!B10*(1-Inputs!B11)^(2-1)*Inputs!B12 | C5: =Inputs!B30*(Inputs!B34*(1+Inputs!B34)^Inputs!B35)/((1+Inputs!B34)^Inputs!B35-1) | D5: =B5-Inputs!B13-C5 | E5: =Inputs!B36 | F5: ='Combined Cashflow'!F6 | G5: =B5+F5-Inputs!B13-Inputs!B27-E5
A6: 3 | B6: =Inputs!B10*(1-Inputs!B11)^(3-1)*Inputs!B12 | C6: =Inputs!B30*(Inputs!B34*(1+Inputs!B34)^Inputs!B35)/((1+Inputs!B34)^Inputs!B35-1) | D6: =B6-Inputs!B13-C6 | E6: =Inputs!B36 | F6: ='Combined Cashflow'!F7 | G6: =B6+F6-Inputs!B13-Inputs!B27-E6
A7: 4 | B7: =Inputs!B10*(1-Inputs!B11)^(4-1)*Inputs!B12 | C7: =Inputs!B30*(Inputs!B34*(1+Inputs!B34)^Inputs!B35)/((1+Inputs!B34)^Inputs!B35-1) | D7: =B7-Inputs!B13-C7 | E7: =Inputs!B36 | F7: ='Combined Cashflow'!F8 | G7: =B7+F7-Inputs!B13-Inputs!B27-E7
A8: 5 | B8: =Inputs!B10*(1-Inputs!B11)^(5-1)*Inputs!B12 | C8: =Inputs!B30*(Inputs!B34*(1+Inputs!B34)^Inputs!B35)/((1+Inputs!B34)^Inputs!B35-1) | D8: =B8-Inputs!B13-C8 | E8: =Inputs!B36 | F8: ='Combined Cashflow'!F9 | G8: =B8+F8-Inputs!B13-Inputs!B27-E8
A9: 6 | B9: =Inputs!B10*(1-Inputs!B11)^(6-1)*Inputs!B12 | C9: =Inputs!B30*(Inputs!B34*(1+Inputs!B34)^Inputs!B35)/((1+Inputs!B34)^Inputs!B35-1) | D9: =B9-Inputs!B13-C9 | E9: =Inputs!B36 | F9: ='Combined Cashflow'!F10 | G9: =B9+F9-Inputs!B13-Inputs!B27-E9
A10: 7 | B10: =Inputs!B10*(1-Inputs!B11)^(7-1)*Inputs!B12 | C10: =Inputs!B30*(Inputs!B34*(1+Inputs!B34)^Inputs!B35)/((1+Inputs!B34)^Inputs!B35-1) | D10: =B10-Inputs!B13-C10 | E10: =Inputs!B36 | F10: ='Combined Cashflow'!F11 | G10: =B10+F10-Inputs!B13-Inputs!B27-E10
A11: 8 | B11: =Inputs!B10*(1-Inputs!B11)^(8-1)*Inputs!B12 | C11: =Inputs!B30*(Inputs!B34*(1+Inputs!B34)^Inputs!B35)/((1+Inputs!B34)^Inputs!B35-1) | D11: =B11-Inputs!B13-C11 | E11: =Inputs!B36 | F11: ='Combined Cashflow'!F12 | G11: =B11+F11-Inputs!B13-Inputs!B27-E11
A12: 9 | B12: =Inputs!B10*(1-Inputs!B11)^(9-1)*Inputs!B12 | C12: =Inputs!B30*(Inputs!B34*(1+Inputs!B34)^Inputs!B35)/((1+Inputs!B34)^Inputs!B35-1) | D12: =B12-Inputs!B13-C12 | E12: =Inputs!B36 | F12: ='Combined Cashflow'!F13 | G12: =B12+F12-Inputs!B13-Inputs!B27-E12
A13: 10 | B13: =Inputs!B10*(1-Inputs!B11)^(10-1)*Inputs!B12 | C13: =Inputs!B30*(Inputs!B34*(1+Inputs!B34)^Inputs!B35)/((1+Inputs!B34)^Inputs!B35-1) | D13: =B13-Inputs!B13-C13 | E13: =Inputs!B36 | F13: ='Combined Cashflow'!F14 | G13: =B13+F13-Inputs!B13-Inputs!B27-E13
A14: 11 | B14: =Inputs!B10*(1-Inputs!B11)^(11-1)*Inputs!B12 | C14: =Inputs!B30*(Inputs!B34*(1+Inputs!B34)^Inputs!B35)/((1+Inputs!B34)^Inputs!B35-1) | D14: =B14-Inputs!B13-C14 | E14: =Inputs!B36 | F14: ='Combined Cashflow'!F15 | G14: =B14+F14-Inputs!B13-Inputs!B27-E14
A15: 12 | B15: =Inputs!B10*(1-Inputs!B11)^(12-1)*Inputs!B12 | C15: =Inputs!B30*(Inputs!B34*(1+Inputs!B34)^Inputs!B35)/((1+Inputs!B34)^Inputs!B35-1) | D15: =B15-Inputs!B13-C15 | E15: =Inputs!B36 | F15: ='Combined Cashflow'!F16 | G15: =B15+F15-Inputs!B13-Inputs!B27-E15
A16: 13 | B16: =Inputs!B10*(1-Inputs!B11)^(13-1)*Inputs!B12 | C16: =Inputs!B30*(Inputs!B34*(1+Inputs!B34)^Inputs!B35)/((1+Inputs!B34)^Inputs!B35-1) | D16: =B16-Inputs!B13-C16 | E16: =Inputs!B36 | F16: ='Combined Cashflow'!F17 | G16: =B16+F16-Inputs!B13-Inputs!B27-E16
A17: 14 | B17: =Inputs!B10*(1-Inputs!B11)^(14-1)*Inputs!B12 | C17: =Inputs!B30*(Inputs!B34*(1+Inputs!B34)^Inputs!B35)/((1+Inputs!B34)^Inputs!B35-1) | D17: =B17-Inputs!B13-C17 | E17: =Inputs!B36 | F17: ='Combined Cashflow'!F18 | G17: =B17+F17-Inputs!B13-Inputs!B27-E17
A18: 15 | B18: =Inputs!B10*(1-Inputs!B11)^(15-1)*Inputs!B12 | C18: =Inputs!B30*(Inputs!B34*(1+Inputs!B34)^Inputs!B35)/((1+Inputs!B34)^Inputs!B35-1) | D18: =B18-Inputs!B13-C18 | E18: =Inputs!B36 | F18: ='Combined Cashflow'!F19 | G18: =B18+F18-Inputs!B13-Inputs!B27-E18
A19: TOTAL | B19: =SUM(B4:B18) | C19: =SUM(C4:C18) | D19: =SUM(D4:D18) | E19: =SUM(E4:E18) | F19: =SUM(F4:F18) | G19: =SUM(G4:G18)
A20: DELTA | B20: Additional 15-year free cash from adding BESS: | G20: =G19-D19
