Workbook

Sheet Summary
B1: BESS PROFITABILITY - GALASCOPE (ESPERIA ENERGY)
B2: Lighthief Cyprus Ltd - Data-Validated Model (Feb 2026) | E2: Change parameters on the Inputs sheet
B4: KEY FINANCIAL METRICS
B5: Investment (EUR) | C5: =Inputs!C16
B6: Simple Payback (years) | C6: =IF(CashFlow!J18<0,"Never",SUMPRODUCT((CashFlow!J4:J18<0)*1)+1+ABS(INDEX(CashFlow!J3:J18,SUMPRODUCT((CashFlow!J4:J18<0)*1)+1))/INDEX(CashFlow!I4:I18,SUMPRODUCT((CashFlow!J4:J18<0)*1)+1))
B7: 15-Year Net Profit (EUR) | C7: =CashFlow!J18
B8: 15-Year ROI (%) | C8: =CashFlow!J18/Inputs!C16
B9: 15-Year Gross Revenue (EUR) | C9: =SUM(CashFlow!G4:G18)
B10: 15-Year Operating Costs (EUR) | C10: =SUM(CashFlow!H4:H18)
B11: Year 1 Net Cash Flow (EUR) | C11: =CashFlow!I4
B12: Year 15 Net Cash Flow (EUR) | C12: =CashFlow!I18
B14: BESS PERFORMANCE
B15: BESS Capture Efficiency | C15: =SUM(DailyAnalysis!G2:G366)/SUM(DailyAnalysis!D2:D366)
B16: Average Daily Fill | C16: =AVERAGE(DailyAnalysis!H2:H366)
B17: Days at 100% Fill | C17: =COUNTIF(DailyAnalysis!H2:H366,">=0.9999")
B18: Days Zero Curtailment | C18: =COUNTIF(CurtailmentData!D2:D366,"<=0")
B19: 15-Year Total Cycles | C19: =CashFlow!E18
B20: Cycle Headroom vs 7000 | C20: =1-CashFlow!E18/Inputs!C13
B21: Average Daily Cycles | C21: =SUM(CashFlow!L4:L18)/(Inputs!C30*365)
B23: CURTAILMENT DATA SUMMARY
B24: Data Source | C24: Galascope 2.5MW, 365 days (Jan-Dec 2025)
B25: Annual PV Potential (MWh, ref) | C25: =SUM(CurtailmentData!F2:F366)/1000
B26: Annual Curtailed (MWh, ref) | C26: =SUM(CurtailmentData!D2:D366)/1000
B27: Curtailment Rate | C27: =C26/C25
B28: Days with Curtailment | C28: =COUNTIF(CurtailmentData!D2:D366,">0")
B30: MARKET DATA VALIDATION
B31: DAM Data Source | C31: 137 TSOC files, Oct 2025 - Feb 2026
B32: Peak Evening Avg (17-21) | C32: EUR 184.13/MWh
B33: Model Discharge Price | C33: =Inputs!C27
B34: Model vs Actual | C34: Conservative by EUR 9.13 (+5.2%)
B35: Midday Trough Avg (09-14) | C35: EUR 102.40/MWh
B37: MONTHLY BREAKDOWN
B38: Month | C38: PV Yield (MWh) | D38: Curtailed (MWh) | E38: Curt % | F38: BESS Captured (MWh) | G38: Avg Fill
B39: Jan | C39: 128 | D39: 117.6 | E39: 0.479 | F39: 235.3 | G39: 0.446
B40: Feb | C40: 162.1 | D40: 107.2 | E40: 0.398 | F40: 209.7 | G40: 0.44
B41: Mar | C41: 150.6 | D41: 286 | E41: 0.655 | F41: 470.9 | G41: 0.892
B42: Apr | C42: 175.8 | D42: 276.1 | E42: 0.611 | F42: 393.9 | G42: 0.771
B43: May | C43: 298.1 | D43: 297.6 | E43: 0.5 | F43: 463 | G43: 0.877
B44: Jun | C44: 432.7 | D44: 188.3 | E44: 0.303 | F44: 313.3 | G44: 0.613
B45: Jul | C45: 486.8 | D45: 127.2 | E45: 0.207 | F45: 232.7 | G45: 0.441
B46: Aug | C46: 408.1 | D46: 141.7 | E46: 0.258 | F46: 268.3 | G46: 0.508
B47: Sep | C47: 310 | D47: 146.4 | E47: 0.321 | F47: 284.2 | G47: 0.556
B48: Oct | C48: 125.9 | D48: 249.6 | E48: 0.665 | F48: 461.9 | G48: 0.875
B49: Nov | C49: 109 | D49: 130.2 | E49: 0.544 | F49: 260.3 | G49: 0.509
B50: Dec | C50: 86.5 | D50: 80.7 | E50: 0.482 | F50: 161.4 | G50: 0.306
B51: ANNUAL | C51: 2873.6 | D51: 2148.6 | E51: 0.428 | F51: 3755
B53: HOW TO USE
B54: All yellow cells on the Inputs sheet can be changed - calculations update automatically.
B55: Blue-highlighted cells on CashFlow (Captured MWh) are pre-computed from 365-day SOH analysis.
B56: To model a different park: change PV Capacity, BESS Power/Energy, and EPC Price on Inputs.
B57: To model higher discharge prices: change Blended Discharge Price (actual DAM peak = EUR 184).
B58: To model price growth: set Annual Price Escalation > 0% on Inputs.
B59: CurtailmentData tab has all 365 days of raw data from Galascope 2.5MW park.
B60: MarketData tab has the full hourly DAM price profile from 137 TSOC settlement files.
B61: SOH_Degradation tab shows the Linyang guaranteed degradation curve.
B62: DailyAnalysis tab calculates day-by-day BESS capture with overflow constraints.

Sheet Inputs
B1: BESS Profitability Calculator - Galascope (Esperia Energy)
B2: Lighthief Cyprus Ltd - Yellow cells are editable inputs
B4: BESS SYSTEM
B5: PV Park Capacity (MW) | C5: 5 | D5: MW | E5: Galascope 1 target - change for different park sizes
B6: Reference Park Capacity (MW) | C6: 2.5 | D6: MW | E6: Galascope 2.5MW - source of actual curtailment data
B7: Scaling Factor | C7: =C5/C6 | D7: x | E7: Auto-calculated: Target / Reference
B8: BESS Power Rating (MW) | C8: 5 | D8: MW | E8: Linyang system power rating
B9: BESS Energy Capacity (MWh) | C9: 20 | D9: MWh | E9: 4x 5.015 MWh containers = 20.06 MWh nameplate
B10: BESS Duration (hours) | C10: =C9/C8 | D10: hrs
B11: Depth of Discharge (%) | C11: 90 | D11: % | E11: Linyang operating specification
B12: Round-Trip Efficiency (%) | C12: 87.8 | D12: % | E12: Linyang confirmed AC-AC RTE
B13: Cycle Life (@ 90% DOD, 70% EOL) | C13: 7000 | D13: cycles
B15: INVESTMENT & COSTS
B16: Turnkey EPC Price (EUR) | C16: 2258900 | D16: EUR | E16: Confirmed Esperia 5MW/20MWh price
B17: Cost per kWh (EUR/kWh) | C17: =C16/(C9*1000) | D17: EUR/kWh
B18: LTSA Tier C - Yr 1-5 (EUR/yr) | C18: 34800 | D18: EUR/yr
B19: Extended Warranty - Yr 6-10 add-on (EUR/yr) | C19: 33234 | D19: EUR/yr
B20: Extended Warranty - Yr 11-15 add-on (EUR/yr) | C20: 41674 | D20: EUR/yr
B21: SCADA/EMS Annual (EUR/yr) | C21: 5000 | D21: EUR/yr
B22: Total OpCost Yr 1-5 (EUR/yr) | C22: =C18+C21
B23: Total OpCost Yr 6-10 (EUR/yr) | C23: =C18+C19+C21
B24: Total OpCost Yr 11-15 (EUR/yr) | C24: =C18+C20+C21
B26: REVENUE ASSUMPTIONS
B27: Blended Discharge Price (EUR/MWh) | C27: 175 | D27: EUR/MWh | E27: Conservative - actual DAM peak 17-21 avg = EUR 184.13
B28: Charge Cost (EUR/MWh) | C28: 0 | D28: EUR/MWh | E28: Curtailed energy = zero opportunity cost
B29: Annual Price Escalation (%) | C29: 0 | D29: % | E29: Conservative - no escalation assumed
B30: Project Life (years) | C30: 15 | D30: years
B32: CURTAILMENT SUMMARY (from actual data)
B33: Annual Curtailed - Ref Park (MWh) | C33: =SUM(CurtailmentData!D2:D366)/1000
B34: Annual Curtailed - Scaled (MWh) | C34: =C33*C7
B35: Annual BESS Captured Yr1 - Scaled (MWh) | C35: =SUM(DailyAnalysis!G2:G366)/1000
B36: Capture Efficiency (%) | C36: =C35/C34
B37: Average Daily BESS Fill (%) | C37: =AVERAGE(DailyAnalysis!H2:H366)

Sheet CurtailmentData
A1: Date | B1: Month | C1: Sun Hours | D1: Curtailed (kWh) | E1: PV Yield (kWh) | F1: Total Potential (kWh) | G1: Curtailment %
A2: 2025-01-01 | B2: 1 | C2: 8.75 | D2: 5641.47 | E2: 2138.17 | F2: 7779.64 | G2: =IF(F2>0, D2/F2, 0)
A3: 2025-01-02 | B3: 1 | C3: 8.75 | D3: 5407.44 | E3: 3351.33 | F3: 8758.77 | G3: =IF(F3>0, D3/F3, 0)
A4: 2025-01-03 | B4: 1 | C4: 8.83 | D4: 2117.06 | E4: 6520.83 | F4: 8637.89 | G4: =IF(F4>0, D4/F4, 0)
A5: 2025-01-04 | B5: 1 | C5: 8.25 | D5: 5.83 | E5: 4942.21 | F5: 4948.04 | G5: =IF(F5>0, D5/F5, 0)
A6: 2025-01-05 | B6: 1 | C6: 7.33 | D6: 0 | E6: 3751.49 | F6: 3751.49 | G6: =IF(F6>0, D6/F6, 0)
A7: 2025-01-06 | B7: 1 | C7: 8.67 | D7: 5370.38 | E7: 2336.04 | F7: 7706.42 | G7: =IF(F7>0, D7/F7, 0)
A8: 2025-01-07 | B8: 1 | C8: 8.75 | D8: 2225.36 | E8: 5943.77 | F8: 8169.13 | G8: =IF(F8>0, D8/F8, 0)
A9: 2025-01-08 | B9: 1 | C9: 8.33 | D9: 653.62 | E9: 5578.62 | F9: 6232.24 | G9: =IF(F9>0, D9/F9, 0)
A10: 2025-01-09 | B10: 1 | C10: 8.5 | D10: 4418.52 | E10: 3671.6 | F10: 8090.12 | G10: =IF(F10>0, D10/F10, 0)
A11: 2025-01-10 | B11: 1 | C11: 8.83 | D11: 1868.59 | E11: 6382.54 | F11: 8251.12 | G11: =IF(F11>0, D11/F11, 0)
A12: 2025-01-11 | B12: 1 | C12: 8.75 | D12: 2929.18 | E12: 5319.32 | F12: 8248.5 | G12: =IF(F12>0, D12/F12, 0)
A13: 2025-01-12 | B13: 1 | C13: 8.67 | D13: 4573.96 | E13: 3737.31 | F13: 8311.27 | G13: =IF(F13>0, D13/F13, 0)
... A366: 2025-12-31 | B366: 12 | C366: 6.17 | D366: 1189.85 | E366: 1641.24 | F366: 2831.09 | G366: =IF(F366>0, D366/F366, 0)

Sheet MarketData
A1: TSOC DAM Hourly Price Profile (Oct 2025 - Feb 2026, 6576 records)
A2: Hour | B2: Avg EUR/MWh | C2: Median | D2: P10 | E2: P90 | F2: Min | G2: Max | H2: Zero-Price % | I2: Count | J2: Band
A3: 00:00 | B3: 173.15 | C3: 174 | D3: 157.5 | E3: 187 | F3: 150 | G3: 194 | H3: 0 | I3: 274 | J3: Night
A4: 01:00 | B4: 170.28 | C4: 171 | D4: 155.5 | E4: 184 | F4: 150 | G4: 192.5 | H4: 0 | I4: 274 | J4: Night
A5: 02:00 | B5: 169.56 | C5: 170 | D5: 155 | E5: 183 | F5: 150 | G5: 192 | H5: 0 | I5: 274 | J5: Night
A6: 03:00 | B6: 169.25 | C6: 169 | D6: 155 | E6: 182 | F6: 150 | G6: 192 | H6: 0 | I6: 274 | J6: Night
A7: 04:00 | B7: 169.37 | C7: 169 | D7: 155 | E7: 182 | F7: 150 | G7: 193 | H7: 0 | I7: 274 | J7: Night
A8: 05:00 | B8: 171.31 | C8: 171 | D8: 157 | E8: 185 | F8: 150 | G8: 194.5 | H8: 0 | I8: 274 | J8: Night
A9: 06:00 | B9: 174.6 | C9: 175.5 | D9: 157.5 | E9: 188.2 | F9: 152 | G9: 198 | H9: 0 | I9: 274 | J9: Morning
A10: 07:00 | B10: 174.76 | C10: 175 | D10: 160 | E10: 188 | F10: 153 | G10: 200 | H10: 0 | I10: 274 | J10: Morning
A11: 08:00 | B11: 166.98 | C11: 169 | D11: 154 | E11: 185 | F11: 0 | G11: 195 | H11: 0.0146 | I11: 274 | J11: Morning
A12: 09:00 | B12: 146.09 | C12: 159 | D12: 69 | E12: 179 | F12: 0 | G12: 192 | H12: 0.0584 | I12: 274 | J12: Midday Trough
A13: 10:00 | B13: 102.79 | C13: 152 | D13: 0 | E13: 171 | F13: 0 | G13: 193.5 | H13: 0.2153 | I13: 274 | J13: Midday Trough
A14: 11:00 | B14: 80.43 | C14: 38.5 | D14: 0 | E14: 170 | F14: 0 | G14: 193.5 | H14: 0.3358 | I14: 274 | J14: Midday Trough
... A26: 23:00 | B26: 173.86 | C26: 175 | D26: 157 | E26: 188 | F26: 150 | G26: 195 | H26: 0 | I26: 274 | J26: Late Evening
A28: Band Summary
A29: Band | B29: Hours | C29: Avg EUR/MWh | D29: Zero % | E29: <=EUR50 %
A30: Night (00-06) | B30: 00:00-06:00 | C30: 170.49 | D30: 0 | E30: 0
A31: Morning (06-09) | B31: 06:00-09:00 | C31: 172.11 | D31: 0.0049 | E31: 0.0049
A32: Midday Trough (09-14) | B32: 09:00-14:00 | C32: 102.4 | D32: 0.2372 | E32: 0.3759
A33: Afternoon (14-17) | B33: 14:00-17:00 | C33: 161.35 | D33: 0.0219 | E33: 0.0596
A34: Peak Evening (17-21) | B34: 17:00-21:00 | C34: 184.13 | D34: 0 | E34: 0
A35: Late Evening (21-24) | B35: 21:00-24:00 | C35: 176.61 | D35: 0 | E35: 0
A37: Peak Evening Avg (17-21): | B37: 184.13

Sheet SOH_Degradation
A1: Linyang SOH Degradation Curve (0.5P, 1 cycle/day, 25 +/- 2C)
A2: Year | B2: SOH % | C2: Usable Capacity (MWh) | D2: Max Daily Charge (kWh) | E2: Cumulative Cycles | F2: Cycle Headroom vs 7000
A3: 1 | B3: 0.9462 | C3: =Inputs!C9*B3*Inputs!C11/100 | D3: =C3*1000 | E3: =CashFlow!E4 | F3: =1-E3/Inputs!C13
A4: 2 | B4: 0.9177 | C4: =Inputs!C9*B4*Inputs!C11/100 | D4: =C4*1000 | E4: =CashFlow!E5 | F4: =1-E4/Inputs!C13
A5: 3 | B5: 0.8991 | C5: =Inputs!C9*B5*Inputs!C11/100 | D5: =C5*1000 | E5: =CashFlow!E6 | F5: =1-E5/Inputs!C13
A6: 4 | B6: 0.8835 | C6: =Inputs!C9*B6*Inputs!C11/100 | D6: =C6*1000 | E6: =CashFlow!E7 | F6: =1-E6/Inputs!C13
A7: 5 | B7: 0.8678 | C7: =Inputs!C9*B7*Inputs!C11/100 | D7: =C7*1000 | E7: =CashFlow!E8 | F7: =1-E7/Inputs!C13
A8: 6 | B8: 0.8534 | C8: =Inputs!C9*B8*Inputs!C11/100 | D8: =C8*1000 | E8: =CashFlow!E9 | F8: =1-E8/Inputs!C13
A9: 7 | B9: 0.839 | C9: =Inputs!C9*B9*Inputs!C11/100 | D9: =C9*1000 | E9: =CashFlow!E10 | F9: =1-E9/Inputs!C13
A10: 8 | B10: 0.8246 | C10: =Inputs!C9*B10*Inputs!C11/100 | D10: =C10*1000 | E10: =CashFlow!E11 | F10: =1-E10/Inputs!C13
A11: 9 | B11: 0.8102 | C11: =Inputs!C9*B11*Inputs!C11/100 | D11: =C11*1000 | E11: =CashFlow!E12 | F11: =1-E11/Inputs!C13
A12: 10 | B12: 0.7958 | C12: =Inputs!C9*B12*Inputs!C11/100 | D12: =C12*1000 | E12: =CashFlow!E13 | F12: =1-E12/Inputs!C13
A13: 11 | B13: 0.7839 | C13: =Inputs!C9*B13*Inputs!C11/100 | D13: =C13*1000 | E13: =CashFlow!E14 | F13: =1-E13/Inputs!C13
A14: 12 | B14: 0.772 | C14: =Inputs!C9*B14*Inputs!C11/100 | D14: =C14*1000 | E14: =CashFlow!E15 | F14: =1-E14/Inputs!C13
A15: 13 | B15: 0.7601 | C15: =Inputs!C9*B15*Inputs!C11/100 | D15: =C15*1000 | E15: =CashFlow!E16 | F15: =1-E15/Inputs!C13
A16: 14 | B16: 0.7481 | C16: =Inputs!C9*B16*Inputs!C11/100 | D16: =C16*1000 | E16: =CashFlow!E17 | F16: =1-E16/Inputs!C13
A17: 15 | B17: 0.7361 | C17: =Inputs!C9*B17*Inputs!C11/100 | D17: =C17*1000 | E17: =CashFlow!E18 | F17: =1-E17/Inputs!C13

Sheet DailyAnalysis
A1: Date | B1: Month | C1: Curtailed Ref (kWh) | D1: Curtailed Scaled (kWh) | E1: BESS Usable Cap Yr1 (kWh) | F1: Overflow (kWh) | G1: Captured (kWh) | H1: Fill % | I1: Discharged (kWh) | J1: Revenue (EUR)
A2: 2025-01-01 | B2: 1 | C2: =CurtailmentData!D2 | D2: =C2*Inputs!C7 | E2: =SOH_Degradation!D3 | F2: =MAX(0, D2-E2) | G2: =MIN(D2, E2) | H2: =IF(E2>0, G2/E2, 0) | I2: =G2*Inputs!C12/100 | J2: =(I2/1000)*(Inputs!C27-Inputs!C28)
A3: 2025-01-02 | B3: 1 | C3: =CurtailmentData!D3 | D3: =C3*Inputs!C7 | E3: =SOH_Degradation!D3 | F3: =MAX(0, D3-E3) | G3: =MIN(D3, E3) | H3: =IF(E3>0, G3/E3, 0) | I3: =G3*Inputs!C12/100 | J3: =(I3/1000)*(Inputs!C27-Inputs!C28)
A4: 2025-01-03 | B4: 1 | C4: =CurtailmentData!D4 | D4: =C4*Inputs!C7 | E4: =SOH_Degradation!D3 | F4: =MAX(0, D4-E4) | G4: =MIN(D4, E4) | H4: =IF(E4>0, G4/E4, 0) | I4: =G4*Inputs!C12/100 | J4: =(I4/1000)*(Inputs!C27-Inputs!C28)
A5: 2025-01-04 | B5: 1 | C5: =CurtailmentData!D5 | D5: =C5*Inputs!C7 | E5: =SOH_Degradation!D3 | F5: =MAX(0, D5-E5) | G5: =MIN(D5, E5) | H5: =IF(E5>0, G5/E5, 0) | I5: =G5*Inputs!C12/100 | J5: =(I5/1000)*(Inputs!C27-Inputs!C28)
A6: 2025-01-05 | B6: 1 | C6: =CurtailmentData!D6 | D6: =C6*Inputs!C7 | E6: =SOH_Degradation!D3 | F6: =MAX(0, D6-E6) | G6: =MIN(D6, E6) | H6: =IF(E6>0, G6/E6, 0) | I6: =G6*Inputs!C12/100 | J6: =(I6/1000)*(Inputs!C27-Inputs!C28)
A7: 2025-01-06 | B7: 1 | C7: =CurtailmentData!D7 | D7: =C7*Inputs!C7 | E7: =SOH_Degradation!D3 | F7: =MAX(0, D7-E7) | G7: =MIN(D7, E7) | H7: =IF(E7>0, G7/E7, 0) | I7: =G7*Inputs!C12/100 | J7: =(I7/1000)*(Inputs!C27-Inputs!C28)
A8: 2025-01-07 | B8: 1 | C8: =CurtailmentData!D8 | D8: =C8*Inputs!C7 | E8: =SOH_Degradation!D3 | F8: =MAX(0, D8-E8) | G8: =MIN(D8, E8) | H8: =IF(E8>0, G8/E8, 0) | I8: =G8*Inputs!C12/100 | J8: =(I8/1000)*(Inputs!C27-Inputs!C28)
A9: 2025-01-08 | B9: 1 | C9: =CurtailmentData!D9 | D9: =C9*Inputs!C7 | E9: =SOH_Degradation!D3 | F9: =MAX(0, D9-E9) | G9: =MIN(D9, E9) | H9: =IF(E9>0, G9/E9, 0) | I9: =G9*Inputs!C12/100 | J9: =(I9/1000)*(Inputs!C27-Inputs!C28)
A10: 2025-01-09 | B10: 1 | C10: =CurtailmentData!D10 | D10: =C10*Inputs!C7 | E10: =SOH_Degradation!D3 | F10: =MAX(0, D10-E10) | G10: =MIN(D10, E10) | H10: =IF(E10>0, G10/E10, 0) | I10: =G10*Inputs!C12/100 | J10: =(I10/1000)*(Inputs!C27-Inputs!C28)
A11: 2025-01-10 | B11: 1 | C11: =CurtailmentData!D11 | D11: =C11*Inputs!C7 | E11: =SOH_Degradation!D3 | F11: =MAX(0, D11-E11) | G11: =MIN(D11, E11) | H11: =IF(E11>0, G11/E11, 0) | I11: =G11*Inputs!C12/100 | J11: =(I11/1000)*(Inputs!C27-Inputs!C28)
A12: 2025-01-11 | B12: 1 | C12: =CurtailmentData!D12 | D12: =C12*Inputs!C7 | E12: =SOH_Degradation!D3 | F12: =MAX(0, D12-E12) | G12: =MIN(D12, E12) | H12: =IF(E12>0, G12/E12, 0) | I12: =G12*Inputs!C12/100 | J12: =(I12/1000)*(Inputs!C27-Inputs!C28)
A13: 2025-01-12 | B13: 1 | C13: =CurtailmentData!D13 | D13: =C13*Inputs!C7 | E13: =SOH_Degradation!D3 | F13: =MAX(0, D13-E13) | G13: =MIN(D13, E13) | H13: =IF(E13>0, G13/E13, 0) | I13: =G13*Inputs!C12/100 | J13: =(I13/1000)*(Inputs!C27-Inputs!C28)
A14: 2025-01-13 | B14: 1 | C14: =CurtailmentData!D14 | D14: =C14*Inputs!C7 | E14: =SOH_Degradation!D3 | F14: =MAX(0, D14-E14) | G14: =MIN(D14, E14) | H14: =IF(E14>0, G14/E14, 0) | I14: =G14*Inputs!C12/100 | J14: =(I14/1000)*(Inputs!C27-Inputs!C28)
A15: 2025-01-14 | B15: 1 | C15: =CurtailmentData!D15 | D15: =C15*Inputs!C7 | E15: =SOH_Degradation!D3 | F15: =MAX(0, D15-E15) | G15: =MIN(D15, E15) | H15: =IF(E15>0, G15/E15, 0) | I15: =G15*Inputs!C12/100 | J15: =(I15/1000)*(Inputs!C27-Inputs!C28)
A16: 2025-01-15 | B16: 1 | C16: =CurtailmentData!D16 | D16: =C16*Inputs!C7 | E16: =SOH_Degradation!D3 | F16: =MAX(0, D16-E16) | G16: =MIN(D16, E16) | H16: =IF(E16>0, G16/E16, 0) | I16: =G16*Inputs!C12/100 | J16: =(I16/1000)*(Inputs!C27-Inputs!C28)
A17: 2025-01-16 | B17: 1 | C17: =CurtailmentData!D17 | D17: =C17*Inputs!C7 | E17: =SOH_Degradation!D3 | F17: =MAX(0, D17-E17) | G17: =MIN(D17, E17) | H17: =IF(E17>0, G17/E17, 0) | I17: =G17*Inputs!C12/100 | J17: =(I17/1000)*(Inputs!C27-Inputs!C28)
A18: 2025-01-17 | B18: 1 | C18: =CurtailmentData!D18 | D18: =C18*Inputs!C7 | E18: =SOH_Degradation!D3 | F18: =MAX(0, D18-E18) | G18: =MIN(D18, E18) | H18: =IF(E18>0, G18/E18, 0) | I18: =G18*Inputs!C12/100 | J18: =(I18/1000)*(Inputs!C27-Inputs!C28)
A19: 2025-01-18 | B19: 1 | C19: =CurtailmentData!D19 | D19: =C19*Inputs!C7 | E19: =SOH_Degradation!D3 | F19: =MAX(0, D19-E19) | G19: =MIN(D19, E19) | H19: =IF(E19>0, G19/E19, 0) | I19: =G19*Inputs!C12/100 | J19: =(I19/1000)*(Inputs!C27-Inputs!C28)
A20: 2025-01-19 | B20: 1 | C20: =CurtailmentData!D20 | D20: =C20*Inputs!C7 | E20: =SOH_Degradation!D3 | F20: =MAX(0, D20-E20) | G20: =MIN(D20, E20) | H20: =IF(E20>0, G20/E20, 0) | I20: =G20*Inputs!C12/100 | J20: =(I20/1000)*(Inputs!C27-Inputs!C28)
A21: 2025-01-20 | B21: 1 | C21: =CurtailmentData!D21 | D21: =C21*Inputs!C7 | E21: =SOH_Degradation!D3 | F21: =MAX(0, D21-E21) | G21: =MIN(D21, E21) | H21: =IF(E21>0, G21/E21, 0) | I21: =G21*Inputs!C12/100 | J21: =(I21/1000)*(Inputs!C27-Inputs!C28)
A22: 2025-01-21 | B22: 1 | C22: =CurtailmentData!D22 | D22: =C22*Inputs!C7 | E22: =SOH_Degradation!D3 | F22: =MAX(0, D22-E22) | G22: =MIN(D22, E22) | H22: =IF(E22>0, G22/E22, 0) | I22: =G22*Inputs!C12/100 | J22: =(I22/1000)*(Inputs!C27-Inputs!C28)
A23: 2025-01-22 | B23: 1 | C23: =CurtailmentData!D23 | D23: =C23*Inputs!C7 | E23: =SOH_Degradation!D3 | F23: =MAX(0, D23-E23) | G23: =MIN(D23, E23) | H23: =IF(E23>0, G23/E23, 0) | I23: =G23*Inputs!C12/100 | J23: =(I23/1000)*(Inputs!C27-Inputs!C28)
A24: 2025-01-23 | B24: 1 | C24: =CurtailmentData!D24 | D24: =C24*Inputs!C7 | E24: =SOH_Degradation!D3 | F24: =MAX(0, D24-E24) | G24: =MIN(D24, E24) | H24: =IF(E24>0, G24/E24, 0) | I24: =G24*Inputs!C12/100 | J24: =(I24/1000)*(Inputs!C27-Inputs!C28)
A25: 2025-01-24 | B25: 1 | C25: =CurtailmentData!D25 | D25: =C25*Inputs!C7 | E25: =SOH_Degradation!D3 | F25: =MAX(0, D25-E25) | G25: =MIN(D25, E25) | H25: =IF(E25>0, G25/E25, 0) | I25: =G25*Inputs!C12/100 | J25: =(I25/1000)*(Inputs!C27-Inputs!C28)
A26: 2025-01-25 | B26: 1 | C26: =CurtailmentData!D26 | D26: =C26*Inputs!C7 | E26: =SOH_Degradation!D3 | F26: =MAX(0, D26-E26) | G26: =MIN(D26, E26) | H26: =IF(E26>0, G26/E26, 0) | I26: =G26*Inputs!C12/100 | J26: =(I26/1000)*(Inputs!C27-Inputs!C28)
A27: 2025-01-26 | B27: 1 | C27: =CurtailmentData!D27 | D27: =C27*Inputs!C7 | E27: =SOH_Degradation!D3 | F27: =MAX(0, D27-E27) | G27: =MIN(D27, E27) | H27: =IF(E27>0, G27/E27, 0) | I27: =G27*Inputs!C12/100 | J27: =(I27/1000)*(Inputs!C27-Inputs!C28)
A28: 2025-01-27 | B28: 1 | C28: =CurtailmentData!D28 | D28: =C28*Inputs!C7 | E28: =SOH_Degradation!D3 | F28: =MAX(0, D28-E28) | G28: =MIN(D28, E28) | H28: =IF(E28>0, G28/E28, 0) | I28: =G28*Inputs!C12/100 | J28: =(I28/1000)*(Inputs!C27-Inputs!C28)
A29: 2025-01-28 | B29: 1 | C29: =CurtailmentData!D29 | D29: =C29*Inputs!C7 | E29: =SOH_Degradation!D3 | F29: =MAX(0, D29-E29) | G29: =MIN(D29, E29) | H29: =IF(E29>0, G29/E29, 0) | I29: =G29*Inputs!C12/100 | J29: =(I29/1000)*(Inputs!C27-Inputs!C28)
A30: 2025-01-29 | B30: 1 | C30: =CurtailmentData!D30 | D30: =C30*Inputs!C7 | E30: =SOH_Degradation!D3 | F30: =MAX(0, D30-E30) | G30: =MIN(D30, E30) | H30: =IF(E30>0, G30/E30, 0) | I30: =G30*Inputs!C12/100 | J30: =(I30/1000)*(Inputs!C27-Inputs!C28)
A31: 2025-01-30 | B31: 1 | C31: =CurtailmentData!D31 | D31: =C31*Inputs!C7 | E31: =SOH_Degradation!D3 | F31: =MAX(0, D31-E31) | G31: =MIN(D31, E31) | H31: =IF(E31>0, G31/E31, 0) | I31: =G31*Inputs!C12/100 | J31: =(I31/1000)*(Inputs!C27-Inputs!C28)
A32: 2025-01-31 | B32: 1 | C32: =CurtailmentData!D32 | D32: =C32*Inputs!C7 | E32: =SOH_Degradation!D3 | F32: =MAX(0, D32-E32) | G32: =MIN(D32, E32) | H32: =IF(E32>0, G32/E32, 0) | I32: =G32*Inputs!C12/100 | J32: =(I32/1000)*(Inputs!C27-Inputs!C28)
A33: 2025-02-01 | B33: 2 | C33: =CurtailmentData!D33 | D33: =C33*Inputs!C7 | E33: =SOH_Degradation!D3 | F33: =MAX(0, D33-E33) | G33: =MIN(D33, E33) | H33: =IF(E33>0, G33/E33, 0) | I33: =G33*Inputs!C12/100 | J33: =(I33/1000)*(Inputs!C27-Inputs!C28)
A34: 2025-02-02 | B34: 2 | C34: =CurtailmentData!D34 | D34: =C34*Inputs!C7 | E34: =SOH_Degradation!D3 | F34: =MAX(0, D34-E34) | G34: =MIN(D34, E34) | H34: =IF(E34>0, G34/E34, 0) | I34: =G34*Inputs!C12/100 | J34: =(I34/1000)*(Inputs!C27-Inputs!C28)
A35: 2025-02-03 | B35: 2 | C35: =CurtailmentData!D35 | D35: =C35*Inputs!C7 | E35: =SOH_Degradation!D3 | F35: =MAX(0, D35-E35) | G35: =MIN(D35, E35) | H35: =IF(E35>0, G35/E35, 0) | I35: =G35*Inputs!C12/100 | J35: =(I35/1000)*(Inputs!C27-Inputs!C28)
A36: 2025-02-04 | B36: 2 | C36: =CurtailmentData!D36 | D36: =C36*Inputs!C7 | E36: =SOH_Degradation!D3 | F36: =MAX(0, D36-E36) | G36: =MIN(D36, E36) | H36: =IF(E36>0, G36/E36, 0) | I36: =G36*Inputs!C12/100 | J36: =(I36/1000)*(Inputs!C27-Inputs!C28)
A37: 2025-02-05 | B37: 2 | C37: =CurtailmentData!D37 | D37: =C37*Inputs!C7 | E37: =SOH_Degradation!D3 | F37: =MAX(0, D37-E37) | G37: =MIN(D37, E37) | H37: =IF(E37>0, G37/E37, 0) | I37: =G37*Inputs!C12/100 | J37: =(I37/1000)*(Inputs!C27-Inputs!C28)
A38: 2025-02-06 | B38: 2 | C38: =CurtailmentData!D38 | D38: =C38*Inputs!C7 | E38: =SOH_Degradation!D3 | F38: =MAX(0, D38-E38) | G38: =MIN(D38, E38) | H38: =IF(E38>0, G38/E38, 0) | I38: =G38*Inputs!C12/100 | J38: =(I38/1000)*(Inputs!C27-Inputs!C28)
A39: 2025-02-07 | B39: 2 | C39: =CurtailmentData!D39 | D39: =C39*Inputs!C7 | E39: =SOH_Degradation!D3 | F39: =MAX(0, D39-E39) | G39: =MIN(D39, E39) | H39: =IF(E39>0, G39/E39, 0) | I39: =G39*Inputs!C12/100 | J39: =(I39/1000)*(Inputs!C27-Inputs!C28)
A40: 2025-02-08 | B40: 2 | C40: =CurtailmentData!D40 | D40: =C40*Inputs!C7 | E40: =SOH_Degradation!D3 | F40: =MAX(0, D40-E40) | G40: =MIN(D40, E40) | H40: =IF(E40>0, G40/E40, 0) | I40: =G40*Inputs!C12/100 | J40: =(I40/1000)*(Inputs!C27-Inputs!C28)
A41: 2025-02-09 | B41: 2 | C41: =CurtailmentData!D41 | D41: =C41*Inputs!C7 | E41: =SOH_Degradation!D3 | F41: =MAX(0, D41-E41) | G41: =MIN(D41, E41) | H41: =IF(E41>0, G41/E41, 0) | I41: =G41*Inputs!C12/100 | J41: =(I41/1000)*(Inputs!C27-Inputs!C28)
A42: 2025-02-10 | B42: 2 | C42: =CurtailmentData!D42 | D42: =C42*Inputs!C7 | E42: =SOH_Degradation!D3 | F42: =MAX(0, D42-E42) | G42: =MIN(D42, E42) | H42: =IF(E42>0, G42/E42, 0) | I42: =G42*Inputs!C12/100 | J42: =(I42/1000)*(Inputs!C27-Inputs!C28)
A43: 2025-02-11 | B43: 2 | C43: =CurtailmentData!D43 | D43: =C43*Inputs!C7 | E43: =SOH_Degradation!D3 | F43: =MAX(0, D43-E43) | G43: =MIN(D43, E43) | H43: =IF(E43>0, G43/E43, 0) | I43: =G43*Inputs!C12/100 | J43: =(I43/1000)*(Inputs!C27-Inputs!C28)
A44: 2025-02-12 | B44: 2 | C44: =CurtailmentData!D44 | D44: =C44*Inputs!C7 | E44: =SOH_Degradation!D3 | F44: =MAX(0, D44-E44) | G44: =MIN(D44, E44) | H44: =IF(E44>0, G44/E44, 0) | I44: =G44*Inputs!C12/100 | J44: =(I44/1000)*(Inputs!C27-Inputs!C28)
A45: 2025-02-13 | B45: 2 | C45: =CurtailmentData!D45 | D45: =C45*Inputs!C7 | E45: =SOH_Degradation!D3 | F45: =MAX(0, D45-E45) | G45: =MIN(D45, E45) | H45: =IF(E45>0, G45/E45, 0) | I45: =G45*Inputs!C12/100 | J45: =(I45/1000)*(Inputs!C27-Inputs!C28)
A46: 2025-02-14 | B46: 2 | C46: =CurtailmentData!D46 | D46: =C46*Inputs!C7 | E46: =SOH_Degradation!D3 | F46: =MAX(0, D46-E46) | G46: =MIN(D46, E46) | H46: =IF(E46>0, G46/E46, 0) | I46: =G46*Inputs!C12/100 | J46: =(I46/1000)*(Inputs!C27-Inputs!C28)
A47: 2025-02-15 | B47: 2 | C47: =CurtailmentData!D47 | D47: =C47*Inputs!C7 | E47: =SOH_Degradation!D3 | F47: =MAX(0, D47-E47) | G47: =MIN(D47, E47) | H47: =IF(E47>0, G47/E47, 0) | I47: =G47*Inputs!C12/100 | J47: =(I47/1000)*(Inputs!C27-Inputs!C28)
A48: 2025-02-16 | B48: 2 | C48: =CurtailmentData!D48 | D48: =C48*Inputs!C7 | E48: =SOH_Degradation!D3 | F48: =MAX(0, D48-E48) | G48: =MIN(D48, E48) | H48: =IF(E48>0, G48/E48, 0) | I48: =G48*Inputs!C12/100 | J48: =(I48/1000)*(Inputs!C27-Inputs!C28)
A49: 2025-02-17 | B49: 2 | C49: =CurtailmentData!D49 | D49: =C49*Inputs!C7 | E49: =SOH_Degradation!D3 | F49: =MAX(0, D49-E49) | G49: =MIN(D49, E49) | H49: =IF(E49>0, G49/E49, 0) | I49: =G49*Inputs!C12/100 | J49: =(I49/1000)*(Inputs!C27-Inputs!C28)
A50: 2025-02-18 | B50: 2 | C50: =CurtailmentData!D50 | D50: =C50*Inputs!C7 | E50: =SOH_Degradation!D3 | F50: =MAX(0, D50-E50) | G50: =MIN(D50, E50) | H50: =IF(E50>0, G50/E50, 0) | I50: =G50*Inputs!C12/100 | J50: =(I50/1000)*(Inputs!C27-Inputs!C28)
A51: 2025-02-19 | B51: 2 | C51: =CurtailmentData!D51 | D51: =C51*Inputs!C7 | E51: =SOH_Degradation!D3 | F51: =MAX(0, D51-E51) | G51: =MIN(D51, E51) | H51: =IF(E51>0, G51/E51, 0) | I51: =G51*Inputs!C12/100 | J51: =(I51/1000)*(Inputs!C27-Inputs!C28)
A52: 2025-02-20 | B52: 2 | C52: =CurtailmentData!D52 | D52: =C52*Inputs!C7 | E52: =SOH_Degradation!D3 | F52: =MAX(0, D52-E52) | G52: =MIN(D52, E52) | H52: =IF(E52>0, G52/E52, 0) | I52: =G52*Inputs!C12/100 | J52: =(I52/1000)*(Inputs!C27-Inputs!C28)
A53: 2025-02-21 | B53: 2 | C53: =CurtailmentData!D53 | D53: =C53*Inputs!C7 | E53: =SOH_Degradation!D3 | F53: =MAX(0, D53-E53) | G53: =MIN(D53, E53) | H53: =IF(E53>0, G53/E53, 0) | I53: =G53*Inputs!C12/100 | J53: =(I53/1000)*(Inputs!C27-Inputs!C28)
A54: 2025-02-22 | B54: 2 | C54: =CurtailmentData!D54 | D54: =C54*Inputs!C7 | E54: =SOH_Degradation!D3 | F54: =MAX(0, D54-E54) | G54: =MIN(D54, E54) | H54: =IF(E54>0, G54/E54, 0) | I54: =G54*Inputs!C12/100 | J54: =(I54/1000)*(Inputs!C27-Inputs!C28)
A55: 2025-02-23 | B55: 2 | C55: =CurtailmentData!D55 | D55: =C55*Inputs!C7 | E55: =SOH_Degradation!D3 | F55: =MAX(0, D55-E55) | G55: =MIN(D55, E55) | H55: =IF(E55>0, G55/E55, 0) | I55: =G55*Inputs!C12/100 | J55: =(I55/1000)*(Inputs!C27-Inputs!C28)
A56: 2025-02-24 | B56: 2 | C56: =CurtailmentData!D56 | D56: =C56*Inputs!C7 | E56: =SOH_Degradation!D3 | F56: =MAX(0, D56-E56) | G56: =MIN(D56, E56) | H56: =IF(E56>0, G56/E56, 0) | I56: =G56*Inputs!C12/100 | J56: =(I56/1000)*(Inputs!C27-Inputs!C28)
A57: 2025-02-25 | B57: 2 | C57: =CurtailmentData!D57 | D57: =C57*Inputs!C7 | E57: =SOH_Degradation!D3 | F57: =MAX(0, D57-E57) | G57: =MIN(D57, E57) | H57: =IF(E57>0, G57/E57, 0) | I57: =G57*Inputs!C12/100 | J57: =(I57/1000)*(Inputs!C27-Inputs!C28)
A58: 2025-02-26 | B58: 2 | C58: =CurtailmentData!D58 | D58: =C58*Inputs!C7 | E58: =SOH_Degradation!D3 | F58: =MAX(0, D58-E58) | G58: =MIN(D58, E58) | H58: =IF(E58>0, G58/E58, 0) | I58: =G58*Inputs!C12/100 | J58: =(I58/1000)*(Inputs!C27-Inputs!C28)
A59: 2025-02-27 | B59: 2 | C59: =CurtailmentData!D59 | D59: =C59*Inputs!C7 | E59: =SOH_Degradation!D3 | F59: =MAX(0, D59-E59) | G59: =MIN(D59, E59) | H59: =IF(E59>0, G59/E59, 0) | I59: =G59*Inputs!C12/100 | J59: =(I59/1000)*(Inputs!C27-Inputs!C28)
A60: 2025-02-28 | B60: 2 | C60: =CurtailmentData!D60 | D60: =C60*Inputs!C7 | E60: =SOH_Degradation!D3 | F60: =MAX(0, D60-E60) | G60: =MIN(D60, E60) | H60: =IF(E60>0, G60/E60, 0) | I60: =G60*Inputs!C12/100 | J60: =(I60/1000)*(Inputs!C27-Inputs!C28)
A61: 2025-03-01 | B61: 3 | C61: =CurtailmentData!D61 | D61: =C61*Inputs!C7 | E61: =SOH_Degradation!D3 | F61: =MAX(0, D61-E61) | G61: =MIN(D61, E61) | H61: =IF(E61>0, G61/E61, 0) | I61: =G61*Inputs!C12/100 | J61: =(I61/1000)*(Inputs!C27-Inputs!C28)
A62: 2025-03-02 | B62: 3 | C62: =CurtailmentData!D62 | D62: =C62*Inputs!C7 | E62: =SOH_Degradation!D3 | F62: =MAX(0, D62-E62) | G62: =MIN(D62, E62) | H62: =IF(E62>0, G62/E62, 0) | I62: =G62*Inputs!C12/100 | J62: =(I62/1000)*(Inputs!C27-Inputs!C28)
A63: 2025-03-03 | B63: 3 | C63: =CurtailmentData!D63 | D63: =C63*Inputs!C7 | E63: =SOH_Degradation!D3 | F63: =MAX(0, D63-E63) | G63: =MIN(D63, E63) | H63: =IF(E63>0, G63/E63, 0) | I63: =G63*Inputs!C12/100 | J63: =(I63/1000)*(Inputs!C27-Inputs!C28)
A64: 2025-03-04 | B64: 3 | C64: =CurtailmentData!D64 | D64: =C64*Inputs!C7 | E64: =SOH_Degradation!D3 | F64: =MAX(0, D64-E64) | G64: =MIN(D64, E64) | H64: =IF(E64>0, G64/E64, 0) | I64: =G64*Inputs!C12/100 | J64: =(I64/1000)*(Inputs!C27-Inputs!C28)
A65: 2025-03-05 | B65: 3 | C65: =CurtailmentData!D65 | D65: =C65*Inputs!C7 | E65: =SOH_Degradation!D3 | F65: =MAX(0, D65-E65) | G65: =MIN(D65, E65) | H65: =IF(E65>0, G65/E65, 0) | I65: =G65*Inputs!C12/100 | J65: =(I65/1000)*(Inputs!C27-Inputs!C28)
A66: 2025-03-06 | B66: 3 | C66: =CurtailmentData!D66 | D66: =C66*Inputs!C7 | E66: =SOH_Degradation!D3 | F66: =MAX(0, D66-E66) | G66: =MIN(D66, E66) | H66: =IF(E66>0, G66/E66, 0) | I66: =G66*Inputs!C12/100 | J66: =(I66/1000)*(Inputs!C27-Inputs!C28)
A67: 2025-03-07 | B67: 3 | C67: =CurtailmentData!D67 | D67: =C67*Inputs!C7 | E67: =SOH_Degradation!D3 | F67: =MAX(0, D67-E67) | G67: =MIN(D67, E67) | H67: =IF(E67>0, G67/E67, 0) | I67: =G67*Inputs!C12/100 | J67: =(I67/1000)*(Inputs!C27-Inputs!C28)
A68: 2025-03-08 | B68: 3 | C68: =CurtailmentData!D68 | D68: =C68*Inputs!C7 | E68: =SOH_Degradation!D3 | F68: =MAX(0, D68-E68) | G68: =MIN(D68, E68) | H68: =IF(E68>0, G68/E68, 0) | I68: =G68*Inputs!C12/100 | J68: =(I68/1000)*(Inputs!C27-Inputs!C28)
A69: 2025-03-09 | B69: 3 | C69: =CurtailmentData!D69 | D69: =C69*Inputs!C7 | E69: =SOH_Degradation!D3 | F69: =MAX(0, D69-E69) | G69: =MIN(D69, E69) | H69: =IF(E69>0, G69/E69, 0) | I69: =G69*Inputs!C12/100 | J69: =(I69/1000)*(Inputs!C27-Inputs!C28)
A70: 2025-03-10 | B70: 3 | C70: =CurtailmentData!D70 | D70: =C70*Inputs!C7 | E70: =SOH_Degradation!D3 | F70: =MAX(0, D70-E70) | G70: =MIN(D70, E70) | H70: =IF(E70>0, G70/E70, 0) | I70: =G70*Inputs!C12/100 | J70: =(I70/1000)*(Inputs!C27-Inputs!C28)
A71: 2025-03-11 | B71: 3 | C71: =CurtailmentData!D71 | D71: =C71*Inputs!C7 | E71: =SOH_Degradation!D3 | F71: =MAX(0, D71-E71) | G71: =MIN(D71, E71) | H71: =IF(E71>0, G71/E71, 0) | I71: =G71*Inputs!C12/100 | J71: =(I71/1000)*(Inputs!C27-Inputs!C28)
A72: 2025-03-12 | B72: 3 | C72: =CurtailmentData!D72 | D72: =C72*Inputs!C7 | E72: =SOH_Degradation!D3 | F72: =MAX(0, D72-E72) | G72: =MIN(D72, E72) | H72: =IF(E72>0, G72/E72, 0) | I72: =G72*Inputs!C12/100 | J72: =(I72/1000)*(Inputs!C27-Inputs!C28)
A73: 2025-03-13 | B73: 3 | C73: =CurtailmentData!D73 | D73: =C73*Inputs!C7 | E73: =SOH_Degradation!D3 | F73: =MAX(0, D73-E73) | G73: =MIN(D73, E73) | H73: =IF(E73>0, G73/E73, 0) | I73: =G73*Inputs!C12/100 | J73: =(I73/1000)*(Inputs!C27-Inputs!C28)
A74: 2025-03-14 | B74: 3 | C74: =CurtailmentData!D74 | D74: =C74*Inputs!C7 | E74: =SOH_Degradation!D3 | F74: =MAX(0, D74-E74) | G74: =MIN(D74, E74) | H74: =IF(E74>0, G74/E74, 0) | I74: =G74*Inputs!C12/100 | J74: =(I74/1000)*(Inputs!C27-Inputs!C28)
A75: 2025-03-15 | B75: 3 | C75: =CurtailmentData!D75 | D75: =C75*Inputs!C7 | E75: =SOH_Degradation!D3 | F75: =MAX(0, D75-E75) | G75: =MIN(D75, E75) | H75: =IF(E75>0, G75/E75, 0) | I75: =G75*Inputs!C12/100 | J75: =(I75/1000)*(Inputs!C27-Inputs!C28)
A76: 2025-03-16 | B76: 3 | C76: =CurtailmentData!D76 | D76: =C76*Inputs!C7 | E76: =SOH_Degradation!D3 | F76: =MAX(0, D76-E76) | G76: =MIN(D76, E76) | H76: =IF(E76>0, G76/E76, 0) | I76: =G76*Inputs!C12/100 | J76: =(I76/1000)*(Inputs!C27-Inputs!C28)
A77: 2025-03-17 | B77: 3 | C77: =CurtailmentData!D77 | D77: =C77*Inputs!C7 | E77: =SOH_Degradation!D3 | F77: =MAX(0, D77-E77) | G77: =MIN(D77, E77) | H77: =IF(E77>0, G77/E77, 0) | I77: =G77*Inputs!C12/100 | J77: =(I77/1000)*(Inputs!C27-Inputs!C28)
A78: 2025-03-18 | B78: 3 | C78: =CurtailmentData!D78 | D78: =C78*Inputs!C7 | E78: =SOH_Degradation!D3 | F78: =MAX(0, D78-E78) | G78: =MIN(D78, E78) | H78: =IF(E78>0, G78/E78, 0) | I78: =G78*Inputs!C12/100 | J78: =(I78/1000)*(Inputs!C27-Inputs!C28)
A79: 2025-03-19 | B79: 3 | C79: =CurtailmentData!D79 | D79: =C79*Inputs!C7 | E79: =SOH_Degradation!D3 | F79: =MAX(0, D79-E79) | G79: =MIN(D79, E79) | H79: =IF(E79>0, G79/E79, 0) | I79: =G79*Inputs!C12/100 | J79: =(I79/1000)*(Inputs!C27-Inputs!C28)
A80: 2025-03-20 | B80: 3 | C80: =CurtailmentData!D80 | D80: =C80*Inputs!C7 | E80: =SOH_Degradation!D3 | F80: =MAX(0, D80-E80) | G80: =MIN(D80, E80) | H80: =IF(E80>0, G80/E80, 0) | I80: =G80*Inputs!C12/100 | J80: =(I80/1000)*(Inputs!C27-Inputs!C28)
A81: 2025-03-21 | B81: 3 | C81: =CurtailmentData!D81 | D81: =C81*Inputs!C7 | E81: =SOH_Degradation!D3 | F81: =MAX(0, D81-E81) | G81: =MIN(D81, E81) | H81: =IF(E81>0, G81/E81, 0) | I81: =G81*Inputs!C12/100 | J81: =(I81/1000)*(Inputs!C27-Inputs!C28)
A82: 2025-03-22 | B82: 3 | C82: =CurtailmentData!D82 | D82: =C82*Inputs!C7 | E82: =SOH_Degradation!D3 | F82: =MAX(0, D82-E82) | G82: =MIN(D82, E82) | H82: =IF(E82>0, G82/E82, 0) | I82: =G82*Inputs!C12/100 | J82: =(I82/1000)*(Inputs!C27-Inputs!C28)
A83: 2025-03-23 | B83: 3 | C83: =CurtailmentData!D83 | D83: =C83*Inputs!C7 | E83: =SOH_Degradation!D3 | F83: =MAX(0, D83-E83) | G83: =MIN(D83, E83) | H83: =IF(E83>0, G83/E83, 0) | I83: =G83*Inputs!C12/100 | J83: =(I83/1000)*(Inputs!C27-Inputs!C28)
A84: 2025-03-24 | B84: 3 | C84: =CurtailmentData!D84 | D84: =C84*Inputs!C7 | E84: =SOH_Degradation!D3 | F84: =MAX(0, D84-E84) | G84: =MIN(D84, E84) | H84: =IF(E84>0, G84/E84, 0) | I84: =G84*Inputs!C12/100 | J84: =(I84/1000)*(Inputs!C27-Inputs!C28)
A85: 2025-03-25 | B85: 3 | C85: =CurtailmentData!D85 | D85: =C85*Inputs!C7 | E85: =SOH_Degradation!D3 | F85: =MAX(0, D85-E85) | G85: =MIN(D85, E85) | H85: =IF(E85>0, G85/E85, 0) | I85: =G85*Inputs!C12/100 | J85: =(I85/1000)*(Inputs!C27-Inputs!C28)
A86: 2025-03-26 | B86: 3 | C86: =CurtailmentData!D86 | D86: =C86*Inputs!C7 | E86: =SOH_Degradation!D3 | F86: =MAX(0, D86-E86) | G86: =MIN(D86, E86) | H86: =IF(E86>0, G86/E86, 0) | I86: =G86*Inputs!C12/100 | J86: =(I86/1000)*(Inputs!C27-Inputs!C28)
A87: 2025-03-27 | B87: 3 | C87: =CurtailmentData!D87 | D87: =C87*Inputs!C7 | E87: =SOH_Degradation!D3 | F87: =MAX(0, D87-E87) | G87: =MIN(D87, E87) | H87: =IF(E87>0, G87/E87, 0) | I87: =G87*Inputs!C12/100 | J87: =(I87/1000)*(Inputs!C27-Inputs!C28)
A88: 2025-03-28 | B88: 3 | C88: =CurtailmentData!D88 | D88: =C88*Inputs!C7 | E88: =SOH_Degradation!D3 | F88: =MAX(0, D88-E88) | G88: =MIN(D88, E88) | H88: =IF(E88>0, G88/E88, 0) | I88: =G88*Inputs!C12/100 | J88: =(I88/1000)*(Inputs!C27-Inputs!C28)
A89: 2025-03-29 | B89: 3 | C89: =CurtailmentData!D89 | D89: =C89*Inputs!C7 | E89: =SOH_Degradation!D3 | F89: =MAX(0, D89-E89) | G89: =MIN(D89, E89) | H89: =IF(E89>0, G89/E89, 0) | I89: =G89*Inputs!C12/100 | J89: =(I89/1000)*(Inputs!C27-Inputs!C28)
A90: 2025-03-30 | B90: 3 | C90: =CurtailmentData!D90 | D90: =C90*Inputs!C7 | E90: =SOH_Degradation!D3 | F90: =MAX(0, D90-E90) | G90: =MIN(D90, E90) | H90: =IF(E90>0, G90/E90, 0) | I90: =G90*Inputs!C12/100 | J90: =(I90/1000)*(Inputs!C27-Inputs!C28)
A91: 2025-03-31 | B91: 3 | C91: =CurtailmentData!D91 | D91: =C91*Inputs!C7 | E91: =SOH_Degradation!D3 | F91: =MAX(0, D91-E91) | G91: =MIN(D91, E91) | H91: =IF(E91>0, G91/E91, 0) | I91: =G91*Inputs!C12/100 | J91: =(I91/1000)*(Inputs!C27-Inputs!C28)
A92: 2025-04-01 | B92: 4 | C92: =CurtailmentData!D92 | D92: =C92*Inputs!C7 | E92: =SOH_Degradation!D3 | F92: =MAX(0, D92-E92) | G92: =MIN(D92, E92) | H92: =IF(E92>0, G92/E92, 0) | I92: =G92*Inputs!C12/100 | J92: =(I92/1000)*(Inputs!C27-Inputs!C28)
A93: 2025-04-02 | B93: 4 | C93: =CurtailmentData!D93 | D93: =C93*Inputs!C7 | E93: =SOH_Degradation!D3 | F93: =MAX(0, D93-E93) | G93: =MIN(D93, E93) | H93: =IF(E93>0, G93/E93, 0) | I93: =G93*Inputs!C12/100 | J93: =(I93/1000)*(Inputs!C27-Inputs!C28)
A94: 2025-04-03 | B94: 4 | C94: =CurtailmentData!D94 | D94: =C94*Inputs!C7 | E94: =SOH_Degradation!D3 | F94: =MAX(0, D94-E94) | G94: =MIN(D94, E94) | H94: =IF(E94>0, G94/E94, 0) | I94: =G94*Inputs!C12/100 | J94: =(I94/1000)*(Inputs!C27-Inputs!C28)
A95: 2025-04-04 | B95: 4 | C95: =CurtailmentData!D95 | D95: =C95*Inputs!C7 | E95: =SOH_Degradation!D3 | F95: =MAX(0, D95-E95) | G95: =MIN(D95, E95) | H95: =IF(E95>0, G95/E95, 0) | I95: =G95*Inputs!C12/100 | J95: =(I95/1000)*(Inputs!C27-Inputs!C28)
A96: 2025-04-05 | B96: 4 | C96: =CurtailmentData!D96 | D96: =C96*Inputs!C7 | E96: =SOH_Degradation!D3 | F96: =MAX(0, D96-E96) | G96: =MIN(D96, E96) | H96: =IF(E96>0, G96/E96, 0) | I96: =G96*Inputs!C12/100 | J96: =(I96/1000)*(Inputs!C27-Inputs!C28)
A97: 2025-04-06 | B97: 4 | C97: =CurtailmentData!D97 | D97: =C97*Inputs!C7 | E97: =SOH_Degradation!D3 | F97: =MAX(0, D97-E97) | G97: =MIN(D97, E97) | H97: =IF(E97>0, G97/E97, 0) | I97: =G97*Inputs!C12/100 | J97: =(I97/1000)*(Inputs!C27-Inputs!C28)
A98: 2025-04-07 | B98: 4 | C98: =CurtailmentData!D98 | D98: =C98*Inputs!C7 | E98: =SOH_Degradation!D3 | F98: =MAX(0, D98-E98) | G98: =MIN(D98, E98) | H98: =IF(E98>0, G98/E98, 0) | I98: =G98*Inputs!C12/100 | J98: =(I98/1000)*(Inputs!C27-Inputs!C28)
A99: 2025-04-08 | B99: 4 | C99: =CurtailmentData!D99 | D99: =C99*Inputs!C7 | E99: =SOH_Degradation!D3 | F99: =MAX(0, D99-E99) | G99: =MIN(D99, E99) | H99: =IF(E99>0, G99/E99, 0) | I99: =G99*Inputs!C12/100 | J99: =(I99/1000)*(Inputs!C27-Inputs!C28)
A100: 2025-04-09 | B100: 4 | C100: =CurtailmentData!D100 | D100: =C100*Inputs!C7 | E100: =SOH_Degradation!D3 | F100: =MAX(0, D100-E100) | G100: =MIN(D100, E100) | H100: =IF(E100>0, G100/E100, 0) | I100: =G100*Inputs!C12/100 | J100: =(I100/1000)*(Inputs!C27-Inputs!C28)
...

Sheet CashFlow
A1: 15-Year Cash Flow Projection - Data-Validated Model
A2: Year | B2: SOH % | C2: Usable MWh | D2: Captured (MWh) | E2: Cumul Cycles | F2: Discharged (MWh) | G2: Gross Revenue (EUR) | H2: Operating Cost (EUR) | I2: Net Cash Flow (EUR) | J2: Cumulative (EUR) | K2: BESS Fill % | L2: Cycles This Year
A3: 0 | G3: Investment: | I3: =-Inputs!C16 | J3: =I3
A4: 1 | B4: =SOH_Degradation!B3 | C4: =SOH_Degradation!C3 | D4: 3755 | E4: 209 | F4: =D4*Inputs!C12/100 | G4: =F4*(Inputs!C27-Inputs!C28)*(1+Inputs!C29/100)^(A4-1) | H4: =Inputs!C22 | I4: =G4-H4 | J4: =J3+I4 | K4: =D4*1000/(C4*1000*365) | L4: =D4/(Inputs!C9*Inputs!C11/100)
A5: 2 | B5: =SOH_Degradation!B4 | C5: =SOH_Degradation!C4 | D5: 3708.4 | E5: 415 | F5: =D5*Inputs!C12/100 | G5: =F5*(Inputs!C27-Inputs!C28)*(1+Inputs!C29/100)^(A5-1) | H5: =Inputs!C22 | I5: =G5-H5 | J5: =J4+I5 | K5: =D5*1000/(C5*1000*365) | L5: =D5/(Inputs!C9*Inputs!C11/100)
A6: 3 | B6: =SOH_Degradation!B5 | C6: =SOH_Degradation!C5 | D6: 3676.5 | E6: 619 | F6: =D6*Inputs!C12/100 | G6: =F6*(Inputs!C27-Inputs!C28)*(1+Inputs!C29/100)^(A6-1) | H6: =Inputs!C22 | I6: =G6-H6 | J6: =J5+I6 | K6: =D6*1000/(C6*1000*365) | L6: =D6/(Inputs!C9*Inputs!C11/100)
A7: 4 | B7: =SOH_Degradation!B6 | C7: =SOH_Degradation!C6 | D7: 3648.5 | E7: 822 | F7: =D7*Inputs!C12/100 | G7: =F7*(Inputs!C27-Inputs!C28)*(1+Inputs!C29/100)^(A7-1) | H7: =Inputs!C22 | I7: =G7-H7 | J7: =J6+I7 | K7: =D7*1000/(C7*1000*365) | L7: =D7/(Inputs!C9*Inputs!C11/100)
A8: 5 | B8: =SOH_Degradation!B7 | C8: =SOH_Degradation!C7 | D8: 3619.8 | E8: 1023 | F8: =D8*Inputs!C12/100 | G8: =F8*(Inputs!C27-Inputs!C28)*(1+Inputs!C29/100)^(A8-1) | H8: =Inputs!C22 | I8: =G8-H8 | J8: =J7+I8 | K8: =D8*1000/(C8*1000*365) | L8: =D8/(Inputs!C9*Inputs!C11/100)
A9: 6 | B9: =SOH_Degradation!B8 | C9: =SOH_Degradation!C8 | D9: 3592.9 | E9: 1222 | F9: =D9*Inputs!C12/100 | G9: =F9*(Inputs!C27-Inputs!C28)*(1+Inputs!C29/100)^(A9-1) | H9: =Inputs!C23 | I9: =G9-H9 | J9: =J8+I9 | K9: =D9*1000/(C9*1000*365) | L9: =D9/(Inputs!C9*Inputs!C11/100)
A10: 7 | B10: =SOH_Degradation!B9 | C10: =SOH_Degradation!C9 | D10: 3565.2 | E10: 1420 | F10: =D10*Inputs!C12/100 | G10: =F10*(Inputs!C27-Inputs!C28)*(1+Inputs!C29/100)^(A10-1) | H10: =Inputs!C23 | I10: =G10-H10 | J10: =J9+I10 | K10: =D10*1000/(C10*1000*365) | L10: =D10/(Inputs!C9*Inputs!C11/100)
A11: 8 | B11: =SOH_Degradation!B10 | C11: =SOH_Degradation!C10 | D11: 3536.3 | E11: 1617 | F11: =D11*Inputs!C12/100 | G11: =F11*(Inputs!C27-Inputs!C28)*(1+Inputs!C29/100)^(A11-1) | H11: =Inputs!C23 | I11: =G11-H11 | J11: =J10+I11 | K11: =D11*1000/(C11*1000*365) | L11: =D11/(Inputs!C9*Inputs!C11/100)
A12: 9 | B12: =SOH_Degradation!B11 | C12: =SOH_Degradation!C11 | D12: 3506.2 | E12: 1812 | F12: =D12*Inputs!C12/100 | G12: =F12*(Inputs!C27-Inputs!C28)*(1+Inputs!C29/100)^(A12-1) | H12: =Inputs!C23 | I12: =G12-H12 | J12: =J11+I12 | K12: =D12*1000/(C12*1000*365) | L12: =D12/(Inputs!C9*Inputs!C11/100)
A13: 10 | B13: =SOH_Degradation!B12 | C13: =SOH_Degradation!C12 | D13: 3475.3 | E13: 2005 | F13: =D13*Inputs!C12/100 | G13: =F13*(Inputs!C27-Inputs!C28)*(1+Inputs!C29/100)^(A13-1) | H13: =Inputs!C23 | I13: =G13-H13 | J13: =J12+I13 | K13: =D13*1000/(C13*1000*365) | L13: =D13/(Inputs!C9*Inputs!C11/100)
A14: 11 | B14: =SOH_Degradation!B13 | C14: =SOH_Degradation!C13 | D14: 3448.1 | E14: 2196 | F14: =D14*Inputs!C12/100 | G14: =F14*(Inputs!C27-Inputs!C28)*(1+Inputs!C29/100)^(A14-1) | H14: =Inputs!C24 | I14: =G14-H14 | J14: =J13+I14 | K14: =D14*1000/(C14*1000*365) | L14: =D14/(Inputs!C9*Inputs!C11/100)
A15: 12 | B15: =SOH_Degradation!B14 | C15: =SOH_Degradation!C14 | D15: 3420.4 | E15: 2386 | F15: =D15*Inputs!C12/100 | G15: =F15*(Inputs!C27-Inputs!C28)*(1+Inputs!C29/100)^(A15-1) | H15: =Inputs!C24 | I15: =G15-H15 | J15: =J14+I15 | K15: =D15*1000/(C15*1000*365) | L15: =D15/(Inputs!C9*Inputs!C11/100)
A16: 13 | B16: =SOH_Degradation!B15 | C16: =SOH_Degradation!C15 | D16: 3391.8 | E16: 2575 | F16: =D16*Inputs!C12/100 | G16: =F16*(Inputs!C27-Inputs!C28)*(1+Inputs!C29/100)^(A16-1) | H16: =Inputs!C24 | I16: =G16-H16 | J16: =J15+I16 | K16: =D16*1000/(C16*1000*365) | L16: =D16/(Inputs!C9*Inputs!C11/100)
A17: 14 | B17: =SOH_Degradation!B16 | C17: =SOH_Degradation!C16 | D17: 3362.7 | E17: 2761 | F17: =D17*Inputs!C12/100 | G17: =F17*(Inputs!C27-Inputs!C28)*(1+Inputs!C29/100)^(A17-1) | H17: =Inputs!C24 | I17: =G17-H17 | J17: =J16+I17 | K17: =D17*1000/(C17*1000*365) | L17: =D17/(Inputs!C9*Inputs!C11/100)
A18: 15 | B18: =SOH_Degradation!B17 | C18: =SOH_Degradation!C17 | D18: 3333 | E18: 2947 | F18: =D18*Inputs!C12/100 | G18: =F18*(Inputs!C27-Inputs!C28)*(1+Inputs!C29/100)^(A18-1) | H18: =Inputs!C24 | I18: =G18-H18 | J18: =J17+I18 | K18: =D18*1000/(C18*1000*365) | L18: =D18/(Inputs!C9*Inputs!C11/100)
A20: TOTALS | D20: =SUM(D4:D18) | F20: =SUM(F4:F18) | G20: =SUM(G4:G18) | H20: =SUM(H4:H18) | I20: =SUM(I4:I18) | L20: =SUM(L4:L18)
