Workbook

Sheet Summary
A1: SHARK FUND
A2: Shapiro & Arkadiusz Renewable Hybrid Assets in Kypros
A3: Financial Plan — Hybrid PV + BESS Investments in Cyprus
A5: FUND OVERVIEW
A6: Target Equity Investment (EUR) | B6: ='Type A - 10MWp'!$B$12*'Type A - 10MWp'!$B$16+'Type B - 5MWp'!$B$12*'Type B - 5MWp'!$B$16+'Type C - 3MWp'!$B$12*'Type C - 3MWp'!$B$16 -> 50074389
A7: Total Debt (EUR) | B7: ='Type A - 10MWp'!$B$13*'Type A - 10MWp'!$B$16+'Type B - 5MWp'!$B$13*'Type B - 5MWp'!$B$16+'Type C - 3MWp'!$B$13*'Type C - 3MWp'!$B$16 -> 22578534
A8: Total CAPEX (EUR) | B8: =B6+B7 -> 72652923
A9: Project Lifetime | B9: =Assumptions!$B$7 -> 20
A10: PV Financing | B10: 100% Equity
A11: BESS Financing | B11: 100% Debt (LTV)
A12: Loan Interest Rate | B12: =Assumptions!$B$38 -> 0.05
A13: Loan Term (years) | B13: =Assumptions!$B$39 -> 15
A14: Corporate Tax Rate | B14: =Assumptions!$B$35 -> 0.125
A16: PORTFOLIO COMPOSITION
A17: Asset Type | B17: Size | C17: Units | D17: Equity/Unit | E17: Debt/Unit | F17: Total Equity | G17: Total Debt | H17: Total CAPEX
A18: Type A: Large Hybrid Park | B18: 10 MWp + 40 MWh | C18: ='Type A - 10MWp'!$B$16 -> 3 | D18: ='Type A - 10MWp'!$B$12 -> 8600770 | E18: ='Type A - 10MWp'!$B$13 -> 3740967 | F18: ='Type A - 10MWp'!$B$12*'Type A - 10MWp'!$B$16 -> 25802310 | G18: ='Type A - 10MWp'!$B$13*'Type A - 10MWp'!$B$16 -> 11222901 | H18: =('Type A - 10MWp'!$B$12+'Type A - 10MWp'!$B$13)*'Type A - 10MWp'!$B$16 -> 37025211
A19: Type B: Medium Hybrid Park | B19: 5 MWp + 20 MWh | C19: ='Type B - 5MWp'!$B$16 -> 3 | D19: ='Type B - 5MWp'!$B$12 -> 4450385 | E19: ='Type B - 5MWp'!$B$13 -> 1919179 | F19: ='Type B - 5MWp'!$B$12*'Type B - 5MWp'!$B$16 -> 13351155 | G19: ='Type B - 5MWp'!$B$13*'Type B - 5MWp'!$B$16 -> 5757537 | H19: =('Type B - 5MWp'!$B$12+'Type B - 5MWp'!$B$13)*'Type B - 5MWp'!$B$16 -> 19108692
A20: Type C: Small Hybrid Park | B20: 3 MWp + 12 MWh | C20: ='Type C - 3MWp'!$B$16 -> 4 | D20: ='Type C - 3MWp'!$B$12 -> 2730231 | E20: ='Type C - 3MWp'!$B$13 -> 1399524 | F20: ='Type C - 3MWp'!$B$12*'Type C - 3MWp'!$B$16 -> 10920924 | G20: ='Type C - 3MWp'!$B$13*'Type C - 3MWp'!$B$16 -> 5598096 | H20: =('Type C - 3MWp'!$B$12+'Type C - 3MWp'!$B$13)*'Type C - 3MWp'!$B$16 -> 16519020
A21: TOTAL PORTFOLIO | C21: =SUM(C18:C20) -> 10 | F21: =SUM(F18:F20) -> 50074389 | G21: =SUM(G18:G20) -> 22578534 | H21: =SUM(H18:H20) -> 72652923
A23: FUND RETURNS BY SCENARIO
A24: Metric | B24: Low (EUR 110/MWh) | C24: Base (EUR 150/MWh) | D24: High (EUR 175/MWh)
A25: Fund Equity IRR | B25: ='Fund Portfolio'!B$36 -> 0.15343254 | C25: ='Fund Portfolio'!C$36 -> 0.19992856 | D25: ='Fund Portfolio'!D$36 -> 0.22836614
A26: Fund Equity NPV (@ 8%) | B26: ='Fund Portfolio'!B$37 -> 28742746 | C26: ='Fund Portfolio'!C$37 -> 48115675 | D26: ='Fund Portfolio'!D$37 -> 60223755
A27: Fund Equity Multiple | B27: ='Fund Portfolio'!B$38 -> 3.1665199 | C27: ='Fund Portfolio'!C$38 -> 3.9251737 | D27: ='Fund Portfolio'!D$38 -> 4.3993322
A28: Fund Total FCFE | B28: ='Fund Portfolio'!B$39 -> 1.5856155e+08 | C28: ='Fund Portfolio'!C$39 -> 1.9655067e+08 | D28: ='Fund Portfolio'!D$39 -> 2.2029387e+08

Sheet Assumptions
A1: SHARK Fund — Assumptions & Inputs
A2: Change the blue-highlighted cells to update the entire model automatically.
A4: GENERAL ASSUMPTIONS
A5: RTB Acquisition Cost (EUR/MWp) | B5: 350000 | C5: Ready-to-build permit cost
A6: BESS Duration (hours) | B6: 4 | C6: 4-hour BESS sizing
A7: Project Lifetime (years) | B7: 20 | C7: Operational years
A9: PV ASSUMPTIONS
A10: PV Annual Yield (MWh/MWp) | B10: 1750 | C10: Cyprus fixed-tilt
A11: PV Degradation — Year 1 | B11: 0.025 | C11: 2.5% first year
A12: PV Degradation — Year 2 onwards | B12: 0.005 | C12: 0.5% per year
A13: PV Curtailment Rate | B13: 0.5 | C13: 50% of PV output curtailed / used by BESS
A14: PV Direct Sale Price (EUR/MWh) | B14: 160 | C14: PPA or market rate
A15: GoO Price (EUR/MWh) | B15: 1 | C15: Guarantees of Origin
A16: PV OPEX — all-in (EUR/MWp/year) | B16: 15000 | C16: O&M, insurance, admin, CERA PV, rent
A18: BESS ASSUMPTIONS
A19: BESS Round-Trip Efficiency (RTE) | B19: 0.863 | C19: DC RTE incl. losses
A20: BESS Initial State of Health | B20: 0.985 | C20: BOL capacity
A21: BESS Annual SOH Degradation | B21: 0.0135 | C21: Linear approx.
A22: BESS Depth of Discharge (DoD) | B22: 0.9
A23: BESS System Availability | B23: 0.98 | C23: Warranted
A24: BESS Cycles Per Day | B24: 1
A25: BESS Grid Purchase Price (EUR/MWh) | B25: 50 | C25: Cost to charge from grid
A26: BESS O&M (EUR/MWh installed/yr) | B26: 1750 | C26: Includes CERA, grounds, monitoring
A27: BESS Management Fee (EUR/MWh installed/yr) | B27: 1500 | C27: Asset management
A28: CERA BESS License (EUR/MW/yr) | B28: 700
A29: BESS Grounds Maintenance (EUR/site/yr) | B29: 4000 | C29: Security, landscaping
A30: Warranty Extension Yr 6-10 (EUR/MWh/yr) | B30: 1800
A31: Warranty Extension Yr 11-15 (EUR/MWh/yr) | B31: 2100
A32: Warranty Extension Yr 16-20 (EUR/MWh/yr) | B32: 2450
A34: FINANCIAL ASSUMPTIONS
A35: Corporate Tax Rate (Cyprus) | B35: 0.125 | C35: 12.5%
A36: Annual OPEX Inflation | B36: 0.01 | C36: 1%
A37: Discount Rate (for NPV) | B37: 0.08 | C37: 8% WACC
A38: Loan Interest Rate | B38: 0.05 | C38: Cyprus commercial
A39: Loan Term (years) | B39: 15 | C39: Senior debt
A41: REVENUE SCENARIOS ASSUMPTIONS
A42: BESS Arbitrage Price — Low (EUR/MWh) | B42: 110 | C42: Conservative
A43: BESS Arbitrage Price — Base (EUR/MWh) | B43: 150 | C43: Blended average
A44: BESS Arbitrage Price — High (EUR/MWh) | B44: 175 | C44: Strong prediction
A46: EPC SELF-COST REFERENCE (from Solarfarms.cy model)
A47: Asset | B47: PV MWp | C47: BESS MWh | D47: PV EPC (EUR) | E47: BESS (EUR) | F47: RTB (EUR) | G47: Total CAPEX
A48: Type A: Large Hybrid Park | B48: 10 | C48: 40 | D48: 5100770 | E48: 3740967 | F48: 3500000 | G48: 12341737
A49: Type B: Medium Hybrid Park | B49: 5 | C49: 20 | D49: 2700385 | E49: 1919179 | F49: 1750000 | G49: 6369564
A50: Type C: Small Hybrid Park | B50: 3 | C50: 12 | D50: 1680231 | E50: 1399524 | F50: 1050000 | G50: 4129755

Sheet Type A - 10MWp
A1: SHARK — Type A: Large Hybrid Park
A2: 10 MWp + 40 MWh Hybrid Park — Per-Unit Financial Model
A4: CAPEX & FINANCING
A5: PV Capacity (MWp) | B5: 10
A6: BESS Capacity (MWh) | B6: 40
A7: BESS Power (MW) | B7: =B6/Assumptions!$B$6 -> 10
A8: PV EPC Self-Cost (EUR) | B8: 5100770
A9: RTB Acquisition (EUR) | B9: =B5*Assumptions!$B$5 -> 3500000
A10: BESS Installed Cost (EUR) | B10: 3740967
A11: Total CAPEX (EUR) | B11: =B8+B9+B10 -> 12341737
A12: Equity (PV + RTB) | B12: =B8+B9 -> 8600770
A13: Debt (BESS — 100% LTV) | B13: =B10 -> 3740967
A14: Annual Debt Service | B14: =-PMT(Assumptions!$B$38,Assumptions!$B$39,B13) -> 360413.32
A15: Annual Depreciation (SL) | B15: =B11/Assumptions!$B$7 -> 617086.85
A16: Units in Portfolio | B16: 3
A18: ANNUAL PRODUCTION & TECHNICAL DATA
A19: Year # | C19: 1 | D19: 2 | E19: 3 | F19: 4 | G19: 5 | H19: 6 | I19: 7 | J19: 8 | K19: 9 | L19: 10 | M19: 11 | N19: 12 | O19: 13 | P19: 14 | Q19: 15 | R19: 16 | S19: 17 | T19: 18 | U19: 19 | V19: 20 | W19: Total/Avg
A20: Calendar | C20: 2026 | D20: 2027 | E20: 2028 | F20: 2029 | G20: 2030 | H20: 2031 | I20: 2032 | J20: 2033 | K20: 2034 | L20: 2035 | M20: 2036 | N20: 2037 | O20: 2038 | P20: 2039 | Q20: 2040 | R20: 2041 | S20: 2042 | T20: 2043 | U20: 2044 | V20: 2045
A21: PV Production (MWh) | C21: =IF(C$19=1,$B$5*Assumptions!$B$10*(1-Assumptions!$B$11),$B$5*Assumptions!$B$10*(1-Assumptions!$B$11)*(1-Assumptions!$B$12)^(C$19-1)) -> 17062.5 | D21: =IF(D$19=1,$B$5*Assumptions!$B$10*(1-Assumptions!$B$11),$B$5*Assumptions!$B$10*(1-Assumptions!$B$11)*(1-Assumptions!$B$12)^(D$19-1)) -> 16977.188 | E21: =IF(E$19=1,$B$5*Assumptions!$B$10*(1-Assumptions!$B$11),$B$5*Assumptions!$B$10*(1-Assumptions!$B$11)*(1-Assumptions!$B$12)^(E$19-1)) -> 16892.302 | F21: =IF(F$19=1,$B$5*Assumptions!$B$10*(1-Assumptions!$B$11),$B$5*Assumptions!$B$10*(1-Assumptions!$B$11)*(1-Assumptions!$B$12)^(F$19-1)) -> 16807.84 | G21: =IF(G$19=1,$B$5*Assumptions!$B$10*(1-Assumptions!$B$11),$B$5*Assumptions!$B$10*(1-Assumptions!$B$11)*(1-Assumptions!$B$12)^(G$19-1)) -> 16723.801 | H21: =IF(H$19=1,$B$5*Assumptions!$B$10*(1-Assumptions!$B$11),$B$5*Assumptions!$B$10*(1-Assumptions!$B$11)*(1-Assumptions!$B$12)^(H$19-1)) -> 16640.182 | I21: =IF(I$19=1,$B$5*Assumptions!$B$10*(1-Assumptions!$B$11),$B$5*Assumptions!$B$10*(1-Assumptions!$B$11)*(1-Assumptions!$B$12)^(I$19-1)) -> 16556.981 | J21: =IF(J$19=1,$B$5*Assumptions!$B$10*(1-Assumptions!$B$11),$B$5*Assumptions!$B$10*(1-Assumptions!$B$11)*(1-Assumptions!$B$12)^(J$19-1)) -> 16474.196 | ... V21: =IF(V$19=1,$B$5*Assumptions!$B$10*(1-Assumptions!$B$11),$B$5*Assumptions!$B$10*(1-Assumptions!$B$11)*(1-Assumptions!$B$12)^(V$19-1)) -> 15512.479 | W21: =SUM(C$21:V$21) -> 325516.74
A22: PV Direct Sales (MWh) | C22: =C$21*(1-Assumptions!$B$13) -> 8531.25 | D22: =D$21*(1-Assumptions!$B$13) -> 8488.5938 | E22: =E$21*(1-Assumptions!$B$13) -> 8446.1508 | F22: =F$21*(1-Assumptions!$B$13) -> 8403.92 | G22: =G$21*(1-Assumptions!$B$13) -> 8361.9004 | H22: =H$21*(1-Assumptions!$B$13) -> 8320.0909 | I22: =I$21*(1-Assumptions!$B$13) -> 8278.4905 | J22: =J$21*(1-Assumptions!$B$13) -> 8237.098 | ... V22: =V$21*(1-Assumptions!$B$13) -> 7756.2394 | W22: =SUM(C$22:V$22) -> 162758.37
A23: PV Curtailed → BESS (MWh) | C23: =C$21*Assumptions!$B$13 -> 8531.25 | D23: =D$21*Assumptions!$B$13 -> 8488.5938 | E23: =E$21*Assumptions!$B$13 -> 8446.1508 | F23: =F$21*Assumptions!$B$13 -> 8403.92 | G23: =G$21*Assumptions!$B$13 -> 8361.9004 | H23: =H$21*Assumptions!$B$13 -> 8320.0909 | I23: =I$21*Assumptions!$B$13 -> 8278.4905 | J23: =J$21*Assumptions!$B$13 -> 8237.098 | ... V23: =V$21*Assumptions!$B$13 -> 7756.2394 | W23: =SUM(C$23:V$23) -> 162758.37
A24: BESS State of Health (%) | C24: =MAX(0.6,Assumptions!$B$20-Assumptions!$B$21*(C$19-1)) -> 0.985 | D24: =MAX(0.6,Assumptions!$B$20-Assumptions!$B$21*(D$19-1)) -> 0.9715 | E24: =MAX(0.6,Assumptions!$B$20-Assumptions!$B$21*(E$19-1)) -> 0.958 | F24: =MAX(0.6,Assumptions!$B$20-Assumptions!$B$21*(F$19-1)) -> 0.9445 | G24: =MAX(0.6,Assumptions!$B$20-Assumptions!$B$21*(G$19-1)) -> 0.931 | H24: =MAX(0.6,Assumptions!$B$20-Assumptions!$B$21*(H$19-1)) -> 0.9175 | I24: =MAX(0.6,Assumptions!$B$20-Assumptions!$B$21*(I$19-1)) -> 0.904 | J24: =MAX(0.6,Assumptions!$B$20-Assumptions!$B$21*(J$19-1)) -> 0.8905 | ... V24: =MAX(0.6,Assumptions!$B$20-Assumptions!$B$21*(V$19-1)) -> 0.7285 | W24: =AVERAGE(C$24:V$24) -> 0.85675
A25: BESS Sellable Energy (MWh) | C25: =$B$6*C$24*Assumptions!$B$22*Assumptions!$B$19*Assumptions!$B$24*365*Assumptions!$B$23 -> 10946.328 | D25: =$B$6*D$24*Assumptions!$B$22*Assumptions!$B$19*Assumptions!$B$24*365*Assumptions!$B$23 -> 10796.302 | E25: =$B$6*E$24*Assumptions!$B$22*Assumptions!$B$19*Assumptions!$B$24*365*Assumptions!$B$23 -> 10646.277 | F25: =$B$6*F$24*Assumptions!$B$22*Assumptions!$B$19*Assumptions!$B$24*365*Assumptions!$B$23 -> 10496.251 | G25: =$B$6*G$24*Assumptions!$B$22*Assumptions!$B$19*Assumptions!$B$24*365*Assumptions!$B$23 -> 10346.225 | H25: =$B$6*H$24*Assumptions!$B$22*Assumptions!$B$19*Assumptions!$B$24*365*Assumptions!$B$23 -> 10196.199 | I25: =$B$6*I$24*Assumptions!$B$22*Assumptions!$B$19*Assumptions!$B$24*365*Assumptions!$B$23 -> 10046.173 | J25: =$B$6*J$24*Assumptions!$B$22*Assumptions!$B$19*Assumptions!$B$24*365*Assumptions!$B$23 -> 9896.1475 | ... V25: =$B$6*V$24*Assumptions!$B$22*Assumptions!$B$19*Assumptions!$B$24*365*Assumptions!$B$23 -> 8095.8377 | W25: =SUM(C$25:V$25) -> 190421.66
A26: BESS Charging Needed (MWh) | C26: =$B$6*C$24*Assumptions!$B$22*Assumptions!$B$24*365*Assumptions!$B$23 -> 12684.042 | D26: =$B$6*D$24*Assumptions!$B$22*Assumptions!$B$24*365*Assumptions!$B$23 -> 12510.2 | E26: =$B$6*E$24*Assumptions!$B$22*Assumptions!$B$24*365*Assumptions!$B$23 -> 12336.358 | F26: =$B$6*F$24*Assumptions!$B$22*Assumptions!$B$24*365*Assumptions!$B$23 -> 12162.515 | G26: =$B$6*G$24*Assumptions!$B$22*Assumptions!$B$24*365*Assumptions!$B$23 -> 11988.673 | H26: =$B$6*H$24*Assumptions!$B$22*Assumptions!$B$24*365*Assumptions!$B$23 -> 11814.831 | I26: =$B$6*I$24*Assumptions!$B$22*Assumptions!$B$24*365*Assumptions!$B$23 -> 11640.989 | J26: =$B$6*J$24*Assumptions!$B$22*Assumptions!$B$24*365*Assumptions!$B$23 -> 11467.147 | ... V26: =$B$6*V$24*Assumptions!$B$22*Assumptions!$B$24*365*Assumptions!$B$23 -> 9381.0402 | W26: =SUM(C$26:V$26) -> 220650.82
A27: Grid Purchases for BESS (MWh) | C27: =MAX(0,C$26-C$23) -> 4152.792 | D27: =MAX(0,D$26-D$23) -> 4021.606 | E27: =MAX(0,E$26-E$23) -> 3890.2068 | F27: =MAX(0,F$26-F$23) -> 3758.5954 | G27: =MAX(0,G$26-G$23) -> 3626.7728 | H27: =MAX(0,H$26-H$23) -> 3494.7401 | I27: =MAX(0,I$26-I$23) -> 3362.4983 | J27: =MAX(0,J$26-J$23) -> 3230.0486 | ... V27: =MAX(0,V$26-V$23) -> 1624.8008 | W27: =SUM(C$27:V$27) -> 57892.454
A29: SCENARIO: LOW CASE (EUR 110/MWh)
A30: PV Direct Revenue | C30: =C$22*Assumptions!$B$14 -> 1365000 | D30: =D$22*Assumptions!$B$14 -> 1358175 | E30: =E$22*Assumptions!$B$14 -> 1351384.1 | F30: =F$22*Assumptions!$B$14 -> 1344627.2 | G30: =G$22*Assumptions!$B$14 -> 1337904.1 | H30: =H$22*Assumptions!$B$14 -> 1331214.5 | I30: =I$22*Assumptions!$B$14 -> 1324558.5 | J30: =J$22*Assumptions!$B$14 -> 1317935.7 | ... V30: =V$22*Assumptions!$B$14 -> 1240998.3 | W30: =SUM(C$30:V$30) -> 26041339
A31: GoO Revenue | C31: =C$21*Assumptions!$B$15 -> 17062.5 | D31: =D$21*Assumptions!$B$15 -> 16977.188 | E31: =E$21*Assumptions!$B$15 -> 16892.302 | F31: =F$21*Assumptions!$B$15 -> 16807.84 | G31: =G$21*Assumptions!$B$15 -> 16723.801 | H31: =H$21*Assumptions!$B$15 -> 16640.182 | I31: =I$21*Assumptions!$B$15 -> 16556.981 | J31: =J$21*Assumptions!$B$15 -> 16474.196 | ... V31: =V$21*Assumptions!$B$15 -> 15512.479 | W31: =SUM(C$31:V$31) -> 325516.74
A32: BESS Arbitrage Revenue | C32: =C$25*Assumptions!$B$42 -> 1204096.1 | D32: =D$25*Assumptions!$B$42 -> 1187593.3 | E32: =E$25*Assumptions!$B$42 -> 1171090.4 | F32: =F$25*Assumptions!$B$42 -> 1154587.6 | G32: =G$25*Assumptions!$B$42 -> 1138084.7 | H32: =H$25*Assumptions!$B$42 -> 1121581.9 | I32: =I$25*Assumptions!$B$42 -> 1105079.1 | J32: =J$25*Assumptions!$B$42 -> 1088576.2 | ... V32: =V$25*Assumptions!$B$42 -> 890542.15 | W32: =SUM(C$32:V$32) -> 20946383
A33: Total Revenue | C33: =C$30+C$31+C$32 -> 2586158.6 | D33: =D$30+D$31+D$32 -> 2562745.5 | E33: =E$30+E$31+E$32 -> 2539366.9 | F33: =F$30+F$31+F$32 -> 2516022.6 | G33: =G$30+G$31+G$32 -> 2492712.6 | H33: =H$30+H$31+H$32 -> 2469436.6 | I33: =I$30+I$31+I$32 -> 2446194.5 | J33: =J$30+J$31+J$32 -> 2422986.1 | ... V33: =V$30+V$31+V$32 -> 2147052.9 | W33: =SUM(C$33:V$33) -> 47313238
A34: Energy Purchase Cost | C34: =C$27*Assumptions!$B$25*(1+Assumptions!$B$36)^(C$19-1) -> 207639.6 | D34: =D$27*Assumptions!$B$25*(1+Assumptions!$B$36)^(D$19-1) -> 203091.11 | E34: =E$27*Assumptions!$B$25*(1+Assumptions!$B$36)^(E$19-1) -> 198420 | F34: =F$27*Assumptions!$B$25*(1+Assumptions!$B$36)^(F$19-1) -> 193624.23 | G34: =G$27*Assumptions!$B$25*(1+Assumptions!$B$36)^(G$19-1) -> 188701.71 | H34: =H$27*Assumptions!$B$25*(1+Assumptions!$B$36)^(H$19-1) -> 183650.35 | I34: =I$27*Assumptions!$B$25*(1+Assumptions!$B$36)^(I$19-1) -> 178467.99 | J34: =J$27*Assumptions!$B$25*(1+Assumptions!$B$36)^(J$19-1) -> 173152.46 | ... V34: =V$27*Assumptions!$B$25*(1+Assumptions!$B$36)^(V$19-1) -> 98146.822 | W34: =SUM(C$34:V$34) -> 3138396.7
A35: PV OPEX | C35: =$B$5*Assumptions!$B$16*(1+Assumptions!$B$36)^(C$19-1) -> 150000 | D35: =$B$5*Assumptions!$B$16*(1+Assumptions!$B$36)^(D$19-1) -> 151500 | E35: =$B$5*Assumptions!$B$16*(1+Assumptions!$B$36)^(E$19-1) -> 153015 | F35: =$B$5*Assumptions!$B$16*(1+Assumptions!$B$36)^(F$19-1) -> 154545.15 | G35: =$B$5*Assumptions!$B$16*(1+Assumptions!$B$36)^(G$19-1) -> 156090.6 | H35: =$B$5*Assumptions!$B$16*(1+Assumptions!$B$36)^(H$19-1) -> 157651.51 | I35: =$B$5*Assumptions!$B$16*(1+Assumptions!$B$36)^(I$19-1) -> 159228.02 | J35: =$B$5*Assumptions!$B$16*(1+Assumptions!$B$36)^(J$19-1) -> 160820.3 | ... V35: =$B$5*Assumptions!$B$16*(1+Assumptions!$B$36)^(V$19-1) -> 181216.34 | W35: =SUM(C$35:V$35) -> 3302850.6
A36: BESS OPEX (O&M+Mgmt+CERA+Grounds) | C36: =($B$6*Assumptions!$B$26+$B$6*Assumptions!$B$27+$B$7*Assumptions!$B$28+Assumptions!$B$29)*(1+Assumptions!$B$36)^(C$19-1) -> 141000 | D36: =($B$6*Assumptions!$B$26+$B$6*Assumptions!$B$27+$B$7*Assumptions!$B$28+Assumptions!$B$29)*(1+Assumptions!$B$36)^(D$19-1) -> 142410 | E36: =($B$6*Assumptions!$B$26+$B$6*Assumptions!$B$27+$B$7*Assumptions!$B$28+Assumptions!$B$29)*(1+Assumptions!$B$36)^(E$19-1) -> 143834.1 | F36: =($B$6*Assumptions!$B$26+$B$6*Assumptions!$B$27+$B$7*Assumptions!$B$28+Assumptions!$B$29)*(1+Assumptions!$B$36)^(F$19-1) -> 145272.44 | G36: =($B$6*Assumptions!$B$26+$B$6*Assumptions!$B$27+$B$7*Assumptions!$B$28+Assumptions!$B$29)*(1+Assumptions!$B$36)^(G$19-1) -> 146725.17 | H36: =($B$6*Assumptions!$B$26+$B$6*Assumptions!$B$27+$B$7*Assumptions!$B$28+Assumptions!$B$29)*(1+Assumptions!$B$36)^(H$19-1) -> 148192.42 | I36: =($B$6*Assumptions!$B$26+$B$6*Assumptions!$B$27+$B$7*Assumptions!$B$28+Assumptions!$B$29)*(1+Assumptions!$B$36)^(I$19-1) -> 149674.34 | J36: =($B$6*Assumptions!$B$26+$B$6*Assumptions!$B$27+$B$7*Assumptions!$B$28+Assumptions!$B$29)*(1+Assumptions!$B$36)^(J$19-1) -> 151171.08 | ... V36: =($B$6*Assumptions!$B$26+$B$6*Assumptions!$B$27+$B$7*Assumptions!$B$28+Assumptions!$B$29)*(1+Assumptions!$B$36)^(V$19-1) -> 170343.36 | W36: =SUM(C$36:V$36) -> 3104679.6
A37: BESS Warranty Extension | C37: =IF(C$19<=5,0,IF(C$19<=10,Assumptions!$B$30,IF(C$19<=15,Assumptions!$B$31,Assumptions!$B$32)))*$B$6*(1+Assumptions!$B$36)^(C$19-1) -> 0 | D37: =IF(D$19<=5,0,IF(D$19<=10,Assumptions!$B$30,IF(D$19<=15,Assumptions!$B$31,Assumptions!$B$32)))*$B$6*(1+Assumptions!$B$36)^(D$19-1) -> 0 | E37: =IF(E$19<=5,0,IF(E$19<=10,Assumptions!$B$30,IF(E$19<=15,Assumptions!$B$31,Assumptions!$B$32)))*$B$6*(1+Assumptions!$B$36)^(E$19-1) -> 0 | F37: =IF(F$19<=5,0,IF(F$19<=10,Assumptions!$B$30,IF(F$19<=15,Assumptions!$B$31,Assumptions!$B$32)))*$B$6*(1+Assumptions!$B$36)^(F$19-1) -> 0 | G37: =IF(G$19<=5,0,IF(G$19<=10,Assumptions!$B$30,IF(G$19<=15,Assumptions!$B$31,Assumptions!$B$32)))*$B$6*(1+Assumptions!$B$36)^(G$19-1) -> 0 | H37: =IF(H$19<=5,0,IF(H$19<=10,Assumptions!$B$30,IF(H$19<=15,Assumptions!$B$31,Assumptions!$B$32)))*$B$6*(1+Assumptions!$B$36)^(H$19-1) -> 75672.724 | I37: =IF(I$19<=5,0,IF(I$19<=10,Assumptions!$B$30,IF(I$19<=15,Assumptions!$B$31,Assumptions!$B$32)))*$B$6*(1+Assumptions!$B$36)^(I$19-1) -> 76429.451 | J37: =IF(J$19<=5,0,IF(J$19<=10,Assumptions!$B$30,IF(J$19<=15,Assumptions!$B$31,Assumptions!$B$32)))*$B$6*(1+Assumptions!$B$36)^(J$19-1) -> 77193.745 | ... V37: =IF(V$19<=5,0,IF(V$19<=10,Assumptions!$B$30,IF(V$19<=15,Assumptions!$B$31,Assumptions!$B$32)))*$B$6*(1+Assumptions!$B$36)^(V$19-1) -> 118394.68 | W37: =SUM(C$37:V$37) -> 1439686.9
A38: Total Operating Costs | C38: =C$34+C$35+C$36+C$37 -> 498639.6 | D38: =D$34+D$35+D$36+D$37 -> 497001.11 | E38: =E$34+E$35+E$36+E$37 -> 495269.1 | F38: =F$34+F$35+F$36+F$37 -> 493441.82 | G38: =G$34+G$35+G$36+G$37 -> 491517.48 | H38: =H$34+H$35+H$36+H$37 -> 565167 | I38: =I$34+I$35+I$36+I$37 -> 563799.8 | J38: =J$34+J$35+J$36+J$37 -> 562337.6 | ... V38: =V$34+V$35+V$36+V$37 -> 568101.2 | W38: =SUM(C$38:V$38) -> 10985614
A39: EBITDA | C39: =C$33-C$38 -> 2087519 | D39: =D$33-D$38 -> 2065744.3 | E39: =E$33-E$38 -> 2044097.8 | F39: =F$33-F$38 -> 2022580.8 | G39: =G$33-G$38 -> 2001195.1 | H39: =H$33-H$38 -> 1904269.6 | I39: =I$33-I$38 -> 1882394.7 | J39: =J$33-J$38 -> 1860648.5 | ... V39: =V$33-V$38 -> 1578951.7 | W39: =SUM(C$39:V$39) -> 36327624
A40: Depreciation | C40: =$B$15 -> 617086.85 | D40: =$B$15 -> 617086.85 | E40: =$B$15 -> 617086.85 | F40: =$B$15 -> 617086.85 | G40: =$B$15 -> 617086.85 | H40: =$B$15 -> 617086.85 | I40: =$B$15 -> 617086.85 | J40: =$B$15 -> 617086.85 | ... V40: =$B$15 -> 617086.85 | W40: =SUM(C$40:V$40) -> 12341737
A41: Interest Expense | C41: =IF(C$19<=Assumptions!$B$39,-IPMT(Assumptions!$B$38,C$19,Assumptions!$B$39,$B$13),0) -> 187048.35 | D41: =IF(D$19<=Assumptions!$B$39,-IPMT(Assumptions!$B$38,D$19,Assumptions!$B$39,$B$13),0) -> 178380.1 | E41: =IF(E$19<=Assumptions!$B$39,-IPMT(Assumptions!$B$38,E$19,Assumptions!$B$39,$B$13),0) -> 169278.44 | F41: =IF(F$19<=Assumptions!$B$39,-IPMT(Assumptions!$B$38,F$19,Assumptions!$B$39,$B$13),0) -> 159721.7 | G41: =IF(G$19<=Assumptions!$B$39,-IPMT(Assumptions!$B$38,G$19,Assumptions!$B$39,$B$13),0) -> 149687.12 | H41: =IF(H$19<=Assumptions!$B$39,-IPMT(Assumptions!$B$38,H$19,Assumptions!$B$39,$B$13),0) -> 139150.81 | I41: =IF(I$19<=Assumptions!$B$39,-IPMT(Assumptions!$B$38,I$19,Assumptions!$B$39,$B$13),0) -> 128087.68 | J41: =IF(J$19<=Assumptions!$B$39,-IPMT(Assumptions!$B$38,J$19,Assumptions!$B$39,$B$13),0) -> 116471.4 | ... V41: =IF(V$19<=Assumptions!$B$39,-IPMT(Assumptions!$B$38,V$19,Assumptions!$B$39,$B$13),0) -> 0 | W41: =SUM(C$41:V$41) -> 1665232.8
A42: Earnings Before Tax | C42: =C$39-C$40-C$41 -> 1283383.8 | D42: =D$39-D$40-D$41 -> 1270277.4 | E42: =E$39-E$40-E$41 -> 1257732.5 | F42: =F$39-F$40-F$41 -> 1245772.3 | G42: =G$39-G$40-G$41 -> 1234421.2 | H42: =H$39-H$40-H$41 -> 1148032 | I42: =I$39-I$40-I$41 -> 1137220.2 | J42: =J$39-J$40-J$41 -> 1127090.3 | ... V42: =V$39-V$40-V$41 -> 961864.87 | W42: =SUM(C$42:V$42) -> 22320655
A43: Corporate Tax (12.5%) | C43: =MAX(0,C$42*Assumptions!$B$35) -> 160422.98 | D43: =MAX(0,D$42*Assumptions!$B$35) -> 158784.67 | E43: =MAX(0,E$42*Assumptions!$B$35) -> 157216.56 | F43: =MAX(0,F$42*Assumptions!$B$35) -> 155721.53 | G43: =MAX(0,G$42*Assumptions!$B$35) -> 154302.65 | H43: =MAX(0,H$42*Assumptions!$B$35) -> 143504 | I43: =MAX(0,I$42*Assumptions!$B$35) -> 142152.52 | J43: =MAX(0,J$42*Assumptions!$B$35) -> 140886.28 | ... V43: =MAX(0,V$42*Assumptions!$B$35) -> 120233.11 | W43: =SUM(C$43:V$43) -> 2790081.8
A44: Net Income | C44: =C$42-C$43 -> 1122960.8 | D44: =D$42-D$43 -> 1111492.7 | E44: =E$42-E$43 -> 1100515.9 | F44: =F$42-F$43 -> 1090050.7 | G44: =G$42-G$43 -> 1080118.5 | H44: =H$42-H$43 -> 1004528 | I44: =I$42-I$43 -> 995067.67 | J44: =J$42-J$43 -> 986203.98 | ... V44: =V$42-V$43 -> 841631.76 | W44: =SUM(C$44:V$44) -> 19530573
A45: Debt Service (Annuity) | C45: =IF(C$19<=Assumptions!$B$39,$B$14,0) -> 360413.32 | D45: =IF(D$19<=Assumptions!$B$39,$B$14,0) -> 360413.32 | E45: =IF(E$19<=Assumptions!$B$39,$B$14,0) -> 360413.32 | F45: =IF(F$19<=Assumptions!$B$39,$B$14,0) -> 360413.32 | G45: =IF(G$19<=Assumptions!$B$39,$B$14,0) -> 360413.32 | H45: =IF(H$19<=Assumptions!$B$39,$B$14,0) -> 360413.32 | I45: =IF(I$19<=Assumptions!$B$39,$B$14,0) -> 360413.32 | J45: =IF(J$19<=Assumptions!$B$39,$B$14,0) -> 360413.32 | ... V45: =IF(V$19<=Assumptions!$B$39,$B$14,0) -> 0 | W45: =SUM(C$45:V$45) -> 5406199.8
A46: Free Cash Flow to Equity | C46: =C$39-C$45-C$43 -> 1566682.7 | D46: =D$39-D$45-D$43 -> 1546546.4 | E46: =E$39-E$45-E$43 -> 1526467.9 | F46: =F$39-F$45-F$43 -> 1506446 | G46: =G$39-G$45-G$43 -> 1486479.2 | H46: =H$39-H$45-H$43 -> 1400352.3 | I46: =I$39-I$45-I$43 -> 1379828.9 | J46: =J$39-J$45-J$43 -> 1359348.9 | ... V46: =V$39-V$45-V$43 -> 1458718.6 | W46: =SUM(C$46:V$46) -> 28131343
A47: Cumulative Cash Flow | C47: =C$46 -> 1566682.7 | D47: =C$47+D$46 -> 3113229.1 | E47: =D$47+E$46 -> 4639696.9 | F47: =E$47+F$46 -> 6146142.9 | G47: =F$47+G$46 -> 7632622.1 | H47: =G$47+H$46 -> 9032974.4 | I47: =H$47+I$46 -> 10412803 | J47: =I$47+J$46 -> 11772152 | K47: =J$47+K$46 -> 13111063 | ... V47: =U$47+V$46 -> 28131343 | W47: =V$47 -> 28131343
A48: DSCR | C48: =IF(C$45>0,C$39/C$45,"N/A") -> 5.7920141 | D48: =IF(D$45>0,D$39/D$45,"N/A") -> 5.7315983 | E48: =IF(E$45>0,E$39/E$45,"N/A") -> 5.6715378 | F48: =IF(F$45>0,F$39/F$45,"N/A") -> 5.611837 | G48: =IF(G$45>0,G$39/G$45,"N/A") -> 5.5525005 | H48: =IF(H$45>0,H$39/H$45,"N/A") -> 5.2835718 | I48: =IF(I$45>0,I$39/I$45,"N/A") -> 5.2228778 | J48: =IF(J$45>0,J$39/J$45,"N/A") -> 5.1625409 | ... V48: =IF(V$45>0,V$39/V$45,"N/A") -> N/A | W48: =AVERAGE(C$48:Q$48) -> 5.2213469
A50: SCENARIO: BASE CASE (EUR 150/MWh Blended)
A51: PV Direct Revenue | C51: =C$22*Assumptions!$B$14 -> 1365000 | D51: =D$22*Assumptions!$B$14 -> 1358175 | E51: =E$22*Assumptions!$B$14 -> 1351384.1 | F51: =F$22*Assumptions!$B$14 -> 1344627.2 | G51: =G$22*Assumptions!$B$14 -> 1337904.1 | H51: =H$22*Assumptions!$B$14 -> 1331214.5 | I51: =I$22*Assumptions!$B$14 -> 1324558.5 | J51: =J$22*Assumptions!$B$14 -> 1317935.7 | ... V51: =V$22*Assumptions!$B$14 -> 1240998.3 | W51: =SUM(C$51:V$51) -> 26041339
A52: GoO Revenue | C52: =C$21*Assumptions!$B$15 -> 17062.5 | D52: =D$21*Assumptions!$B$15 -> 16977.188 | E52: =E$21*Assumptions!$B$15 -> 16892.302 | F52: =F$21*Assumptions!$B$15 -> 16807.84 | G52: =G$21*Assumptions!$B$15 -> 16723.801 | H52: =H$21*Assumptions!$B$15 -> 16640.182 | I52: =I$21*Assumptions!$B$15 -> 16556.981 | J52: =J$21*Assumptions!$B$15 -> 16474.196 | ... V52: =V$21*Assumptions!$B$15 -> 15512.479 | W52: =SUM(C$52:V$52) -> 325516.74
A53: BESS Arbitrage Revenue | C53: =C$25*Assumptions!$B$43 -> 1641949.2 | D53: =D$25*Assumptions!$B$43 -> 1619445.4 | E53: =E$25*Assumptions!$B$43 -> 1596941.5 | F53: =F$25*Assumptions!$B$43 -> 1574437.6 | G53: =G$25*Assumptions!$B$43 -> 1551933.7 | H53: =H$25*Assumptions!$B$43 -> 1529429.9 | I53: =I$25*Assumptions!$B$43 -> 1506926 | J53: =J$25*Assumptions!$B$43 -> 1484422.1 | ... V53: =V$25*Assumptions!$B$43 -> 1214375.7 | W53: =SUM(C$53:V$53) -> 28563249
A54: Total Revenue | C54: =C$51+C$52+C$53 -> 3024011.7 | D54: =D$51+D$52+D$53 -> 2994597.6 | E54: =E$51+E$52+E$53 -> 2965217.9 | F54: =F$51+F$52+F$53 -> 2935872.7 | G54: =G$51+G$52+G$53 -> 2906561.6 | H54: =H$51+H$52+H$53 -> 2877284.6 | I54: =I$51+I$52+I$53 -> 2848041.5 | J54: =J$51+J$52+J$53 -> 2818832 | ... V54: =V$51+V$52+V$53 -> 2470886.4 | W54: =SUM(C$54:V$54) -> 54930105
A55: Energy Purchase Cost | C55: =C$27*Assumptions!$B$25*(1+Assumptions!$B$36)^(C$19-1) -> 207639.6 | D55: =D$27*Assumptions!$B$25*(1+Assumptions!$B$36)^(D$19-1) -> 203091.11 | E55: =E$27*Assumptions!$B$25*(1+Assumptions!$B$36)^(E$19-1) -> 198420 | F55: =F$27*Assumptions!$B$25*(1+Assumptions!$B$36)^(F$19-1) -> 193624.23 | G55: =G$27*Assumptions!$B$25*(1+Assumptions!$B$36)^(G$19-1) -> 188701.71 | H55: =H$27*Assumptions!$B$25*(1+Assumptions!$B$36)^(H$19-1) -> 183650.35 | I55: =I$27*Assumptions!$B$25*(1+Assumptions!$B$36)^(I$19-1) -> 178467.99 | J55: =J$27*Assumptions!$B$25*(1+Assumptions!$B$36)^(J$19-1) -> 173152.46 | ... V55: =V$27*Assumptions!$B$25*(1+Assumptions!$B$36)^(V$19-1) -> 98146.822 | W55: =SUM(C$55:V$55) -> 3138396.7
A56: PV OPEX | C56: =$B$5*Assumptions!$B$16*(1+Assumptions!$B$36)^(C$19-1) -> 150000 | D56: =$B$5*Assumptions!$B$16*(1+Assumptions!$B$36)^(D$19-1) -> 151500 | E56: =$B$5*Assumptions!$B$16*(1+Assumptions!$B$36)^(E$19-1) -> 153015 | F56: =$B$5*Assumptions!$B$16*(1+Assumptions!$B$36)^(F$19-1) -> 154545.15 | G56: =$B$5*Assumptions!$B$16*(1+Assumptions!$B$36)^(G$19-1) -> 156090.6 | H56: =$B$5*Assumptions!$B$16*(1+Assumptions!$B$36)^(H$19-1) -> 157651.51 | I56: =$B$5*Assumptions!$B$16*(1+Assumptions!$B$36)^(I$19-1) -> 159228.02 | J56: =$B$5*Assumptions!$B$16*(1+Assumptions!$B$36)^(J$19-1) -> 160820.3 | ... V56: =$B$5*Assumptions!$B$16*(1+Assumptions!$B$36)^(V$19-1) -> 181216.34 | W56: =SUM(C$56:V$56) -> 3302850.6
A57: BESS OPEX (O&M+Mgmt+CERA+Grounds) | C57: =($B$6*Assumptions!$B$26+$B$6*Assumptions!$B$27+$B$7*Assumptions!$B$28+Assumptions!$B$29)*(1+Assumptions!$B$36)^(C$19-1) -> 141000 | D57: =($B$6*Assumptions!$B$26+$B$6*Assumptions!$B$27+$B$7*Assumptions!$B$28+Assumptions!$B$29)*(1+Assumptions!$B$36)^(D$19-1) -> 142410 | E57: =($B$6*Assumptions!$B$26+$B$6*Assumptions!$B$27+$B$7*Assumptions!$B$28+Assumptions!$B$29)*(1+Assumptions!$B$36)^(E$19-1) -> 143834.1 | F57: =($B$6*Assumptions!$B$26+$B$6*Assumptions!$B$27+$B$7*Assumptions!$B$28+Assumptions!$B$29)*(1+Assumptions!$B$36)^(F$19-1) -> 145272.44 | G57: =($B$6*Assumptions!$B$26+$B$6*Assumptions!$B$27+$B$7*Assumptions!$B$28+Assumptions!$B$29)*(1+Assumptions!$B$36)^(G$19-1) -> 146725.17 | H57: =($B$6*Assumptions!$B$26+$B$6*Assumptions!$B$27+$B$7*Assumptions!$B$28+Assumptions!$B$29)*(1+Assumptions!$B$36)^(H$19-1) -> 148192.42 | I57: =($B$6*Assumptions!$B$26+$B$6*Assumptions!$B$27+$B$7*Assumptions!$B$28+Assumptions!$B$29)*(1+Assumptions!$B$36)^(I$19-1) -> 149674.34 | J57: =($B$6*Assumptions!$B$26+$B$6*Assumptions!$B$27+$B$7*Assumptions!$B$28+Assumptions!$B$29)*(1+Assumptions!$B$36)^(J$19-1) -> 151171.08 | ... V57: =($B$6*Assumptions!$B$26+$B$6*Assumptions!$B$27+$B$7*Assumptions!$B$28+Assumptions!$B$29)*(1+Assumptions!$B$36)^(V$19-1) -> 170343.36 | W57: =SUM(C$57:V$57) -> 3104679.6
A58: BESS Warranty Extension | C58: =IF(C$19<=5,0,IF(C$19<=10,Assumptions!$B$30,IF(C$19<=15,Assumptions!$B$31,Assumptions!$B$32)))*$B$6*(1+Assumptions!$B$36)^(C$19-1) -> 0 | D58: =IF(D$19<=5,0,IF(D$19<=10,Assumptions!$B$30,IF(D$19<=15,Assumptions!$B$31,Assumptions!$B$32)))*$B$6*(1+Assumptions!$B$36)^(D$19-1) -> 0 | E58: =IF(E$19<=5,0,IF(E$19<=10,Assumptions!$B$30,IF(E$19<=15,Assumptions!$B$31,Assumptions!$B$32)))*$B$6*(1+Assumptions!$B$36)^(E$19-1) -> 0 | F58: =IF(F$19<=5,0,IF(F$19<=10,Assumptions!$B$30,IF(F$19<=15,Assumptions!$B$31,Assumptions!$B$32)))*$B$6*(1+Assumptions!$B$36)^(F$19-1) -> 0 | G58: =IF(G$19<=5,0,IF(G$19<=10,Assumptions!$B$30,IF(G$19<=15,Assumptions!$B$31,Assumptions!$B$32)))*$B$6*(1+Assumptions!$B$36)^(G$19-1) -> 0 | H58: =IF(H$19<=5,0,IF(H$19<=10,Assumptions!$B$30,IF(H$19<=15,Assumptions!$B$31,Assumptions!$B$32)))*$B$6*(1+Assumptions!$B$36)^(H$19-1) -> 75672.724 | I58: =IF(I$19<=5,0,IF(I$19<=10,Assumptions!$B$30,IF(I$19<=15,Assumptions!$B$31,Assumptions!$B$32)))*$B$6*(1+Assumptions!$B$36)^(I$19-1) -> 76429.451 | J58: =IF(J$19<=5,0,IF(J$19<=10,Assumptions!$B$30,IF(J$19<=15,Assumptions!$B$31,Assumptions!$B$32)))*$B$6*(1+Assumptions!$B$36)^(J$19-1) -> 77193.745 | ... V58: =IF(V$19<=5,0,IF(V$19<=10,Assumptions!$B$30,IF(V$19<=15,Assumptions!$B$31,Assumptions!$B$32)))*$B$6*(1+Assumptions!$B$36)^(V$19-1) -> 118394.68 | W58: =SUM(C$58:V$58) -> 1439686.9
A59: Total Operating Costs | C59: =C$55+C$56+C$57+C$58 -> 498639.6 | D59: =D$55+D$56+D$57+D$58 -> 497001.11 | E59: =E$55+E$56+E$57+E$58 -> 495269.1 | F59: =F$55+F$56+F$57+F$58 -> 493441.82 | G59: =G$55+G$56+G$57+G$58 -> 491517.48 | H59: =H$55+H$56+H$57+H$58 -> 565167 | I59: =I$55+I$56+I$57+I$58 -> 563799.8 | J59: =J$55+J$56+J$57+J$58 -> 562337.6 | ... V59: =V$55+V$56+V$57+V$58 -> 568101.2 | W59: =SUM(C$59:V$59) -> 10985614
A60: EBITDA | C60: =C$54-C$59 -> 2525372.1 | D60: =D$54-D$59 -> 2497596.4 | E60: =E$54-E$59 -> 2469948.8 | F60: =F$54-F$59 -> 2442430.8 | G60: =G$54-G$59 -> 2415044.1 | H60: =H$54-H$59 -> 2312117.6 | I60: =I$54-I$59 -> 2284241.7 | J60: =J$54-J$59 -> 2256494.4 | ... V60: =V$54-V$59 -> 1902785.2 | W60: =SUM(C$60:V$60) -> 43944491
A61: Depreciation | C61: =$B$15 -> 617086.85 | D61: =$B$15 -> 617086.85 | E61: =$B$15 -> 617086.85 | F61: =$B$15 -> 617086.85 | G61: =$B$15 -> 617086.85 | H61: =$B$15 -> 617086.85 | I61: =$B$15 -> 617086.85 | J61: =$B$15 -> 617086.85 | ... V61: =$B$15 -> 617086.85 | W61: =SUM(C$61:V$61) -> 12341737
A62: Interest Expense | C62: =IF(C$19<=Assumptions!$B$39,-IPMT(Assumptions!$B$38,C$19,Assumptions!$B$39,$B$13),0) -> 187048.35 | D62: =IF(D$19<=Assumptions!$B$39,-IPMT(Assumptions!$B$38,D$19,Assumptions!$B$39,$B$13),0) -> 178380.1 | E62: =IF(E$19<=Assumptions!$B$39,-IPMT(Assumptions!$B$38,E$19,Assumptions!$B$39,$B$13),0) -> 169278.44 | F62: =IF(F$19<=Assumptions!$B$39,-IPMT(Assumptions!$B$38,F$19,Assumptions!$B$39,$B$13),0) -> 159721.7 | G62: =IF(G$19<=Assumptions!$B$39,-IPMT(Assumptions!$B$38,G$19,Assumptions!$B$39,$B$13),0) -> 149687.12 | H62: =IF(H$19<=Assumptions!$B$39,-IPMT(Assumptions!$B$38,H$19,Assumptions!$B$39,$B$13),0) -> 139150.81 | I62: =IF(I$19<=Assumptions!$B$39,-IPMT(Assumptions!$B$38,I$19,Assumptions!$B$39,$B$13),0) -> 128087.68 | J62: =IF(J$19<=Assumptions!$B$39,-IPMT(Assumptions!$B$38,J$19,Assumptions!$B$39,$B$13),0) -> 116471.4 | ... V62: =IF(V$19<=Assumptions!$B$39,-IPMT(Assumptions!$B$38,V$19,Assumptions!$B$39,$B$13),0) -> 0 | W62: =SUM(C$62:V$62) -> 1665232.8
A63: Earnings Before Tax | C63: =C$60-C$61-C$62 -> 1721236.9 | D63: =D$60-D$61-D$62 -> 1702129.5 | E63: =E$60-E$61-E$62 -> 1683583.5 | F63: =F$60-F$61-F$62 -> 1665622.3 | G63: =G$60-G$61-G$62 -> 1648270.2 | H63: =H$60-H$61-H$62 -> 1555880 | I63: =I$60-I$61-I$62 -> 1539067.1 | J63: =J$60-J$61-J$62 -> 1522936.2 | ... V63: =V$60-V$61-V$62 -> 1285698.4 | W63: =SUM(C$63:V$63) -> 29937521
A64: Corporate Tax (12.5%) | C64: =MAX(0,C$63*Assumptions!$B$35) -> 215154.62 | D64: =MAX(0,D$63*Assumptions!$B$35) -> 212766.19 | E64: =MAX(0,E$63*Assumptions!$B$35) -> 210447.94 | F64: =MAX(0,F$63*Assumptions!$B$35) -> 208202.79 | G64: =MAX(0,G$63*Assumptions!$B$35) -> 206033.77 | H64: =MAX(0,H$63*Assumptions!$B$35) -> 194484.99 | I64: =MAX(0,I$63*Assumptions!$B$35) -> 192383.39 | J64: =MAX(0,J$63*Assumptions!$B$35) -> 190367.02 | ... V64: =MAX(0,V$63*Assumptions!$B$35) -> 160712.3 | W64: =SUM(C$64:V$64) -> 3742190.1
A65: Net Income | C65: =C$63-C$64 -> 1506082.3 | D65: =D$63-D$64 -> 1489363.3 | E65: =E$63-E$64 -> 1473135.6 | F65: =F$63-F$64 -> 1457419.5 | G65: =G$63-G$64 -> 1442236.4 | H65: =H$63-H$64 -> 1361395 | I65: =I$63-I$64 -> 1346683.7 | J65: =J$63-J$64 -> 1332569.1 | ... V65: =V$63-V$64 -> 1124986.1 | W65: =SUM(C$65:V$65) -> 26195331
A66: Debt Service (Annuity) | C66: =IF(C$19<=Assumptions!$B$39,$B$14,0) -> 360413.32 | D66: =IF(D$19<=Assumptions!$B$39,$B$14,0) -> 360413.32 | E66: =IF(E$19<=Assumptions!$B$39,$B$14,0) -> 360413.32 | F66: =IF(F$19<=Assumptions!$B$39,$B$14,0) -> 360413.32 | G66: =IF(G$19<=Assumptions!$B$39,$B$14,0) -> 360413.32 | H66: =IF(H$19<=Assumptions!$B$39,$B$14,0) -> 360413.32 | I66: =IF(I$19<=Assumptions!$B$39,$B$14,0) -> 360413.32 | J66: =IF(J$19<=Assumptions!$B$39,$B$14,0) -> 360413.32 | ... V66: =IF(V$19<=Assumptions!$B$39,$B$14,0) -> 0 | W66: =SUM(C$66:V$66) -> 5406199.8
A67: Free Cash Flow to Equity | C67: =C$60-C$66-C$64 -> 1949804.2 | D67: =D$60-D$66-D$64 -> 1924416.9 | E67: =E$60-E$66-E$64 -> 1899087.6 | F67: =F$60-F$66-F$64 -> 1873814.7 | G67: =G$60-G$66-G$64 -> 1848597 | H67: =H$60-H$66-H$64 -> 1757219.3 | I67: =I$60-I$66-I$64 -> 1731444.9 | J67: =J$60-J$66-J$64 -> 1705714.1 | ... V67: =V$60-V$66-V$64 -> 1742072.9 | W67: =SUM(C$67:V$67) -> 34796101
A68: Cumulative Cash Flow | C68: =C$67 -> 1949804.2 | D68: =C$68+D$67 -> 3874221.1 | E68: =D$68+E$67 -> 5773308.7 | F68: =E$68+F$67 -> 7647123.4 | G68: =F$68+G$67 -> 9495720.5 | H68: =G$68+H$67 -> 11252940 | I68: =H$68+I$67 -> 12984385 | J68: =I$68+J$67 -> 14690099 | K68: =J$68+K$67 -> 16370123 | ... V68: =U$68+V$67 -> 34796101 | W68: =V$68 -> 34796101
A69: DSCR | C69: =IF(C$66>0,C$60/C$66,"N/A") -> 7.006878 | D69: =IF(D$66>0,D$60/D$66,"N/A") -> 6.9298117 | E69: =IF(E$66>0,E$60/E$66,"N/A") -> 6.8531008 | F69: =IF(F$66>0,F$60/F$66,"N/A") -> 6.7767497 | G69: =IF(G$66>0,G$60/G$66,"N/A") -> 6.7007627 | H69: =IF(H$66>0,H$60/H$66,"N/A") -> 6.4151836 | I69: =IF(I$66>0,I$60/I$66,"N/A") -> 6.3378392 | J69: =IF(J$66>0,J$60/J$66,"N/A") -> 6.2608519 | ... V69: =IF(V$66>0,V$60/V$66,"N/A") -> N/A | W69: =AVERAGE(C$69:Q$69) -> 6.3196579
A71: SCENARIO: HIGH CASE (EUR 175/MWh)
A72: PV Direct Revenue | C72: =C$22*Assumptions!$B$14 -> 1365000 | D72: =D$22*Assumptions!$B$14 -> 1358175 | E72: =E$22*Assumptions!$B$14 -> 1351384.1 | F72: =F$22*Assumptions!$B$14 -> 1344627.2 | G72: =G$22*Assumptions!$B$14 -> 1337904.1 | H72: =H$22*Assumptions!$B$14 -> 1331214.5 | I72: =I$22*Assumptions!$B$14 -> 1324558.5 | J72: =J$22*Assumptions!$B$14 -> 1317935.7 | ... V72: =V$22*Assumptions!$B$14 -> 1240998.3 | W72: =SUM(C$72:V$72) -> 26041339
A73: GoO Revenue | C73: =C$21*Assumptions!$B$15 -> 17062.5 | D73: =D$21*Assumptions!$B$15 -> 16977.188 | E73: =E$21*Assumptions!$B$15 -> 16892.302 | F73: =F$21*Assumptions!$B$15 -> 16807.84 | G73: =G$21*Assumptions!$B$15 -> 16723.801 | H73: =H$21*Assumptions!$B$15 -> 16640.182 | I73: =I$21*Assumptions!$B$15 -> 16556.981 | J73: =J$21*Assumptions!$B$15 -> 16474.196 | ... V73: =V$21*Assumptions!$B$15 -> 15512.479 | W73: =SUM(C$73:V$73) -> 325516.74
A74: BESS Arbitrage Revenue | C74: =C$25*Assumptions!$B$44 -> 1915607.4 | D74: =D$25*Assumptions!$B$44 -> 1889352.9 | E74: =E$25*Assumptions!$B$44 -> 1863098.4 | F74: =F$25*Assumptions!$B$44 -> 1836843.9 | G74: =G$25*Assumptions!$B$44 -> 1810589.4 | H74: =H$25*Assumptions!$B$44 -> 1784334.9 | I74: =I$25*Assumptions!$B$44 -> 1758080.3 | J74: =J$25*Assumptions!$B$44 -> 1731825.8 | ... V74: =V$25*Assumptions!$B$44 -> 1416771.6 | W74: =SUM(C$74:V$74) -> 33323790
A75: Total Revenue | C75: =C$72+C$73+C$74 -> 3297669.9 | D75: =D$72+D$73+D$74 -> 3264505.1 | E75: =E$72+E$73+E$74 -> 3231374.8 | F75: =F$72+F$73+F$74 -> 3198278.9 | G75: =G$72+G$73+G$74 -> 3165217.2 | H75: =H$72+H$73+H$74 -> 3132189.6 | I75: =I$72+I$73+I$74 -> 3099195.8 | J75: =J$72+J$73+J$74 -> 3066235.7 | ... V75: =V$72+V$73+V$74 -> 2673282.4 | W75: =SUM(C$75:V$75) -> 59690646
A76: Energy Purchase Cost | C76: =C$27*Assumptions!$B$25*(1+Assumptions!$B$36)^(C$19-1) -> 207639.6 | D76: =D$27*Assumptions!$B$25*(1+Assumptions!$B$36)^(D$19-1) -> 203091.11 | E76: =E$27*Assumptions!$B$25*(1+Assumptions!$B$36)^(E$19-1) -> 198420 | F76: =F$27*Assumptions!$B$25*(1+Assumptions!$B$36)^(F$19-1) -> 193624.23 | G76: =G$27*Assumptions!$B$25*(1+Assumptions!$B$36)^(G$19-1) -> 188701.71 | H76: =H$27*Assumptions!$B$25*(1+Assumptions!$B$36)^(H$19-1) -> 183650.35 | I76: =I$27*Assumptions!$B$25*(1+Assumptions!$B$36)^(I$19-1) -> 178467.99 | J76: =J$27*Assumptions!$B$25*(1+Assumptions!$B$36)^(J$19-1) -> 173152.46 | ... V76: =V$27*Assumptions!$B$25*(1+Assumptions!$B$36)^(V$19-1) -> 98146.822 | W76: =SUM(C$76:V$76) -> 3138396.7
A77: PV OPEX | C77: =$B$5*Assumptions!$B$16*(1+Assumptions!$B$36)^(C$19-1) -> 150000 | D77: =$B$5*Assumptions!$B$16*(1+Assumptions!$B$36)^(D$19-1) -> 151500 | E77: =$B$5*Assumptions!$B$16*(1+Assumptions!$B$36)^(E$19-1) -> 153015 | F77: =$B$5*Assumptions!$B$16*(1+Assumptions!$B$36)^(F$19-1) -> 154545.15 | G77: =$B$5*Assumptions!$B$16*(1+Assumptions!$B$36)^(G$19-1) -> 156090.6 | H77: =$B$5*Assumptions!$B$16*(1+Assumptions!$B$36)^(H$19-1) -> 157651.51 | I77: =$B$5*Assumptions!$B$16*(1+Assumptions!$B$36)^(I$19-1) -> 159228.02 | J77: =$B$5*Assumptions!$B$16*(1+Assumptions!$B$36)^(J$19-1) -> 160820.3 | ... V77: =$B$5*Assumptions!$B$16*(1+Assumptions!$B$36)^(V$19-1) -> 181216.34 | W77: =SUM(C$77:V$77) -> 3302850.6
A78: BESS OPEX (O&M+Mgmt+CERA+Grounds) | C78: =($B$6*Assumptions!$B$26+$B$6*Assumptions!$B$27+$B$7*Assumptions!$B$28+Assumptions!$B$29)*(1+Assumptions!$B$36)^(C$19-1) -> 141000 | D78: =($B$6*Assumptions!$B$26+$B$6*Assumptions!$B$27+$B$7*Assumptions!$B$28+Assumptions!$B$29)*(1+Assumptions!$B$36)^(D$19-1) -> 142410 | E78: =($B$6*Assumptions!$B$26+$B$6*Assumptions!$B$27+$B$7*Assumptions!$B$28+Assumptions!$B$29)*(1+Assumptions!$B$36)^(E$19-1) -> 143834.1 | F78: =($B$6*Assumptions!$B$26+$B$6*Assumptions!$B$27+$B$7*Assumptions!$B$28+Assumptions!$B$29)*(1+Assumptions!$B$36)^(F$19-1) -> 145272.44 | G78: =($B$6*Assumptions!$B$26+$B$6*Assumptions!$B$27+$B$7*Assumptions!$B$28+Assumptions!$B$29)*(1+Assumptions!$B$36)^(G$19-1) -> 146725.17 | H78: =($B$6*Assumptions!$B$26+$B$6*Assumptions!$B$27+$B$7*Assumptions!$B$28+Assumptions!$B$29)*(1+Assumptions!$B$36)^(H$19-1) -> 148192.42 | I78: =($B$6*Assumptions!$B$26+$B$6*Assumptions!$B$27+$B$7*Assumptions!$B$28+Assumptions!$B$29)*(1+Assumptions!$B$36)^(I$19-1) -> 149674.34 | J78: =($B$6*Assumptions!$B$26+$B$6*Assumptions!$B$27+$B$7*Assumptions!$B$28+Assumptions!$B$29)*(1+Assumptions!$B$36)^(J$19-1) -> 151171.08 | ... V78: =($B$6*Assumptions!$B$26+$B$6*Assumptions!$B$27+$B$7*Assumptions!$B$28+Assumptions!$B$29)*(1+Assumptions!$B$36)^(V$19-1) -> 170343.36 | W78: =SUM(C$78:V$78) -> 3104679.6
A79: BESS Warranty Extension | C79: =IF(C$19<=5,0,IF(C$19<=10,Assumptions!$B$30,IF(C$19<=15,Assumptions!$B$31,Assumptions!$B$32)))*$B$6*(1+Assumptions!$B$36)^(C$19-1) -> 0 | D79: =IF(D$19<=5,0,IF(D$19<=10,Assumptions!$B$30,IF(D$19<=15,Assumptions!$B$31,Assumptions!$B$32)))*$B$6*(1+Assumptions!$B$36)^(D$19-1) -> 0 | E79: =IF(E$19<=5,0,IF(E$19<=10,Assumptions!$B$30,IF(E$19<=15,Assumptions!$B$31,Assumptions!$B$32)))*$B$6*(1+Assumptions!$B$36)^(E$19-1) -> 0 | F79: =IF(F$19<=5,0,IF(F$19<=10,Assumptions!$B$30,IF(F$19<=15,Assumptions!$B$31,Assumptions!$B$32)))*$B$6*(1+Assumptions!$B$36)^(F$19-1) -> 0 | G79: =IF(G$19<=5,0,IF(G$19<=10,Assumptions!$B$30,IF(G$19<=15,Assumptions!$B$31,Assumptions!$B$32)))*$B$6*(1+Assumptions!$B$36)^(G$19-1) -> 0 | H79: =IF(H$19<=5,0,IF(H$19<=10,Assumptions!$B$30,IF(H$19<=15,Assumptions!$B$31,Assumptions!$B$32)))*$B$6*(1+Assumptions!$B$36)^(H$19-1) -> 75672.724 | I79: =IF(I$19<=5,0,IF(I$19<=10,Assumptions!$B$30,IF(I$19<=15,Assumptions!$B$31,Assumptions!$B$32)))*$B$6*(1+Assumptions!$B$36)^(I$19-1) -> 76429.451 | J79: =IF(J$19<=5,0,IF(J$19<=10,Assumptions!$B$30,IF(J$19<=15,Assumptions!$B$31,Assumptions!$B$32)))*$B$6*(1+Assumptions!$B$36)^(J$19-1) -> 77193.745 | ... V79: =IF(V$19<=5,0,IF(V$19<=10,Assumptions!$B$30,IF(V$19<=15,Assumptions!$B$31,Assumptions!$B$32)))*$B$6*(1+Assumptions!$B$36)^(V$19-1) -> 118394.68 | W79: =SUM(C$79:V$79) -> 1439686.9
A80: Total Operating Costs | C80: =C$76+C$77+C$78+C$79 -> 498639.6 | D80: =D$76+D$77+D$78+D$79 -> 497001.11 | E80: =E$76+E$77+E$78+E$79 -> 495269.1 | F80: =F$76+F$77+F$78+F$79 -> 493441.82 | G80: =G$76+G$77+G$78+G$79 -> 491517.48 | H80: =H$76+H$77+H$78+H$79 -> 565167 | I80: =I$76+I$77+I$78+I$79 -> 563799.8 | J80: =J$76+J$77+J$78+J$79 -> 562337.6 | ... V80: =V$76+V$77+V$78+V$79 -> 568101.2 | W80: =SUM(C$80:V$80) -> 10985614
A81: EBITDA | C81: =C$75-C$80 -> 2799030.3 | D81: =D$75-D$80 -> 2767504 | E81: =E$75-E$80 -> 2736105.7 | F81: =F$75-F$80 -> 2704837.1 | G81: =G$75-G$80 -> 2673699.8 | H81: =H$75-H$80 -> 2567022.6 | I81: =I$75-I$80 -> 2535396 | J81: =J$75-J$80 -> 2503898.1 | ... V81: =V$75-V$80 -> 2105181.2 | W81: =SUM(C$81:V$81) -> 48705032
A82: Depreciation | C82: =$B$15 -> 617086.85 | D82: =$B$15 -> 617086.85 | E82: =$B$15 -> 617086.85 | F82: =$B$15 -> 617086.85 | G82: =$B$15 -> 617086.85 | H82: =$B$15 -> 617086.85 | I82: =$B$15 -> 617086.85 | J82: =$B$15 -> 617086.85 | ... V82: =$B$15 -> 617086.85 | W82: =SUM(C$82:V$82) -> 12341737
A83: Interest Expense | C83: =IF(C$19<=Assumptions!$B$39,-IPMT(Assumptions!$B$38,C$19,Assumptions!$B$39,$B$13),0) -> 187048.35 | D83: =IF(D$19<=Assumptions!$B$39,-IPMT(Assumptions!$B$38,D$19,Assumptions!$B$39,$B$13),0) -> 178380.1 | E83: =IF(E$19<=Assumptions!$B$39,-IPMT(Assumptions!$B$38,E$19,Assumptions!$B$39,$B$13),0) -> 169278.44 | F83: =IF(F$19<=Assumptions!$B$39,-IPMT(Assumptions!$B$38,F$19,Assumptions!$B$39,$B$13),0) -> 159721.7 | G83: =IF(G$19<=Assumptions!$B$39,-IPMT(Assumptions!$B$38,G$19,Assumptions!$B$39,$B$13),0) -> 149687.12 | H83: =IF(H$19<=Assumptions!$B$39,-IPMT(Assumptions!$B$38,H$19,Assumptions!$B$39,$B$13),0) -> 139150.81 | I83: =IF(I$19<=Assumptions!$B$39,-IPMT(Assumptions!$B$38,I$19,Assumptions!$B$39,$B$13),0) -> 128087.68 | J83: =IF(J$19<=Assumptions!$B$39,-IPMT(Assumptions!$B$38,J$19,Assumptions!$B$39,$B$13),0) -> 116471.4 | ... V83: =IF(V$19<=Assumptions!$B$39,-IPMT(Assumptions!$B$38,V$19,Assumptions!$B$39,$B$13),0) -> 0 | W83: =SUM(C$83:V$83) -> 1665232.8
A84: Earnings Before Tax | C84: =C$81-C$82-C$83 -> 1994895.1 | D84: =D$81-D$82-D$83 -> 1972037.1 | E84: =E$81-E$82-E$83 -> 1949740.4 | F84: =F$81-F$82-F$83 -> 1928028.6 | G84: =G$81-G$82-G$83 -> 1906925.8 | H84: =H$81-H$82-H$83 -> 1810784.9 | I84: =I$81-I$82-I$83 -> 1790221.5 | J84: =J$81-J$82-J$83 -> 1770339.9 | ... V84: =V$81-V$82-V$83 -> 1488094.3 | W84: =SUM(C$84:V$84) -> 34698062
A85: Corporate Tax (12.5%) | C85: =MAX(0,C$84*Assumptions!$B$35) -> 249361.89 | D85: =MAX(0,D$84*Assumptions!$B$35) -> 246504.63 | E85: =MAX(0,E$84*Assumptions!$B$35) -> 243717.56 | F85: =MAX(0,F$84*Assumptions!$B$35) -> 241003.57 | G85: =MAX(0,G$84*Assumptions!$B$35) -> 238365.72 | H85: =MAX(0,H$84*Assumptions!$B$35) -> 226348.12 | I85: =MAX(0,I$84*Assumptions!$B$35) -> 223777.68 | J85: =MAX(0,J$84*Assumptions!$B$35) -> 221292.48 | ... V85: =MAX(0,V$84*Assumptions!$B$35) -> 186011.79 | W85: =SUM(C$85:V$85) -> 4337257.8
A86: Net Income | C86: =C$84-C$85 -> 1745533.2 | D86: =D$84-D$85 -> 1725532.4 | E86: =E$84-E$85 -> 1706022.9 | F86: =F$84-F$85 -> 1687025 | G86: =G$84-G$85 -> 1668560.1 | H86: =H$84-H$85 -> 1584436.8 | I86: =I$84-I$85 -> 1566443.8 | J86: =J$84-J$85 -> 1549047.4 | ... V86: =V$84-V$85 -> 1302082.5 | W86: =SUM(C$86:V$86) -> 30360805
A87: Debt Service (Annuity) | C87: =IF(C$19<=Assumptions!$B$39,$B$14,0) -> 360413.32 | D87: =IF(D$19<=Assumptions!$B$39,$B$14,0) -> 360413.32 | E87: =IF(E$19<=Assumptions!$B$39,$B$14,0) -> 360413.32 | F87: =IF(F$19<=Assumptions!$B$39,$B$14,0) -> 360413.32 | G87: =IF(G$19<=Assumptions!$B$39,$B$14,0) -> 360413.32 | H87: =IF(H$19<=Assumptions!$B$39,$B$14,0) -> 360413.32 | I87: =IF(I$19<=Assumptions!$B$39,$B$14,0) -> 360413.32 | J87: =IF(J$19<=Assumptions!$B$39,$B$14,0) -> 360413.32 | ... V87: =IF(V$19<=Assumptions!$B$39,$B$14,0) -> 0 | W87: =SUM(C$87:V$87) -> 5406199.8
A88: Free Cash Flow to Equity | C88: =C$81-C$87-C$85 -> 2189255.1 | D88: =D$81-D$87-D$85 -> 2160586.1 | E88: =E$81-E$87-E$85 -> 2131974.9 | F88: =F$81-F$87-F$85 -> 2103420.2 | G88: =G$81-G$87-G$85 -> 2074920.7 | H88: =H$81-H$87-H$85 -> 1980261.2 | I88: =I$81-I$87-I$85 -> 1951205 | J88: =J$81-J$87-J$85 -> 1922192.3 | ... V88: =V$81-V$87-V$85 -> 1919169.4 | W88: =SUM(C$88:V$88) -> 38961575
A89: Cumulative Cash Flow | C89: =C$88 -> 2189255.1 | D89: =C$89+D$88 -> 4349841.2 | E89: =D$89+E$88 -> 6481816 | F89: =E$89+F$88 -> 8585236.3 | G89: =F$89+G$88 -> 10660157 | H89: =G$89+H$88 -> 12640418 | I89: =H$89+I$88 -> 14591623 | J89: =I$89+J$88 -> 16513815 | K89: =J$89+K$88 -> 18407036 | ... V89: =U$89+V$88 -> 38961575 | W89: =V$89 -> 38961575
A90: DSCR | C90: =IF(C$87>0,C$81/C$87,"N/A") -> 7.7661679 | D90: =IF(D$87>0,D$81/D$87,"N/A") -> 7.6786952 | E90: =IF(E$87>0,E$81/E$87,"N/A") -> 7.5915778 | F90: =IF(F$87>0,F$81/F$87,"N/A") -> 7.5048201 | G90: =IF(G$87>0,G$81/G$87,"N/A") -> 7.4184266 | H90: =IF(H$87>0,H$81/H$87,"N/A") -> 7.122441 | I90: =IF(I$87>0,I$81/I$87,"N/A") -> 7.0346901 | J90: =IF(J$87>0,J$81/J$87,"N/A") -> 6.9472963 | ... V90: =IF(V$87>0,V$81/V$87,"N/A") -> N/A | W90: =AVERAGE(C$90:Q$90) -> 7.0061022
A92: RETURNS SUMMARY (PER UNIT)
A93: Metric | B93: Low (110) | C93: Base (150) | D93: High (175)
A94: Equity IRR | B94: =IRR(B$101:V$101) -> 0.16010303 | C94: =IRR(B$102:V$102) -> 0.20738031 | D94: =IRR(B$103:V$103) -> 0.23633322
A95: Project IRR (Unlevered) | B95: =IRR(B$104:V$104) -> 0.13009701 | C95: =IRR(B$105:V$105) -> 0.16457882 | D95: =IRR(B$106:V$106) -> 0.18549618
A96: Equity NPV (@ 8%) | B96: {=NPV(Assumptions!$B$37,C$101:V$101)+B$101} -> 5403352.4 | C96: {=NPV(Assumptions!$B$37,C$102:V$102)+B$102} -> 8802111.8 | D96: {=NPV(Assumptions!$B$37,C$103:V$103)+B$103} -> 10926336
A97: Equity Multiple | B97: =SUM(C$101:V$101)/(-B$101) -> 3.2707935 | C97: =SUM(C$102:V$102)/(-B$102) -> 4.045696 | D97: =SUM(C$103:V$103)/(-B$103) -> 4.5300101
A98: Avg DSCR (loan period) | B98: =AVERAGE(C$48:Q$48) -> 5.2213469 | C98: =AVERAGE(C$69:Q$69) -> 6.3196579 | D98: =AVERAGE(C$90:Q$90) -> 7.0061022
A99: Total FCFE (20 years) | B99: =SUM(C$101:V$101) -> 28131343 | C99: =SUM(C$102:V$102) -> 34796101 | D99: =SUM(C$103:V$103) -> 38961575
A101: Equity CF (Low) | B101: =-$B$12 -> -8600770 | C101: =C$46 -> 1566682.7 | D101: =D$46 -> 1546546.4 | E101: =E$46 -> 1526467.9 | F101: =F$46 -> 1506446 | G101: =G$46 -> 1486479.2 | H101: =H$46 -> 1400352.3 | I101: =I$46 -> 1379828.9 | J101: =J$46 -> 1359348.9 | ... V101: =V$46 -> 1458718.6
A102: Equity CF (Base) | B102: =-$B$12 -> -8600770 | C102: =C$67 -> 1949804.2 | D102: =D$67 -> 1924416.9 | E102: =E$67 -> 1899087.6 | F102: =F$67 -> 1873814.7 | G102: =G$67 -> 1848597 | H102: =H$67 -> 1757219.3 | I102: =I$67 -> 1731444.9 | J102: =J$67 -> 1705714.1 | ... V102: =V$67 -> 1742072.9
A103: Equity CF (High) | B103: =-$B$12 -> -8600770 | C103: =C$88 -> 2189255.1 | D103: =D$88 -> 2160586.1 | E103: =E$88 -> 2131974.9 | F103: =F$88 -> 2103420.2 | G103: =G$88 -> 2074920.7 | H103: =H$88 -> 1980261.2 | I103: =I$88 -> 1951205 | J103: =J$88 -> 1922192.3 | ... V103: =V$88 -> 1919169.4
A104: Project CF (Low) | B104: =-$B$11 -> -12341737 | C104: =C$39-MAX(0,(C$39-C$40)*Assumptions!$B$35) -> 1903715 | D104: =D$39-MAX(0,(D$39-D$40)*Assumptions!$B$35) -> 1884662.2 | E104: =E$39-MAX(0,(E$39-E$40)*Assumptions!$B$35) -> 1865721.4 | F104: =F$39-MAX(0,(F$39-F$40)*Assumptions!$B$35) -> 1846894.1 | G104: =G$39-MAX(0,(G$39-G$40)*Assumptions!$B$35) -> 1828181.6 | H104: =H$39-MAX(0,(H$39-H$40)*Assumptions!$B$35) -> 1743371.8 | I104: =I$39-MAX(0,(I$39-I$40)*Assumptions!$B$35) -> 1724231.2 | J104: =J$39-MAX(0,(J$39-J$40)*Assumptions!$B$35) -> 1705203.3 | ... V104: =V$39-MAX(0,(V$39-V$40)*Assumptions!$B$35) -> 1458718.6
A105: Project CF (Base) | B105: =-$B$11 -> -12341737 | C105: =C$60-MAX(0,(C$60-C$61)*Assumptions!$B$35) -> 2286836.5 | D105: =D$60-MAX(0,(D$60-D$61)*Assumptions!$B$35) -> 2262532.7 | E105: =E$60-MAX(0,(E$60-E$61)*Assumptions!$B$35) -> 2238341.1 | F105: =F$60-MAX(0,(F$60-F$61)*Assumptions!$B$35) -> 2214262.8 | G105: =G$60-MAX(0,(G$60-G$61)*Assumptions!$B$35) -> 2190299.5 | H105: =H$60-MAX(0,(H$60-H$61)*Assumptions!$B$35) -> 2100238.8 | I105: =I$60-MAX(0,(I$60-I$61)*Assumptions!$B$35) -> 2075847.3 | J105: =J$60-MAX(0,(J$60-J$61)*Assumptions!$B$35) -> 2051568.5 | ... V105: =V$60-MAX(0,(V$60-V$61)*Assumptions!$B$35) -> 1742072.9
A106: Project CF (High) | B106: =-$B$11 -> -12341737 | C106: =C$81-MAX(0,(C$81-C$82)*Assumptions!$B$35) -> 2526287.4 | D106: =D$81-MAX(0,(D$81-D$82)*Assumptions!$B$35) -> 2498701.9 | E106: =E$81-MAX(0,(E$81-E$82)*Assumptions!$B$35) -> 2471228.4 | F106: =F$81-MAX(0,(F$81-F$82)*Assumptions!$B$35) -> 2443868.3 | G106: =G$81-MAX(0,(G$81-G$82)*Assumptions!$B$35) -> 2416623.1 | H106: =H$81-MAX(0,(H$81-H$82)*Assumptions!$B$35) -> 2323280.6 | I106: =I$81-MAX(0,(I$81-I$82)*Assumptions!$B$35) -> 2295607.3 | J106: =J$81-MAX(0,(J$81-J$82)*Assumptions!$B$35) -> 2268046.7 | ... V106: =V$81-MAX(0,(V$81-V$82)*Assumptions!$B$35) -> 1919169.4

Sheet Type B - 5MWp
A1: SHARK — Type B: Medium Hybrid Park
A2: 5 MWp + 20 MWh Hybrid Park — Per-Unit Financial Model
A4: CAPEX & FINANCING
A5: PV Capacity (MWp) | B5: 5
A6: BESS Capacity (MWh) | B6: 20
A7: BESS Power (MW) | B7: =B6/Assumptions!$B$6 -> 5
A8: PV EPC Self-Cost (EUR) | B8: 2700385
A9: RTB Acquisition (EUR) | B9: =B5*Assumptions!$B$5 -> 1750000
A10: BESS Installed Cost (EUR) | B10: 1919179
A11: Total CAPEX (EUR) | B11: =B8+B9+B10 -> 6369564
A12: Equity (PV + RTB) | B12: =B8+B9 -> 4450385
A13: Debt (BESS — 100% LTV) | B13: =B10 -> 1919179
A14: Annual Debt Service | B14: =-PMT(Assumptions!$B$38,Assumptions!$B$39,B13) -> 184898.1
A15: Annual Depreciation (SL) | B15: =B11/Assumptions!$B$7 -> 318478.2
A16: Units in Portfolio | B16: 3
A18: ANNUAL PRODUCTION & TECHNICAL DATA
A19: Year # | C19: 1 | D19: 2 | E19: 3 | F19: 4 | G19: 5 | H19: 6 | I19: 7 | J19: 8 | K19: 9 | L19: 10 | M19: 11 | N19: 12 | O19: 13 | P19: 14 | Q19: 15 | R19: 16 | S19: 17 | T19: 18 | U19: 19 | V19: 20 | W19: Total/Avg
A20: Calendar | C20: 2026 | D20: 2027 | E20: 2028 | F20: 2029 | G20: 2030 | H20: 2031 | I20: 2032 | J20: 2033 | K20: 2034 | L20: 2035 | M20: 2036 | N20: 2037 | O20: 2038 | P20: 2039 | Q20: 2040 | R20: 2041 | S20: 2042 | T20: 2043 | U20: 2044 | V20: 2045
A21: PV Production (MWh) | C21: =IF(C$19=1,$B$5*Assumptions!$B$10*(1-Assumptions!$B$11),$B$5*Assumptions!$B$10*(1-Assumptions!$B$11)*(1-Assumptions!$B$12)^(C$19-1)) -> 8531.25 | D21: =IF(D$19=1,$B$5*Assumptions!$B$10*(1-Assumptions!$B$11),$B$5*Assumptions!$B$10*(1-Assumptions!$B$11)*(1-Assumptions!$B$12)^(D$19-1)) -> 8488.5938 | E21: =IF(E$19=1,$B$5*Assumptions!$B$10*(1-Assumptions!$B$11),$B$5*Assumptions!$B$10*(1-Assumptions!$B$11)*(1-Assumptions!$B$12)^(E$19-1)) -> 8446.1508 | F21: =IF(F$19=1,$B$5*Assumptions!$B$10*(1-Assumptions!$B$11),$B$5*Assumptions!$B$10*(1-Assumptions!$B$11)*(1-Assumptions!$B$12)^(F$19-1)) -> 8403.92 | G21: =IF(G$19=1,$B$5*Assumptions!$B$10*(1-Assumptions!$B$11),$B$5*Assumptions!$B$10*(1-Assumptions!$B$11)*(1-Assumptions!$B$12)^(G$19-1)) -> 8361.9004 | H21: =IF(H$19=1,$B$5*Assumptions!$B$10*(1-Assumptions!$B$11),$B$5*Assumptions!$B$10*(1-Assumptions!$B$11)*(1-Assumptions!$B$12)^(H$19-1)) -> 8320.0909 | I21: =IF(I$19=1,$B$5*Assumptions!$B$10*(1-Assumptions!$B$11),$B$5*Assumptions!$B$10*(1-Assumptions!$B$11)*(1-Assumptions!$B$12)^(I$19-1)) -> 8278.4905 | J21: =IF(J$19=1,$B$5*Assumptions!$B$10*(1-Assumptions!$B$11),$B$5*Assumptions!$B$10*(1-Assumptions!$B$11)*(1-Assumptions!$B$12)^(J$19-1)) -> 8237.098 | ... V21: =IF(V$19=1,$B$5*Assumptions!$B$10*(1-Assumptions!$B$11),$B$5*Assumptions!$B$10*(1-Assumptions!$B$11)*(1-Assumptions!$B$12)^(V$19-1)) -> 7756.2394 | W21: =SUM(C$21:V$21) -> 162758.37
A22: PV Direct Sales (MWh) | C22: =C$21*(1-Assumptions!$B$13) -> 4265.625 | D22: =D$21*(1-Assumptions!$B$13) -> 4244.2969 | E22: =E$21*(1-Assumptions!$B$13) -> 4223.0754 | F22: =F$21*(1-Assumptions!$B$13) -> 4201.96 | G22: =G$21*(1-Assumptions!$B$13) -> 4180.9502 | H22: =H$21*(1-Assumptions!$B$13) -> 4160.0455 | I22: =I$21*(1-Assumptions!$B$13) -> 4139.2452 | J22: =J$21*(1-Assumptions!$B$13) -> 4118.549 | ... V22: =V$21*(1-Assumptions!$B$13) -> 3878.1197 | W22: =SUM(C$22:V$22) -> 81379.184
A23: PV Curtailed → BESS (MWh) | C23: =C$21*Assumptions!$B$13 -> 4265.625 | D23: =D$21*Assumptions!$B$13 -> 4244.2969 | E23: =E$21*Assumptions!$B$13 -> 4223.0754 | F23: =F$21*Assumptions!$B$13 -> 4201.96 | G23: =G$21*Assumptions!$B$13 -> 4180.9502 | H23: =H$21*Assumptions!$B$13 -> 4160.0455 | I23: =I$21*Assumptions!$B$13 -> 4139.2452 | J23: =J$21*Assumptions!$B$13 -> 4118.549 | ... V23: =V$21*Assumptions!$B$13 -> 3878.1197 | W23: =SUM(C$23:V$23) -> 81379.184
A24: BESS State of Health (%) | C24: =MAX(0.6,Assumptions!$B$20-Assumptions!$B$21*(C$19-1)) -> 0.985 | D24: =MAX(0.6,Assumptions!$B$20-Assumptions!$B$21*(D$19-1)) -> 0.9715 | E24: =MAX(0.6,Assumptions!$B$20-Assumptions!$B$21*(E$19-1)) -> 0.958 | F24: =MAX(0.6,Assumptions!$B$20-Assumptions!$B$21*(F$19-1)) -> 0.9445 | G24: =MAX(0.6,Assumptions!$B$20-Assumptions!$B$21*(G$19-1)) -> 0.931 | H24: =MAX(0.6,Assumptions!$B$20-Assumptions!$B$21*(H$19-1)) -> 0.9175 | I24: =MAX(0.6,Assumptions!$B$20-Assumptions!$B$21*(I$19-1)) -> 0.904 | J24: =MAX(0.6,Assumptions!$B$20-Assumptions!$B$21*(J$19-1)) -> 0.8905 | ... V24: =MAX(0.6,Assumptions!$B$20-Assumptions!$B$21*(V$19-1)) -> 0.7285 | W24: =AVERAGE(C$24:V$24) -> 0.85675
A25: BESS Sellable Energy (MWh) | C25: =$B$6*C$24*Assumptions!$B$22*Assumptions!$B$19*Assumptions!$B$24*365*Assumptions!$B$23 -> 5473.1641 | D25: =$B$6*D$24*Assumptions!$B$22*Assumptions!$B$19*Assumptions!$B$24*365*Assumptions!$B$23 -> 5398.1512 | E25: =$B$6*E$24*Assumptions!$B$22*Assumptions!$B$19*Assumptions!$B$24*365*Assumptions!$B$23 -> 5323.1383 | F25: =$B$6*F$24*Assumptions!$B$22*Assumptions!$B$19*Assumptions!$B$24*365*Assumptions!$B$23 -> 5248.1254 | G25: =$B$6*G$24*Assumptions!$B$22*Assumptions!$B$19*Assumptions!$B$24*365*Assumptions!$B$23 -> 5173.1125 | H25: =$B$6*H$24*Assumptions!$B$22*Assumptions!$B$19*Assumptions!$B$24*365*Assumptions!$B$23 -> 5098.0996 | I25: =$B$6*I$24*Assumptions!$B$22*Assumptions!$B$19*Assumptions!$B$24*365*Assumptions!$B$23 -> 5023.0867 | J25: =$B$6*J$24*Assumptions!$B$22*Assumptions!$B$19*Assumptions!$B$24*365*Assumptions!$B$23 -> 4948.0738 | ... V25: =$B$6*V$24*Assumptions!$B$22*Assumptions!$B$19*Assumptions!$B$24*365*Assumptions!$B$23 -> 4047.9188 | W25: =SUM(C$25:V$25) -> 95210.83
A26: BESS Charging Needed (MWh) | C26: =$B$6*C$24*Assumptions!$B$22*Assumptions!$B$24*365*Assumptions!$B$23 -> 6342.021 | D26: =$B$6*D$24*Assumptions!$B$22*Assumptions!$B$24*365*Assumptions!$B$23 -> 6255.0999 | E26: =$B$6*E$24*Assumptions!$B$22*Assumptions!$B$24*365*Assumptions!$B$23 -> 6168.1788 | F26: =$B$6*F$24*Assumptions!$B$22*Assumptions!$B$24*365*Assumptions!$B$23 -> 6081.2577 | G26: =$B$6*G$24*Assumptions!$B$22*Assumptions!$B$24*365*Assumptions!$B$23 -> 5994.3366 | H26: =$B$6*H$24*Assumptions!$B$22*Assumptions!$B$24*365*Assumptions!$B$23 -> 5907.4155 | I26: =$B$6*I$24*Assumptions!$B$22*Assumptions!$B$24*365*Assumptions!$B$23 -> 5820.4944 | J26: =$B$6*J$24*Assumptions!$B$22*Assumptions!$B$24*365*Assumptions!$B$23 -> 5733.5733 | ... V26: =$B$6*V$24*Assumptions!$B$22*Assumptions!$B$24*365*Assumptions!$B$23 -> 4690.5201 | W26: =SUM(C$26:V$26) -> 110325.41
A27: Grid Purchases for BESS (MWh) | C27: =MAX(0,C$26-C$23) -> 2076.396 | D27: =MAX(0,D$26-D$23) -> 2010.803 | E27: =MAX(0,E$26-E$23) -> 1945.1034 | F27: =MAX(0,F$26-F$23) -> 1879.2977 | G27: =MAX(0,G$26-G$23) -> 1813.3864 | H27: =MAX(0,H$26-H$23) -> 1747.37 | I27: =MAX(0,I$26-I$23) -> 1681.2492 | J27: =MAX(0,J$26-J$23) -> 1615.0243 | ... V27: =MAX(0,V$26-V$23) -> 812.40042 | W27: =SUM(C$27:V$27) -> 28946.227
A29: SCENARIO: LOW CASE (EUR 110/MWh)
A30: PV Direct Revenue | C30: =C$22*Assumptions!$B$14 -> 682500 | D30: =D$22*Assumptions!$B$14 -> 679087.5 | E30: =E$22*Assumptions!$B$14 -> 675692.06 | F30: =F$22*Assumptions!$B$14 -> 672313.6 | G30: =G$22*Assumptions!$B$14 -> 668952.03 | H30: =H$22*Assumptions!$B$14 -> 665607.27 | I30: =I$22*Assumptions!$B$14 -> 662279.24 | J30: =J$22*Assumptions!$B$14 -> 658967.84 | ... V30: =V$22*Assumptions!$B$14 -> 620499.15 | W30: =SUM(C$30:V$30) -> 13020669
A31: GoO Revenue | C31: =C$21*Assumptions!$B$15 -> 8531.25 | D31: =D$21*Assumptions!$B$15 -> 8488.5938 | E31: =E$21*Assumptions!$B$15 -> 8446.1508 | F31: =F$21*Assumptions!$B$15 -> 8403.92 | G31: =G$21*Assumptions!$B$15 -> 8361.9004 | H31: =H$21*Assumptions!$B$15 -> 8320.0909 | I31: =I$21*Assumptions!$B$15 -> 8278.4905 | J31: =J$21*Assumptions!$B$15 -> 8237.098 | ... V31: =V$21*Assumptions!$B$15 -> 7756.2394 | W31: =SUM(C$31:V$31) -> 162758.37
A32: BESS Arbitrage Revenue | C32: =C$25*Assumptions!$B$42 -> 602048.05 | D32: =D$25*Assumptions!$B$42 -> 593796.63 | E32: =E$25*Assumptions!$B$42 -> 585545.21 | F32: =F$25*Assumptions!$B$42 -> 577293.79 | G32: =G$25*Assumptions!$B$42 -> 569042.37 | H32: =H$25*Assumptions!$B$42 -> 560790.95 | I32: =I$25*Assumptions!$B$42 -> 552539.53 | J32: =J$25*Assumptions!$B$42 -> 544288.11 | ... V32: =V$25*Assumptions!$B$42 -> 445271.07 | W32: =SUM(C$32:V$32) -> 10473191
A33: Total Revenue | C33: =C$30+C$31+C$32 -> 1293079.3 | D33: =D$30+D$31+D$32 -> 1281372.7 | E33: =E$30+E$31+E$32 -> 1269683.4 | F33: =F$30+F$31+F$32 -> 1258011.3 | G33: =G$30+G$31+G$32 -> 1246356.3 | H33: =H$30+H$31+H$32 -> 1234718.3 | I33: =I$30+I$31+I$32 -> 1223097.3 | J33: =J$30+J$31+J$32 -> 1211493.1 | ... V33: =V$30+V$31+V$32 -> 1073526.5 | W33: =SUM(C$33:V$33) -> 23656619
A34: Energy Purchase Cost | C34: =C$27*Assumptions!$B$25*(1+Assumptions!$B$36)^(C$19-1) -> 103819.8 | D34: =D$27*Assumptions!$B$25*(1+Assumptions!$B$36)^(D$19-1) -> 101545.55 | E34: =E$27*Assumptions!$B$25*(1+Assumptions!$B$36)^(E$19-1) -> 99209.999 | F34: =F$27*Assumptions!$B$25*(1+Assumptions!$B$36)^(F$19-1) -> 96812.114 | G34: =G$27*Assumptions!$B$25*(1+Assumptions!$B$36)^(G$19-1) -> 94350.857 | H34: =H$27*Assumptions!$B$25*(1+Assumptions!$B$36)^(H$19-1) -> 91825.174 | I34: =I$27*Assumptions!$B$25*(1+Assumptions!$B$36)^(I$19-1) -> 89233.993 | J34: =J$27*Assumptions!$B$25*(1+Assumptions!$B$36)^(J$19-1) -> 86576.232 | ... V34: =V$27*Assumptions!$B$25*(1+Assumptions!$B$36)^(V$19-1) -> 49073.411 | W34: =SUM(C$34:V$34) -> 1569198.4
A35: PV OPEX | C35: =$B$5*Assumptions!$B$16*(1+Assumptions!$B$36)^(C$19-1) -> 75000 | D35: =$B$5*Assumptions!$B$16*(1+Assumptions!$B$36)^(D$19-1) -> 75750 | E35: =$B$5*Assumptions!$B$16*(1+Assumptions!$B$36)^(E$19-1) -> 76507.5 | F35: =$B$5*Assumptions!$B$16*(1+Assumptions!$B$36)^(F$19-1) -> 77272.575 | G35: =$B$5*Assumptions!$B$16*(1+Assumptions!$B$36)^(G$19-1) -> 78045.301 | H35: =$B$5*Assumptions!$B$16*(1+Assumptions!$B$36)^(H$19-1) -> 78825.754 | I35: =$B$5*Assumptions!$B$16*(1+Assumptions!$B$36)^(I$19-1) -> 79614.011 | J35: =$B$5*Assumptions!$B$16*(1+Assumptions!$B$36)^(J$19-1) -> 80410.151 | ... V35: =$B$5*Assumptions!$B$16*(1+Assumptions!$B$36)^(V$19-1) -> 90608.171 | W35: =SUM(C$35:V$35) -> 1651425.3
A36: BESS OPEX (O&M+Mgmt+CERA+Grounds) | C36: =($B$6*Assumptions!$B$26+$B$6*Assumptions!$B$27+$B$7*Assumptions!$B$28+Assumptions!$B$29)*(1+Assumptions!$B$36)^(C$19-1) -> 72500 | D36: =($B$6*Assumptions!$B$26+$B$6*Assumptions!$B$27+$B$7*Assumptions!$B$28+Assumptions!$B$29)*(1+Assumptions!$B$36)^(D$19-1) -> 73225 | E36: =($B$6*Assumptions!$B$26+$B$6*Assumptions!$B$27+$B$7*Assumptions!$B$28+Assumptions!$B$29)*(1+Assumptions!$B$36)^(E$19-1) -> 73957.25 | F36: =($B$6*Assumptions!$B$26+$B$6*Assumptions!$B$27+$B$7*Assumptions!$B$28+Assumptions!$B$29)*(1+Assumptions!$B$36)^(F$19-1) -> 74696.822 | G36: =($B$6*Assumptions!$B$26+$B$6*Assumptions!$B$27+$B$7*Assumptions!$B$28+Assumptions!$B$29)*(1+Assumptions!$B$36)^(G$19-1) -> 75443.791 | H36: =($B$6*Assumptions!$B$26+$B$6*Assumptions!$B$27+$B$7*Assumptions!$B$28+Assumptions!$B$29)*(1+Assumptions!$B$36)^(H$19-1) -> 76198.229 | I36: =($B$6*Assumptions!$B$26+$B$6*Assumptions!$B$27+$B$7*Assumptions!$B$28+Assumptions!$B$29)*(1+Assumptions!$B$36)^(I$19-1) -> 76960.211 | J36: =($B$6*Assumptions!$B$26+$B$6*Assumptions!$B$27+$B$7*Assumptions!$B$28+Assumptions!$B$29)*(1+Assumptions!$B$36)^(J$19-1) -> 77729.813 | ... V36: =($B$6*Assumptions!$B$26+$B$6*Assumptions!$B$27+$B$7*Assumptions!$B$28+Assumptions!$B$29)*(1+Assumptions!$B$36)^(V$19-1) -> 87587.899 | W36: =SUM(C$36:V$36) -> 1596377.8
A37: BESS Warranty Extension | C37: =IF(C$19<=5,0,IF(C$19<=10,Assumptions!$B$30,IF(C$19<=15,Assumptions!$B$31,Assumptions!$B$32)))*$B$6*(1+Assumptions!$B$36)^(C$19-1) -> 0 | D37: =IF(D$19<=5,0,IF(D$19<=10,Assumptions!$B$30,IF(D$19<=15,Assumptions!$B$31,Assumptions!$B$32)))*$B$6*(1+Assumptions!$B$36)^(D$19-1) -> 0 | E37: =IF(E$19<=5,0,IF(E$19<=10,Assumptions!$B$30,IF(E$19<=15,Assumptions!$B$31,Assumptions!$B$32)))*$B$6*(1+Assumptions!$B$36)^(E$19-1) -> 0 | F37: =IF(F$19<=5,0,IF(F$19<=10,Assumptions!$B$30,IF(F$19<=15,Assumptions!$B$31,Assumptions!$B$32)))*$B$6*(1+Assumptions!$B$36)^(F$19-1) -> 0 | G37: =IF(G$19<=5,0,IF(G$19<=10,Assumptions!$B$30,IF(G$19<=15,Assumptions!$B$31,Assumptions!$B$32)))*$B$6*(1+Assumptions!$B$36)^(G$19-1) -> 0 | H37: =IF(H$19<=5,0,IF(H$19<=10,Assumptions!$B$30,IF(H$19<=15,Assumptions!$B$31,Assumptions!$B$32)))*$B$6*(1+Assumptions!$B$36)^(H$19-1) -> 37836.362 | I37: =IF(I$19<=5,0,IF(I$19<=10,Assumptions!$B$30,IF(I$19<=15,Assumptions!$B$31,Assumptions!$B$32)))*$B$6*(1+Assumptions!$B$36)^(I$19-1) -> 38214.725 | J37: =IF(J$19<=5,0,IF(J$19<=10,Assumptions!$B$30,IF(J$19<=15,Assumptions!$B$31,Assumptions!$B$32)))*$B$6*(1+Assumptions!$B$36)^(J$19-1) -> 38596.873 | ... V37: =IF(V$19<=5,0,IF(V$19<=10,Assumptions!$B$30,IF(V$19<=15,Assumptions!$B$31,Assumptions!$B$32)))*$B$6*(1+Assumptions!$B$36)^(V$19-1) -> 59197.339 | W37: =SUM(C$37:V$37) -> 719843.47
A38: Total Operating Costs | C38: =C$34+C$35+C$36+C$37 -> 251319.8 | D38: =D$34+D$35+D$36+D$37 -> 250520.55 | E38: =E$34+E$35+E$36+E$37 -> 249674.75 | F38: =F$34+F$35+F$36+F$37 -> 248781.51 | G38: =G$34+G$35+G$36+G$37 -> 247839.95 | H38: =H$34+H$35+H$36+H$37 -> 284685.52 | I38: =I$34+I$35+I$36+I$37 -> 284022.94 | J38: =J$34+J$35+J$36+J$37 -> 283313.07 | ... V38: =V$34+V$35+V$36+V$37 -> 286466.82 | W38: =SUM(C$38:V$38) -> 5536844.9
A39: EBITDA | C39: =C$33-C$38 -> 1041759.5 | D39: =D$33-D$38 -> 1030852.2 | E39: =E$33-E$38 -> 1020008.7 | F39: =F$33-F$38 -> 1009229.8 | G39: =G$33-G$38 -> 998516.36 | H39: =H$33-H$38 -> 950032.8 | I39: =I$33-I$38 -> 939074.32 | J39: =J$33-J$38 -> 928179.98 | ... V39: =V$33-V$38 -> 787059.64 | W39: =SUM(C$39:V$39) -> 18119774
A40: Depreciation | C40: =$B$15 -> 318478.2 | D40: =$B$15 -> 318478.2 | E40: =$B$15 -> 318478.2 | F40: =$B$15 -> 318478.2 | G40: =$B$15 -> 318478.2 | H40: =$B$15 -> 318478.2 | I40: =$B$15 -> 318478.2 | J40: =$B$15 -> 318478.2 | ... V40: =$B$15 -> 318478.2 | W40: =SUM(C$40:V$40) -> 6369564
A41: Interest Expense | C41: =IF(C$19<=Assumptions!$B$39,-IPMT(Assumptions!$B$38,C$19,Assumptions!$B$39,$B$13),0) -> 95958.95 | D41: =IF(D$19<=Assumptions!$B$39,-IPMT(Assumptions!$B$38,D$19,Assumptions!$B$39,$B$13),0) -> 91511.993 | E41: =IF(E$19<=Assumptions!$B$39,-IPMT(Assumptions!$B$38,E$19,Assumptions!$B$39,$B$13),0) -> 86842.688 | F41: =IF(F$19<=Assumptions!$B$39,-IPMT(Assumptions!$B$38,F$19,Assumptions!$B$39,$B$13),0) -> 81939.917 | G41: =IF(G$19<=Assumptions!$B$39,-IPMT(Assumptions!$B$38,G$19,Assumptions!$B$39,$B$13),0) -> 76792.008 | H41: =IF(H$19<=Assumptions!$B$39,-IPMT(Assumptions!$B$38,H$19,Assumptions!$B$39,$B$13),0) -> 71386.704 | I41: =IF(I$19<=Assumptions!$B$39,-IPMT(Assumptions!$B$38,I$19,Assumptions!$B$39,$B$13),0) -> 65711.134 | J41: =IF(J$19<=Assumptions!$B$39,-IPMT(Assumptions!$B$38,J$19,Assumptions!$B$39,$B$13),0) -> 59751.786 | ... V41: =IF(V$19<=Assumptions!$B$39,-IPMT(Assumptions!$B$38,V$19,Assumptions!$B$39,$B$13),0) -> 0 | W41: =SUM(C$41:V$41) -> 854292.43
A42: Earnings Before Tax | C42: =C$39-C$40-C$41 -> 627322.35 | D42: =D$39-D$40-D$41 -> 620861.98 | E42: =E$39-E$40-E$41 -> 614687.79 | F42: =F$39-F$40-F$41 -> 608811.69 | G42: =G$39-G$40-G$41 -> 603246.15 | H42: =H$39-H$40-H$41 -> 560167.9 | I42: =I$39-I$40-I$41 -> 554884.99 | J42: =J$39-J$40-J$41 -> 549950 | ... V42: =V$39-V$40-V$41 -> 468581.44 | W42: =SUM(C$42:V$42) -> 10895918
A43: Corporate Tax (12.5%) | C43: =MAX(0,C$42*Assumptions!$B$35) -> 78415.294 | D43: =MAX(0,D$42*Assumptions!$B$35) -> 77607.748 | E43: =MAX(0,E$42*Assumptions!$B$35) -> 76835.974 | F43: =MAX(0,F$42*Assumptions!$B$35) -> 76101.461 | G43: =MAX(0,G$42*Assumptions!$B$35) -> 75405.769 | H43: =MAX(0,H$42*Assumptions!$B$35) -> 70020.987 | I43: =MAX(0,I$42*Assumptions!$B$35) -> 69360.623 | J43: =MAX(0,J$42*Assumptions!$B$35) -> 68743.75 | ... V43: =MAX(0,V$42*Assumptions!$B$35) -> 58572.68 | W43: =SUM(C$43:V$43) -> 1361989.7
A44: Net Income | C44: =C$42-C$43 -> 548907.06 | D44: =D$42-D$43 -> 543254.23 | E44: =E$42-E$43 -> 537851.82 | F44: =F$42-F$43 -> 532710.23 | G44: =G$42-G$43 -> 527840.38 | H44: =H$42-H$43 -> 490146.91 | I44: =I$42-I$43 -> 485524.36 | J44: =J$42-J$43 -> 481206.25 | ... V44: =V$42-V$43 -> 410008.76 | W44: =SUM(C$44:V$44) -> 9533928
A45: Debt Service (Annuity) | C45: =IF(C$19<=Assumptions!$B$39,$B$14,0) -> 184898.1 | D45: =IF(D$19<=Assumptions!$B$39,$B$14,0) -> 184898.1 | E45: =IF(E$19<=Assumptions!$B$39,$B$14,0) -> 184898.1 | F45: =IF(F$19<=Assumptions!$B$39,$B$14,0) -> 184898.1 | G45: =IF(G$19<=Assumptions!$B$39,$B$14,0) -> 184898.1 | H45: =IF(H$19<=Assumptions!$B$39,$B$14,0) -> 184898.1 | I45: =IF(I$19<=Assumptions!$B$39,$B$14,0) -> 184898.1 | J45: =IF(J$19<=Assumptions!$B$39,$B$14,0) -> 184898.1 | ... V45: =IF(V$19<=Assumptions!$B$39,$B$14,0) -> 0 | W45: =SUM(C$45:V$45) -> 2773471.4
A46: Free Cash Flow to Equity | C46: =C$39-C$45-C$43 -> 778446.11 | D46: =D$39-D$45-D$43 -> 768346.33 | E46: =E$39-E$45-E$43 -> 758274.61 | F46: =F$39-F$45-F$43 -> 748230.25 | G46: =G$39-G$45-G$43 -> 738212.5 | H46: =H$39-H$45-H$43 -> 695113.72 | I46: =I$39-I$45-I$43 -> 684815.6 | J46: =J$39-J$45-J$43 -> 674538.14 | ... V46: =V$39-V$45-V$43 -> 728486.96 | W46: =SUM(C$46:V$46) -> 13984313
A47: Cumulative Cash Flow | C47: =C$46 -> 778446.11 | D47: =C$47+D$46 -> 1546792.4 | E47: =D$47+E$46 -> 2305067.1 | F47: =E$47+F$46 -> 3053297.3 | G47: =F$47+G$46 -> 3791509.8 | H47: =G$47+H$46 -> 4486623.5 | I47: =H$47+I$46 -> 5171439.1 | J47: =I$47+J$46 -> 5845977.3 | K47: =J$47+K$46 -> 6510257.5 | ... V47: =U$47+V$46 -> 13984313 | W47: =V$47 -> 13984313
A48: DSCR | C48: =IF(C$45>0,C$39/C$45,"N/A") -> 5.634236 | D48: =IF(D$45>0,D$39/D$45,"N/A") -> 5.575245 | E48: =IF(E$45>0,E$39/E$45,"N/A") -> 5.5165992 | F48: =IF(F$45>0,F$39/F$45,"N/A") -> 5.4583029 | G48: =IF(G$45>0,G$39/G$45,"N/A") -> 5.4003604 | H48: =IF(H$45>0,H$39/H$45,"N/A") -> 5.1381427 | I48: =IF(I$45>0,I$39/I$45,"N/A") -> 5.078875 | J48: =IF(J$45>0,J$39/J$45,"N/A") -> 5.0199543 | ... V48: =IF(V$45>0,V$39/V$45,"N/A") -> N/A | W48: =AVERAGE(C$48:Q$48) -> 5.0772574
A50: SCENARIO: BASE CASE (EUR 150/MWh Blended)
A51: PV Direct Revenue | C51: =C$22*Assumptions!$B$14 -> 682500 | D51: =D$22*Assumptions!$B$14 -> 679087.5 | E51: =E$22*Assumptions!$B$14 -> 675692.06 | F51: =F$22*Assumptions!$B$14 -> 672313.6 | G51: =G$22*Assumptions!$B$14 -> 668952.03 | H51: =H$22*Assumptions!$B$14 -> 665607.27 | I51: =I$22*Assumptions!$B$14 -> 662279.24 | J51: =J$22*Assumptions!$B$14 -> 658967.84 | ... V51: =V$22*Assumptions!$B$14 -> 620499.15 | W51: =SUM(C$51:V$51) -> 13020669
A52: GoO Revenue | C52: =C$21*Assumptions!$B$15 -> 8531.25 | D52: =D$21*Assumptions!$B$15 -> 8488.5938 | E52: =E$21*Assumptions!$B$15 -> 8446.1508 | F52: =F$21*Assumptions!$B$15 -> 8403.92 | G52: =G$21*Assumptions!$B$15 -> 8361.9004 | H52: =H$21*Assumptions!$B$15 -> 8320.0909 | I52: =I$21*Assumptions!$B$15 -> 8278.4905 | J52: =J$21*Assumptions!$B$15 -> 8237.098 | ... V52: =V$21*Assumptions!$B$15 -> 7756.2394 | W52: =SUM(C$52:V$52) -> 162758.37
A53: BESS Arbitrage Revenue | C53: =C$25*Assumptions!$B$43 -> 820974.62 | D53: =D$25*Assumptions!$B$43 -> 809722.68 | E53: =E$25*Assumptions!$B$43 -> 798470.75 | F53: =F$25*Assumptions!$B$43 -> 787218.81 | G53: =G$25*Assumptions!$B$43 -> 775966.87 | H53: =H$25*Assumptions!$B$43 -> 764714.94 | I53: =I$25*Assumptions!$B$43 -> 753463 | J53: =J$25*Assumptions!$B$43 -> 742211.06 | ... V53: =V$25*Assumptions!$B$43 -> 607187.83 | W53: =SUM(C$53:V$53) -> 14281624
A54: Total Revenue | C54: =C$51+C$52+C$53 -> 1512005.9 | D54: =D$51+D$52+D$53 -> 1497298.8 | E54: =E$51+E$52+E$53 -> 1482609 | F54: =F$51+F$52+F$53 -> 1467936.3 | G54: =G$51+G$52+G$53 -> 1453280.8 | H54: =H$51+H$52+H$53 -> 1438642.3 | I54: =I$51+I$52+I$53 -> 1424020.7 | J54: =J$51+J$52+J$53 -> 1409416 | ... V54: =V$51+V$52+V$53 -> 1235443.2 | W54: =SUM(C$54:V$54) -> 27465052
A55: Energy Purchase Cost | C55: =C$27*Assumptions!$B$25*(1+Assumptions!$B$36)^(C$19-1) -> 103819.8 | D55: =D$27*Assumptions!$B$25*(1+Assumptions!$B$36)^(D$19-1) -> 101545.55 | E55: =E$27*Assumptions!$B$25*(1+Assumptions!$B$36)^(E$19-1) -> 99209.999 | F55: =F$27*Assumptions!$B$25*(1+Assumptions!$B$36)^(F$19-1) -> 96812.114 | G55: =G$27*Assumptions!$B$25*(1+Assumptions!$B$36)^(G$19-1) -> 94350.857 | H55: =H$27*Assumptions!$B$25*(1+Assumptions!$B$36)^(H$19-1) -> 91825.174 | I55: =I$27*Assumptions!$B$25*(1+Assumptions!$B$36)^(I$19-1) -> 89233.993 | J55: =J$27*Assumptions!$B$25*(1+Assumptions!$B$36)^(J$19-1) -> 86576.232 | ... V55: =V$27*Assumptions!$B$25*(1+Assumptions!$B$36)^(V$19-1) -> 49073.411 | W55: =SUM(C$55:V$55) -> 1569198.4
A56: PV OPEX | C56: =$B$5*Assumptions!$B$16*(1+Assumptions!$B$36)^(C$19-1) -> 75000 | D56: =$B$5*Assumptions!$B$16*(1+Assumptions!$B$36)^(D$19-1) -> 75750 | E56: =$B$5*Assumptions!$B$16*(1+Assumptions!$B$36)^(E$19-1) -> 76507.5 | F56: =$B$5*Assumptions!$B$16*(1+Assumptions!$B$36)^(F$19-1) -> 77272.575 | G56: =$B$5*Assumptions!$B$16*(1+Assumptions!$B$36)^(G$19-1) -> 78045.301 | H56: =$B$5*Assumptions!$B$16*(1+Assumptions!$B$36)^(H$19-1) -> 78825.754 | I56: =$B$5*Assumptions!$B$16*(1+Assumptions!$B$36)^(I$19-1) -> 79614.011 | J56: =$B$5*Assumptions!$B$16*(1+Assumptions!$B$36)^(J$19-1) -> 80410.151 | ... V56: =$B$5*Assumptions!$B$16*(1+Assumptions!$B$36)^(V$19-1) -> 90608.171 | W56: =SUM(C$56:V$56) -> 1651425.3
A57: BESS OPEX (O&M+Mgmt+CERA+Grounds) | C57: =($B$6*Assumptions!$B$26+$B$6*Assumptions!$B$27+$B$7*Assumptions!$B$28+Assumptions!$B$29)*(1+Assumptions!$B$36)^(C$19-1) -> 72500 | D57: =($B$6*Assumptions!$B$26+$B$6*Assumptions!$B$27+$B$7*Assumptions!$B$28+Assumptions!$B$29)*(1+Assumptions!$B$36)^(D$19-1) -> 73225 | E57: =($B$6*Assumptions!$B$26+$B$6*Assumptions!$B$27+$B$7*Assumptions!$B$28+Assumptions!$B$29)*(1+Assumptions!$B$36)^(E$19-1) -> 73957.25 | F57: =($B$6*Assumptions!$B$26+$B$6*Assumptions!$B$27+$B$7*Assumptions!$B$28+Assumptions!$B$29)*(1+Assumptions!$B$36)^(F$19-1) -> 74696.822 | G57: =($B$6*Assumptions!$B$26+$B$6*Assumptions!$B$27+$B$7*Assumptions!$B$28+Assumptions!$B$29)*(1+Assumptions!$B$36)^(G$19-1) -> 75443.791 | H57: =($B$6*Assumptions!$B$26+$B$6*Assumptions!$B$27+$B$7*Assumptions!$B$28+Assumptions!$B$29)*(1+Assumptions!$B$36)^(H$19-1) -> 76198.229 | I57: =($B$6*Assumptions!$B$26+$B$6*Assumptions!$B$27+$B$7*Assumptions!$B$28+Assumptions!$B$29)*(1+Assumptions!$B$36)^(I$19-1) -> 76960.211 | J57: =($B$6*Assumptions!$B$26+$B$6*Assumptions!$B$27+$B$7*Assumptions!$B$28+Assumptions!$B$29)*(1+Assumptions!$B$36)^(J$19-1) -> 77729.813 | ... V57: =($B$6*Assumptions!$B$26+$B$6*Assumptions!$B$27+$B$7*Assumptions!$B$28+Assumptions!$B$29)*(1+Assumptions!$B$36)^(V$19-1) -> 87587.899 | W57: =SUM(C$57:V$57) -> 1596377.8
A58: BESS Warranty Extension | C58: =IF(C$19<=5,0,IF(C$19<=10,Assumptions!$B$30,IF(C$19<=15,Assumptions!$B$31,Assumptions!$B$32)))*$B$6*(1+Assumptions!$B$36)^(C$19-1) -> 0 | D58: =IF(D$19<=5,0,IF(D$19<=10,Assumptions!$B$30,IF(D$19<=15,Assumptions!$B$31,Assumptions!$B$32)))*$B$6*(1+Assumptions!$B$36)^(D$19-1) -> 0 | E58: =IF(E$19<=5,0,IF(E$19<=10,Assumptions!$B$30,IF(E$19<=15,Assumptions!$B$31,Assumptions!$B$32)))*$B$6*(1+Assumptions!$B$36)^(E$19-1) -> 0 | F58: =IF(F$19<=5,0,IF(F$19<=10,Assumptions!$B$30,IF(F$19<=15,Assumptions!$B$31,Assumptions!$B$32)))*$B$6*(1+Assumptions!$B$36)^(F$19-1) -> 0 | G58: =IF(G$19<=5,0,IF(G$19<=10,Assumptions!$B$30,IF(G$19<=15,Assumptions!$B$31,Assumptions!$B$32)))*$B$6*(1+Assumptions!$B$36)^(G$19-1) -> 0 | H58: =IF(H$19<=5,0,IF(H$19<=10,Assumptions!$B$30,IF(H$19<=15,Assumptions!$B$31,Assumptions!$B$32)))*$B$6*(1+Assumptions!$B$36)^(H$19-1) -> 37836.362 | I58: =IF(I$19<=5,0,IF(I$19<=10,Assumptions!$B$30,IF(I$19<=15,Assumptions!$B$31,Assumptions!$B$32)))*$B$6*(1+Assumptions!$B$36)^(I$19-1) -> 38214.725 | J58: =IF(J$19<=5,0,IF(J$19<=10,Assumptions!$B$30,IF(J$19<=15,Assumptions!$B$31,Assumptions!$B$32)))*$B$6*(1+Assumptions!$B$36)^(J$19-1) -> 38596.873 | ... V58: =IF(V$19<=5,0,IF(V$19<=10,Assumptions!$B$30,IF(V$19<=15,Assumptions!$B$31,Assumptions!$B$32)))*$B$6*(1+Assumptions!$B$36)^(V$19-1) -> 59197.339 | W58: =SUM(C$58:V$58) -> 719843.47
A59: Total Operating Costs | C59: =C$55+C$56+C$57+C$58 -> 251319.8 | D59: =D$55+D$56+D$57+D$58 -> 250520.55 | E59: =E$55+E$56+E$57+E$58 -> 249674.75 | F59: =F$55+F$56+F$57+F$58 -> 248781.51 | G59: =G$55+G$56+G$57+G$58 -> 247839.95 | H59: =H$55+H$56+H$57+H$58 -> 284685.52 | I59: =I$55+I$56+I$57+I$58 -> 284022.94 | J59: =J$55+J$56+J$57+J$58 -> 283313.07 | ... V59: =V$55+V$56+V$57+V$58 -> 286466.82 | W59: =SUM(C$59:V$59) -> 5536844.9
A60: EBITDA | C60: =C$54-C$59 -> 1260686.1 | D60: =D$54-D$59 -> 1246778.2 | E60: =E$54-E$59 -> 1232934.2 | F60: =F$54-F$59 -> 1219154.8 | G60: =G$54-G$59 -> 1205440.9 | H60: =H$54-H$59 -> 1153956.8 | I60: =I$54-I$59 -> 1139997.8 | J60: =J$54-J$59 -> 1126102.9 | ... V60: =V$54-V$59 -> 948976.4 | W60: =SUM(C$60:V$60) -> 21928207
A61: Depreciation | C61: =$B$15 -> 318478.2 | D61: =$B$15 -> 318478.2 | E61: =$B$15 -> 318478.2 | F61: =$B$15 -> 318478.2 | G61: =$B$15 -> 318478.2 | H61: =$B$15 -> 318478.2 | I61: =$B$15 -> 318478.2 | J61: =$B$15 -> 318478.2 | ... V61: =$B$15 -> 318478.2 | W61: =SUM(C$61:V$61) -> 6369564
A62: Interest Expense | C62: =IF(C$19<=Assumptions!$B$39,-IPMT(Assumptions!$B$38,C$19,Assumptions!$B$39,$B$13),0) -> 95958.95 | D62: =IF(D$19<=Assumptions!$B$39,-IPMT(Assumptions!$B$38,D$19,Assumptions!$B$39,$B$13),0) -> 91511.993 | E62: =IF(E$19<=Assumptions!$B$39,-IPMT(Assumptions!$B$38,E$19,Assumptions!$B$39,$B$13),0) -> 86842.688 | F62: =IF(F$19<=Assumptions!$B$39,-IPMT(Assumptions!$B$38,F$19,Assumptions!$B$39,$B$13),0) -> 81939.917 | G62: =IF(G$19<=Assumptions!$B$39,-IPMT(Assumptions!$B$38,G$19,Assumptions!$B$39,$B$13),0) -> 76792.008 | H62: =IF(H$19<=Assumptions!$B$39,-IPMT(Assumptions!$B$38,H$19,Assumptions!$B$39,$B$13),0) -> 71386.704 | I62: =IF(I$19<=Assumptions!$B$39,-IPMT(Assumptions!$B$38,I$19,Assumptions!$B$39,$B$13),0) -> 65711.134 | J62: =IF(J$19<=Assumptions!$B$39,-IPMT(Assumptions!$B$38,J$19,Assumptions!$B$39,$B$13),0) -> 59751.786 | ... V62: =IF(V$19<=Assumptions!$B$39,-IPMT(Assumptions!$B$38,V$19,Assumptions!$B$39,$B$13),0) -> 0 | W62: =SUM(C$62:V$62) -> 854292.43
A63: Earnings Before Tax | C63: =C$60-C$61-C$62 -> 846248.92 | D63: =D$60-D$61-D$62 -> 836788.03 | E63: =E$60-E$61-E$62 -> 827613.32 | F63: =F$60-F$61-F$62 -> 818736.7 | G63: =G$60-G$61-G$62 -> 810170.65 | H63: =H$60-H$61-H$62 -> 764091.88 | I63: =I$60-I$61-I$62 -> 755808.45 | J63: =J$60-J$61-J$62 -> 747872.95 | ... V63: =V$60-V$61-V$62 -> 630498.19 | W63: =SUM(C$63:V$63) -> 14704351
A64: Corporate Tax (12.5%) | C64: =MAX(0,C$63*Assumptions!$B$35) -> 105781.11 | D64: =MAX(0,D$63*Assumptions!$B$35) -> 104598.5 | E64: =MAX(0,E$63*Assumptions!$B$35) -> 103451.67 | F64: =MAX(0,F$63*Assumptions!$B$35) -> 102342.09 | G64: =MAX(0,G$63*Assumptions!$B$35) -> 101271.33 | H64: =MAX(0,H$63*Assumptions!$B$35) -> 95511.485 | I64: =MAX(0,I$63*Assumptions!$B$35) -> 94476.057 | J64: =MAX(0,J$63*Assumptions!$B$35) -> 93484.118 | ... V64: =MAX(0,V$63*Assumptions!$B$35) -> 78812.274 | W64: =SUM(C$64:V$64) -> 1838043.9
A65: Net Income | C65: =C$63-C$64 -> 740467.8 | D65: =D$63-D$64 -> 732189.53 | E65: =E$63-E$64 -> 724161.66 | F65: =F$63-F$64 -> 716394.61 | G65: =G$63-G$64 -> 708899.32 | H65: =H$63-H$64 -> 668580.39 | I65: =I$63-I$64 -> 661332.4 | J65: =J$63-J$64 -> 654388.83 | ... V65: =V$63-V$64 -> 551685.92 | W65: =SUM(C$65:V$65) -> 12866307
A66: Debt Service (Annuity) | C66: =IF(C$19<=Assumptions!$B$39,$B$14,0) -> 184898.1 | D66: =IF(D$19<=Assumptions!$B$39,$B$14,0) -> 184898.1 | E66: =IF(E$19<=Assumptions!$B$39,$B$14,0) -> 184898.1 | F66: =IF(F$19<=Assumptions!$B$39,$B$14,0) -> 184898.1 | G66: =IF(G$19<=Assumptions!$B$39,$B$14,0) -> 184898.1 | H66: =IF(H$19<=Assumptions!$B$39,$B$14,0) -> 184898.1 | I66: =IF(I$19<=Assumptions!$B$39,$B$14,0) -> 184898.1 | J66: =IF(J$19<=Assumptions!$B$39,$B$14,0) -> 184898.1 | ... V66: =IF(V$19<=Assumptions!$B$39,$B$14,0) -> 0 | W66: =SUM(C$66:V$66) -> 2773471.4
A67: Free Cash Flow to Equity | C67: =C$60-C$66-C$64 -> 970006.86 | D67: =D$60-D$66-D$64 -> 957281.62 | E67: =E$60-E$66-E$64 -> 944584.45 | F67: =F$60-F$66-F$64 -> 931914.64 | G67: =G$60-G$66-G$64 -> 919271.43 | H67: =H$60-H$66-H$64 -> 873547.2 | I67: =I$60-I$66-I$64 -> 860623.64 | J67: =J$60-J$66-J$64 -> 847720.72 | ... V67: =V$60-V$66-V$64 -> 870164.12 | W67: =SUM(C$67:V$67) -> 17316692
A68: Cumulative Cash Flow | C68: =C$67 -> 970006.86 | D68: =C$68+D$67 -> 1927288.5 | E68: =D$68+E$67 -> 2871872.9 | F68: =E$68+F$67 -> 3803787.6 | G68: =F$68+G$67 -> 4723059 | H68: =G$68+H$67 -> 5596606.2 | I68: =H$68+I$67 -> 6457229.8 | J68: =I$68+J$67 -> 7304950.6 | K68: =J$68+K$67 -> 8139788 | ... V68: =U$68+V$67 -> 17316692 | W68: =V$68 -> 17316692
A69: DSCR | C69: =IF(C$66>0,C$60/C$66,"N/A") -> 6.818275 | D69: =IF(D$66>0,D$60/D$66,"N/A") -> 6.7430561 | E69: =IF(E$66>0,E$60/E$66,"N/A") -> 6.6681823 | F69: =IF(F$66>0,F$60/F$66,"N/A") -> 6.5936581 | G69: =IF(G$66>0,G$60/G$66,"N/A") -> 6.5194877 | H69: =IF(H$66>0,H$60/H$66,"N/A") -> 6.241042 | I69: =IF(I$66>0,I$60/I$66,"N/A") -> 6.1655464 | J69: =IF(J$66>0,J$60/J$66,"N/A") -> 6.0903977 | ... V69: =IF(V$66>0,V$60/V$66,"N/A") -> N/A | W69: =AVERAGE(C$69:Q$69) -> 6.1477009
A71: SCENARIO: HIGH CASE (EUR 175/MWh)
A72: PV Direct Revenue | C72: =C$22*Assumptions!$B$14 -> 682500 | D72: =D$22*Assumptions!$B$14 -> 679087.5 | E72: =E$22*Assumptions!$B$14 -> 675692.06 | F72: =F$22*Assumptions!$B$14 -> 672313.6 | G72: =G$22*Assumptions!$B$14 -> 668952.03 | H72: =H$22*Assumptions!$B$14 -> 665607.27 | I72: =I$22*Assumptions!$B$14 -> 662279.24 | J72: =J$22*Assumptions!$B$14 -> 658967.84 | ... V72: =V$22*Assumptions!$B$14 -> 620499.15 | W72: =SUM(C$72:V$72) -> 13020669
A73: GoO Revenue | C73: =C$21*Assumptions!$B$15 -> 8531.25 | D73: =D$21*Assumptions!$B$15 -> 8488.5938 | E73: =E$21*Assumptions!$B$15 -> 8446.1508 | F73: =F$21*Assumptions!$B$15 -> 8403.92 | G73: =G$21*Assumptions!$B$15 -> 8361.9004 | H73: =H$21*Assumptions!$B$15 -> 8320.0909 | I73: =I$21*Assumptions!$B$15 -> 8278.4905 | J73: =J$21*Assumptions!$B$15 -> 8237.098 | ... V73: =V$21*Assumptions!$B$15 -> 7756.2394 | W73: =SUM(C$73:V$73) -> 162758.37
A74: BESS Arbitrage Revenue | C74: =C$25*Assumptions!$B$44 -> 957803.72 | D74: =D$25*Assumptions!$B$44 -> 944676.46 | E74: =E$25*Assumptions!$B$44 -> 931549.2 | F74: =F$25*Assumptions!$B$44 -> 918421.94 | G74: =G$25*Assumptions!$B$44 -> 905294.69 | H74: =H$25*Assumptions!$B$44 -> 892167.43 | I74: =I$25*Assumptions!$B$44 -> 879040.17 | J74: =J$25*Assumptions!$B$44 -> 865912.91 | ... V74: =V$25*Assumptions!$B$44 -> 708385.8 | W74: =SUM(C$74:V$74) -> 16661895
A75: Total Revenue | C75: =C$72+C$73+C$74 -> 1648835 | D75: =D$72+D$73+D$74 -> 1632252.6 | E75: =E$72+E$73+E$74 -> 1615687.4 | F75: =F$72+F$73+F$74 -> 1599139.5 | G75: =G$72+G$73+G$74 -> 1582608.6 | H75: =H$72+H$73+H$74 -> 1566094.8 | I75: =I$72+I$73+I$74 -> 1549597.9 | J75: =J$72+J$73+J$74 -> 1533117.8 | ... V75: =V$72+V$73+V$74 -> 1336641.2 | W75: =SUM(C$75:V$75) -> 29845323
A76: Energy Purchase Cost | C76: =C$27*Assumptions!$B$25*(1+Assumptions!$B$36)^(C$19-1) -> 103819.8 | D76: =D$27*Assumptions!$B$25*(1+Assumptions!$B$36)^(D$19-1) -> 101545.55 | E76: =E$27*Assumptions!$B$25*(1+Assumptions!$B$36)^(E$19-1) -> 99209.999 | F76: =F$27*Assumptions!$B$25*(1+Assumptions!$B$36)^(F$19-1) -> 96812.114 | G76: =G$27*Assumptions!$B$25*(1+Assumptions!$B$36)^(G$19-1) -> 94350.857 | H76: =H$27*Assumptions!$B$25*(1+Assumptions!$B$36)^(H$19-1) -> 91825.174 | I76: =I$27*Assumptions!$B$25*(1+Assumptions!$B$36)^(I$19-1) -> 89233.993 | J76: =J$27*Assumptions!$B$25*(1+Assumptions!$B$36)^(J$19-1) -> 86576.232 | ... V76: =V$27*Assumptions!$B$25*(1+Assumptions!$B$36)^(V$19-1) -> 49073.411 | W76: =SUM(C$76:V$76) -> 1569198.4
A77: PV OPEX | C77: =$B$5*Assumptions!$B$16*(1+Assumptions!$B$36)^(C$19-1) -> 75000 | D77: =$B$5*Assumptions!$B$16*(1+Assumptions!$B$36)^(D$19-1) -> 75750 | E77: =$B$5*Assumptions!$B$16*(1+Assumptions!$B$36)^(E$19-1) -> 76507.5 | F77: =$B$5*Assumptions!$B$16*(1+Assumptions!$B$36)^(F$19-1) -> 77272.575 | G77: =$B$5*Assumptions!$B$16*(1+Assumptions!$B$36)^(G$19-1) -> 78045.301 | H77: =$B$5*Assumptions!$B$16*(1+Assumptions!$B$36)^(H$19-1) -> 78825.754 | I77: =$B$5*Assumptions!$B$16*(1+Assumptions!$B$36)^(I$19-1) -> 79614.011 | J77: =$B$5*Assumptions!$B$16*(1+Assumptions!$B$36)^(J$19-1) -> 80410.151 | ... V77: =$B$5*Assumptions!$B$16*(1+Assumptions!$B$36)^(V$19-1) -> 90608.171 | W77: =SUM(C$77:V$77) -> 1651425.3
A78: BESS OPEX (O&M+Mgmt+CERA+Grounds) | C78: =($B$6*Assumptions!$B$26+$B$6*Assumptions!$B$27+$B$7*Assumptions!$B$28+Assumptions!$B$29)*(1+Assumptions!$B$36)^(C$19-1) -> 72500 | D78: =($B$6*Assumptions!$B$26+$B$6*Assumptions!$B$27+$B$7*Assumptions!$B$28+Assumptions!$B$29)*(1+Assumptions!$B$36)^(D$19-1) -> 73225 | E78: =($B$6*Assumptions!$B$26+$B$6*Assumptions!$B$27+$B$7*Assumptions!$B$28+Assumptions!$B$29)*(1+Assumptions!$B$36)^(E$19-1) -> 73957.25 | F78: =($B$6*Assumptions!$B$26+$B$6*Assumptions!$B$27+$B$7*Assumptions!$B$28+Assumptions!$B$29)*(1+Assumptions!$B$36)^(F$19-1) -> 74696.822 | G78: =($B$6*Assumptions!$B$26+$B$6*Assumptions!$B$27+$B$7*Assumptions!$B$28+Assumptions!$B$29)*(1+Assumptions!$B$36)^(G$19-1) -> 75443.791 | H78: =($B$6*Assumptions!$B$26+$B$6*Assumptions!$B$27+$B$7*Assumptions!$B$28+Assumptions!$B$29)*(1+Assumptions!$B$36)^(H$19-1) -> 76198.229 | I78: =($B$6*Assumptions!$B$26+$B$6*Assumptions!$B$27+$B$7*Assumptions!$B$28+Assumptions!$B$29)*(1+Assumptions!$B$36)^(I$19-1) -> 76960.211 | J78: =($B$6*Assumptions!$B$26+$B$6*Assumptions!$B$27+$B$7*Assumptions!$B$28+Assumptions!$B$29)*(1+Assumptions!$B$36)^(J$19-1) -> 77729.813 | ... V78: =($B$6*Assumptions!$B$26+$B$6*Assumptions!$B$27+$B$7*Assumptions!$B$28+Assumptions!$B$29)*(1+Assumptions!$B$36)^(V$19-1) -> 87587.899 | W78: =SUM(C$78:V$78) -> 1596377.8
A79: BESS Warranty Extension | C79: =IF(C$19<=5,0,IF(C$19<=10,Assumptions!$B$30,IF(C$19<=15,Assumptions!$B$31,Assumptions!$B$32)))*$B$6*(1+Assumptions!$B$36)^(C$19-1) -> 0 | D79: =IF(D$19<=5,0,IF(D$19<=10,Assumptions!$B$30,IF(D$19<=15,Assumptions!$B$31,Assumptions!$B$32)))*$B$6*(1+Assumptions!$B$36)^(D$19-1) -> 0 | E79: =IF(E$19<=5,0,IF(E$19<=10,Assumptions!$B$30,IF(E$19<=15,Assumptions!$B$31,Assumptions!$B$32)))*$B$6*(1+Assumptions!$B$36)^(E$19-1) -> 0 | F79: =IF(F$19<=5,0,IF(F$19<=10,Assumptions!$B$30,IF(F$19<=15,Assumptions!$B$31,Assumptions!$B$32)))*$B$6*(1+Assumptions!$B$36)^(F$19-1) -> 0 | G79: =IF(G$19<=5,0,IF(G$19<=10,Assumptions!$B$30,IF(G$19<=15,Assumptions!$B$31,Assumptions!$B$32)))*$B$6*(1+Assumptions!$B$36)^(G$19-1) -> 0 | H79: =IF(H$19<=5,0,IF(H$19<=10,Assumptions!$B$30,IF(H$19<=15,Assumptions!$B$31,Assumptions!$B$32)))*$B$6*(1+Assumptions!$B$36)^(H$19-1) -> 37836.362 | I79: =IF(I$19<=5,0,IF(I$19<=10,Assumptions!$B$30,IF(I$19<=15,Assumptions!$B$31,Assumptions!$B$32)))*$B$6*(1+Assumptions!$B$36)^(I$19-1) -> 38214.725 | J79: =IF(J$19<=5,0,IF(J$19<=10,Assumptions!$B$30,IF(J$19<=15,Assumptions!$B$31,Assumptions!$B$32)))*$B$6*(1+Assumptions!$B$36)^(J$19-1) -> 38596.873 | ... V79: =IF(V$19<=5,0,IF(V$19<=10,Assumptions!$B$30,IF(V$19<=15,Assumptions!$B$31,Assumptions!$B$32)))*$B$6*(1+Assumptions!$B$36)^(V$19-1) -> 59197.339 | W79: =SUM(C$79:V$79) -> 719843.47
A80: Total Operating Costs | C80: =C$76+C$77+C$78+C$79 -> 251319.8 | D80: =D$76+D$77+D$78+D$79 -> 250520.55 | E80: =E$76+E$77+E$78+E$79 -> 249674.75 | F80: =F$76+F$77+F$78+F$79 -> 248781.51 | G80: =G$76+G$77+G$78+G$79 -> 247839.95 | H80: =H$76+H$77+H$78+H$79 -> 284685.52 | I80: =I$76+I$77+I$78+I$79 -> 284022.94 | J80: =J$76+J$77+J$78+J$79 -> 283313.07 | ... V80: =V$76+V$77+V$78+V$79 -> 286466.82 | W80: =SUM(C$80:V$80) -> 5536844.9
A81: EBITDA | C81: =C$75-C$80 -> 1397515.2 | D81: =D$75-D$80 -> 1381732 | E81: =E$75-E$80 -> 1366012.7 | F81: =F$75-F$80 -> 1350358 | G81: =G$75-G$80 -> 1334768.7 | H81: =H$75-H$80 -> 1281409.3 | I81: =I$75-I$80 -> 1265575 | J81: =J$75-J$80 -> 1249804.8 | ... V81: =V$75-V$80 -> 1050174.4 | W81: =SUM(C$81:V$81) -> 24308478
A82: Depreciation | C82: =$B$15 -> 318478.2 | D82: =$B$15 -> 318478.2 | E82: =$B$15 -> 318478.2 | F82: =$B$15 -> 318478.2 | G82: =$B$15 -> 318478.2 | H82: =$B$15 -> 318478.2 | I82: =$B$15 -> 318478.2 | J82: =$B$15 -> 318478.2 | ... V82: =$B$15 -> 318478.2 | W82: =SUM(C$82:V$82) -> 6369564
A83: Interest Expense | C83: =IF(C$19<=Assumptions!$B$39,-IPMT(Assumptions!$B$38,C$19,Assumptions!$B$39,$B$13),0) -> 95958.95 | D83: =IF(D$19<=Assumptions!$B$39,-IPMT(Assumptions!$B$38,D$19,Assumptions!$B$39,$B$13),0) -> 91511.993 | E83: =IF(E$19<=Assumptions!$B$39,-IPMT(Assumptions!$B$38,E$19,Assumptions!$B$39,$B$13),0) -> 86842.688 | F83: =IF(F$19<=Assumptions!$B$39,-IPMT(Assumptions!$B$38,F$19,Assumptions!$B$39,$B$13),0) -> 81939.917 | G83: =IF(G$19<=Assumptions!$B$39,-IPMT(Assumptions!$B$38,G$19,Assumptions!$B$39,$B$13),0) -> 76792.008 | H83: =IF(H$19<=Assumptions!$B$39,-IPMT(Assumptions!$B$38,H$19,Assumptions!$B$39,$B$13),0) -> 71386.704 | I83: =IF(I$19<=Assumptions!$B$39,-IPMT(Assumptions!$B$38,I$19,Assumptions!$B$39,$B$13),0) -> 65711.134 | J83: =IF(J$19<=Assumptions!$B$39,-IPMT(Assumptions!$B$38,J$19,Assumptions!$B$39,$B$13),0) -> 59751.786 | ... V83: =IF(V$19<=Assumptions!$B$39,-IPMT(Assumptions!$B$38,V$19,Assumptions!$B$39,$B$13),0) -> 0 | W83: =SUM(C$83:V$83) -> 854292.43
A84: Earnings Before Tax | C84: =C$81-C$82-C$83 -> 983078.02 | D84: =D$81-D$82-D$83 -> 971741.81 | E84: =E$81-E$82-E$83 -> 960691.78 | F84: =F$81-F$82-F$83 -> 949939.84 | G84: =G$81-G$82-G$83 -> 939498.46 | H84: =H$81-H$82-H$83 -> 891544.37 | I84: =I$81-I$82-I$83 -> 881385.62 | J84: =J$81-J$82-J$83 -> 871574.79 | ... V84: =V$81-V$82-V$83 -> 731696.17 | W84: =SUM(C$84:V$84) -> 17084622
A85: Corporate Tax (12.5%) | C85: =MAX(0,C$84*Assumptions!$B$35) -> 122884.75 | D85: =MAX(0,D$84*Assumptions!$B$35) -> 121467.73 | E85: =MAX(0,E$84*Assumptions!$B$35) -> 120086.47 | F85: =MAX(0,F$84*Assumptions!$B$35) -> 118742.48 | G85: =MAX(0,G$84*Assumptions!$B$35) -> 117437.31 | H85: =MAX(0,H$84*Assumptions!$B$35) -> 111443.05 | I85: =MAX(0,I$84*Assumptions!$B$35) -> 110173.2 | J85: =MAX(0,J$84*Assumptions!$B$35) -> 108946.85 | ... V85: =MAX(0,V$84*Assumptions!$B$35) -> 91462.021 | W85: =SUM(C$85:V$85) -> 2135577.7
A86: Net Income | C86: =C$84-C$85 -> 860193.27 | D86: =D$84-D$85 -> 850274.08 | E86: =E$84-E$85 -> 840605.31 | F86: =F$84-F$85 -> 831197.36 | G86: =G$84-G$85 -> 822061.15 | H86: =H$84-H$85 -> 780101.32 | I86: =I$84-I$85 -> 771212.42 | J86: =J$84-J$85 -> 762627.94 | ... V86: =V$84-V$85 -> 640234.15 | W86: =SUM(C$86:V$86) -> 14949044
A87: Debt Service (Annuity) | C87: =IF(C$19<=Assumptions!$B$39,$B$14,0) -> 184898.1 | D87: =IF(D$19<=Assumptions!$B$39,$B$14,0) -> 184898.1 | E87: =IF(E$19<=Assumptions!$B$39,$B$14,0) -> 184898.1 | F87: =IF(F$19<=Assumptions!$B$39,$B$14,0) -> 184898.1 | G87: =IF(G$19<=Assumptions!$B$39,$B$14,0) -> 184898.1 | H87: =IF(H$19<=Assumptions!$B$39,$B$14,0) -> 184898.1 | I87: =IF(I$19<=Assumptions!$B$39,$B$14,0) -> 184898.1 | J87: =IF(J$19<=Assumptions!$B$39,$B$14,0) -> 184898.1 | ... V87: =IF(V$19<=Assumptions!$B$39,$B$14,0) -> 0 | W87: =SUM(C$87:V$87) -> 2773471.4
A88: Free Cash Flow to Equity | C88: =C$81-C$87-C$85 -> 1089732.3 | D88: =D$81-D$87-D$85 -> 1075366.2 | E88: =E$81-E$87-E$85 -> 1061028.1 | F88: =F$81-F$87-F$85 -> 1046717.4 | G88: =G$81-G$87-G$85 -> 1032433.3 | H88: =H$81-H$87-H$85 -> 985068.13 | I88: =I$81-I$87-I$85 -> 970503.66 | J88: =J$81-J$87-J$85 -> 955959.83 | ... V88: =V$81-V$87-V$85 -> 958712.35 | W88: =SUM(C$88:V$88) -> 19399429
A89: Cumulative Cash Flow | C89: =C$88 -> 1089732.3 | D89: =C$89+D$88 -> 2165098.5 | E89: =D$89+E$88 -> 3226126.6 | F89: =E$89+F$88 -> 4272844 | G89: =F$89+G$88 -> 5305277.3 | H89: =G$89+H$88 -> 6290345.4 | I89: =H$89+I$88 -> 7260849 | J89: =I$89+J$88 -> 8216808.9 | K89: =J$89+K$88 -> 9158244.5 | ... V89: =U$89+V$88 -> 19399429 | W89: =V$89 -> 19399429
A90: DSCR | C90: =IF(C$87>0,C$81/C$87,"N/A") -> 7.5582995 | D90: =IF(D$87>0,D$81/D$87,"N/A") -> 7.472938 | E90: =IF(E$87>0,E$81/E$87,"N/A") -> 7.3879218 | F90: =IF(F$87>0,F$81/F$87,"N/A") -> 7.3032551 | G90: =IF(G$87>0,G$81/G$87,"N/A") -> 7.2189422 | H90: =IF(H$87>0,H$81/H$87,"N/A") -> 6.9303541 | I90: =IF(I$87>0,I$81/I$87,"N/A") -> 6.844716 | J90: =IF(J$87>0,J$81/J$87,"N/A") -> 6.7594248 | ... V90: =IF(V$87>0,V$81/V$87,"N/A") -> N/A | W90: =AVERAGE(C$90:Q$90) -> 6.816728
A92: RETURNS SUMMARY (PER UNIT)
A93: Metric | B93: Low (110) | C93: Base (150) | D93: High (175)
A94: Equity IRR | B94: =IRR(B$101:V$101) -> 0.15221289 | C94: =IRR(B$102:V$102) -> 0.19817566 | D94: =IRR(B$103:V$103) -> 0.22627513
A95: Project IRR (Unlevered) | B95: =IRR(B$104:V$104) -> 0.12446672 | C95: =IRR(B$105:V$105) -> 0.15813866 | D95: =IRR(B$106:V$106) -> 0.17853336
A96: Equity NPV (@ 8%) | B96: {=NPV(Assumptions!$B$37,C$101:V$101)+B$101} -> 2507036.3 | C96: {=NPV(Assumptions!$B$37,C$102:V$102)+B$102} -> 4206416 | D96: {=NPV(Assumptions!$B$37,C$103:V$103)+B$103} -> 5268528.3
A97: Equity Multiple | B97: =SUM(C$101:V$101)/(-B$101) -> 3.1422704 | C97: =SUM(C$102:V$102)/(-B$102) -> 3.8910548 | D97: =SUM(C$103:V$103)/(-B$103) -> 4.3590451
A98: Avg DSCR (loan period) | B98: =AVERAGE(C$48:Q$48) -> 5.0772574 | C98: =AVERAGE(C$69:Q$69) -> 6.1477009 | D98: =AVERAGE(C$90:Q$90) -> 6.816728
A99: Total FCFE (20 years) | B99: =SUM(C$101:V$101) -> 13984313 | C99: =SUM(C$102:V$102) -> 17316692 | D99: =SUM(C$103:V$103) -> 19399429
A101: Equity CF (Low) | B101: =-$B$12 -> -4450385 | C101: =C$46 -> 778446.11 | D101: =D$46 -> 768346.33 | E101: =E$46 -> 758274.61 | F101: =F$46 -> 748230.25 | G101: =G$46 -> 738212.5 | H101: =H$46 -> 695113.72 | I101: =I$46 -> 684815.6 | J101: =J$46 -> 674538.14 | ... V101: =V$46 -> 728486.96
A102: Equity CF (Base) | B102: =-$B$12 -> -4450385 | C102: =C$67 -> 970006.86 | D102: =D$67 -> 957281.62 | E102: =E$67 -> 944584.45 | F102: =F$67 -> 931914.64 | G102: =G$67 -> 919271.43 | H102: =H$67 -> 873547.2 | I102: =I$67 -> 860623.64 | J102: =J$67 -> 847720.72 | ... V102: =V$67 -> 870164.12
A103: Equity CF (High) | B103: =-$B$12 -> -4450385 | C103: =C$88 -> 1089732.3 | D103: =D$88 -> 1075366.2 | E103: =E$88 -> 1061028.1 | F103: =F$88 -> 1046717.4 | G103: =G$88 -> 1032433.3 | H103: =H$88 -> 985068.13 | I103: =I$88 -> 970503.66 | J103: =J$88 -> 955959.83 | ... V103: =V$88 -> 958712.35
A104: Project CF (Low) | B104: =-$B$11 -> -6369564 | C104: =C$39-MAX(0,(C$39-C$40)*Assumptions!$B$35) -> 951349.34 | D104: =D$39-MAX(0,(D$39-D$40)*Assumptions!$B$35) -> 941805.43 | E104: =E$39-MAX(0,(E$39-E$40)*Assumptions!$B$35) -> 932317.37 | F104: =F$39-MAX(0,(F$39-F$40)*Assumptions!$B$35) -> 922885.85 | G104: =G$39-MAX(0,(G$39-G$40)*Assumptions!$B$35) -> 913511.59 | H104: =H$39-MAX(0,(H$39-H$40)*Assumptions!$B$35) -> 871088.48 | I104: =I$39-MAX(0,(I$39-I$40)*Assumptions!$B$35) -> 861499.81 | J104: =J$39-MAX(0,(J$39-J$40)*Assumptions!$B$35) -> 851967.26 | ... V104: =V$39-MAX(0,(V$39-V$40)*Assumptions!$B$35) -> 728486.96
A105: Project CF (Base) | B105: =-$B$11 -> -6369564 | C105: =C$60-MAX(0,(C$60-C$61)*Assumptions!$B$35) -> 1142910.1 | D105: =D$60-MAX(0,(D$60-D$61)*Assumptions!$B$35) -> 1130740.7 | E105: =E$60-MAX(0,(E$60-E$61)*Assumptions!$B$35) -> 1118627.2 | F105: =F$60-MAX(0,(F$60-F$61)*Assumptions!$B$35) -> 1106570.2 | G105: =G$60-MAX(0,(G$60-G$61)*Assumptions!$B$35) -> 1094570.5 | H105: =H$60-MAX(0,(H$60-H$61)*Assumptions!$B$35) -> 1049522 | I105: =I$60-MAX(0,(I$60-I$61)*Assumptions!$B$35) -> 1037307.8 | J105: =J$60-MAX(0,(J$60-J$61)*Assumptions!$B$35) -> 1025149.8 | ... V105: =V$60-MAX(0,(V$60-V$61)*Assumptions!$B$35) -> 870164.12
A106: Project CF (High) | B106: =-$B$11 -> -6369564 | C106: =C$81-MAX(0,(C$81-C$82)*Assumptions!$B$35) -> 1262635.6 | D106: =D$81-MAX(0,(D$81-D$82)*Assumptions!$B$35) -> 1248825.3 | E106: =E$81-MAX(0,(E$81-E$82)*Assumptions!$B$35) -> 1235070.9 | F106: =F$81-MAX(0,(F$81-F$82)*Assumptions!$B$35) -> 1221373 | G106: =G$81-MAX(0,(G$81-G$82)*Assumptions!$B$35) -> 1207732.4 | H106: =H$81-MAX(0,(H$81-H$82)*Assumptions!$B$35) -> 1161042.9 | I106: =I$81-MAX(0,(I$81-I$82)*Assumptions!$B$35) -> 1147187.9 | J106: =J$81-MAX(0,(J$81-J$82)*Assumptions!$B$35) -> 1133389 | ... V106: =V$81-MAX(0,(V$81-V$82)*Assumptions!$B$35) -> 958712.35

Sheet Type C - 3MWp
A1: SHARK — Type C: Small Hybrid Park
A2: 3 MWp + 12 MWh Hybrid Park — Per-Unit Financial Model
A4: CAPEX & FINANCING
A5: PV Capacity (MWp) | B5: 3
A6: BESS Capacity (MWh) | B6: 12
A7: BESS Power (MW) | B7: =B6/Assumptions!$B$6 -> 3
A8: PV EPC Self-Cost (EUR) | B8: 1680231
A9: RTB Acquisition (EUR) | B9: =B5*Assumptions!$B$5 -> 1050000
A10: BESS Installed Cost (EUR) | B10: 1399524
A11: Total CAPEX (EUR) | B11: =B8+B9+B10 -> 4129755
A12: Equity (PV + RTB) | B12: =B8+B9 -> 2730231
A13: Debt (BESS — 100% LTV) | B13: =B10 -> 1399524
A14: Annual Debt Service | B14: =-PMT(Assumptions!$B$38,Assumptions!$B$39,B13) -> 134833.34
A15: Annual Depreciation (SL) | B15: =B11/Assumptions!$B$7 -> 206487.75
A16: Units in Portfolio | B16: 4
A18: ANNUAL PRODUCTION & TECHNICAL DATA
A19: Year # | C19: 1 | D19: 2 | E19: 3 | F19: 4 | G19: 5 | H19: 6 | I19: 7 | J19: 8 | K19: 9 | L19: 10 | M19: 11 | N19: 12 | O19: 13 | P19: 14 | Q19: 15 | R19: 16 | S19: 17 | T19: 18 | U19: 19 | V19: 20 | W19: Total/Avg
A20: Calendar | C20: 2026 | D20: 2027 | E20: 2028 | F20: 2029 | G20: 2030 | H20: 2031 | I20: 2032 | J20: 2033 | K20: 2034 | L20: 2035 | M20: 2036 | N20: 2037 | O20: 2038 | P20: 2039 | Q20: 2040 | R20: 2041 | S20: 2042 | T20: 2043 | U20: 2044 | V20: 2045
A21: PV Production (MWh) | C21: =IF(C$19=1,$B$5*Assumptions!$B$10*(1-Assumptions!$B$11),$B$5*Assumptions!$B$10*(1-Assumptions!$B$11)*(1-Assumptions!$B$12)^(C$19-1)) -> 5118.75 | D21: =IF(D$19=1,$B$5*Assumptions!$B$10*(1-Assumptions!$B$11),$B$5*Assumptions!$B$10*(1-Assumptions!$B$11)*(1-Assumptions!$B$12)^(D$19-1)) -> 5093.1562 | E21: =IF(E$19=1,$B$5*Assumptions!$B$10*(1-Assumptions!$B$11),$B$5*Assumptions!$B$10*(1-Assumptions!$B$11)*(1-Assumptions!$B$12)^(E$19-1)) -> 5067.6905 | F21: =IF(F$19=1,$B$5*Assumptions!$B$10*(1-Assumptions!$B$11),$B$5*Assumptions!$B$10*(1-Assumptions!$B$11)*(1-Assumptions!$B$12)^(F$19-1)) -> 5042.352 | G21: =IF(G$19=1,$B$5*Assumptions!$B$10*(1-Assumptions!$B$11),$B$5*Assumptions!$B$10*(1-Assumptions!$B$11)*(1-Assumptions!$B$12)^(G$19-1)) -> 5017.1403 | H21: =IF(H$19=1,$B$5*Assumptions!$B$10*(1-Assumptions!$B$11),$B$5*Assumptions!$B$10*(1-Assumptions!$B$11)*(1-Assumptions!$B$12)^(H$19-1)) -> 4992.0546 | I21: =IF(I$19=1,$B$5*Assumptions!$B$10*(1-Assumptions!$B$11),$B$5*Assumptions!$B$10*(1-Assumptions!$B$11)*(1-Assumptions!$B$12)^(I$19-1)) -> 4967.0943 | J21: =IF(J$19=1,$B$5*Assumptions!$B$10*(1-Assumptions!$B$11),$B$5*Assumptions!$B$10*(1-Assumptions!$B$11)*(1-Assumptions!$B$12)^(J$19-1)) -> 4942.2588 | ... V21: =IF(V$19=1,$B$5*Assumptions!$B$10*(1-Assumptions!$B$11),$B$5*Assumptions!$B$10*(1-Assumptions!$B$11)*(1-Assumptions!$B$12)^(V$19-1)) -> 4653.7436 | W21: =SUM(C$21:V$21) -> 97655.021
A22: PV Direct Sales (MWh) | C22: =C$21*(1-Assumptions!$B$13) -> 2559.375 | D22: =D$21*(1-Assumptions!$B$13) -> 2546.5781 | E22: =E$21*(1-Assumptions!$B$13) -> 2533.8452 | F22: =F$21*(1-Assumptions!$B$13) -> 2521.176 | G22: =G$21*(1-Assumptions!$B$13) -> 2508.5701 | H22: =H$21*(1-Assumptions!$B$13) -> 2496.0273 | I22: =I$21*(1-Assumptions!$B$13) -> 2483.5471 | J22: =J$21*(1-Assumptions!$B$13) -> 2471.1294 | ... V22: =V$21*(1-Assumptions!$B$13) -> 2326.8718 | W22: =SUM(C$22:V$22) -> 48827.51
A23: PV Curtailed → BESS (MWh) | C23: =C$21*Assumptions!$B$13 -> 2559.375 | D23: =D$21*Assumptions!$B$13 -> 2546.5781 | E23: =E$21*Assumptions!$B$13 -> 2533.8452 | F23: =F$21*Assumptions!$B$13 -> 2521.176 | G23: =G$21*Assumptions!$B$13 -> 2508.5701 | H23: =H$21*Assumptions!$B$13 -> 2496.0273 | I23: =I$21*Assumptions!$B$13 -> 2483.5471 | J23: =J$21*Assumptions!$B$13 -> 2471.1294 | ... V23: =V$21*Assumptions!$B$13 -> 2326.8718 | W23: =SUM(C$23:V$23) -> 48827.51
A24: BESS State of Health (%) | C24: =MAX(0.6,Assumptions!$B$20-Assumptions!$B$21*(C$19-1)) -> 0.985 | D24: =MAX(0.6,Assumptions!$B$20-Assumptions!$B$21*(D$19-1)) -> 0.9715 | E24: =MAX(0.6,Assumptions!$B$20-Assumptions!$B$21*(E$19-1)) -> 0.958 | F24: =MAX(0.6,Assumptions!$B$20-Assumptions!$B$21*(F$19-1)) -> 0.9445 | G24: =MAX(0.6,Assumptions!$B$20-Assumptions!$B$21*(G$19-1)) -> 0.931 | H24: =MAX(0.6,Assumptions!$B$20-Assumptions!$B$21*(H$19-1)) -> 0.9175 | I24: =MAX(0.6,Assumptions!$B$20-Assumptions!$B$21*(I$19-1)) -> 0.904 | J24: =MAX(0.6,Assumptions!$B$20-Assumptions!$B$21*(J$19-1)) -> 0.8905 | ... V24: =MAX(0.6,Assumptions!$B$20-Assumptions!$B$21*(V$19-1)) -> 0.7285 | W24: =AVERAGE(C$24:V$24) -> 0.85675
A25: BESS Sellable Energy (MWh) | C25: =$B$6*C$24*Assumptions!$B$22*Assumptions!$B$19*Assumptions!$B$24*365*Assumptions!$B$23 -> 3283.8985 | D25: =$B$6*D$24*Assumptions!$B$22*Assumptions!$B$19*Assumptions!$B$24*365*Assumptions!$B$23 -> 3238.8907 | E25: =$B$6*E$24*Assumptions!$B$22*Assumptions!$B$19*Assumptions!$B$24*365*Assumptions!$B$23 -> 3193.883 | F25: =$B$6*F$24*Assumptions!$B$22*Assumptions!$B$19*Assumptions!$B$24*365*Assumptions!$B$23 -> 3148.8752 | G25: =$B$6*G$24*Assumptions!$B$22*Assumptions!$B$19*Assumptions!$B$24*365*Assumptions!$B$23 -> 3103.8675 | H25: =$B$6*H$24*Assumptions!$B$22*Assumptions!$B$19*Assumptions!$B$24*365*Assumptions!$B$23 -> 3058.8597 | I25: =$B$6*I$24*Assumptions!$B$22*Assumptions!$B$19*Assumptions!$B$24*365*Assumptions!$B$23 -> 3013.852 | J25: =$B$6*J$24*Assumptions!$B$22*Assumptions!$B$19*Assumptions!$B$24*365*Assumptions!$B$23 -> 2968.8443 | ... V25: =$B$6*V$24*Assumptions!$B$22*Assumptions!$B$19*Assumptions!$B$24*365*Assumptions!$B$23 -> 2428.7513 | W25: =SUM(C$25:V$25) -> 57126.498
A26: BESS Charging Needed (MWh) | C26: =$B$6*C$24*Assumptions!$B$22*Assumptions!$B$24*365*Assumptions!$B$23 -> 3805.2126 | D26: =$B$6*D$24*Assumptions!$B$22*Assumptions!$B$24*365*Assumptions!$B$23 -> 3753.0599 | E26: =$B$6*E$24*Assumptions!$B$22*Assumptions!$B$24*365*Assumptions!$B$23 -> 3700.9073 | F26: =$B$6*F$24*Assumptions!$B$22*Assumptions!$B$24*365*Assumptions!$B$23 -> 3648.7546 | G26: =$B$6*G$24*Assumptions!$B$22*Assumptions!$B$24*365*Assumptions!$B$23 -> 3596.602 | H26: =$B$6*H$24*Assumptions!$B$22*Assumptions!$B$24*365*Assumptions!$B$23 -> 3544.4493 | I26: =$B$6*I$24*Assumptions!$B$22*Assumptions!$B$24*365*Assumptions!$B$23 -> 3492.2966 | J26: =$B$6*J$24*Assumptions!$B$22*Assumptions!$B$24*365*Assumptions!$B$23 -> 3440.144 | ... V26: =$B$6*V$24*Assumptions!$B$22*Assumptions!$B$24*365*Assumptions!$B$23 -> 2814.3121 | W26: =SUM(C$26:V$26) -> 66195.247
A27: Grid Purchases for BESS (MWh) | C27: =MAX(0,C$26-C$23) -> 1245.8376 | D27: =MAX(0,D$26-D$23) -> 1206.4818 | E27: =MAX(0,E$26-E$23) -> 1167.062 | F27: =MAX(0,F$26-F$23) -> 1127.5786 | G27: =MAX(0,G$26-G$23) -> 1088.0318 | H27: =MAX(0,H$26-H$23) -> 1048.422 | I27: =MAX(0,I$26-I$23) -> 1008.7495 | J27: =MAX(0,J$26-J$23) -> 969.01457 | ... V27: =MAX(0,V$26-V$23) -> 487.44025 | W27: =SUM(C$27:V$27) -> 17367.736
A29: SCENARIO: LOW CASE (EUR 110/MWh)
A30: PV Direct Revenue | C30: =C$22*Assumptions!$B$14 -> 409500 | D30: =D$22*Assumptions!$B$14 -> 407452.5 | E30: =E$22*Assumptions!$B$14 -> 405415.24 | F30: =F$22*Assumptions!$B$14 -> 403388.16 | G30: =G$22*Assumptions!$B$14 -> 401371.22 | H30: =H$22*Assumptions!$B$14 -> 399364.36 | I30: =I$22*Assumptions!$B$14 -> 397367.54 | J30: =J$22*Assumptions!$B$14 -> 395380.7 | ... V30: =V$22*Assumptions!$B$14 -> 372299.49 | W30: =SUM(C$30:V$30) -> 7812401.7
A31: GoO Revenue | C31: =C$21*Assumptions!$B$15 -> 5118.75 | D31: =D$21*Assumptions!$B$15 -> 5093.1562 | E31: =E$21*Assumptions!$B$15 -> 5067.6905 | F31: =F$21*Assumptions!$B$15 -> 5042.352 | G31: =G$21*Assumptions!$B$15 -> 5017.1403 | H31: =H$21*Assumptions!$B$15 -> 4992.0546 | I31: =I$21*Assumptions!$B$15 -> 4967.0943 | J31: =J$21*Assumptions!$B$15 -> 4942.2588 | ... V31: =V$21*Assumptions!$B$15 -> 4653.7436 | W31: =SUM(C$31:V$31) -> 97655.021
A32: BESS Arbitrage Revenue | C32: =C$25*Assumptions!$B$42 -> 361228.83 | D32: =D$25*Assumptions!$B$42 -> 356277.98 | E32: =E$25*Assumptions!$B$42 -> 351327.13 | F32: =F$25*Assumptions!$B$42 -> 346376.28 | G32: =G$25*Assumptions!$B$42 -> 341425.42 | H32: =H$25*Assumptions!$B$42 -> 336474.57 | I32: =I$25*Assumptions!$B$42 -> 331523.72 | J32: =J$25*Assumptions!$B$42 -> 326572.87 | ... V32: =V$25*Assumptions!$B$42 -> 267162.64 | W32: =SUM(C$32:V$32) -> 6283914.8
A33: Total Revenue | C33: =C$30+C$31+C$32 -> 775847.58 | D33: =D$30+D$31+D$32 -> 768823.64 | E33: =E$30+E$31+E$32 -> 761810.06 | F33: =F$30+F$31+F$32 -> 754806.79 | G33: =G$30+G$31+G$32 -> 747813.78 | H33: =H$30+H$31+H$32 -> 740830.99 | I33: =I$30+I$31+I$32 -> 733858.36 | J33: =J$30+J$31+J$32 -> 726895.83 | ... V33: =V$30+V$31+V$32 -> 644115.88 | W33: =SUM(C$33:V$33) -> 14193971
A34: Energy Purchase Cost | C34: =C$27*Assumptions!$B$25*(1+Assumptions!$B$36)^(C$19-1) -> 62291.88 | D34: =D$27*Assumptions!$B$25*(1+Assumptions!$B$36)^(D$19-1) -> 60927.332 | E34: =E$27*Assumptions!$B$25*(1+Assumptions!$B$36)^(E$19-1) -> 59526 | F34: =F$27*Assumptions!$B$25*(1+Assumptions!$B$36)^(F$19-1) -> 58087.269 | G34: =G$27*Assumptions!$B$25*(1+Assumptions!$B$36)^(G$19-1) -> 56610.514 | H34: =H$27*Assumptions!$B$25*(1+Assumptions!$B$36)^(H$19-1) -> 55095.104 | I34: =I$27*Assumptions!$B$25*(1+Assumptions!$B$36)^(I$19-1) -> 53540.396 | J34: =J$27*Assumptions!$B$25*(1+Assumptions!$B$36)^(J$19-1) -> 51945.739 | ... V34: =V$27*Assumptions!$B$25*(1+Assumptions!$B$36)^(V$19-1) -> 29444.047 | W34: =SUM(C$34:V$34) -> 941519.02
A35: PV OPEX | C35: =$B$5*Assumptions!$B$16*(1+Assumptions!$B$36)^(C$19-1) -> 45000 | D35: =$B$5*Assumptions!$B$16*(1+Assumptions!$B$36)^(D$19-1) -> 45450 | E35: =$B$5*Assumptions!$B$16*(1+Assumptions!$B$36)^(E$19-1) -> 45904.5 | F35: =$B$5*Assumptions!$B$16*(1+Assumptions!$B$36)^(F$19-1) -> 46363.545 | G35: =$B$5*Assumptions!$B$16*(1+Assumptions!$B$36)^(G$19-1) -> 46827.18 | H35: =$B$5*Assumptions!$B$16*(1+Assumptions!$B$36)^(H$19-1) -> 47295.452 | I35: =$B$5*Assumptions!$B$16*(1+Assumptions!$B$36)^(I$19-1) -> 47768.407 | J35: =$B$5*Assumptions!$B$16*(1+Assumptions!$B$36)^(J$19-1) -> 48246.091 | ... V35: =$B$5*Assumptions!$B$16*(1+Assumptions!$B$36)^(V$19-1) -> 54364.903 | W35: =SUM(C$35:V$35) -> 990855.18
A36: BESS OPEX (O&M+Mgmt+CERA+Grounds) | C36: =($B$6*Assumptions!$B$26+$B$6*Assumptions!$B$27+$B$7*Assumptions!$B$28+Assumptions!$B$29)*(1+Assumptions!$B$36)^(C$19-1) -> 45100 | D36: =($B$6*Assumptions!$B$26+$B$6*Assumptions!$B$27+$B$7*Assumptions!$B$28+Assumptions!$B$29)*(1+Assumptions!$B$36)^(D$19-1) -> 45551 | E36: =($B$6*Assumptions!$B$26+$B$6*Assumptions!$B$27+$B$7*Assumptions!$B$28+Assumptions!$B$29)*(1+Assumptions!$B$36)^(E$19-1) -> 46006.51 | F36: =($B$6*Assumptions!$B$26+$B$6*Assumptions!$B$27+$B$7*Assumptions!$B$28+Assumptions!$B$29)*(1+Assumptions!$B$36)^(F$19-1) -> 46466.575 | G36: =($B$6*Assumptions!$B$26+$B$6*Assumptions!$B$27+$B$7*Assumptions!$B$28+Assumptions!$B$29)*(1+Assumptions!$B$36)^(G$19-1) -> 46931.241 | H36: =($B$6*Assumptions!$B$26+$B$6*Assumptions!$B$27+$B$7*Assumptions!$B$28+Assumptions!$B$29)*(1+Assumptions!$B$36)^(H$19-1) -> 47400.553 | I36: =($B$6*Assumptions!$B$26+$B$6*Assumptions!$B$27+$B$7*Assumptions!$B$28+Assumptions!$B$29)*(1+Assumptions!$B$36)^(I$19-1) -> 47874.559 | J36: =($B$6*Assumptions!$B$26+$B$6*Assumptions!$B$27+$B$7*Assumptions!$B$28+Assumptions!$B$29)*(1+Assumptions!$B$36)^(J$19-1) -> 48353.304 | ... V36: =($B$6*Assumptions!$B$26+$B$6*Assumptions!$B$27+$B$7*Assumptions!$B$28+Assumptions!$B$29)*(1+Assumptions!$B$36)^(V$19-1) -> 54485.714 | W36: =SUM(C$36:V$36) -> 993057.08
A37: BESS Warranty Extension | C37: =IF(C$19<=5,0,IF(C$19<=10,Assumptions!$B$30,IF(C$19<=15,Assumptions!$B$31,Assumptions!$B$32)))*$B$6*(1+Assumptions!$B$36)^(C$19-1) -> 0 | D37: =IF(D$19<=5,0,IF(D$19<=10,Assumptions!$B$30,IF(D$19<=15,Assumptions!$B$31,Assumptions!$B$32)))*$B$6*(1+Assumptions!$B$36)^(D$19-1) -> 0 | E37: =IF(E$19<=5,0,IF(E$19<=10,Assumptions!$B$30,IF(E$19<=15,Assumptions!$B$31,Assumptions!$B$32)))*$B$6*(1+Assumptions!$B$36)^(E$19-1) -> 0 | F37: =IF(F$19<=5,0,IF(F$19<=10,Assumptions!$B$30,IF(F$19<=15,Assumptions!$B$31,Assumptions!$B$32)))*$B$6*(1+Assumptions!$B$36)^(F$19-1) -> 0 | G37: =IF(G$19<=5,0,IF(G$19<=10,Assumptions!$B$30,IF(G$19<=15,Assumptions!$B$31,Assumptions!$B$32)))*$B$6*(1+Assumptions!$B$36)^(G$19-1) -> 0 | H37: =IF(H$19<=5,0,IF(H$19<=10,Assumptions!$B$30,IF(H$19<=15,Assumptions!$B$31,Assumptions!$B$32)))*$B$6*(1+Assumptions!$B$36)^(H$19-1) -> 22701.817 | I37: =IF(I$19<=5,0,IF(I$19<=10,Assumptions!$B$30,IF(I$19<=15,Assumptions!$B$31,Assumptions!$B$32)))*$B$6*(1+Assumptions!$B$36)^(I$19-1) -> 22928.835 | J37: =IF(J$19<=5,0,IF(J$19<=10,Assumptions!$B$30,IF(J$19<=15,Assumptions!$B$31,Assumptions!$B$32)))*$B$6*(1+Assumptions!$B$36)^(J$19-1) -> 23158.124 | ... V37: =IF(V$19<=5,0,IF(V$19<=10,Assumptions!$B$30,IF(V$19<=15,Assumptions!$B$31,Assumptions!$B$32)))*$B$6*(1+Assumptions!$B$36)^(V$19-1) -> 35518.403 | W37: =SUM(C$37:V$37) -> 431906.08
A38: Total Operating Costs | C38: =C$34+C$35+C$36+C$37 -> 152391.88 | D38: =D$34+D$35+D$36+D$37 -> 151928.33 | E38: =E$34+E$35+E$36+E$37 -> 151437.01 | F38: =F$34+F$35+F$36+F$37 -> 150917.39 | G38: =G$34+G$35+G$36+G$37 -> 150368.94 | H38: =H$34+H$35+H$36+H$37 -> 172492.93 | I38: =I$34+I$35+I$36+I$37 -> 172112.2 | J38: =J$34+J$35+J$36+J$37 -> 171703.26 | ... V38: =V$34+V$35+V$36+V$37 -> 173813.07 | W38: =SUM(C$38:V$38) -> 3357337.4
A39: EBITDA | C39: =C$33-C$38 -> 623455.7 | D39: =D$33-D$38 -> 616895.3 | E39: =E$33-E$38 -> 610373.05 | F39: =F$33-F$38 -> 603889.4 | G39: =G$33-G$38 -> 597444.85 | H39: =H$33-H$38 -> 568338.06 | I39: =I$33-I$38 -> 561746.16 | J39: =J$33-J$38 -> 555192.57 | ... V39: =V$33-V$38 -> 470302.81 | W39: =SUM(C$39:V$39) -> 10836634
A40: Depreciation | C40: =$B$15 -> 206487.75 | D40: =$B$15 -> 206487.75 | E40: =$B$15 -> 206487.75 | F40: =$B$15 -> 206487.75 | G40: =$B$15 -> 206487.75 | H40: =$B$15 -> 206487.75 | I40: =$B$15 -> 206487.75 | J40: =$B$15 -> 206487.75 | ... V40: =$B$15 -> 206487.75 | W40: =SUM(C$40:V$40) -> 4129755
A41: Interest Expense | C41: =IF(C$19<=Assumptions!$B$39,-IPMT(Assumptions!$B$38,C$19,Assumptions!$B$39,$B$13),0) -> 69976.2 | D41: =IF(D$19<=Assumptions!$B$39,-IPMT(Assumptions!$B$38,D$19,Assumptions!$B$39,$B$13),0) -> 66733.343 | E41: =IF(E$19<=Assumptions!$B$39,-IPMT(Assumptions!$B$38,E$19,Assumptions!$B$39,$B$13),0) -> 63328.343 | F41: =IF(F$19<=Assumptions!$B$39,-IPMT(Assumptions!$B$38,F$19,Assumptions!$B$39,$B$13),0) -> 59753.093 | G41: =IF(G$19<=Assumptions!$B$39,-IPMT(Assumptions!$B$38,G$19,Assumptions!$B$39,$B$13),0) -> 55999.08 | H41: =IF(H$19<=Assumptions!$B$39,-IPMT(Assumptions!$B$38,H$19,Assumptions!$B$39,$B$13),0) -> 52057.367 | I41: =IF(I$19<=Assumptions!$B$39,-IPMT(Assumptions!$B$38,I$19,Assumptions!$B$39,$B$13),0) -> 47918.568 | J41: =IF(J$19<=Assumptions!$B$39,-IPMT(Assumptions!$B$38,J$19,Assumptions!$B$39,$B$13),0) -> 43572.829 | ... V41: =IF(V$19<=Assumptions!$B$39,-IPMT(Assumptions!$B$38,V$19,Assumptions!$B$39,$B$13),0) -> 0 | W41: =SUM(C$41:V$41) -> 622976.16
A42: Earnings Before Tax | C42: =C$39-C$40-C$41 -> 346991.75 | D42: =D$39-D$40-D$41 -> 343674.21 | E42: =E$39-E$40-E$41 -> 340556.95 | F42: =F$39-F$40-F$41 -> 337648.56 | G42: =G$39-G$40-G$41 -> 334958.02 | H42: =H$39-H$40-H$41 -> 309792.95 | I42: =I$39-I$40-I$41 -> 307339.84 | J42: =J$39-J$40-J$41 -> 305131.99 | ... V42: =V$39-V$40-V$41 -> 263815.06 | W42: =SUM(C$42:V$42) -> 6083902.9
A43: Corporate Tax (12.5%) | C43: =MAX(0,C$42*Assumptions!$B$35) -> 43373.969 | D43: =MAX(0,D$42*Assumptions!$B$35) -> 42959.276 | E43: =MAX(0,E$42*Assumptions!$B$35) -> 42569.619 | F43: =MAX(0,F$42*Assumptions!$B$35) -> 42206.07 | G43: =MAX(0,G$42*Assumptions!$B$35) -> 41869.752 | H43: =MAX(0,H$42*Assumptions!$B$35) -> 38724.118 | I43: =MAX(0,I$42*Assumptions!$B$35) -> 38417.48 | J43: =MAX(0,J$42*Assumptions!$B$35) -> 38141.499 | ... V43: =MAX(0,V$42*Assumptions!$B$35) -> 32976.883 | W43: =SUM(C$43:V$43) -> 760487.87
A44: Net Income | C44: =C$42-C$43 -> 303617.78 | D44: =D$42-D$43 -> 300714.94 | E44: =E$42-E$43 -> 297987.33 | F44: =F$42-F$43 -> 295442.49 | G44: =G$42-G$43 -> 293088.27 | H44: =H$42-H$43 -> 271068.83 | I44: =I$42-I$43 -> 268922.36 | J44: =J$42-J$43 -> 266990.5 | ... V44: =V$42-V$43 -> 230838.18 | W44: =SUM(C$44:V$44) -> 5323415.1
A45: Debt Service (Annuity) | C45: =IF(C$19<=Assumptions!$B$39,$B$14,0) -> 134833.34 | D45: =IF(D$19<=Assumptions!$B$39,$B$14,0) -> 134833.34 | E45: =IF(E$19<=Assumptions!$B$39,$B$14,0) -> 134833.34 | F45: =IF(F$19<=Assumptions!$B$39,$B$14,0) -> 134833.34 | G45: =IF(G$19<=Assumptions!$B$39,$B$14,0) -> 134833.34 | H45: =IF(H$19<=Assumptions!$B$39,$B$14,0) -> 134833.34 | I45: =IF(I$19<=Assumptions!$B$39,$B$14,0) -> 134833.34 | J45: =IF(J$19<=Assumptions!$B$39,$B$14,0) -> 134833.34 | ... V45: =IF(V$19<=Assumptions!$B$39,$B$14,0) -> 0 | W45: =SUM(C$45:V$45) -> 2022500.2
A46: Free Cash Flow to Equity | C46: =C$39-C$45-C$43 -> 445248.39 | D46: =D$39-D$45-D$43 -> 439102.68 | E46: =E$39-E$45-E$43 -> 432970.08 | F46: =F$39-F$45-F$43 -> 426849.99 | G46: =G$39-G$45-G$43 -> 420741.75 | H46: =H$39-H$45-H$43 -> 394780.6 | I46: =I$39-I$45-I$43 -> 388495.34 | J46: =J$39-J$45-J$43 -> 382217.73 | ... V46: =V$39-V$45-V$43 -> 437325.93 | W46: =SUM(C$46:V$46) -> 8053646.1
A47: Cumulative Cash Flow | C47: =C$46 -> 445248.39 | D47: =C$47+D$46 -> 884351.07 | E47: =D$47+E$46 -> 1317321.2 | F47: =E$47+F$46 -> 1744171.1 | G47: =F$47+G$46 -> 2164912.9 | H47: =G$47+H$46 -> 2559693.5 | I47: =H$47+I$46 -> 2948188.8 | J47: =I$47+J$46 -> 3330406.6 | K47: =J$47+K$46 -> 3706353.5 | ... V47: =U$47+V$46 -> 8053646.1 | W47: =V$47 -> 8053646.1
A48: DSCR | C48: =IF(C$45>0,C$39/C$45,"N/A") -> 4.6238985 | D48: =IF(D$45>0,D$39/D$45,"N/A") -> 4.5752429 | E48: =IF(E$45>0,E$39/E$45,"N/A") -> 4.5268702 | F48: =IF(F$45>0,F$39/F$45,"N/A") -> 4.4787838 | G48: =IF(G$45>0,G$39/G$45,"N/A") -> 4.4309874 | H48: =IF(H$45>0,H$39/H$45,"N/A") -> 4.2151151 | I48: =IF(I$45>0,I$39/I$45,"N/A") -> 4.1662258 | J48: =IF(J$45>0,J$39/J$45,"N/A") -> 4.1176207 | ... V48: =IF(V$45>0,V$39/V$45,"N/A") -> N/A | W48: =AVERAGE(C$48:Q$48) -> 4.1647572
A50: SCENARIO: BASE CASE (EUR 150/MWh Blended)
A51: PV Direct Revenue | C51: =C$22*Assumptions!$B$14 -> 409500 | D51: =D$22*Assumptions!$B$14 -> 407452.5 | E51: =E$22*Assumptions!$B$14 -> 405415.24 | F51: =F$22*Assumptions!$B$14 -> 403388.16 | G51: =G$22*Assumptions!$B$14 -> 401371.22 | H51: =H$22*Assumptions!$B$14 -> 399364.36 | I51: =I$22*Assumptions!$B$14 -> 397367.54 | J51: =J$22*Assumptions!$B$14 -> 395380.7 | ... V51: =V$22*Assumptions!$B$14 -> 372299.49 | W51: =SUM(C$51:V$51) -> 7812401.7
A52: GoO Revenue | C52: =C$21*Assumptions!$B$15 -> 5118.75 | D52: =D$21*Assumptions!$B$15 -> 5093.1562 | E52: =E$21*Assumptions!$B$15 -> 5067.6905 | F52: =F$21*Assumptions!$B$15 -> 5042.352 | G52: =G$21*Assumptions!$B$15 -> 5017.1403 | H52: =H$21*Assumptions!$B$15 -> 4992.0546 | I52: =I$21*Assumptions!$B$15 -> 4967.0943 | J52: =J$21*Assumptions!$B$15 -> 4942.2588 | ... V52: =V$21*Assumptions!$B$15 -> 4653.7436 | W52: =SUM(C$52:V$52) -> 97655.021
A53: BESS Arbitrage Revenue | C53: =C$25*Assumptions!$B$43 -> 492584.77 | D53: =D$25*Assumptions!$B$43 -> 485833.61 | E53: =E$25*Assumptions!$B$43 -> 479082.45 | F53: =F$25*Assumptions!$B$43 -> 472331.29 | G53: =G$25*Assumptions!$B$43 -> 465580.12 | H53: =H$25*Assumptions!$B$43 -> 458828.96 | I53: =I$25*Assumptions!$B$43 -> 452077.8 | J53: =J$25*Assumptions!$B$43 -> 445326.64 | ... V53: =V$25*Assumptions!$B$43 -> 364312.7 | W53: =SUM(C$53:V$53) -> 8568974.7
A54: Total Revenue | C54: =C$51+C$52+C$53 -> 907203.52 | D54: =D$51+D$52+D$53 -> 898379.27 | E54: =E$51+E$52+E$53 -> 889565.38 | F54: =F$51+F$52+F$53 -> 880761.8 | G54: =G$51+G$52+G$53 -> 871968.48 | H54: =H$51+H$52+H$53 -> 863185.38 | I54: =I$51+I$52+I$53 -> 854412.44 | J54: =J$51+J$52+J$53 -> 845649.6 | ... V54: =V$51+V$52+V$53 -> 741265.93 | W54: =SUM(C$54:V$54) -> 16479031
A55: Energy Purchase Cost | C55: =C$27*Assumptions!$B$25*(1+Assumptions!$B$36)^(C$19-1) -> 62291.88 | D55: =D$27*Assumptions!$B$25*(1+Assumptions!$B$36)^(D$19-1) -> 60927.332 | E55: =E$27*Assumptions!$B$25*(1+Assumptions!$B$36)^(E$19-1) -> 59526 | F55: =F$27*Assumptions!$B$25*(1+Assumptions!$B$36)^(F$19-1) -> 58087.269 | G55: =G$27*Assumptions!$B$25*(1+Assumptions!$B$36)^(G$19-1) -> 56610.514 | H55: =H$27*Assumptions!$B$25*(1+Assumptions!$B$36)^(H$19-1) -> 55095.104 | I55: =I$27*Assumptions!$B$25*(1+Assumptions!$B$36)^(I$19-1) -> 53540.396 | J55: =J$27*Assumptions!$B$25*(1+Assumptions!$B$36)^(J$19-1) -> 51945.739 | ... V55: =V$27*Assumptions!$B$25*(1+Assumptions!$B$36)^(V$19-1) -> 29444.047 | W55: =SUM(C$55:V$55) -> 941519.02
A56: PV OPEX | C56: =$B$5*Assumptions!$B$16*(1+Assumptions!$B$36)^(C$19-1) -> 45000 | D56: =$B$5*Assumptions!$B$16*(1+Assumptions!$B$36)^(D$19-1) -> 45450 | E56: =$B$5*Assumptions!$B$16*(1+Assumptions!$B$36)^(E$19-1) -> 45904.5 | F56: =$B$5*Assumptions!$B$16*(1+Assumptions!$B$36)^(F$19-1) -> 46363.545 | G56: =$B$5*Assumptions!$B$16*(1+Assumptions!$B$36)^(G$19-1) -> 46827.18 | H56: =$B$5*Assumptions!$B$16*(1+Assumptions!$B$36)^(H$19-1) -> 47295.452 | I56: =$B$5*Assumptions!$B$16*(1+Assumptions!$B$36)^(I$19-1) -> 47768.407 | J56: =$B$5*Assumptions!$B$16*(1+Assumptions!$B$36)^(J$19-1) -> 48246.091 | ... V56: =$B$5*Assumptions!$B$16*(1+Assumptions!$B$36)^(V$19-1) -> 54364.903 | W56: =SUM(C$56:V$56) -> 990855.18
A57: BESS OPEX (O&M+Mgmt+CERA+Grounds) | C57: =($B$6*Assumptions!$B$26+$B$6*Assumptions!$B$27+$B$7*Assumptions!$B$28+Assumptions!$B$29)*(1+Assumptions!$B$36)^(C$19-1) -> 45100 | D57: =($B$6*Assumptions!$B$26+$B$6*Assumptions!$B$27+$B$7*Assumptions!$B$28+Assumptions!$B$29)*(1+Assumptions!$B$36)^(D$19-1) -> 45551 | E57: =($B$6*Assumptions!$B$26+$B$6*Assumptions!$B$27+$B$7*Assumptions!$B$28+Assumptions!$B$29)*(1+Assumptions!$B$36)^(E$19-1) -> 46006.51 | F57: =($B$6*Assumptions!$B$26+$B$6*Assumptions!$B$27+$B$7*Assumptions!$B$28+Assumptions!$B$29)*(1+Assumptions!$B$36)^(F$19-1) -> 46466.575 | G57: =($B$6*Assumptions!$B$26+$B$6*Assumptions!$B$27+$B$7*Assumptions!$B$28+Assumptions!$B$29)*(1+Assumptions!$B$36)^(G$19-1) -> 46931.241 | H57: =($B$6*Assumptions!$B$26+$B$6*Assumptions!$B$27+$B$7*Assumptions!$B$28+Assumptions!$B$29)*(1+Assumptions!$B$36)^(H$19-1) -> 47400.553 | I57: =($B$6*Assumptions!$B$26+$B$6*Assumptions!$B$27+$B$7*Assumptions!$B$28+Assumptions!$B$29)*(1+Assumptions!$B$36)^(I$19-1) -> 47874.559 | J57: =($B$6*Assumptions!$B$26+$B$6*Assumptions!$B$27+$B$7*Assumptions!$B$28+Assumptions!$B$29)*(1+Assumptions!$B$36)^(J$19-1) -> 48353.304 | ... V57: =($B$6*Assumptions!$B$26+$B$6*Assumptions!$B$27+$B$7*Assumptions!$B$28+Assumptions!$B$29)*(1+Assumptions!$B$36)^(V$19-1) -> 54485.714 | W57: =SUM(C$57:V$57) -> 993057.08
A58: BESS Warranty Extension | C58: =IF(C$19<=5,0,IF(C$19<=10,Assumptions!$B$30,IF(C$19<=15,Assumptions!$B$31,Assumptions!$B$32)))*$B$6*(1+Assumptions!$B$36)^(C$19-1) -> 0 | D58: =IF(D$19<=5,0,IF(D$19<=10,Assumptions!$B$30,IF(D$19<=15,Assumptions!$B$31,Assumptions!$B$32)))*$B$6*(1+Assumptions!$B$36)^(D$19-1) -> 0 | E58: =IF(E$19<=5,0,IF(E$19<=10,Assumptions!$B$30,IF(E$19<=15,Assumptions!$B$31,Assumptions!$B$32)))*$B$6*(1+Assumptions!$B$36)^(E$19-1) -> 0 | F58: =IF(F$19<=5,0,IF(F$19<=10,Assumptions!$B$30,IF(F$19<=15,Assumptions!$B$31,Assumptions!$B$32)))*$B$6*(1+Assumptions!$B$36)^(F$19-1) -> 0 | G58: =IF(G$19<=5,0,IF(G$19<=10,Assumptions!$B$30,IF(G$19<=15,Assumptions!$B$31,Assumptions!$B$32)))*$B$6*(1+Assumptions!$B$36)^(G$19-1) -> 0 | H58: =IF(H$19<=5,0,IF(H$19<=10,Assumptions!$B$30,IF(H$19<=15,Assumptions!$B$31,Assumptions!$B$32)))*$B$6*(1+Assumptions!$B$36)^(H$19-1) -> 22701.817 | I58: =IF(I$19<=5,0,IF(I$19<=10,Assumptions!$B$30,IF(I$19<=15,Assumptions!$B$31,Assumptions!$B$32)))*$B$6*(1+Assumptions!$B$36)^(I$19-1) -> 22928.835 | J58: =IF(J$19<=5,0,IF(J$19<=10,Assumptions!$B$30,IF(J$19<=15,Assumptions!$B$31,Assumptions!$B$32)))*$B$6*(1+Assumptions!$B$36)^(J$19-1) -> 23158.124 | ... V58: =IF(V$19<=5,0,IF(V$19<=10,Assumptions!$B$30,IF(V$19<=15,Assumptions!$B$31,Assumptions!$B$32)))*$B$6*(1+Assumptions!$B$36)^(V$19-1) -> 35518.403 | W58: =SUM(C$58:V$58) -> 431906.08
A59: Total Operating Costs | C59: =C$55+C$56+C$57+C$58 -> 152391.88 | D59: =D$55+D$56+D$57+D$58 -> 151928.33 | E59: =E$55+E$56+E$57+E$58 -> 151437.01 | F59: =F$55+F$56+F$57+F$58 -> 150917.39 | G59: =G$55+G$56+G$57+G$58 -> 150368.94 | H59: =H$55+H$56+H$57+H$58 -> 172492.93 | I59: =I$55+I$56+I$57+I$58 -> 172112.2 | J59: =J$55+J$56+J$57+J$58 -> 171703.26 | ... V59: =V$55+V$56+V$57+V$58 -> 173813.07 | W59: =SUM(C$59:V$59) -> 3357337.4
A60: EBITDA | C60: =C$54-C$59 -> 754811.64 | D60: =D$54-D$59 -> 746450.93 | E60: =E$54-E$59 -> 738128.37 | F60: =F$54-F$59 -> 729844.41 | G60: =G$54-G$59 -> 721599.55 | H60: =H$54-H$59 -> 690692.45 | I60: =I$54-I$59 -> 682300.24 | J60: =J$54-J$59 -> 673946.34 | ... V60: =V$54-V$59 -> 567452.86 | W60: =SUM(C$60:V$60) -> 13121694
A61: Depreciation | C61: =$B$15 -> 206487.75 | D61: =$B$15 -> 206487.75 | E61: =$B$15 -> 206487.75 | F61: =$B$15 -> 206487.75 | G61: =$B$15 -> 206487.75 | H61: =$B$15 -> 206487.75 | I61: =$B$15 -> 206487.75 | J61: =$B$15 -> 206487.75 | ... V61: =$B$15 -> 206487.75 | W61: =SUM(C$61:V$61) -> 4129755
A62: Interest Expense | C62: =IF(C$19<=Assumptions!$B$39,-IPMT(Assumptions!$B$38,C$19,Assumptions!$B$39,$B$13),0) -> 69976.2 | D62: =IF(D$19<=Assumptions!$B$39,-IPMT(Assumptions!$B$38,D$19,Assumptions!$B$39,$B$13),0) -> 66733.343 | E62: =IF(E$19<=Assumptions!$B$39,-IPMT(Assumptions!$B$38,E$19,Assumptions!$B$39,$B$13),0) -> 63328.343 | F62: =IF(F$19<=Assumptions!$B$39,-IPMT(Assumptions!$B$38,F$19,Assumptions!$B$39,$B$13),0) -> 59753.093 | G62: =IF(G$19<=Assumptions!$B$39,-IPMT(Assumptions!$B$38,G$19,Assumptions!$B$39,$B$13),0) -> 55999.08 | H62: =IF(H$19<=Assumptions!$B$39,-IPMT(Assumptions!$B$38,H$19,Assumptions!$B$39,$B$13),0) -> 52057.367 | I62: =IF(I$19<=Assumptions!$B$39,-IPMT(Assumptions!$B$38,I$19,Assumptions!$B$39,$B$13),0) -> 47918.568 | J62: =IF(J$19<=Assumptions!$B$39,-IPMT(Assumptions!$B$38,J$19,Assumptions!$B$39,$B$13),0) -> 43572.829 | ... V62: =IF(V$19<=Assumptions!$B$39,-IPMT(Assumptions!$B$38,V$19,Assumptions!$B$39,$B$13),0) -> 0 | W62: =SUM(C$62:V$62) -> 622976.16
A63: Earnings Before Tax | C63: =C$60-C$61-C$62 -> 478347.69 | D63: =D$60-D$61-D$62 -> 473229.84 | E63: =E$60-E$61-E$62 -> 468312.27 | F63: =F$60-F$61-F$62 -> 463603.57 | G63: =G$60-G$61-G$62 -> 459112.72 | H63: =H$60-H$61-H$62 -> 432147.34 | I63: =I$60-I$61-I$62 -> 427893.92 | J63: =J$60-J$61-J$62 -> 423885.76 | ... V63: =V$60-V$61-V$62 -> 360965.11 | W63: =SUM(C$63:V$63) -> 8368962.8
A64: Corporate Tax (12.5%) | C64: =MAX(0,C$63*Assumptions!$B$35) -> 59793.461 | D64: =MAX(0,D$63*Assumptions!$B$35) -> 59153.73 | E64: =MAX(0,E$63*Assumptions!$B$35) -> 58539.034 | F64: =MAX(0,F$63*Assumptions!$B$35) -> 57950.446 | G64: =MAX(0,G$63*Assumptions!$B$35) -> 57389.09 | H64: =MAX(0,H$63*Assumptions!$B$35) -> 54018.417 | I64: =MAX(0,I$63*Assumptions!$B$35) -> 53486.74 | J64: =MAX(0,J$63*Assumptions!$B$35) -> 52985.721 | ... V64: =MAX(0,V$63*Assumptions!$B$35) -> 45120.639 | W64: =SUM(C$64:V$64) -> 1046120.4
A65: Net Income | C65: =C$63-C$64 -> 418554.23 | D65: =D$63-D$64 -> 414076.11 | E65: =E$63-E$64 -> 409773.24 | F65: =F$63-F$64 -> 405653.12 | G65: =G$63-G$64 -> 401723.63 | H65: =H$63-H$64 -> 378128.92 | I65: =I$63-I$64 -> 374407.18 | J65: =J$63-J$64 -> 370900.04 | ... V65: =V$63-V$64 -> 315844.47 | W65: =SUM(C$65:V$65) -> 7322842.5
A66: Debt Service (Annuity) | C66: =IF(C$19<=Assumptions!$B$39,$B$14,0) -> 134833.34 | D66: =IF(D$19<=Assumptions!$B$39,$B$14,0) -> 134833.34 | E66: =IF(E$19<=Assumptions!$B$39,$B$14,0) -> 134833.34 | F66: =IF(F$19<=Assumptions!$B$39,$B$14,0) -> 134833.34 | G66: =IF(G$19<=Assumptions!$B$39,$B$14,0) -> 134833.34 | H66: =IF(H$19<=Assumptions!$B$39,$B$14,0) -> 134833.34 | I66: =IF(I$19<=Assumptions!$B$39,$B$14,0) -> 134833.34 | J66: =IF(J$19<=Assumptions!$B$39,$B$14,0) -> 134833.34 | ... V66: =IF(V$19<=Assumptions!$B$39,$B$14,0) -> 0 | W66: =SUM(C$66:V$66) -> 2022500.2
A67: Free Cash Flow to Equity | C67: =C$60-C$66-C$64 -> 560184.84 | D67: =D$60-D$66-D$64 -> 552463.86 | E67: =E$60-E$66-E$64 -> 544755.99 | F67: =F$60-F$66-F$64 -> 537060.62 | G67: =G$60-G$66-G$64 -> 529377.12 | H67: =H$60-H$66-H$64 -> 501840.69 | I67: =I$60-I$66-I$64 -> 493980.16 | J67: =J$60-J$66-J$64 -> 486127.28 | ... V67: =V$60-V$66-V$64 -> 522332.22 | W67: =SUM(C$67:V$67) -> 10053073
A68: Cumulative Cash Flow | C68: =C$67 -> 560184.84 | D68: =C$68+D$67 -> 1112648.7 | E68: =D$68+E$67 -> 1657404.7 | F68: =E$68+F$67 -> 2194465.3 | G68: =F$68+G$67 -> 2723842.4 | H68: =G$68+H$67 -> 3225683.1 | I68: =H$68+I$67 -> 3719663.3 | J68: =I$68+J$67 -> 4205790.5 | K68: =J$68+K$67 -> 4684071.8 | ... V68: =U$68+V$67 -> 10053073 | W68: =V$68 -> 10053073
A69: DSCR | C69: =IF(C$66>0,C$60/C$66,"N/A") -> 5.5981082 | D69: =IF(D$66>0,D$60/D$66,"N/A") -> 5.5361004 | E69: =IF(E$66>0,E$60/E$66,"N/A") -> 5.4743756 | F69: =IF(F$66>0,F$60/F$66,"N/A") -> 5.4129371 | G69: =IF(G$66>0,G$60/G$66,"N/A") -> 5.3517886 | H69: =IF(H$66>0,H$60/H$66,"N/A") -> 5.1225642 | I69: =IF(I$66>0,I$60/I$66,"N/A") -> 5.0603228 | J69: =IF(J$66>0,J$60/J$66,"N/A") -> 4.9983656 | ... V69: =IF(V$66>0,V$60/V$66,"N/A") -> N/A | W69: =AVERAGE(C$69:Q$69) -> 5.045502
A71: SCENARIO: HIGH CASE (EUR 175/MWh)
A72: PV Direct Revenue | C72: =C$22*Assumptions!$B$14 -> 409500 | D72: =D$22*Assumptions!$B$14 -> 407452.5 | E72: =E$22*Assumptions!$B$14 -> 405415.24 | F72: =F$22*Assumptions!$B$14 -> 403388.16 | G72: =G$22*Assumptions!$B$14 -> 401371.22 | H72: =H$22*Assumptions!$B$14 -> 399364.36 | I72: =I$22*Assumptions!$B$14 -> 397367.54 | J72: =J$22*Assumptions!$B$14 -> 395380.7 | ... V72: =V$22*Assumptions!$B$14 -> 372299.49 | W72: =SUM(C$72:V$72) -> 7812401.7
A73: GoO Revenue | C73: =C$21*Assumptions!$B$15 -> 5118.75 | D73: =D$21*Assumptions!$B$15 -> 5093.1562 | E73: =E$21*Assumptions!$B$15 -> 5067.6905 | F73: =F$21*Assumptions!$B$15 -> 5042.352 | G73: =G$21*Assumptions!$B$15 -> 5017.1403 | H73: =H$21*Assumptions!$B$15 -> 4992.0546 | I73: =I$21*Assumptions!$B$15 -> 4967.0943 | J73: =J$21*Assumptions!$B$15 -> 4942.2588 | ... V73: =V$21*Assumptions!$B$15 -> 4653.7436 | W73: =SUM(C$73:V$73) -> 97655.021
A74: BESS Arbitrage Revenue | C74: =C$25*Assumptions!$B$44 -> 574682.23 | D74: =D$25*Assumptions!$B$44 -> 566805.88 | E74: =E$25*Assumptions!$B$44 -> 558929.52 | F74: =F$25*Assumptions!$B$44 -> 551053.17 | G74: =G$25*Assumptions!$B$44 -> 543176.81 | H74: =H$25*Assumptions!$B$44 -> 535300.46 | I74: =I$25*Assumptions!$B$44 -> 527424.1 | J74: =J$25*Assumptions!$B$44 -> 519547.74 | ... V74: =V$25*Assumptions!$B$44 -> 425031.48 | W74: =SUM(C$74:V$74) -> 9997137.1
A75: Total Revenue | C75: =C$72+C$73+C$74 -> 989300.98 | D75: =D$72+D$73+D$74 -> 979351.53 | E75: =E$72+E$73+E$74 -> 969412.45 | F75: =F$72+F$73+F$74 -> 959483.68 | G75: =G$72+G$73+G$74 -> 949565.17 | H75: =H$72+H$73+H$74 -> 939656.87 | I75: =I$72+I$73+I$74 -> 929758.74 | J75: =J$72+J$73+J$74 -> 919870.71 | ... V75: =V$72+V$73+V$74 -> 801984.71 | W75: =SUM(C$75:V$75) -> 17907194
A76: Energy Purchase Cost | C76: =C$27*Assumptions!$B$25*(1+Assumptions!$B$36)^(C$19-1) -> 62291.88 | D76: =D$27*Assumptions!$B$25*(1+Assumptions!$B$36)^(D$19-1) -> 60927.332 | E76: =E$27*Assumptions!$B$25*(1+Assumptions!$B$36)^(E$19-1) -> 59526 | F76: =F$27*Assumptions!$B$25*(1+Assumptions!$B$36)^(F$19-1) -> 58087.269 | G76: =G$27*Assumptions!$B$25*(1+Assumptions!$B$36)^(G$19-1) -> 56610.514 | H76: =H$27*Assumptions!$B$25*(1+Assumptions!$B$36)^(H$19-1) -> 55095.104 | I76: =I$27*Assumptions!$B$25*(1+Assumptions!$B$36)^(I$19-1) -> 53540.396 | J76: =J$27*Assumptions!$B$25*(1+Assumptions!$B$36)^(J$19-1) -> 51945.739 | ... V76: =V$27*Assumptions!$B$25*(1+Assumptions!$B$36)^(V$19-1) -> 29444.047 | W76: =SUM(C$76:V$76) -> 941519.02
A77: PV OPEX | C77: =$B$5*Assumptions!$B$16*(1+Assumptions!$B$36)^(C$19-1) -> 45000 | D77: =$B$5*Assumptions!$B$16*(1+Assumptions!$B$36)^(D$19-1) -> 45450 | E77: =$B$5*Assumptions!$B$16*(1+Assumptions!$B$36)^(E$19-1) -> 45904.5 | F77: =$B$5*Assumptions!$B$16*(1+Assumptions!$B$36)^(F$19-1) -> 46363.545 | G77: =$B$5*Assumptions!$B$16*(1+Assumptions!$B$36)^(G$19-1) -> 46827.18 | H77: =$B$5*Assumptions!$B$16*(1+Assumptions!$B$36)^(H$19-1) -> 47295.452 | I77: =$B$5*Assumptions!$B$16*(1+Assumptions!$B$36)^(I$19-1) -> 47768.407 | J77: =$B$5*Assumptions!$B$16*(1+Assumptions!$B$36)^(J$19-1) -> 48246.091 | ... V77: =$B$5*Assumptions!$B$16*(1+Assumptions!$B$36)^(V$19-1) -> 54364.903 | W77: =SUM(C$77:V$77) -> 990855.18
A78: BESS OPEX (O&M+Mgmt+CERA+Grounds) | C78: =($B$6*Assumptions!$B$26+$B$6*Assumptions!$B$27+$B$7*Assumptions!$B$28+Assumptions!$B$29)*(1+Assumptions!$B$36)^(C$19-1) -> 45100 | D78: =($B$6*Assumptions!$B$26+$B$6*Assumptions!$B$27+$B$7*Assumptions!$B$28+Assumptions!$B$29)*(1+Assumptions!$B$36)^(D$19-1) -> 45551 | E78: =($B$6*Assumptions!$B$26+$B$6*Assumptions!$B$27+$B$7*Assumptions!$B$28+Assumptions!$B$29)*(1+Assumptions!$B$36)^(E$19-1) -> 46006.51 | F78: =($B$6*Assumptions!$B$26+$B$6*Assumptions!$B$27+$B$7*Assumptions!$B$28+Assumptions!$B$29)*(1+Assumptions!$B$36)^(F$19-1) -> 46466.575 | G78: =($B$6*Assumptions!$B$26+$B$6*Assumptions!$B$27+$B$7*Assumptions!$B$28+Assumptions!$B$29)*(1+Assumptions!$B$36)^(G$19-1) -> 46931.241 | H78: =($B$6*Assumptions!$B$26+$B$6*Assumptions!$B$27+$B$7*Assumptions!$B$28+Assumptions!$B$29)*(1+Assumptions!$B$36)^(H$19-1) -> 47400.553 | I78: =($B$6*Assumptions!$B$26+$B$6*Assumptions!$B$27+$B$7*Assumptions!$B$28+Assumptions!$B$29)*(1+Assumptions!$B$36)^(I$19-1) -> 47874.559 | J78: =($B$6*Assumptions!$B$26+$B$6*Assumptions!$B$27+$B$7*Assumptions!$B$28+Assumptions!$B$29)*(1+Assumptions!$B$36)^(J$19-1) -> 48353.304 | ... V78: =($B$6*Assumptions!$B$26+$B$6*Assumptions!$B$27+$B$7*Assumptions!$B$28+Assumptions!$B$29)*(1+Assumptions!$B$36)^(V$19-1) -> 54485.714 | W78: =SUM(C$78:V$78) -> 993057.08
A79: BESS Warranty Extension | C79: =IF(C$19<=5,0,IF(C$19<=10,Assumptions!$B$30,IF(C$19<=15,Assumptions!$B$31,Assumptions!$B$32)))*$B$6*(1+Assumptions!$B$36)^(C$19-1) -> 0 | D79: =IF(D$19<=5,0,IF(D$19<=10,Assumptions!$B$30,IF(D$19<=15,Assumptions!$B$31,Assumptions!$B$32)))*$B$6*(1+Assumptions!$B$36)^(D$19-1) -> 0 | E79: =IF(E$19<=5,0,IF(E$19<=10,Assumptions!$B$30,IF(E$19<=15,Assumptions!$B$31,Assumptions!$B$32)))*$B$6*(1+Assumptions!$B$36)^(E$19-1) -> 0 | F79: =IF(F$19<=5,0,IF(F$19<=10,Assumptions!$B$30,IF(F$19<=15,Assumptions!$B$31,Assumptions!$B$32)))*$B$6*(1+Assumptions!$B$36)^(F$19-1) -> 0 | G79: =IF(G$19<=5,0,IF(G$19<=10,Assumptions!$B$30,IF(G$19<=15,Assumptions!$B$31,Assumptions!$B$32)))*$B$6*(1+Assumptions!$B$36)^(G$19-1) -> 0 | H79: =IF(H$19<=5,0,IF(H$19<=10,Assumptions!$B$30,IF(H$19<=15,Assumptions!$B$31,Assumptions!$B$32)))*$B$6*(1+Assumptions!$B$36)^(H$19-1) -> 22701.817 | I79: =IF(I$19<=5,0,IF(I$19<=10,Assumptions!$B$30,IF(I$19<=15,Assumptions!$B$31,Assumptions!$B$32)))*$B$6*(1+Assumptions!$B$36)^(I$19-1) -> 22928.835 | J79: =IF(J$19<=5,0,IF(J$19<=10,Assumptions!$B$30,IF(J$19<=15,Assumptions!$B$31,Assumptions!$B$32)))*$B$6*(1+Assumptions!$B$36)^(J$19-1) -> 23158.124 | ... V79: =IF(V$19<=5,0,IF(V$19<=10,Assumptions!$B$30,IF(V$19<=15,Assumptions!$B$31,Assumptions!$B$32)))*$B$6*(1+Assumptions!$B$36)^(V$19-1) -> 35518.403 | W79: =SUM(C$79:V$79) -> 431906.08
A80: Total Operating Costs | C80: =C$76+C$77+C$78+C$79 -> 152391.88 | D80: =D$76+D$77+D$78+D$79 -> 151928.33 | E80: =E$76+E$77+E$78+E$79 -> 151437.01 | F80: =F$76+F$77+F$78+F$79 -> 150917.39 | G80: =G$76+G$77+G$78+G$79 -> 150368.94 | H80: =H$76+H$77+H$78+H$79 -> 172492.93 | I80: =I$76+I$77+I$78+I$79 -> 172112.2 | J80: =J$76+J$77+J$78+J$79 -> 171703.26 | ... V80: =V$76+V$77+V$78+V$79 -> 173813.07 | W80: =SUM(C$80:V$80) -> 3357337.4
A81: EBITDA | C81: =C$75-C$80 -> 836909.1 | D81: =D$75-D$80 -> 827423.2 | E81: =E$75-E$80 -> 817975.44 | F81: =F$75-F$80 -> 808566.29 | G81: =G$75-G$80 -> 799196.24 | H81: =H$75-H$80 -> 767163.95 | I81: =I$75-I$80 -> 757646.54 | J81: =J$75-J$80 -> 748167.45 | ... V81: =V$75-V$80 -> 628171.65 | W81: =SUM(C$81:V$81) -> 14549856
A82: Depreciation | C82: =$B$15 -> 206487.75 | D82: =$B$15 -> 206487.75 | E82: =$B$15 -> 206487.75 | F82: =$B$15 -> 206487.75 | G82: =$B$15 -> 206487.75 | H82: =$B$15 -> 206487.75 | I82: =$B$15 -> 206487.75 | J82: =$B$15 -> 206487.75 | ... V82: =$B$15 -> 206487.75 | W82: =SUM(C$82:V$82) -> 4129755
A83: Interest Expense | C83: =IF(C$19<=Assumptions!$B$39,-IPMT(Assumptions!$B$38,C$19,Assumptions!$B$39,$B$13),0) -> 69976.2 | D83: =IF(D$19<=Assumptions!$B$39,-IPMT(Assumptions!$B$38,D$19,Assumptions!$B$39,$B$13),0) -> 66733.343 | E83: =IF(E$19<=Assumptions!$B$39,-IPMT(Assumptions!$B$38,E$19,Assumptions!$B$39,$B$13),0) -> 63328.343 | F83: =IF(F$19<=Assumptions!$B$39,-IPMT(Assumptions!$B$38,F$19,Assumptions!$B$39,$B$13),0) -> 59753.093 | G83: =IF(G$19<=Assumptions!$B$39,-IPMT(Assumptions!$B$38,G$19,Assumptions!$B$39,$B$13),0) -> 55999.08 | H83: =IF(H$19<=Assumptions!$B$39,-IPMT(Assumptions!$B$38,H$19,Assumptions!$B$39,$B$13),0) -> 52057.367 | I83: =IF(I$19<=Assumptions!$B$39,-IPMT(Assumptions!$B$38,I$19,Assumptions!$B$39,$B$13),0) -> 47918.568 | J83: =IF(J$19<=Assumptions!$B$39,-IPMT(Assumptions!$B$38,J$19,Assumptions!$B$39,$B$13),0) -> 43572.829 | ... V83: =IF(V$19<=Assumptions!$B$39,-IPMT(Assumptions!$B$38,V$19,Assumptions!$B$39,$B$13),0) -> 0 | W83: =SUM(C$83:V$83) -> 622976.16
A84: Earnings Before Tax | C84: =C$81-C$82-C$83 -> 560445.15 | D84: =D$81-D$82-D$83 -> 554202.11 | E84: =E$81-E$82-E$83 -> 548159.35 | F84: =F$81-F$82-F$83 -> 542325.45 | G84: =G$81-G$82-G$83 -> 536709.41 | H84: =H$81-H$82-H$83 -> 508618.83 | I84: =I$81-I$82-I$83 -> 503240.22 | J84: =J$81-J$82-J$83 -> 498106.87 | ... V84: =V$81-V$82-V$83 -> 421683.9 | W84: =SUM(C$84:V$84) -> 9797125.3
A85: Corporate Tax (12.5%) | C85: =MAX(0,C$84*Assumptions!$B$35) -> 70055.644 | D85: =MAX(0,D$84*Assumptions!$B$35) -> 69275.264 | E85: =MAX(0,E$84*Assumptions!$B$35) -> 68519.918 | F85: =MAX(0,F$84*Assumptions!$B$35) -> 67790.681 | G85: =MAX(0,G$84*Assumptions!$B$35) -> 67088.676 | H85: =MAX(0,H$84*Assumptions!$B$35) -> 63577.354 | I85: =MAX(0,I$84*Assumptions!$B$35) -> 62905.028 | J85: =MAX(0,J$84*Assumptions!$B$35) -> 62263.359 | ... V85: =MAX(0,V$84*Assumptions!$B$35) -> 52710.487 | W85: =SUM(C$85:V$85) -> 1224640.7
A86: Net Income | C86: =C$84-C$85 -> 490389.51 | D86: =D$84-D$85 -> 484926.85 | E86: =E$84-E$85 -> 479639.43 | F86: =F$84-F$85 -> 474534.77 | G86: =G$84-G$85 -> 469620.73 | H86: =H$84-H$85 -> 445041.48 | I86: =I$84-I$85 -> 440335.19 | J86: =J$84-J$85 -> 435843.51 | ... V86: =V$84-V$85 -> 368973.41 | W86: =SUM(C$86:V$86) -> 8572484.6
A87: Debt Service (Annuity) | C87: =IF(C$19<=Assumptions!$B$39,$B$14,0) -> 134833.34 | D87: =IF(D$19<=Assumptions!$B$39,$B$14,0) -> 134833.34 | E87: =IF(E$19<=Assumptions!$B$39,$B$14,0) -> 134833.34 | F87: =IF(F$19<=Assumptions!$B$39,$B$14,0) -> 134833.34 | G87: =IF(G$19<=Assumptions!$B$39,$B$14,0) -> 134833.34 | H87: =IF(H$19<=Assumptions!$B$39,$B$14,0) -> 134833.34 | I87: =IF(I$19<=Assumptions!$B$39,$B$14,0) -> 134833.34 | J87: =IF(J$19<=Assumptions!$B$39,$B$14,0) -> 134833.34 | ... V87: =IF(V$19<=Assumptions!$B$39,$B$14,0) -> 0 | W87: =SUM(C$87:V$87) -> 2022500.2
A88: Free Cash Flow to Equity | C88: =C$81-C$87-C$85 -> 632020.12 | D88: =D$81-D$87-D$85 -> 623314.59 | E88: =E$81-E$87-E$85 -> 614622.18 | F88: =F$81-F$87-F$85 -> 605942.27 | G88: =G$81-G$87-G$85 -> 597274.22 | H88: =H$81-H$87-H$85 -> 568753.25 | I88: =I$81-I$87-I$85 -> 559908.17 | J88: =J$81-J$87-J$85 -> 551070.75 | ... V88: =V$81-V$87-V$85 -> 575461.16 | W88: =SUM(C$88:V$88) -> 11302716
A89: Cumulative Cash Flow | C89: =C$88 -> 632020.12 | D89: =C$89+D$88 -> 1255334.7 | E89: =D$89+E$88 -> 1869956.9 | F89: =E$89+F$88 -> 2475899.2 | G89: =F$89+G$88 -> 3073173.4 | H89: =G$89+H$88 -> 3641926.6 | I89: =H$89+I$88 -> 4201834.8 | J89: =I$89+J$88 -> 4752905.5 | K89: =J$89+K$88 -> 5295145.7 | ... V89: =U$89+V$88 -> 11302716 | W89: =V$89 -> 11302716
A90: DSCR | C90: =IF(C$87>0,C$81/C$87,"N/A") -> 6.2069892 | D90: =IF(D$87>0,D$81/D$87,"N/A") -> 6.1366364 | E90: =IF(E$87>0,E$81/E$87,"N/A") -> 6.0665665 | F90: =IF(F$87>0,F$81/F$87,"N/A") -> 5.9967829 | G90: =IF(G$87>0,G$81/G$87,"N/A") -> 5.9272893 | H90: =IF(H$87>0,H$81/H$87,"N/A") -> 5.6897198 | I90: =IF(I$87>0,I$81/I$87,"N/A") -> 5.6191334 | J90: =IF(J$87>0,J$81/J$87,"N/A") -> 5.5488311 | ... V90: =IF(V$87>0,V$81/V$87,"N/A") -> N/A | W90: =AVERAGE(C$90:Q$90) -> 5.5959675
A92: RETURNS SUMMARY (PER UNIT)
A93: Metric | B93: Low (110) | C93: Base (150) | D93: High (175)
A94: Equity IRR | B94: =IRR(B$101:V$101) -> 0.1390503 | C94: =IRR(B$102:V$102) -> 0.18437841 | D94: =IRR(B$103:V$103) -> 0.21202465
A95: Project IRR (Unlevered) | B95: =IRR(B$104:V$104) -> 0.1116448 | C95: =IRR(B$105:V$105) -> 0.14343621 | D95: =IRR(B$106:V$106) -> 0.16262283
A96: Equity NPV (@ 8%) | B96: {=NPV(Assumptions!$B$37,C$101:V$101)+B$101} -> 1252895.1 | C96: {=NPV(Assumptions!$B$37,C$102:V$102)+B$102} -> 2272522.9 | D96: {=NPV(Assumptions!$B$37,C$103:V$103)+B$103} -> 2909790.3
A97: Equity Multiple | B97: =SUM(C$101:V$101)/(-B$101) -> 2.9498039 | C97: =SUM(C$102:V$102)/(-B$102) -> 3.6821329 | D97: =SUM(C$103:V$103)/(-B$103) -> 4.1398386
A98: Avg DSCR (loan period) | B98: =AVERAGE(C$48:Q$48) -> 4.1647572 | C98: =AVERAGE(C$69:Q$69) -> 5.045502 | D98: =AVERAGE(C$90:Q$90) -> 5.5959675
A99: Total FCFE (20 years) | B99: =SUM(C$101:V$101) -> 8053646.1 | C99: =SUM(C$102:V$102) -> 10053073 | D99: =SUM(C$103:V$103) -> 11302716
A101: Equity CF (Low) | B101: =-$B$12 -> -2730231 | C101: =C$46 -> 445248.39 | D101: =D$46 -> 439102.68 | E101: =E$46 -> 432970.08 | F101: =F$46 -> 426849.99 | G101: =G$46 -> 420741.75 | H101: =H$46 -> 394780.6 | I101: =I$46 -> 388495.34 | J101: =J$46 -> 382217.73 | ... V101: =V$46 -> 437325.93
A102: Equity CF (Base) | B102: =-$B$12 -> -2730231 | C102: =C$67 -> 560184.84 | D102: =D$67 -> 552463.86 | E102: =E$67 -> 544755.99 | F102: =F$67 -> 537060.62 | G102: =G$67 -> 529377.12 | H102: =H$67 -> 501840.69 | I102: =I$67 -> 493980.16 | J102: =J$67 -> 486127.28 | ... V102: =V$67 -> 522332.22
A103: Equity CF (High) | B103: =-$B$12 -> -2730231 | C103: =C$88 -> 632020.12 | D103: =D$88 -> 623314.59 | E103: =E$88 -> 614622.18 | F103: =F$88 -> 605942.27 | G103: =G$88 -> 597274.22 | H103: =H$88 -> 568753.25 | I103: =I$88 -> 559908.17 | J103: =J$88 -> 551070.75 | ... V103: =V$88 -> 575461.16
A104: Project CF (Low) | B104: =-$B$11 -> -4129755 | C104: =C$39-MAX(0,(C$39-C$40)*Assumptions!$B$35) -> 571334.71 | D104: =D$39-MAX(0,(D$39-D$40)*Assumptions!$B$35) -> 565594.36 | E104: =E$39-MAX(0,(E$39-E$40)*Assumptions!$B$35) -> 559887.38 | F104: =F$39-MAX(0,(F$39-F$40)*Assumptions!$B$35) -> 554214.19 | G104: =G$39-MAX(0,(G$39-G$40)*Assumptions!$B$35) -> 548575.21 | H104: =H$39-MAX(0,(H$39-H$40)*Assumptions!$B$35) -> 523106.78 | I104: =I$39-MAX(0,(I$39-I$40)*Assumptions!$B$35) -> 517338.86 | J104: =J$39-MAX(0,(J$39-J$40)*Assumptions!$B$35) -> 511604.47 | ... V104: =V$39-MAX(0,(V$39-V$40)*Assumptions!$B$35) -> 437325.93
A105: Project CF (Base) | B105: =-$B$11 -> -4129755 | C105: =C$60-MAX(0,(C$60-C$61)*Assumptions!$B$35) -> 686271.15 | D105: =D$60-MAX(0,(D$60-D$61)*Assumptions!$B$35) -> 678955.54 | E105: =E$60-MAX(0,(E$60-E$61)*Assumptions!$B$35) -> 671673.29 | F105: =F$60-MAX(0,(F$60-F$61)*Assumptions!$B$35) -> 664424.83 | G105: =G$60-MAX(0,(G$60-G$61)*Assumptions!$B$35) -> 657210.57 | H105: =H$60-MAX(0,(H$60-H$61)*Assumptions!$B$35) -> 630166.87 | I105: =I$60-MAX(0,(I$60-I$61)*Assumptions!$B$35) -> 622823.68 | J105: =J$60-MAX(0,(J$60-J$61)*Assumptions!$B$35) -> 615514.02 | ... V105: =V$60-MAX(0,(V$60-V$61)*Assumptions!$B$35) -> 522332.22
A106: Project CF (High) | B106: =-$B$11 -> -4129755 | C106: =C$81-MAX(0,(C$81-C$82)*Assumptions!$B$35) -> 758106.43 | D106: =D$81-MAX(0,(D$81-D$82)*Assumptions!$B$35) -> 749806.27 | E106: =E$81-MAX(0,(E$81-E$82)*Assumptions!$B$35) -> 741539.48 | F106: =F$81-MAX(0,(F$81-F$82)*Assumptions!$B$35) -> 733306.47 | G106: =G$81-MAX(0,(G$81-G$82)*Assumptions!$B$35) -> 725107.68 | H106: =H$81-MAX(0,(H$81-H$82)*Assumptions!$B$35) -> 697079.42 | I106: =I$81-MAX(0,(I$81-I$82)*Assumptions!$B$35) -> 688751.69 | J106: =J$81-MAX(0,(J$81-J$82)*Assumptions!$B$35) -> 680457.49 | ... V106: =V$81-MAX(0,(V$81-V$82)*Assumptions!$B$35) -> 575461.16

Sheet Fund Portfolio
A1: SHARK Fund — Aggregated Portfolio Model
A2: All formulas reference asset sheets and scale by unit count
A4: PORTFOLIO — LOW CASE (EUR 110/MWh)
A5: Year | C5: 2026 | D5: 2027 | E5: 2028 | F5: 2029 | G5: 2030 | H5: 2031 | I5: 2032 | J5: 2033 | K5: 2034 | L5: 2035 | M5: 2036 | N5: 2037 | O5: 2038 | P5: 2039 | Q5: 2040 | R5: 2041 | S5: 2042 | T5: 2043 | U5: 2044 | V5: 2045 | W5: Total / Avg
A6: Total Revenue | C6: ='Type A - 10MWp'!C$33*'Type A - 10MWp'!$B$16+'Type B - 5MWp'!C$33*'Type B - 5MWp'!$B$16+'Type C - 3MWp'!C$33*'Type C - 3MWp'!$B$16 -> 14741104 | D6: ='Type A - 10MWp'!D$33*'Type A - 10MWp'!$B$16+'Type B - 5MWp'!D$33*'Type B - 5MWp'!$B$16+'Type C - 3MWp'!D$33*'Type C - 3MWp'!$B$16 -> 14607649 | E6: ='Type A - 10MWp'!E$33*'Type A - 10MWp'!$B$16+'Type B - 5MWp'!E$33*'Type B - 5MWp'!$B$16+'Type C - 3MWp'!E$33*'Type C - 3MWp'!$B$16 -> 14474391 | F6: ='Type A - 10MWp'!F$33*'Type A - 10MWp'!$B$16+'Type B - 5MWp'!F$33*'Type B - 5MWp'!$B$16+'Type C - 3MWp'!F$33*'Type C - 3MWp'!$B$16 -> 14341329 | G6: ='Type A - 10MWp'!G$33*'Type A - 10MWp'!$B$16+'Type B - 5MWp'!G$33*'Type B - 5MWp'!$B$16+'Type C - 3MWp'!G$33*'Type C - 3MWp'!$B$16 -> 14208462 | H6: ='Type A - 10MWp'!H$33*'Type A - 10MWp'!$B$16+'Type B - 5MWp'!H$33*'Type B - 5MWp'!$B$16+'Type C - 3MWp'!H$33*'Type C - 3MWp'!$B$16 -> 14075789 | I6: ='Type A - 10MWp'!I$33*'Type A - 10MWp'!$B$16+'Type B - 5MWp'!I$33*'Type B - 5MWp'!$B$16+'Type C - 3MWp'!I$33*'Type C - 3MWp'!$B$16 -> 13943309 | J6: ='Type A - 10MWp'!J$33*'Type A - 10MWp'!$B$16+'Type B - 5MWp'!J$33*'Type B - 5MWp'!$B$16+'Type C - 3MWp'!J$33*'Type C - 3MWp'!$B$16 -> 13811021 | ... V6: ='Type A - 10MWp'!V$33*'Type A - 10MWp'!$B$16+'Type B - 5MWp'!V$33*'Type B - 5MWp'!$B$16+'Type C - 3MWp'!V$33*'Type C - 3MWp'!$B$16 -> 12238202 | W6: =SUM(C$6:V$6) -> 2.6968546e+08
A7: Total Operating Costs | C7: ='Type A - 10MWp'!C$38*'Type A - 10MWp'!$B$16+'Type B - 5MWp'!C$38*'Type B - 5MWp'!$B$16+'Type C - 3MWp'!C$38*'Type C - 3MWp'!$B$16 -> 2859445.7 | D7: ='Type A - 10MWp'!D$38*'Type A - 10MWp'!$B$16+'Type B - 5MWp'!D$38*'Type B - 5MWp'!$B$16+'Type C - 3MWp'!D$38*'Type C - 3MWp'!$B$16 -> 2850278.3 | E7: ='Type A - 10MWp'!E$38*'Type A - 10MWp'!$B$16+'Type B - 5MWp'!E$38*'Type B - 5MWp'!$B$16+'Type C - 3MWp'!E$38*'Type C - 3MWp'!$B$16 -> 2840579.6 | F7: ='Type A - 10MWp'!F$38*'Type A - 10MWp'!$B$16+'Type B - 5MWp'!F$38*'Type B - 5MWp'!$B$16+'Type C - 3MWp'!F$38*'Type C - 3MWp'!$B$16 -> 2830339.5 | G7: ='Type A - 10MWp'!G$38*'Type A - 10MWp'!$B$16+'Type B - 5MWp'!G$38*'Type B - 5MWp'!$B$16+'Type C - 3MWp'!G$38*'Type C - 3MWp'!$B$16 -> 2819548 | H7: ='Type A - 10MWp'!H$38*'Type A - 10MWp'!$B$16+'Type B - 5MWp'!H$38*'Type B - 5MWp'!$B$16+'Type C - 3MWp'!H$38*'Type C - 3MWp'!$B$16 -> 3239529.2 | I7: ='Type A - 10MWp'!I$38*'Type A - 10MWp'!$B$16+'Type B - 5MWp'!I$38*'Type B - 5MWp'!$B$16+'Type C - 3MWp'!I$38*'Type C - 3MWp'!$B$16 -> 3231917 | J7: ='Type A - 10MWp'!J$38*'Type A - 10MWp'!$B$16+'Type B - 5MWp'!J$38*'Type B - 5MWp'!$B$16+'Type C - 3MWp'!J$38*'Type C - 3MWp'!$B$16 -> 3223765 | ... V7: ='Type A - 10MWp'!V$38*'Type A - 10MWp'!$B$16+'Type B - 5MWp'!V$38*'Type B - 5MWp'!$B$16+'Type C - 3MWp'!V$38*'Type C - 3MWp'!$B$16 -> 3258956.3 | W7: =SUM(C$7:V$7) -> 62996726
A8: Portfolio EBITDA | C8: ='Type A - 10MWp'!C$39*'Type A - 10MWp'!$B$16+'Type B - 5MWp'!C$39*'Type B - 5MWp'!$B$16+'Type C - 3MWp'!C$39*'Type C - 3MWp'!$B$16 -> 11881658 | D8: ='Type A - 10MWp'!D$39*'Type A - 10MWp'!$B$16+'Type B - 5MWp'!D$39*'Type B - 5MWp'!$B$16+'Type C - 3MWp'!D$39*'Type C - 3MWp'!$B$16 -> 11757371 | E8: ='Type A - 10MWp'!E$39*'Type A - 10MWp'!$B$16+'Type B - 5MWp'!E$39*'Type B - 5MWp'!$B$16+'Type C - 3MWp'!E$39*'Type C - 3MWp'!$B$16 -> 11633811 | F8: ='Type A - 10MWp'!F$39*'Type A - 10MWp'!$B$16+'Type B - 5MWp'!F$39*'Type B - 5MWp'!$B$16+'Type C - 3MWp'!F$39*'Type C - 3MWp'!$B$16 -> 11510989 | G8: ='Type A - 10MWp'!G$39*'Type A - 10MWp'!$B$16+'Type B - 5MWp'!G$39*'Type B - 5MWp'!$B$16+'Type C - 3MWp'!G$39*'Type C - 3MWp'!$B$16 -> 11388914 | H8: ='Type A - 10MWp'!H$39*'Type A - 10MWp'!$B$16+'Type B - 5MWp'!H$39*'Type B - 5MWp'!$B$16+'Type C - 3MWp'!H$39*'Type C - 3MWp'!$B$16 -> 10836260 | I8: ='Type A - 10MWp'!I$39*'Type A - 10MWp'!$B$16+'Type B - 5MWp'!I$39*'Type B - 5MWp'!$B$16+'Type C - 3MWp'!I$39*'Type C - 3MWp'!$B$16 -> 10711392 | J8: ='Type A - 10MWp'!J$39*'Type A - 10MWp'!$B$16+'Type B - 5MWp'!J$39*'Type B - 5MWp'!$B$16+'Type C - 3MWp'!J$39*'Type C - 3MWp'!$B$16 -> 10587256 | ... V8: ='Type A - 10MWp'!V$39*'Type A - 10MWp'!$B$16+'Type B - 5MWp'!V$39*'Type B - 5MWp'!$B$16+'Type C - 3MWp'!V$39*'Type C - 3MWp'!$B$16 -> 8979245.3 | W8: =SUM(C$8:V$8) -> 2.0668873e+08
A9: Total Debt Service | C9: ='Type A - 10MWp'!C$45*'Type A - 10MWp'!$B$16+'Type B - 5MWp'!C$45*'Type B - 5MWp'!$B$16+'Type C - 3MWp'!C$45*'Type C - 3MWp'!$B$16 -> 2175267.6 | D9: ='Type A - 10MWp'!D$45*'Type A - 10MWp'!$B$16+'Type B - 5MWp'!D$45*'Type B - 5MWp'!$B$16+'Type C - 3MWp'!D$45*'Type C - 3MWp'!$B$16 -> 2175267.6 | E9: ='Type A - 10MWp'!E$45*'Type A - 10MWp'!$B$16+'Type B - 5MWp'!E$45*'Type B - 5MWp'!$B$16+'Type C - 3MWp'!E$45*'Type C - 3MWp'!$B$16 -> 2175267.6 | F9: ='Type A - 10MWp'!F$45*'Type A - 10MWp'!$B$16+'Type B - 5MWp'!F$45*'Type B - 5MWp'!$B$16+'Type C - 3MWp'!F$45*'Type C - 3MWp'!$B$16 -> 2175267.6 | G9: ='Type A - 10MWp'!G$45*'Type A - 10MWp'!$B$16+'Type B - 5MWp'!G$45*'Type B - 5MWp'!$B$16+'Type C - 3MWp'!G$45*'Type C - 3MWp'!$B$16 -> 2175267.6 | H9: ='Type A - 10MWp'!H$45*'Type A - 10MWp'!$B$16+'Type B - 5MWp'!H$45*'Type B - 5MWp'!$B$16+'Type C - 3MWp'!H$45*'Type C - 3MWp'!$B$16 -> 2175267.6 | I9: ='Type A - 10MWp'!I$45*'Type A - 10MWp'!$B$16+'Type B - 5MWp'!I$45*'Type B - 5MWp'!$B$16+'Type C - 3MWp'!I$45*'Type C - 3MWp'!$B$16 -> 2175267.6 | J9: ='Type A - 10MWp'!J$45*'Type A - 10MWp'!$B$16+'Type B - 5MWp'!J$45*'Type B - 5MWp'!$B$16+'Type C - 3MWp'!J$45*'Type C - 3MWp'!$B$16 -> 2175267.6 | ... V9: ='Type A - 10MWp'!V$45*'Type A - 10MWp'!$B$16+'Type B - 5MWp'!V$45*'Type B - 5MWp'!$B$16+'Type C - 3MWp'!V$45*'Type C - 3MWp'!$B$16 -> 0 | W9: =SUM(C$9:V$9) -> 32629014
A10: Total Tax | C10: ='Type A - 10MWp'!C$43*'Type A - 10MWp'!$B$16+'Type B - 5MWp'!C$43*'Type B - 5MWp'!$B$16+'Type C - 3MWp'!C$43*'Type C - 3MWp'!$B$16 -> 890010.69 | D10: ='Type A - 10MWp'!D$43*'Type A - 10MWp'!$B$16+'Type B - 5MWp'!D$43*'Type B - 5MWp'!$B$16+'Type C - 3MWp'!D$43*'Type C - 3MWp'!$B$16 -> 881014.37 | E10: ='Type A - 10MWp'!E$43*'Type A - 10MWp'!$B$16+'Type B - 5MWp'!E$43*'Type B - 5MWp'!$B$16+'Type C - 3MWp'!E$43*'Type C - 3MWp'!$B$16 -> 872436.07 | F10: ='Type A - 10MWp'!F$43*'Type A - 10MWp'!$B$16+'Type B - 5MWp'!F$43*'Type B - 5MWp'!$B$16+'Type C - 3MWp'!F$43*'Type C - 3MWp'!$B$16 -> 864293.26 | G10: ='Type A - 10MWp'!G$43*'Type A - 10MWp'!$B$16+'Type B - 5MWp'!G$43*'Type B - 5MWp'!$B$16+'Type C - 3MWp'!G$43*'Type C - 3MWp'!$B$16 -> 856604.25 | H10: ='Type A - 10MWp'!H$43*'Type A - 10MWp'!$B$16+'Type B - 5MWp'!H$43*'Type B - 5MWp'!$B$16+'Type C - 3MWp'!H$43*'Type C - 3MWp'!$B$16 -> 795471.43 | I10: ='Type A - 10MWp'!I$43*'Type A - 10MWp'!$B$16+'Type B - 5MWp'!I$43*'Type B - 5MWp'!$B$16+'Type C - 3MWp'!I$43*'Type C - 3MWp'!$B$16 -> 788209.36 | J10: ='Type A - 10MWp'!J$43*'Type A - 10MWp'!$B$16+'Type B - 5MWp'!J$43*'Type B - 5MWp'!$B$16+'Type C - 3MWp'!J$43*'Type C - 3MWp'!$B$16 -> 781456.09 | ... V10: ='Type A - 10MWp'!V$43*'Type A - 10MWp'!$B$16+'Type B - 5MWp'!V$43*'Type B - 5MWp'!$B$16+'Type C - 3MWp'!V$43*'Type C - 3MWp'!$B$16 -> 668324.9 | W10: =SUM(C$10:V$10) -> 15498166
A11: Portfolio FCFE | C11: ='Type A - 10MWp'!C$46*'Type A - 10MWp'!$B$16+'Type B - 5MWp'!C$46*'Type B - 5MWp'!$B$16+'Type C - 3MWp'!C$46*'Type C - 3MWp'!$B$16 -> 8816380 | D11: ='Type A - 10MWp'!D$46*'Type A - 10MWp'!$B$16+'Type B - 5MWp'!D$46*'Type B - 5MWp'!$B$16+'Type C - 3MWp'!D$46*'Type C - 3MWp'!$B$16 -> 8701088.8 | E11: ='Type A - 10MWp'!E$46*'Type A - 10MWp'!$B$16+'Type B - 5MWp'!E$46*'Type B - 5MWp'!$B$16+'Type C - 3MWp'!E$46*'Type C - 3MWp'!$B$16 -> 8586107.8 | F11: ='Type A - 10MWp'!F$46*'Type A - 10MWp'!$B$16+'Type B - 5MWp'!F$46*'Type B - 5MWp'!$B$16+'Type C - 3MWp'!F$46*'Type C - 3MWp'!$B$16 -> 8471428.6 | G11: ='Type A - 10MWp'!G$46*'Type A - 10MWp'!$B$16+'Type B - 5MWp'!G$46*'Type B - 5MWp'!$B$16+'Type C - 3MWp'!G$46*'Type C - 3MWp'!$B$16 -> 8357042 | H11: ='Type A - 10MWp'!H$46*'Type A - 10MWp'!$B$16+'Type B - 5MWp'!H$46*'Type B - 5MWp'!$B$16+'Type C - 3MWp'!H$46*'Type C - 3MWp'!$B$16 -> 7865520.5 | I11: ='Type A - 10MWp'!I$46*'Type A - 10MWp'!$B$16+'Type B - 5MWp'!I$46*'Type B - 5MWp'!$B$16+'Type C - 3MWp'!I$46*'Type C - 3MWp'!$B$16 -> 7747914.8 | J11: ='Type A - 10MWp'!J$46*'Type A - 10MWp'!$B$16+'Type B - 5MWp'!J$46*'Type B - 5MWp'!$B$16+'Type C - 3MWp'!J$46*'Type C - 3MWp'!$B$16 -> 7630532.1 | ... V11: ='Type A - 10MWp'!V$46*'Type A - 10MWp'!$B$16+'Type B - 5MWp'!V$46*'Type B - 5MWp'!$B$16+'Type C - 3MWp'!V$46*'Type C - 3MWp'!$B$16 -> 8310920.4 | W11: =SUM(C$11:V$11) -> 1.5856155e+08
A12: Cumulative Portfolio CF | C12: =C$11 -> 8816380 | D12: =C$12+D$11 -> 17517469 | E12: =D$12+E$11 -> 26103577 | F12: =E$12+F$11 -> 34575005 | G12: =F$12+G$11 -> 42932047 | H12: =G$12+H$11 -> 50797568 | I12: =H$12+I$11 -> 58545483 | J12: =I$12+J$11 -> 66176015 | K12: =J$12+K$11 -> 73689374 | ... V12: =U$12+V$11 -> 1.5856155e+08 | W12: =V$12 -> 1.5856155e+08
A14: PORTFOLIO — BASE CASE (EUR 150/MWh Blended)
A15: Year | C15: 2026 | D15: 2027 | E15: 2028 | F15: 2029 | G15: 2030 | H15: 2031 | I15: 2032 | J15: 2033 | K15: 2034 | L15: 2035 | M15: 2036 | N15: 2037 | O15: 2038 | P15: 2039 | Q15: 2040 | R15: 2041 | S15: 2042 | T15: 2043 | U15: 2044 | V15: 2045 | W15: Total / Avg
A16: Total Revenue | C16: ='Type A - 10MWp'!C$54*'Type A - 10MWp'!$B$16+'Type B - 5MWp'!C$54*'Type B - 5MWp'!$B$16+'Type C - 3MWp'!C$54*'Type C - 3MWp'!$B$16 -> 17236867 | D16: ='Type A - 10MWp'!D$54*'Type A - 10MWp'!$B$16+'Type B - 5MWp'!D$54*'Type B - 5MWp'!$B$16+'Type C - 3MWp'!D$54*'Type C - 3MWp'!$B$16 -> 17069206 | E16: ='Type A - 10MWp'!E$54*'Type A - 10MWp'!$B$16+'Type B - 5MWp'!E$54*'Type B - 5MWp'!$B$16+'Type C - 3MWp'!E$54*'Type C - 3MWp'!$B$16 -> 16901742 | F16: ='Type A - 10MWp'!F$54*'Type A - 10MWp'!$B$16+'Type B - 5MWp'!F$54*'Type B - 5MWp'!$B$16+'Type C - 3MWp'!F$54*'Type C - 3MWp'!$B$16 -> 16734474 | G16: ='Type A - 10MWp'!G$54*'Type A - 10MWp'!$B$16+'Type B - 5MWp'!G$54*'Type B - 5MWp'!$B$16+'Type C - 3MWp'!G$54*'Type C - 3MWp'!$B$16 -> 16567401 | H16: ='Type A - 10MWp'!H$54*'Type A - 10MWp'!$B$16+'Type B - 5MWp'!H$54*'Type B - 5MWp'!$B$16+'Type C - 3MWp'!H$54*'Type C - 3MWp'!$B$16 -> 16400522 | I16: ='Type A - 10MWp'!I$54*'Type A - 10MWp'!$B$16+'Type B - 5MWp'!I$54*'Type B - 5MWp'!$B$16+'Type C - 3MWp'!I$54*'Type C - 3MWp'!$B$16 -> 16233836 | J16: ='Type A - 10MWp'!J$54*'Type A - 10MWp'!$B$16+'Type B - 5MWp'!J$54*'Type B - 5MWp'!$B$16+'Type C - 3MWp'!J$54*'Type C - 3MWp'!$B$16 -> 16067342 | ... V16: ='Type A - 10MWp'!V$54*'Type A - 10MWp'!$B$16+'Type B - 5MWp'!V$54*'Type B - 5MWp'!$B$16+'Type C - 3MWp'!V$54*'Type C - 3MWp'!$B$16 -> 14084053 | W16: =SUM(C$16:V$16) -> 3.131016e+08
A17: Total Operating Costs | C17: ='Type A - 10MWp'!C$59*'Type A - 10MWp'!$B$16+'Type B - 5MWp'!C$59*'Type B - 5MWp'!$B$16+'Type C - 3MWp'!C$59*'Type C - 3MWp'!$B$16 -> 2859445.7 | D17: ='Type A - 10MWp'!D$59*'Type A - 10MWp'!$B$16+'Type B - 5MWp'!D$59*'Type B - 5MWp'!$B$16+'Type C - 3MWp'!D$59*'Type C - 3MWp'!$B$16 -> 2850278.3 | E17: ='Type A - 10MWp'!E$59*'Type A - 10MWp'!$B$16+'Type B - 5MWp'!E$59*'Type B - 5MWp'!$B$16+'Type C - 3MWp'!E$59*'Type C - 3MWp'!$B$16 -> 2840579.6 | F17: ='Type A - 10MWp'!F$59*'Type A - 10MWp'!$B$16+'Type B - 5MWp'!F$59*'Type B - 5MWp'!$B$16+'Type C - 3MWp'!F$59*'Type C - 3MWp'!$B$16 -> 2830339.5 | G17: ='Type A - 10MWp'!G$59*'Type A - 10MWp'!$B$16+'Type B - 5MWp'!G$59*'Type B - 5MWp'!$B$16+'Type C - 3MWp'!G$59*'Type C - 3MWp'!$B$16 -> 2819548 | H17: ='Type A - 10MWp'!H$59*'Type A - 10MWp'!$B$16+'Type B - 5MWp'!H$59*'Type B - 5MWp'!$B$16+'Type C - 3MWp'!H$59*'Type C - 3MWp'!$B$16 -> 3239529.2 | I17: ='Type A - 10MWp'!I$59*'Type A - 10MWp'!$B$16+'Type B - 5MWp'!I$59*'Type B - 5MWp'!$B$16+'Type C - 3MWp'!I$59*'Type C - 3MWp'!$B$16 -> 3231917 | J17: ='Type A - 10MWp'!J$59*'Type A - 10MWp'!$B$16+'Type B - 5MWp'!J$59*'Type B - 5MWp'!$B$16+'Type C - 3MWp'!J$59*'Type C - 3MWp'!$B$16 -> 3223765 | ... V17: ='Type A - 10MWp'!V$59*'Type A - 10MWp'!$B$16+'Type B - 5MWp'!V$59*'Type B - 5MWp'!$B$16+'Type C - 3MWp'!V$59*'Type C - 3MWp'!$B$16 -> 3258956.3 | W17: =SUM(C$17:V$17) -> 62996726
A18: Portfolio EBITDA | C18: ='Type A - 10MWp'!C$60*'Type A - 10MWp'!$B$16+'Type B - 5MWp'!C$60*'Type B - 5MWp'!$B$16+'Type C - 3MWp'!C$60*'Type C - 3MWp'!$B$16 -> 14377421 | D18: ='Type A - 10MWp'!D$60*'Type A - 10MWp'!$B$16+'Type B - 5MWp'!D$60*'Type B - 5MWp'!$B$16+'Type C - 3MWp'!D$60*'Type C - 3MWp'!$B$16 -> 14218928 | E18: ='Type A - 10MWp'!E$60*'Type A - 10MWp'!$B$16+'Type B - 5MWp'!E$60*'Type B - 5MWp'!$B$16+'Type C - 3MWp'!E$60*'Type C - 3MWp'!$B$16 -> 14061163 | F18: ='Type A - 10MWp'!F$60*'Type A - 10MWp'!$B$16+'Type B - 5MWp'!F$60*'Type B - 5MWp'!$B$16+'Type C - 3MWp'!F$60*'Type C - 3MWp'!$B$16 -> 13904135 | G18: ='Type A - 10MWp'!G$60*'Type A - 10MWp'!$B$16+'Type B - 5MWp'!G$60*'Type B - 5MWp'!$B$16+'Type C - 3MWp'!G$60*'Type C - 3MWp'!$B$16 -> 13747853 | H18: ='Type A - 10MWp'!H$60*'Type A - 10MWp'!$B$16+'Type B - 5MWp'!H$60*'Type B - 5MWp'!$B$16+'Type C - 3MWp'!H$60*'Type C - 3MWp'!$B$16 -> 13160993 | I18: ='Type A - 10MWp'!I$60*'Type A - 10MWp'!$B$16+'Type B - 5MWp'!I$60*'Type B - 5MWp'!$B$16+'Type C - 3MWp'!I$60*'Type C - 3MWp'!$B$16 -> 13001919 | J18: ='Type A - 10MWp'!J$60*'Type A - 10MWp'!$B$16+'Type B - 5MWp'!J$60*'Type B - 5MWp'!$B$16+'Type C - 3MWp'!J$60*'Type C - 3MWp'!$B$16 -> 12843577 | ... V18: ='Type A - 10MWp'!V$60*'Type A - 10MWp'!$B$16+'Type B - 5MWp'!V$60*'Type B - 5MWp'!$B$16+'Type C - 3MWp'!V$60*'Type C - 3MWp'!$B$16 -> 10825096 | W18: =SUM(C$18:V$18) -> 250104870
A19: Total Debt Service | C19: ='Type A - 10MWp'!C$66*'Type A - 10MWp'!$B$16+'Type B - 5MWp'!C$66*'Type B - 5MWp'!$B$16+'Type C - 3MWp'!C$66*'Type C - 3MWp'!$B$16 -> 2175267.6 | D19: ='Type A - 10MWp'!D$66*'Type A - 10MWp'!$B$16+'Type B - 5MWp'!D$66*'Type B - 5MWp'!$B$16+'Type C - 3MWp'!D$66*'Type C - 3MWp'!$B$16 -> 2175267.6 | E19: ='Type A - 10MWp'!E$66*'Type A - 10MWp'!$B$16+'Type B - 5MWp'!E$66*'Type B - 5MWp'!$B$16+'Type C - 3MWp'!E$66*'Type C - 3MWp'!$B$16 -> 2175267.6 | F19: ='Type A - 10MWp'!F$66*'Type A - 10MWp'!$B$16+'Type B - 5MWp'!F$66*'Type B - 5MWp'!$B$16+'Type C - 3MWp'!F$66*'Type C - 3MWp'!$B$16 -> 2175267.6 | G19: ='Type A - 10MWp'!G$66*'Type A - 10MWp'!$B$16+'Type B - 5MWp'!G$66*'Type B - 5MWp'!$B$16+'Type C - 3MWp'!G$66*'Type C - 3MWp'!$B$16 -> 2175267.6 | H19: ='Type A - 10MWp'!H$66*'Type A - 10MWp'!$B$16+'Type B - 5MWp'!H$66*'Type B - 5MWp'!$B$16+'Type C - 3MWp'!H$66*'Type C - 3MWp'!$B$16 -> 2175267.6 | I19: ='Type A - 10MWp'!I$66*'Type A - 10MWp'!$B$16+'Type B - 5MWp'!I$66*'Type B - 5MWp'!$B$16+'Type C - 3MWp'!I$66*'Type C - 3MWp'!$B$16 -> 2175267.6 | J19: ='Type A - 10MWp'!J$66*'Type A - 10MWp'!$B$16+'Type B - 5MWp'!J$66*'Type B - 5MWp'!$B$16+'Type C - 3MWp'!J$66*'Type C - 3MWp'!$B$16 -> 2175267.6 | ... V19: ='Type A - 10MWp'!V$66*'Type A - 10MWp'!$B$16+'Type B - 5MWp'!V$66*'Type B - 5MWp'!$B$16+'Type C - 3MWp'!V$66*'Type C - 3MWp'!$B$16 -> 0 | W19: =SUM(C$19:V$19) -> 32629014
A20: Total Tax | C20: ='Type A - 10MWp'!C$64*'Type A - 10MWp'!$B$16+'Type B - 5MWp'!C$64*'Type B - 5MWp'!$B$16+'Type C - 3MWp'!C$64*'Type C - 3MWp'!$B$16 -> 1201981 | D20: ='Type A - 10MWp'!D$64*'Type A - 10MWp'!$B$16+'Type B - 5MWp'!D$64*'Type B - 5MWp'!$B$16+'Type C - 3MWp'!D$64*'Type C - 3MWp'!$B$16 -> 1188709 | E20: ='Type A - 10MWp'!E$64*'Type A - 10MWp'!$B$16+'Type B - 5MWp'!E$64*'Type B - 5MWp'!$B$16+'Type C - 3MWp'!E$64*'Type C - 3MWp'!$B$16 -> 1175855 | F20: ='Type A - 10MWp'!F$64*'Type A - 10MWp'!$B$16+'Type B - 5MWp'!F$64*'Type B - 5MWp'!$B$16+'Type C - 3MWp'!F$64*'Type C - 3MWp'!$B$16 -> 1163436.4 | G20: ='Type A - 10MWp'!G$64*'Type A - 10MWp'!$B$16+'Type B - 5MWp'!G$64*'Type B - 5MWp'!$B$16+'Type C - 3MWp'!G$64*'Type C - 3MWp'!$B$16 -> 1151471.7 | H20: ='Type A - 10MWp'!H$64*'Type A - 10MWp'!$B$16+'Type B - 5MWp'!H$64*'Type B - 5MWp'!$B$16+'Type C - 3MWp'!H$64*'Type C - 3MWp'!$B$16 -> 1086063.1 | I20: ='Type A - 10MWp'!I$64*'Type A - 10MWp'!$B$16+'Type B - 5MWp'!I$64*'Type B - 5MWp'!$B$16+'Type C - 3MWp'!I$64*'Type C - 3MWp'!$B$16 -> 1074525.3 | J20: ='Type A - 10MWp'!J$64*'Type A - 10MWp'!$B$16+'Type B - 5MWp'!J$64*'Type B - 5MWp'!$B$16+'Type C - 3MWp'!J$64*'Type C - 3MWp'!$B$16 -> 1063496.3 | ... V20: ='Type A - 10MWp'!V$64*'Type A - 10MWp'!$B$16+'Type B - 5MWp'!V$64*'Type B - 5MWp'!$B$16+'Type C - 3MWp'!V$64*'Type C - 3MWp'!$B$16 -> 899056.27 | W20: =SUM(C$20:V$20) -> 20925183
A21: Portfolio FCFE | C21: ='Type A - 10MWp'!C$67*'Type A - 10MWp'!$B$16+'Type B - 5MWp'!C$67*'Type B - 5MWp'!$B$16+'Type C - 3MWp'!C$67*'Type C - 3MWp'!$B$16 -> 11000173 | D21: ='Type A - 10MWp'!D$67*'Type A - 10MWp'!$B$16+'Type B - 5MWp'!D$67*'Type B - 5MWp'!$B$16+'Type C - 3MWp'!D$67*'Type C - 3MWp'!$B$16 -> 10854951 | E21: ='Type A - 10MWp'!E$67*'Type A - 10MWp'!$B$16+'Type B - 5MWp'!E$67*'Type B - 5MWp'!$B$16+'Type C - 3MWp'!E$67*'Type C - 3MWp'!$B$16 -> 10710040 | F21: ='Type A - 10MWp'!F$67*'Type A - 10MWp'!$B$16+'Type B - 5MWp'!F$67*'Type B - 5MWp'!$B$16+'Type C - 3MWp'!F$67*'Type C - 3MWp'!$B$16 -> 10565431 | G21: ='Type A - 10MWp'!G$67*'Type A - 10MWp'!$B$16+'Type B - 5MWp'!G$67*'Type B - 5MWp'!$B$16+'Type C - 3MWp'!G$67*'Type C - 3MWp'!$B$16 -> 10421114 | H21: ='Type A - 10MWp'!H$67*'Type A - 10MWp'!$B$16+'Type B - 5MWp'!H$67*'Type B - 5MWp'!$B$16+'Type C - 3MWp'!H$67*'Type C - 3MWp'!$B$16 -> 9899662.3 | I21: ='Type A - 10MWp'!I$67*'Type A - 10MWp'!$B$16+'Type B - 5MWp'!I$67*'Type B - 5MWp'!$B$16+'Type C - 3MWp'!I$67*'Type C - 3MWp'!$B$16 -> 9752126.4 | J21: ='Type A - 10MWp'!J$67*'Type A - 10MWp'!$B$16+'Type B - 5MWp'!J$67*'Type B - 5MWp'!$B$16+'Type C - 3MWp'!J$67*'Type C - 3MWp'!$B$16 -> 9604813.5 | ... V21: ='Type A - 10MWp'!V$67*'Type A - 10MWp'!$B$16+'Type B - 5MWp'!V$67*'Type B - 5MWp'!$B$16+'Type C - 3MWp'!V$67*'Type C - 3MWp'!$B$16 -> 9926040 | W21: =SUM(C$21:V$21) -> 1.9655067e+08
A22: Cumulative Portfolio CF | C22: =C$21 -> 11000173 | D22: =C$22+D$21 -> 21855124 | E22: =D$22+E$21 -> 32565164 | F22: =E$22+F$21 -> 43130594 | G22: =F$22+G$21 -> 53551708 | H22: =G$22+H$21 -> 63451370 | I22: =H$22+I$21 -> 73203497 | J22: =I$22+J$21 -> 82808310 | K22: =J$22+K$21 -> 92266021 | ... V22: =U$22+V$21 -> 1.9655067e+08 | W22: =V$22 -> 1.9655067e+08
A24: PORTFOLIO — HIGH CASE (EUR 175/MWh)
A25: Year | C25: 2026 | D25: 2027 | E25: 2028 | F25: 2029 | G25: 2030 | H25: 2031 | I25: 2032 | J25: 2033 | K25: 2034 | L25: 2035 | M25: 2036 | N25: 2037 | O25: 2038 | P25: 2039 | Q25: 2040 | R25: 2041 | S25: 2042 | T25: 2043 | U25: 2044 | V25: 2045 | W25: Total / Avg
A26: Total Revenue | C26: ='Type A - 10MWp'!C$75*'Type A - 10MWp'!$B$16+'Type B - 5MWp'!C$75*'Type B - 5MWp'!$B$16+'Type C - 3MWp'!C$75*'Type C - 3MWp'!$B$16 -> 18796719 | D26: ='Type A - 10MWp'!D$75*'Type A - 10MWp'!$B$16+'Type B - 5MWp'!D$75*'Type B - 5MWp'!$B$16+'Type C - 3MWp'!D$75*'Type C - 3MWp'!$B$16 -> 18607679 | E26: ='Type A - 10MWp'!E$75*'Type A - 10MWp'!$B$16+'Type B - 5MWp'!E$75*'Type B - 5MWp'!$B$16+'Type C - 3MWp'!E$75*'Type C - 3MWp'!$B$16 -> 18418837 | F26: ='Type A - 10MWp'!F$75*'Type A - 10MWp'!$B$16+'Type B - 5MWp'!F$75*'Type B - 5MWp'!$B$16+'Type C - 3MWp'!F$75*'Type C - 3MWp'!$B$16 -> 18230190 | G26: ='Type A - 10MWp'!G$75*'Type A - 10MWp'!$B$16+'Type B - 5MWp'!G$75*'Type B - 5MWp'!$B$16+'Type C - 3MWp'!G$75*'Type C - 3MWp'!$B$16 -> 18041738 | H26: ='Type A - 10MWp'!H$75*'Type A - 10MWp'!$B$16+'Type B - 5MWp'!H$75*'Type B - 5MWp'!$B$16+'Type C - 3MWp'!H$75*'Type C - 3MWp'!$B$16 -> 17853481 | I26: ='Type A - 10MWp'!I$75*'Type A - 10MWp'!$B$16+'Type B - 5MWp'!I$75*'Type B - 5MWp'!$B$16+'Type C - 3MWp'!I$75*'Type C - 3MWp'!$B$16 -> 17665416 | J26: ='Type A - 10MWp'!J$75*'Type A - 10MWp'!$B$16+'Type B - 5MWp'!J$75*'Type B - 5MWp'!$B$16+'Type C - 3MWp'!J$75*'Type C - 3MWp'!$B$16 -> 17477543 | ... V26: ='Type A - 10MWp'!V$75*'Type A - 10MWp'!$B$16+'Type B - 5MWp'!V$75*'Type B - 5MWp'!$B$16+'Type C - 3MWp'!V$75*'Type C - 3MWp'!$B$16 -> 15237710 | W26: =SUM(C$26:V$26) -> 3.4023668e+08
A27: Total Operating Costs | C27: ='Type A - 10MWp'!C$80*'Type A - 10MWp'!$B$16+'Type B - 5MWp'!C$80*'Type B - 5MWp'!$B$16+'Type C - 3MWp'!C$80*'Type C - 3MWp'!$B$16 -> 2859445.7 | D27: ='Type A - 10MWp'!D$80*'Type A - 10MWp'!$B$16+'Type B - 5MWp'!D$80*'Type B - 5MWp'!$B$16+'Type C - 3MWp'!D$80*'Type C - 3MWp'!$B$16 -> 2850278.3 | E27: ='Type A - 10MWp'!E$80*'Type A - 10MWp'!$B$16+'Type B - 5MWp'!E$80*'Type B - 5MWp'!$B$16+'Type C - 3MWp'!E$80*'Type C - 3MWp'!$B$16 -> 2840579.6 | F27: ='Type A - 10MWp'!F$80*'Type A - 10MWp'!$B$16+'Type B - 5MWp'!F$80*'Type B - 5MWp'!$B$16+'Type C - 3MWp'!F$80*'Type C - 3MWp'!$B$16 -> 2830339.5 | G27: ='Type A - 10MWp'!G$80*'Type A - 10MWp'!$B$16+'Type B - 5MWp'!G$80*'Type B - 5MWp'!$B$16+'Type C - 3MWp'!G$80*'Type C - 3MWp'!$B$16 -> 2819548 | H27: ='Type A - 10MWp'!H$80*'Type A - 10MWp'!$B$16+'Type B - 5MWp'!H$80*'Type B - 5MWp'!$B$16+'Type C - 3MWp'!H$80*'Type C - 3MWp'!$B$16 -> 3239529.2 | I27: ='Type A - 10MWp'!I$80*'Type A - 10MWp'!$B$16+'Type B - 5MWp'!I$80*'Type B - 5MWp'!$B$16+'Type C - 3MWp'!I$80*'Type C - 3MWp'!$B$16 -> 3231917 | J27: ='Type A - 10MWp'!J$80*'Type A - 10MWp'!$B$16+'Type B - 5MWp'!J$80*'Type B - 5MWp'!$B$16+'Type C - 3MWp'!J$80*'Type C - 3MWp'!$B$16 -> 3223765 | ... V27: ='Type A - 10MWp'!V$80*'Type A - 10MWp'!$B$16+'Type B - 5MWp'!V$80*'Type B - 5MWp'!$B$16+'Type C - 3MWp'!V$80*'Type C - 3MWp'!$B$16 -> 3258956.3 | W27: =SUM(C$27:V$27) -> 62996726
A28: Portfolio EBITDA | C28: ='Type A - 10MWp'!C$81*'Type A - 10MWp'!$B$16+'Type B - 5MWp'!C$81*'Type B - 5MWp'!$B$16+'Type C - 3MWp'!C$81*'Type C - 3MWp'!$B$16 -> 15937273 | D28: ='Type A - 10MWp'!D$81*'Type A - 10MWp'!$B$16+'Type B - 5MWp'!D$81*'Type B - 5MWp'!$B$16+'Type C - 3MWp'!D$81*'Type C - 3MWp'!$B$16 -> 15757401 | E28: ='Type A - 10MWp'!E$81*'Type A - 10MWp'!$B$16+'Type B - 5MWp'!E$81*'Type B - 5MWp'!$B$16+'Type C - 3MWp'!E$81*'Type C - 3MWp'!$B$16 -> 15578257 | F28: ='Type A - 10MWp'!F$81*'Type A - 10MWp'!$B$16+'Type B - 5MWp'!F$81*'Type B - 5MWp'!$B$16+'Type C - 3MWp'!F$81*'Type C - 3MWp'!$B$16 -> 15399850 | G28: ='Type A - 10MWp'!G$81*'Type A - 10MWp'!$B$16+'Type B - 5MWp'!G$81*'Type B - 5MWp'!$B$16+'Type C - 3MWp'!G$81*'Type C - 3MWp'!$B$16 -> 15222190 | H28: ='Type A - 10MWp'!H$81*'Type A - 10MWp'!$B$16+'Type B - 5MWp'!H$81*'Type B - 5MWp'!$B$16+'Type C - 3MWp'!H$81*'Type C - 3MWp'!$B$16 -> 14613951 | I28: ='Type A - 10MWp'!I$81*'Type A - 10MWp'!$B$16+'Type B - 5MWp'!I$81*'Type B - 5MWp'!$B$16+'Type C - 3MWp'!I$81*'Type C - 3MWp'!$B$16 -> 14433499 | J28: ='Type A - 10MWp'!J$81*'Type A - 10MWp'!$B$16+'Type B - 5MWp'!J$81*'Type B - 5MWp'!$B$16+'Type C - 3MWp'!J$81*'Type C - 3MWp'!$B$16 -> 14253778 | ... V28: ='Type A - 10MWp'!V$81*'Type A - 10MWp'!$B$16+'Type B - 5MWp'!V$81*'Type B - 5MWp'!$B$16+'Type C - 3MWp'!V$81*'Type C - 3MWp'!$B$16 -> 11978753 | W28: =SUM(C$28:V$28) -> 2.7723996e+08
A29: Total Debt Service | C29: ='Type A - 10MWp'!C$87*'Type A - 10MWp'!$B$16+'Type B - 5MWp'!C$87*'Type B - 5MWp'!$B$16+'Type C - 3MWp'!C$87*'Type C - 3MWp'!$B$16 -> 2175267.6 | D29: ='Type A - 10MWp'!D$87*'Type A - 10MWp'!$B$16+'Type B - 5MWp'!D$87*'Type B - 5MWp'!$B$16+'Type C - 3MWp'!D$87*'Type C - 3MWp'!$B$16 -> 2175267.6 | E29: ='Type A - 10MWp'!E$87*'Type A - 10MWp'!$B$16+'Type B - 5MWp'!E$87*'Type B - 5MWp'!$B$16+'Type C - 3MWp'!E$87*'Type C - 3MWp'!$B$16 -> 2175267.6 | F29: ='Type A - 10MWp'!F$87*'Type A - 10MWp'!$B$16+'Type B - 5MWp'!F$87*'Type B - 5MWp'!$B$16+'Type C - 3MWp'!F$87*'Type C - 3MWp'!$B$16 -> 2175267.6 | G29: ='Type A - 10MWp'!G$87*'Type A - 10MWp'!$B$16+'Type B - 5MWp'!G$87*'Type B - 5MWp'!$B$16+'Type C - 3MWp'!G$87*'Type C - 3MWp'!$B$16 -> 2175267.6 | H29: ='Type A - 10MWp'!H$87*'Type A - 10MWp'!$B$16+'Type B - 5MWp'!H$87*'Type B - 5MWp'!$B$16+'Type C - 3MWp'!H$87*'Type C - 3MWp'!$B$16 -> 2175267.6 | I29: ='Type A - 10MWp'!I$87*'Type A - 10MWp'!$B$16+'Type B - 5MWp'!I$87*'Type B - 5MWp'!$B$16+'Type C - 3MWp'!I$87*'Type C - 3MWp'!$B$16 -> 2175267.6 | J29: ='Type A - 10MWp'!J$87*'Type A - 10MWp'!$B$16+'Type B - 5MWp'!J$87*'Type B - 5MWp'!$B$16+'Type C - 3MWp'!J$87*'Type C - 3MWp'!$B$16 -> 2175267.6 | ... V29: ='Type A - 10MWp'!V$87*'Type A - 10MWp'!$B$16+'Type B - 5MWp'!V$87*'Type B - 5MWp'!$B$16+'Type C - 3MWp'!V$87*'Type C - 3MWp'!$B$16 -> 0 | W29: =SUM(C$29:V$29) -> 32629014
A30: Total Tax | C30: ='Type A - 10MWp'!C$85*'Type A - 10MWp'!$B$16+'Type B - 5MWp'!C$85*'Type B - 5MWp'!$B$16+'Type C - 3MWp'!C$85*'Type C - 3MWp'!$B$16 -> 1396962.5 | D30: ='Type A - 10MWp'!D$85*'Type A - 10MWp'!$B$16+'Type B - 5MWp'!D$85*'Type B - 5MWp'!$B$16+'Type C - 3MWp'!D$85*'Type C - 3MWp'!$B$16 -> 1381018.1 | E30: ='Type A - 10MWp'!E$85*'Type A - 10MWp'!$B$16+'Type B - 5MWp'!E$85*'Type B - 5MWp'!$B$16+'Type C - 3MWp'!E$85*'Type C - 3MWp'!$B$16 -> 1365491.8 | F30: ='Type A - 10MWp'!F$85*'Type A - 10MWp'!$B$16+'Type B - 5MWp'!F$85*'Type B - 5MWp'!$B$16+'Type C - 3MWp'!F$85*'Type C - 3MWp'!$B$16 -> 1350400.9 | G30: ='Type A - 10MWp'!G$85*'Type A - 10MWp'!$B$16+'Type B - 5MWp'!G$85*'Type B - 5MWp'!$B$16+'Type C - 3MWp'!G$85*'Type C - 3MWp'!$B$16 -> 1335763.8 | H30: ='Type A - 10MWp'!H$85*'Type A - 10MWp'!$B$16+'Type B - 5MWp'!H$85*'Type B - 5MWp'!$B$16+'Type C - 3MWp'!H$85*'Type C - 3MWp'!$B$16 -> 1267682.9 | I30: ='Type A - 10MWp'!I$85*'Type A - 10MWp'!$B$16+'Type B - 5MWp'!I$85*'Type B - 5MWp'!$B$16+'Type C - 3MWp'!I$85*'Type C - 3MWp'!$B$16 -> 1253472.8 | J30: ='Type A - 10MWp'!J$85*'Type A - 10MWp'!$B$16+'Type B - 5MWp'!J$85*'Type B - 5MWp'!$B$16+'Type C - 3MWp'!J$85*'Type C - 3MWp'!$B$16 -> 1239771.4 | ... V30: ='Type A - 10MWp'!V$85*'Type A - 10MWp'!$B$16+'Type B - 5MWp'!V$85*'Type B - 5MWp'!$B$16+'Type C - 3MWp'!V$85*'Type C - 3MWp'!$B$16 -> 1043263.4 | W30: =SUM(C$30:V$30) -> 24317069
A31: Portfolio FCFE | C31: ='Type A - 10MWp'!C$88*'Type A - 10MWp'!$B$16+'Type B - 5MWp'!C$88*'Type B - 5MWp'!$B$16+'Type C - 3MWp'!C$88*'Type C - 3MWp'!$B$16 -> 12365043 | D31: ='Type A - 10MWp'!D$88*'Type A - 10MWp'!$B$16+'Type B - 5MWp'!D$88*'Type B - 5MWp'!$B$16+'Type C - 3MWp'!D$88*'Type C - 3MWp'!$B$16 -> 12201115 | E31: ='Type A - 10MWp'!E$88*'Type A - 10MWp'!$B$16+'Type B - 5MWp'!E$88*'Type B - 5MWp'!$B$16+'Type C - 3MWp'!E$88*'Type C - 3MWp'!$B$16 -> 12037498 | F31: ='Type A - 10MWp'!F$88*'Type A - 10MWp'!$B$16+'Type B - 5MWp'!F$88*'Type B - 5MWp'!$B$16+'Type C - 3MWp'!F$88*'Type C - 3MWp'!$B$16 -> 11874182 | G31: ='Type A - 10MWp'!G$88*'Type A - 10MWp'!$B$16+'Type B - 5MWp'!G$88*'Type B - 5MWp'!$B$16+'Type C - 3MWp'!G$88*'Type C - 3MWp'!$B$16 -> 11711159 | H31: ='Type A - 10MWp'!H$88*'Type A - 10MWp'!$B$16+'Type B - 5MWp'!H$88*'Type B - 5MWp'!$B$16+'Type C - 3MWp'!H$88*'Type C - 3MWp'!$B$16 -> 11171001 | I31: ='Type A - 10MWp'!I$88*'Type A - 10MWp'!$B$16+'Type B - 5MWp'!I$88*'Type B - 5MWp'!$B$16+'Type C - 3MWp'!I$88*'Type C - 3MWp'!$B$16 -> 11004759 | J31: ='Type A - 10MWp'!J$88*'Type A - 10MWp'!$B$16+'Type B - 5MWp'!J$88*'Type B - 5MWp'!$B$16+'Type C - 3MWp'!J$88*'Type C - 3MWp'!$B$16 -> 10838739 | ... V31: ='Type A - 10MWp'!V$88*'Type A - 10MWp'!$B$16+'Type B - 5MWp'!V$88*'Type B - 5MWp'!$B$16+'Type C - 3MWp'!V$88*'Type C - 3MWp'!$B$16 -> 10935490 | W31: =SUM(C$31:V$31) -> 2.2029387e+08
A32: Cumulative Portfolio CF | C32: =C$31 -> 12365043 | D32: =C$32+D$31 -> 24566158 | E32: =D$32+E$31 -> 36603656 | F32: =E$32+F$31 -> 48477837 | G32: =F$32+G$31 -> 60188996 | H32: =G$32+H$31 -> 71359997 | I32: =H$32+I$31 -> 82364756 | J32: =I$32+J$31 -> 93203495 | K32: =J$32+K$31 -> 1.0387643e+08 | ... V32: =U$32+V$31 -> 2.2029387e+08 | W32: =V$32 -> 2.2029387e+08
A34: FUND-LEVEL RETURNS COMPARISON
A35: Metric | B35: Low (110) | C35: Base (150) | D35: High (175)
A36: Fund Equity IRR | B36: =IRR(B$41:V$41) -> 0.15343254 | C36: =IRR(B$42:V$42) -> 0.19992856 | D36: =IRR(B$43:V$43) -> 0.22836614
A37: Fund Equity NPV (@ 8%) | B37: {=NPV(Assumptions!$B$37,C$41:V$41)+B$41} -> 28742746 | C37: {=NPV(Assumptions!$B$37,C$42:V$42)+B$42} -> 48115675 | D37: {=NPV(Assumptions!$B$37,C$43:V$43)+B$43} -> 60223755
A38: Fund Equity Multiple | B38: =SUM(C$41:V$41)/(-B$41) -> 3.1665199 | C38: =SUM(C$42:V$42)/(-B$42) -> 3.9251737 | D38: =SUM(C$43:V$43)/(-B$43) -> 4.3993322
A39: Fund Total FCFE (20 yr) | B39: =SUM(C$41:V$41) -> 1.5856155e+08 | C39: =SUM(C$42:V$42) -> 1.9655067e+08 | D39: =SUM(C$43:V$43) -> 2.2029387e+08
A41: Fund Equity CF (Low) | B41: =-('Type A - 10MWp'!$B$12*'Type A - 10MWp'!$B$16+'Type B - 5MWp'!$B$12*'Type B - 5MWp'!$B$16+'Type C - 3MWp'!$B$12*'Type C - 3MWp'!$B$16) -> -50074389 | C41: ='Type A - 10MWp'!C$46*'Type A - 10MWp'!$B$16+'Type B - 5MWp'!C$46*'Type B - 5MWp'!$B$16+'Type C - 3MWp'!C$46*'Type C - 3MWp'!$B$16 -> 8816380 | D41: ='Type A - 10MWp'!D$46*'Type A - 10MWp'!$B$16+'Type B - 5MWp'!D$46*'Type B - 5MWp'!$B$16+'Type C - 3MWp'!D$46*'Type C - 3MWp'!$B$16 -> 8701088.8 | E41: ='Type A - 10MWp'!E$46*'Type A - 10MWp'!$B$16+'Type B - 5MWp'!E$46*'Type B - 5MWp'!$B$16+'Type C - 3MWp'!E$46*'Type C - 3MWp'!$B$16 -> 8586107.8 | F41: ='Type A - 10MWp'!F$46*'Type A - 10MWp'!$B$16+'Type B - 5MWp'!F$46*'Type B - 5MWp'!$B$16+'Type C - 3MWp'!F$46*'Type C - 3MWp'!$B$16 -> 8471428.6 | G41: ='Type A - 10MWp'!G$46*'Type A - 10MWp'!$B$16+'Type B - 5MWp'!G$46*'Type B - 5MWp'!$B$16+'Type C - 3MWp'!G$46*'Type C - 3MWp'!$B$16 -> 8357042 | H41: ='Type A - 10MWp'!H$46*'Type A - 10MWp'!$B$16+'Type B - 5MWp'!H$46*'Type B - 5MWp'!$B$16+'Type C - 3MWp'!H$46*'Type C - 3MWp'!$B$16 -> 7865520.5 | I41: ='Type A - 10MWp'!I$46*'Type A - 10MWp'!$B$16+'Type B - 5MWp'!I$46*'Type B - 5MWp'!$B$16+'Type C - 3MWp'!I$46*'Type C - 3MWp'!$B$16 -> 7747914.8 | J41: ='Type A - 10MWp'!J$46*'Type A - 10MWp'!$B$16+'Type B - 5MWp'!J$46*'Type B - 5MWp'!$B$16+'Type C - 3MWp'!J$46*'Type C - 3MWp'!$B$16 -> 7630532.1 | ... V41: ='Type A - 10MWp'!V$46*'Type A - 10MWp'!$B$16+'Type B - 5MWp'!V$46*'Type B - 5MWp'!$B$16+'Type C - 3MWp'!V$46*'Type C - 3MWp'!$B$16 -> 8310920.4
A42: Fund Equity CF (Base) | B42: =-('Type A - 10MWp'!$B$12*'Type A - 10MWp'!$B$16+'Type B - 5MWp'!$B$12*'Type B - 5MWp'!$B$16+'Type C - 3MWp'!$B$12*'Type C - 3MWp'!$B$16) -> -50074389 | C42: ='Type A - 10MWp'!C$67*'Type A - 10MWp'!$B$16+'Type B - 5MWp'!C$67*'Type B - 5MWp'!$B$16+'Type C - 3MWp'!C$67*'Type C - 3MWp'!$B$16 -> 11000173 | D42: ='Type A - 10MWp'!D$67*'Type A - 10MWp'!$B$16+'Type B - 5MWp'!D$67*'Type B - 5MWp'!$B$16+'Type C - 3MWp'!D$67*'Type C - 3MWp'!$B$16 -> 10854951 | E42: ='Type A - 10MWp'!E$67*'Type A - 10MWp'!$B$16+'Type B - 5MWp'!E$67*'Type B - 5MWp'!$B$16+'Type C - 3MWp'!E$67*'Type C - 3MWp'!$B$16 -> 10710040 | F42: ='Type A - 10MWp'!F$67*'Type A - 10MWp'!$B$16+'Type B - 5MWp'!F$67*'Type B - 5MWp'!$B$16+'Type C - 3MWp'!F$67*'Type C - 3MWp'!$B$16 -> 10565431 | G42: ='Type A - 10MWp'!G$67*'Type A - 10MWp'!$B$16+'Type B - 5MWp'!G$67*'Type B - 5MWp'!$B$16+'Type C - 3MWp'!G$67*'Type C - 3MWp'!$B$16 -> 10421114 | H42: ='Type A - 10MWp'!H$67*'Type A - 10MWp'!$B$16+'Type B - 5MWp'!H$67*'Type B - 5MWp'!$B$16+'Type C - 3MWp'!H$67*'Type C - 3MWp'!$B$16 -> 9899662.3 | I42: ='Type A - 10MWp'!I$67*'Type A - 10MWp'!$B$16+'Type B - 5MWp'!I$67*'Type B - 5MWp'!$B$16+'Type C - 3MWp'!I$67*'Type C - 3MWp'!$B$16 -> 9752126.4 | J42: ='Type A - 10MWp'!J$67*'Type A - 10MWp'!$B$16+'Type B - 5MWp'!J$67*'Type B - 5MWp'!$B$16+'Type C - 3MWp'!J$67*'Type C - 3MWp'!$B$16 -> 9604813.5 | ... V42: ='Type A - 10MWp'!V$67*'Type A - 10MWp'!$B$16+'Type B - 5MWp'!V$67*'Type B - 5MWp'!$B$16+'Type C - 3MWp'!V$67*'Type C - 3MWp'!$B$16 -> 9926040
A43: Fund Equity CF (High) | B43: =-('Type A - 10MWp'!$B$12*'Type A - 10MWp'!$B$16+'Type B - 5MWp'!$B$12*'Type B - 5MWp'!$B$16+'Type C - 3MWp'!$B$12*'Type C - 3MWp'!$B$16) -> -50074389 | C43: ='Type A - 10MWp'!C$88*'Type A - 10MWp'!$B$16+'Type B - 5MWp'!C$88*'Type B - 5MWp'!$B$16+'Type C - 3MWp'!C$88*'Type C - 3MWp'!$B$16 -> 12365043 | D43: ='Type A - 10MWp'!D$88*'Type A - 10MWp'!$B$16+'Type B - 5MWp'!D$88*'Type B - 5MWp'!$B$16+'Type C - 3MWp'!D$88*'Type C - 3MWp'!$B$16 -> 12201115 | E43: ='Type A - 10MWp'!E$88*'Type A - 10MWp'!$B$16+'Type B - 5MWp'!E$88*'Type B - 5MWp'!$B$16+'Type C - 3MWp'!E$88*'Type C - 3MWp'!$B$16 -> 12037498 | F43: ='Type A - 10MWp'!F$88*'Type A - 10MWp'!$B$16+'Type B - 5MWp'!F$88*'Type B - 5MWp'!$B$16+'Type C - 3MWp'!F$88*'Type C - 3MWp'!$B$16 -> 11874182 | G43: ='Type A - 10MWp'!G$88*'Type A - 10MWp'!$B$16+'Type B - 5MWp'!G$88*'Type B - 5MWp'!$B$16+'Type C - 3MWp'!G$88*'Type C - 3MWp'!$B$16 -> 11711159 | H43: ='Type A - 10MWp'!H$88*'Type A - 10MWp'!$B$16+'Type B - 5MWp'!H$88*'Type B - 5MWp'!$B$16+'Type C - 3MWp'!H$88*'Type C - 3MWp'!$B$16 -> 11171001 | I43: ='Type A - 10MWp'!I$88*'Type A - 10MWp'!$B$16+'Type B - 5MWp'!I$88*'Type B - 5MWp'!$B$16+'Type C - 3MWp'!I$88*'Type C - 3MWp'!$B$16 -> 11004759 | J43: ='Type A - 10MWp'!J$88*'Type A - 10MWp'!$B$16+'Type B - 5MWp'!J$88*'Type B - 5MWp'!$B$16+'Type C - 3MWp'!J$88*'Type C - 3MWp'!$B$16 -> 10838739 | ... V43: ='Type A - 10MWp'!V$88*'Type A - 10MWp'!$B$16+'Type B - 5MWp'!V$88*'Type B - 5MWp'!$B$16+'Type C - 3MWp'!V$88*'Type C - 3MWp'!$B$16 -> 10935490
A45: PER-ASSET-TYPE EQUITY IRR COMPARISON
A46: Asset Type | B46: Size | C46: Units | D46: Low IRR | E46: Base IRR | F46: High IRR
A47: Type A: Large Hybrid Park | B47: 10 MWp + 40 MWh | C47: ='Type A - 10MWp'!$B$16 -> 3 | D47: ='Type A - 10MWp'!$B$94 -> 0.16010303 | E47: ='Type A - 10MWp'!$C$94 -> 0.20738031 | F47: ='Type A - 10MWp'!$D$94 -> 0.23633322
A48: Type B: Medium Hybrid Park | B48: 5 MWp + 20 MWh | C48: ='Type B - 5MWp'!$B$16 -> 3 | D48: ='Type B - 5MWp'!$B$94 -> 0.15221289 | E48: ='Type B - 5MWp'!$C$94 -> 0.19817566 | F48: ='Type B - 5MWp'!$D$94 -> 0.22627513
A49: Type C: Small Hybrid Park | B49: 3 MWp + 12 MWh | C49: ='Type C - 3MWp'!$B$16 -> 4 | D49: ='Type C - 3MWp'!$B$94 -> 0.1390503 | E49: ='Type C - 3MWp'!$C$94 -> 0.18437841 | F49: ='Type C - 3MWp'!$D$94 -> 0.21202465

Sheet Debt Schedules
A1: SHARK Fund — BESS Debt Amortization Schedules
A2: All cells use Excel PMT/IPMT/PPMT formulas linked to Assumptions
A4: Type A: Large Hybrid Park — BESS Loan (40 MWh)
A5: Principal (EUR) | B5: ='Type A - 10MWp'!$B$10 -> 3740967 | C5: Rate | D5: =Assumptions!$B$38 -> 0.05 | E5: Term | F5: =Assumptions!$B$39 -> 15 | G5: Payment/yr | H5: ='Type A - 10MWp'!$B$14 -> 360413.32
A6: Year | B6: 2026 | C6: 2027 | D6: 2028 | E6: 2029 | F6: 2030 | G6: 2031 | H6: 2032 | I6: 2033 | J6: 2034 | K6: 2035 | L6: 2036 | M6: 2037 | N6: 2038 | O6: 2039 | P6: 2040 | Q6: Total
A7: Opening Balance | B7: ='Type A - 10MWp'!$B$10 -> 3740967 | C7: =B$11 -> 3567602 | D7: =C$11 -> 3385568.8 | E7: =D$11 -> 3194433.9 | F7: =E$11 -> 2993742.3 | G7: =F$11 -> 2783016.1 | H7: =G$11 -> 2561753.6 | I7: =H$11 -> 2329428 | J7: =I$11 -> 2085486 | ... P7: =O$11 -> 343250.78
A8: Interest | B8: =B$7*Assumptions!$B$38 -> 187048.35 | C8: =C$7*Assumptions!$B$38 -> 178380.1 | D8: =D$7*Assumptions!$B$38 -> 169278.44 | E8: =E$7*Assumptions!$B$38 -> 159721.7 | F8: =F$7*Assumptions!$B$38 -> 149687.12 | G8: =G$7*Assumptions!$B$38 -> 139150.81 | H8: =H$7*Assumptions!$B$38 -> 128087.68 | I8: =I$7*Assumptions!$B$38 -> 116471.4 | ... P8: =P$7*Assumptions!$B$38 -> 17162.539 | Q8: =SUM(B$8:P$8) -> 1665232.8
A9: Total Payment | B9: ='Type A - 10MWp'!$B$14 -> 360413.32 | C9: ='Type A - 10MWp'!$B$14 -> 360413.32 | D9: ='Type A - 10MWp'!$B$14 -> 360413.32 | E9: ='Type A - 10MWp'!$B$14 -> 360413.32 | F9: ='Type A - 10MWp'!$B$14 -> 360413.32 | G9: ='Type A - 10MWp'!$B$14 -> 360413.32 | H9: ='Type A - 10MWp'!$B$14 -> 360413.32 | I9: ='Type A - 10MWp'!$B$14 -> 360413.32 | ... P9: ='Type A - 10MWp'!$B$14 -> 360413.32 | Q9: =SUM(B$9:P$9) -> 5406199.8
A10: Principal Repayment | B10: =B$9-B$8 -> 173364.97 | C10: =C$9-C$8 -> 182033.22 | D10: =D$9-D$8 -> 191134.88 | E10: =E$9-E$8 -> 200691.62 | F10: =F$9-F$8 -> 210726.2 | G10: =G$9-G$8 -> 221262.51 | H10: =H$9-H$8 -> 232325.64 | I10: =I$9-I$8 -> 243941.92 | ... P10: =P$9-P$8 -> 343250.78 | Q10: =SUM(B$10:P$10) -> 3740967
A11: Closing Balance | B11: =B$7-B$10 -> 3567602 | C11: =C$7-C$10 -> 3385568.8 | D11: =D$7-D$10 -> 3194433.9 | E11: =E$7-E$10 -> 2993742.3 | F11: =F$7-F$10 -> 2783016.1 | G11: =G$7-G$10 -> 2561753.6 | H11: =H$7-H$10 -> 2329428 | I11: =I$7-I$10 -> 2085486 | ... P11: =P$7-P$10 -> 5.6461431e-09
A14: Type B: Medium Hybrid Park — BESS Loan (20 MWh)
A15: Principal (EUR) | B15: ='Type B - 5MWp'!$B$10 -> 1919179 | C15: Rate | D15: =Assumptions!$B$38 -> 0.05 | E15: Term | F15: =Assumptions!$B$39 -> 15 | G15: Payment/yr | H15: ='Type B - 5MWp'!$B$14 -> 184898.1
A16: Year | B16: 2026 | C16: 2027 | D16: 2028 | E16: 2029 | F16: 2030 | G16: 2031 | H16: 2032 | I16: 2033 | J16: 2034 | K16: 2035 | L16: 2036 | M16: 2037 | N16: 2038 | O16: 2039 | P16: 2040 | Q16: Total
A17: Opening Balance | B17: ='Type B - 5MWp'!$B$10 -> 1919179 | C17: =B$21 -> 1830239.9 | D17: =C$21 -> 1736853.8 | E17: =D$21 -> 1638798.3 | F17: =E$21 -> 1535840.2 | G17: =F$21 -> 1427734.1 | H17: =G$21 -> 1314222.7 | I17: =H$21 -> 1195035.7 | J17: =I$21 -> 1069889.4 | ... P17: =O$21 -> 176093.42
A18: Interest | B18: =B$17*Assumptions!$B$38 -> 95958.95 | C18: =C$17*Assumptions!$B$38 -> 91511.993 | D18: =D$17*Assumptions!$B$38 -> 86842.688 | E18: =E$17*Assumptions!$B$38 -> 81939.917 | F18: =F$17*Assumptions!$B$38 -> 76792.008 | G18: =G$17*Assumptions!$B$38 -> 71386.704 | H18: =H$17*Assumptions!$B$38 -> 65711.134 | I18: =I$17*Assumptions!$B$38 -> 59751.786 | ... P18: =P$17*Assumptions!$B$38 -> 8804.6712 | Q18: =SUM(B$18:P$18) -> 854292.43
A19: Total Payment | B19: ='Type B - 5MWp'!$B$14 -> 184898.1 | C19: ='Type B - 5MWp'!$B$14 -> 184898.1 | D19: ='Type B - 5MWp'!$B$14 -> 184898.1 | E19: ='Type B - 5MWp'!$B$14 -> 184898.1 | F19: ='Type B - 5MWp'!$B$14 -> 184898.1 | G19: ='Type B - 5MWp'!$B$14 -> 184898.1 | H19: ='Type B - 5MWp'!$B$14 -> 184898.1 | I19: ='Type B - 5MWp'!$B$14 -> 184898.1 | ... P19: ='Type B - 5MWp'!$B$14 -> 184898.1 | Q19: =SUM(B$19:P$19) -> 2773471.4
A20: Principal Repayment | B20: =B$19-B$18 -> 88939.145 | C20: =C$19-C$18 -> 93386.102 | D20: =D$19-D$18 -> 98055.408 | E20: =E$19-E$18 -> 102958.18 | F20: =F$19-F$18 -> 108106.09 | G20: =G$19-G$18 -> 113511.39 | H20: =H$19-H$18 -> 119186.96 | I20: =I$19-I$18 -> 125146.31 | ... P20: =P$19-P$18 -> 176093.42 | Q20: =SUM(B$20:P$20) -> 1919179
A21: Closing Balance | B21: =B$17-B$20 -> 1830239.9 | C21: =C$17-C$20 -> 1736853.8 | D21: =D$17-D$20 -> 1638798.3 | E21: =E$17-E$20 -> 1535840.2 | F21: =F$17-F$20 -> 1427734.1 | G21: =G$17-G$20 -> 1314222.7 | H21: =H$17-H$20 -> 1195035.7 | I21: =I$17-I$20 -> 1069889.4 | ... P21: =P$17-P$20 -> 2.7357601e-09
A24: Type C: Small Hybrid Park — BESS Loan (12 MWh)
A25: Principal (EUR) | B25: ='Type C - 3MWp'!$B$10 -> 1399524 | C25: Rate | D25: =Assumptions!$B$38 -> 0.05 | E25: Term | F25: =Assumptions!$B$39 -> 15 | G25: Payment/yr | H25: ='Type C - 3MWp'!$B$14 -> 134833.34
A26: Year | B26: 2026 | C26: 2027 | D26: 2028 | E26: 2029 | F26: 2030 | G26: 2031 | H26: 2032 | I26: 2033 | J26: 2034 | K26: 2035 | L26: 2036 | M26: 2037 | N26: 2038 | O26: 2039 | P26: 2040 | Q26: Total
A27: Opening Balance | B27: ='Type C - 3MWp'!$B$10 -> 1399524 | C27: =B$31 -> 1334666.9 | D27: =C$31 -> 1266566.9 | E27: =D$31 -> 1195061.9 | F27: =E$31 -> 1119981.6 | G27: =F$31 -> 1041147.3 | H27: =G$31 -> 958371.36 | I27: =H$31 -> 871456.59 | J27: =I$31 -> 780196.07 | ... P27: =O$31 -> 128412.71
A28: Interest | B28: =B$27*Assumptions!$B$38 -> 69976.2 | C28: =C$27*Assumptions!$B$38 -> 66733.343 | D28: =D$27*Assumptions!$B$38 -> 63328.343 | E28: =E$27*Assumptions!$B$38 -> 59753.093 | F28: =F$27*Assumptions!$B$38 -> 55999.08 | G28: =G$27*Assumptions!$B$38 -> 52057.367 | H28: =H$27*Assumptions!$B$38 -> 47918.568 | I28: =I$27*Assumptions!$B$38 -> 43572.829 | ... P28: =P$27*Assumptions!$B$38 -> 6420.6354 | Q28: =SUM(B$28:P$28) -> 622976.16
A29: Total Payment | B29: ='Type C - 3MWp'!$B$14 -> 134833.34 | C29: ='Type C - 3MWp'!$B$14 -> 134833.34 | D29: ='Type C - 3MWp'!$B$14 -> 134833.34 | E29: ='Type C - 3MWp'!$B$14 -> 134833.34 | F29: ='Type C - 3MWp'!$B$14 -> 134833.34 | G29: ='Type C - 3MWp'!$B$14 -> 134833.34 | H29: ='Type C - 3MWp'!$B$14 -> 134833.34 | I29: ='Type C - 3MWp'!$B$14 -> 134833.34 | ... P29: ='Type C - 3MWp'!$B$14 -> 134833.34 | Q29: =SUM(B$29:P$29) -> 2022500.2
A30: Principal Repayment | B30: =B$29-B$28 -> 64857.144 | C30: =C$29-C$28 -> 68100.001 | D30: =D$29-D$28 -> 71505.001 | E30: =E$29-E$28 -> 75080.251 | F30: =F$29-F$28 -> 78834.264 | G30: =G$29-G$28 -> 82775.977 | H30: =H$29-H$28 -> 86914.776 | I30: =I$29-I$28 -> 91260.514 | ... P30: =P$29-P$28 -> 128412.71 | Q30: =SUM(B$30:P$30) -> 1399524
A31: Closing Balance | B31: =B$27-B$30 -> 1334666.9 | C31: =C$27-C$30 -> 1266566.9 | D31: =D$27-D$30 -> 1195061.9 | E31: =E$27-E$30 -> 1119981.6 | F31: =F$27-F$30 -> 1041147.3 | G31: =G$27-G$30 -> 958371.36 | H31: =H$27-H$30 -> 871456.59 | I31: =I$27-I$30 -> 780196.07 | ... P31: =P$27-P$30 -> 2.066372e-09
